Workbook

Sheet Bohol
A2: Region | B2: REGION_VII
A3: Province | B3: BOHOL
A4: Number of Districts | B4: 3
A5: Sector | B5: Subsector/ Value Chain | C5: Job Requirement | D5: Tasks | E5: Program | F5: Type of Program (TR, CS, New and Emerging, Diploma Programs) | G5: Provincial Rank (Averaged Across Districts)
H6: D1 | O6: D2 | X6: D3
A7: AGRICULTURE FORESTRY AND FISHERY | B7: CROP PRODUCTION | C7: AGRI CROPS PRODUCER | D7: PRODUCE SEEDS AND FERTILIZER | E7: AGRICULTURAL CROPS PRODUCTION NC II | F7: With TR | G7: HIGH | H7: TRUE | I7: TRUE | J7: FALSE | K7: FALSE | L7: FALSE | M7: TRUE | N7: 1 | O7: HIGH | P7: TRUE | Q7: TRUE | R7: FALSE | S7: FALSE | T7: FALSE | U7: TRUE | V7: 1 | W7: HIGH | X7: TRUE | Y7: TRUE | Z7: FALSE | AA7: FALSE | AB7: FALSE | AC7: TRUE | AD7: 1 | AE7: HIGH
A8: AGRICULTURE FORESTRY AND FISHERY | B8: FOOD PROCESSING | C8: ANIMAL BUTCHERING AND SLAUGHTERING | D8: PREPARE, HANDLE, STUN, SLAUGHTER, INSPECT, PROCES, COLLECT, STORE, DISPOSE AND LABEL MEAT | E8: SLAUGHTERING OPERATIONS (LARGE ANIMAL) NC II | F8: With TR | G8: HIGH | H8: TRUE | I8: TRUE | J8: FALSE | K8: FALSE | L8: TRUE | M8: FALSE | N8: 1.5 | O8: HIGH | P8: FALSE | Q8: FALSE | R8: FALSE | S8: FALSE | T8: FALSE | U8: FALSE | X8: TRUE | Y8: TRUE | Z8: FALSE | AA8: FALSE | AB8: TRUE | AC8: FALSE | AD8: 1.5 | AE8: HIGH
A9: AGRICULTURE FORESTRY AND FISHERY | B9: FISHERY | C9: BANGUS FRY PRODUCTION | D9: COLLECT AND INCUBATE EGG IN HATCHERY | E9: AQUACULTURE (HATCHERY OPERATION) NC II | F9: With TR | G9: HIGH | H9: TRUE | I9: TRUE | J9: FALSE | K9: FALSE | L9: FALSE | M9: TRUE | N9: 1 | O9: HIGH | P9: TRUE | Q9: TRUE | R9: FALSE | S9: FALSE | T9: FALSE | U9: TRUE | V9: 1 | W9: HIGH | X9: TRUE | Y9: TRUE | Z9: FALSE | AA9: FALSE | AB9: FALSE | AC9: TRUE | AD9: 1 | AE9: HIGH
A10: AGRICULTURE FORESTRY AND FISHERY | B10: AGRICULTURE FORESTRY AND FISHERY | C10: BEEKEEPING | D10: MANAGE BEEHIVE | E10: BEEKEEPING LEVEL II | F10: With TR | G10: MEDIUM | H10: FALSE | I10: FALSE | J10: TRUE | K10: FALSE | L10: TRUE | M10: FALSE | N10: 2 | O10: MEDIUM | P10: FALSE | Q10: FALSE | R10: TRUE | S10: FALSE | T10: TRUE | U10: FALSE | V10: 2 | W10: MEDIUM | X10: FALSE | Y10: FALSE | Z10: TRUE | AA10: FALSE | AB10: TRUE | AC10: FALSE | AD10: 2 | AE10: MEDIUM
A11: AGRICULTURE FORESTRY AND FISHERY | B11: FERRO CEMENT TANK | C11: BUILD FERRO CEMENT TANK | D11: DESIGN, PREPARE, FABRICATE, INSTALL, MIX AND MAINTAIN FERRO CEMENT CONSTRUCTION | E11: NONE | F11: New and Emerging | G11: HIGH | H11: TRUE | I11: TRUE | J11: FALSE | K11: FALSE | L11: FALSE | M11: TRUE | N11: 1 | O11: HIGH | P11: TRUE | Q11: TRUE | R11: FALSE | S11: FALSE | T11: FALSE | U11: TRUE | V11: 1 | W11: HIGH | X11: TRUE | Y11: TRUE | Z11: FALSE | AA11: FALSE | AB11: FALSE | AC11: TRUE | AD11: 1 | AE11: HIGH
A12: AGRICULTURE FORESTRY AND FISHERY | B12: CROP PRODUCTION | C12: CACAO PROCESSING | D12: PROCESS CACAO PRODUCTS AND BY PRODUCTS | E12: CACAO PRODUCTION LEVEL II | F12: With TR | G12: MEDIUM | H12: FALSE | I12: FALSE | J12: TRUE | K12: FALSE | L12: TRUE | M12: FALSE | N12: 2 | O12: MEDIUM | P12: FALSE | Q12: FALSE | R12: FALSE | S12: FALSE | T12: FALSE | U12: FALSE | X12: FALSE | Y12: FALSE | Z12: TRUE | AA12: FALSE | AB12: TRUE | AC12: FALSE | AD12: 2 | AE12: MEDIUM
A13: AGRICULTURE FORESTRY AND FISHERY | B13: ANIMAL HUSBANDRY AND LIVESTOCK PRODUCTION | C13: CHICKEN LAYER GROWER | D13: BROOD, HOUSE, FEED, MANAGE CHICKEN LAYER | E13: ANIMAL PRODUCTION (POULTRY-CHICKEN) NC II | F13: With TR | G13: HIGH | H13: TRUE | I13: TRUE | J13: FALSE | K13: FALSE | L13: FALSE | M13: TRUE | N13: 1 | O13: HIGH | P13: TRUE | Q13: TRUE | R13: FALSE | S13: FALSE | T13: FALSE | U13: TRUE | V13: 1 | W13: HIGH | X13: TRUE | Y13: TRUE | Z13: FALSE | AA13: FALSE | AB13: FALSE | AC13: TRUE | AD13: 1 | AE13: HIGH
A14: AGRICULTURE FORESTRY AND FISHERY | B14: ANIMAL HUSBANDRY AND LIVESTOCK PRODUCTION | C14: EGG PRODUCER | D14: COLLECT AND HANDLE EGG | E14: ANIMAL PRODUCTION (POULTRY-CHICKEN) NC II | F14: With TR | G14: HIGH | H14: TRUE | I14: TRUE | J14: FALSE | K14: FALSE | L14: FALSE | M14: TRUE | N14: 1 | O14: HIGH | P14: TRUE | Q14: TRUE | R14: FALSE | S14: FALSE | T14: FALSE | U14: TRUE | V14: 1 | W14: HIGH | X14: TRUE | Y14: TRUE | Z14: FALSE | AA14: FALSE | AB14: FALSE | AC14: TRUE | AD14: 1 | AE14: HIGH
A15: AGRICULTURE FORESTRY AND FISHERY | B15: CROP PRODUCTION | C15: FARM MACHINERIES OPERATIONS | D15: OPEARATE FARM MACHINERIES | E15: AGRICULTURAL MACHINERY OPERATION NC II | F15: With TR | G15: HIGH | H15: TRUE | I15: TRUE | J15: FALSE | K15: FALSE | L15: FALSE | M15: TRUE | N15: 1 | O15: HIGH | P15: TRUE | Q15: TRUE | R15: FALSE | S15: FALSE | T15: FALSE | U15: TRUE | V15: 1 | W15: HIGH | X15: TRUE | Y15: TRUE | Z15: FALSE | AA15: FALSE | AB15: FALSE | AC15: TRUE | AD15: 1 | AE15: HIGH
A16: AGRICULTURE FORESTRY AND FISHERY | B16: CROP PRODUCTION | C16: FARM MANAGEMENT & TECHNOLOGICAL AWARENESS | D16: TRAIN IN FARM MACHINERY | E16: AGRICULTURAL MACHINERY OPERATION NC II | F16: With TR | G16: MEDIUM | H16: TRUE | I16: FALSE | J16: TRUE | K16: FALSE | L16: TRUE | M16: FALSE | N16: 2 | O16: MEDIUM | P16: TRUE | Q16: FALSE | R16: TRUE | S16: FALSE | T16: TRUE | U16: FALSE | V16: 2 | W16: MEDIUM | X16: TRUE | Y16: FALSE | Z16: TRUE | AA16: FALSE | AB16: TRUE | AC16: FALSE | AD16: 2 | AE16: MEDIUM
A17: AGRICULTURE FORESTRY AND FISHERY | B17: CROP PRODUCTION | C17: FARM MECHANICS & OPERATORS | D17: REPAIR FARM EQUIPMENT | E17: NONE | F17: New and Emerging | G17: HIGH | H17: FALSE | I17: FALSE | J17: FALSE | K17: FALSE | L17: FALSE | M17: FALSE | P17: TRUE | Q17: TRUE | R17: FALSE | S17: FALSE | T17: TRUE | U17: FALSE | V17: 1.5 | W17: HIGH | X17: TRUE | Y17: TRUE | Z17: FALSE | AA17: FALSE | AB17: TRUE | AC17: FALSE | AD17: 1.5 | AE17: HIGH
A18: AGRICULTURE FORESTRY AND FISHERY | B18: FISHERIES | C18: FRESHWATER FISH GROWER | D18: COLLECT AND INCUBATE EGG IN HATCHERY | E18: AQUACULTURE (HATCHERY OPERATION) NC II | F18: With TR | G18: LOW | H18: FALSE | I18: FALSE | J18: TRUE | K18: TRUE | L18: FALSE | M18: FALSE | N18: 2.5 | O18: LOW | P18: FALSE | Q18: FALSE | R18: TRUE | S18: TRUE | T18: FALSE | U18: FALSE | V18: 2.5 | W18: LOW | X18: FALSE | Y18: FALSE | Z18: TRUE | AA18: TRUE | AB18: FALSE | AC18: FALSE | AD18: 2.5 | AE18: LOW
A19: AGRICULTURE FORESTRY AND FISHERY | B19: CROP PRODUCTION | C19: FRUITS, COCONUT TREES, UBI & CACAO PRODUCTION & PROCESSING | D19: UBI PRODUCTION AND PROCESSING | E19: NONE | F19: New and Emerging | G19: HIGH | H19: TRUE | I19: TRUE | J19: FALSE | K19: FALSE | L19: TRUE | M19: FALSE | N19: 1.5 | O19: HIGH | P19: TRUE | Q19: TRUE | R19: FALSE | S19: FALSE | T19: TRUE | U19: FALSE | V19: 1.5 | W19: HIGH | X19: TRUE | Y19: TRUE | Z19: FALSE | AA19: FALSE | AB19: TRUE | AC19: FALSE | AD19: 1.5 | AE19: HIGH
A20: AGRICULTURE FORESTRY AND FISHERY | B20: CROP PRODUCTION | C20: HEAVY EQUIPMENT OPERATOR (BACKHOE, GRADER) | D20: OPERATE BACKHOE AND GRADER FOR DIGGING WATER RESERVOIR | E20: HEAVY EQUIPMENT OPERATION (BACKHOE LOADER) NC II | F20: With TR | G20: HIGH | H20: TRUE | I20: TRUE | J20: FALSE | K20: FALSE | L20: FALSE | M20: TRUE | N20: 1 | O20: HIGH | P20: TRUE | Q20: TRUE | R20: FALSE | S20: FALSE | T20: FALSE | U20: TRUE | V20: 1 | W20: HIGH | X20: TRUE | Y20: TRUE | Z20: FALSE | AA20: FALSE | AB20: FALSE | AC20: TRUE | AD20: 1 | AE20: HIGH
A21: AGRICULTURE FORESTRY AND FISHERY | B21: CROP PRODUCTION | C21: HIGH /ORGANIC QUALITY SEEDS GROWER | D21: PRODUCE ORGANIC VEGETABLE SEEDS | E21: NONE | F21: New and Emerging | G21: HIGH | H21: TRUE | I21: TRUE | J21: FALSE | K21: FALSE | L21: FALSE | M21: TRUE | N21: 1 | O21: HIGH | P21: TRUE | Q21: TRUE | R21: FALSE | S21: FALSE | T21: FALSE | U21: TRUE | V21: 1 | W21: HIGH | X21: TRUE | Y21: TRUE | Z21: FALSE | AA21: FALSE | AB21: FALSE | AC21: TRUE | AD21: 1 | AE21: HIGH
A22: AGRICULTURE FORESTRY AND FISHERY | B22: CROP PRODUCTION | C22: HIGH QUALITY INBREED RICE GROWER | D22: RICE PRODUCTION SEED CERTIFICATION AND FARM MECHANIZATION | E22: NONE | F22: New and Emerging | G22: MEDIUM | H22: TRUE | I22: FALSE | J22: TRUE | K22: FALSE | L22: TRUE | M22: FALSE | N22: 2 | O22: MEDIUM | P22: FALSE | Q22: FALSE | R22: TRUE | S22: FALSE | T22: TRUE | U22: FALSE | V22: 2 | W22: MEDIUM | X22: FALSE | Y22: FALSE | Z22: TRUE | AA22: FALSE | AB22: TRUE | AC22: FALSE | AD22: 2 | AE22: MEDIUM
A23: AGRICULTURE FORESTRY AND FISHERY | B23: CROP PRODUCTION | C23: INTERCROPPING TECHNICIAN | D23: IDENTIFY COMPATIBLE CROPS WITH COCONUT | E23: NONE | F23: New and Emerging | G23: MEDIUM | H23: TRUE | I23: FALSE | J23: TRUE | K23: FALSE | L23: TRUE | M23: FALSE | N23: 2 | O23: MEDIUM | P23: FALSE | Q23: FALSE | R23: TRUE | S23: FALSE | T23: TRUE | U23: FALSE | V23: 2 | W23: MEDIUM | X23: FALSE | Y23: FALSE | Z23: TRUE | AA23: FALSE | AB23: TRUE | AC23: FALSE | AD23: 2 | AE23: MEDIUM
A24: AGRICULTURE FORESTRY AND FISHERY | B24: CROP PRODUCTION | C24: INTERGRATED COCONUT AND CASH CROPS PRODUCTION AND PROCESSING (BY PRODUCTS LIKE SHELL,DUST, COIR) | D24: PRODUCE COCONUT and PROCESS COCONUT PRDUCTS AND BY PRODUCTS | E24: COCONUT PRODUCTION LEVEL II | F24: With CS | G24: HIGH | H24: TRUE | I24: TRUE | J24: FALSE | K24: FALSE | L24: TRUE | M24: FALSE | N24: 1.5 | O24: HIGH | P24: TRUE | Q24: TRUE | R24: FALSE | S24: FALSE | T24: TRUE | U24: FALSE | V24: 1.5 | W24: HIGH | X24: TRUE | Y24: TRUE | Z24: FALSE | AA24: FALSE | AB24: TRUE | AC24: FALSE | AD24: 1.5 | AE24: HIGH
A25: AGRICULTURE FORESTRY AND FISHERY | B25: HORTICULTURE | C25: LANDSCAPE PLANTS (ORNAMENTAL AND CUT FLOWER) CULTURE, CARE AND MAINTENANCE | D25: PROPAGATE, PLANT CARE, MAINTAIN, LANDSCAPE AND MANAGE ORNAMENTAL PLANTS | E25: LANDSCAPE INSTALLATION AND MAINTENANCE (SOFTSCAPE) NC II | F25: With TR | G25: HIGH | H25: TRUE | I25: TRUE | J25: FALSE | K25: FALSE | L25: TRUE | M25: FALSE | N25: 1.5 | O25: HIGH | P25: TRUE | Q25: TRUE | R25: FALSE | S25: FALSE | T25: TRUE | U25: FALSE | V25: 1.5 | W25: HIGH | X25: TRUE | Y25: TRUE | Z25: FALSE | AA25: FALSE | AB25: TRUE | AC25: FALSE | AD25: 1.5 | AE25: HIGH
A26: AGRICULTURE FORESTRY AND FISHERY | B26: CROP PRODUCTION | C26: MAKE ORGANIC FERTILIZER & CONCOCTION | D26: PRODUCE ORGANIC FERTILIZER, SEEDS, RICE | E26: ORGANIC AGRICULTURE PRODUCTION NC II | F26: With TR | G26: HIGH | H26: TRUE | I26: TRUE | J26: FALSE | K26: FALSE | L26: FALSE | M26: TRUE | N26: 1 | O26: HIGH | P26: TRUE | Q26: TRUE | R26: FALSE | S26: FALSE | T26: FALSE | U26: TRUE | V26: 1 | W26: HIGH | X26: TRUE | Y26: TRUE | Z26: FALSE | AA26: FALSE | AB26: FALSE | AC26: TRUE | AD26: 1 | AE26: HIGH
A27: AGRICULTURE FORESTRY AND FISHERY | B27: CROP PRODUCTION | C27: MEDICINAL TEA PRODUCTION AND PROCESSING (TURMERIC,SALABAT,MORINGA,ETC.) | D27: PRODUCE AND PROCESS MEDICINAL PLANTS | E27: NONE | F27: New and Emerging | G27: HIGH | H27: TRUE | I27: TRUE | J27: FALSE | K27: FALSE | L27: FALSE | M27: TRUE | N27: 1 | O27: HIGH | P27: TRUE | Q27: TRUE | R27: FALSE | S27: FALSE | T27: FALSE | U27: TRUE | V27: 1 | W27: HIGH | X27: TRUE | Y27: TRUE | Z27: FALSE | AA27: FALSE | AB27: FALSE | AC27: TRUE | AD27: 1 | AE27: HIGH
A28: AGRICULTURE FORESTRY AND FISHERY | B28: AGRICULTURE | C28: REPAIR OF FARM MECHANICAL EQUIPMENT | D28: REPAIR FARM EQUIPMENT | E28: NONE | F28: New and Emerging | G28: HIGH | H28: TRUE | I28: TRUE | J28: FALSE | K28: FALSE | L28: FALSE | M28: TRUE | N28: 1 | O28: HIGH | P28: TRUE | Q28: TRUE | R28: FALSE | S28: FALSE | T28: FALSE | U28: TRUE | V28: 1 | W28: HIGH | X28: TRUE | Y28: TRUE | Z28: FALSE | AA28: FALSE | AB28: FALSE | AC28: TRUE | AD28: 1 | AE28: HIGH
A29: AGRICULTURE FORESTRY AND FISHERY | B29: CROP PRODUCTION | C29: RICE MACHINES OPERATORS | D29: OPERATE RICE MACHINERIES | E29: RICE MACHINERY OPERATIONS NC II | F29: With TR | G29: HIGH | H29: FALSE | I29: TRUE | J29: FALSE | K29: FALSE | L29: TRUE | M29: FALSE | N29: 1.5 | O29: HIGH | P29: FALSE | Q29: TRUE | R29: FALSE | S29: FALSE | T29: TRUE | U29: FALSE | V29: 1.5 | W29: HIGH | X29: FALSE | Y29: TRUE | Z29: FALSE | AA29: FALSE | AB29: TRUE | AC29: FALSE | AD29: 1.5 | AE29: HIGH
... A89: INFORMATION AND COMMUNICATION TECHNOLOGY | B89: CONTACT CENTER AND BPO | C89: CALL CENTER AGENTS | D89: ASSESS AND RESOLVE CLIENT CONCERN | E89: CONTACT CENTER SERVICES NC II | F89: With TR | G89: HIGH | H89: TRUE | I89: TRUE | J89: FALSE | K89: FALSE | L89: FALSE | M89: TRUE | N89: 1 | O89: HIGH | P89: TRUE | Q89: TRUE | R89: FALSE | S89: FALSE | T89: FALSE | U89: TRUE | V89: 1 | W89: HIGH | X89: TRUE | Y89: TRUE | Z89: FALSE | AA89: FALSE | AB89: FALSE | AC89: TRUE | AD89: 1 | AE89: HIGH
A90: INFORMATION AND COMMUNICATION TECHNOLOGY | B90: INFORMATION TECHNOLOGY SERVICES | C90: COMPUTER LITERATE AND PROFICIENT TO WINDOWS OS, APPLE OS, X, MS OFFICE AND GOOGLE APPLICATION | D90: PERFORM OFFICE APPLICATION SOFTWARES | E90: COMPUTER SYSTEMS SERVICING NC II | F90: With TR | G90: MEDIUM | H90: FALSE | I90: FALSE | J90: FALSE | K90: FALSE | L90: FALSE | M90: FALSE | P90: TRUE | Q90: TRUE | R90: FALSE | S90: TRUE | T90: FALSE | U90: FALSE | V90: 2 | W90: MEDIUM | X90: TRUE | Y90: TRUE | Z90: FALSE | AA90: TRUE | AB90: FALSE | AC90: FALSE | AD90: 2 | AE90: MEDIUM
A91: INFORMATION AND COMMUNICATION TECHNOLOGY | B91: CONTACT CENTER AND BPO | C91: CUSTOMER SERVICE REPRESENTATIVE | D91: ASSESS AND RESOLVE CUSTOMER CONCERN | E91: CONTACT CENTER SERVICES NC II | F91: With TR | G91: HIGH | H91: TRUE | I91: TRUE | J91: FALSE | K91: FALSE | L91: FALSE | M91: TRUE | N91: 1 | O91: HIGH | P91: TRUE | Q91: TRUE | R91: FALSE | S91: FALSE | T91: FALSE | U91: TRUE | V91: 1 | W91: HIGH | X91: TRUE | Y91: TRUE | Z91: FALSE | AA91: FALSE | AB91: FALSE | AC91: TRUE | AD91: 1 | AE91: HIGH
A92: INFORMATION AND COMMUNICATION TECHNOLOGY | B92: INFORMATION TECHNOLOGY SERVICES | C92: CYBER SECURITY | D92: MANAGE AND SECURE CYBERSPACE | E92: CYBER RISK ASSESSMENT LEVEL III | F92: With TR | G92: HIGH | H92: FALSE | I92: FALSE | J92: FALSE | K92: FALSE | L92: FALSE | M92: FALSE | P92: TRUE | Q92: TRUE | R92: FALSE | S92: FALSE | T92: FALSE | U92: TRUE | V92: 1 | W92: HIGH | X92: FALSE | Y92: FALSE | Z92: FALSE | AA92: FALSE | AB92: FALSE | AC92: FALSE
A93: INFORMATION AND COMMUNICATION TECHNOLOGY | B93: E-COMMERCE | C93: DATA ANALYST | D93: ANALYZE DATA HISTORICALS TO PROVIDE FORECAST | E93: DATA ANALYTICS LEVEL III | F93: With TR | G93: HIGH | H93: TRUE | I93: TRUE | J93: FALSE | K93: FALSE | L93: FALSE | M93: TRUE | N93: 1 | O93: HIGH | P93: TRUE | Q93: TRUE | R93: FALSE | S93: FALSE | T93: FALSE | U93: TRUE | V93: 1 | W93: HIGH | X93: TRUE | Y93: TRUE | Z93: FALSE | AA93: FALSE | AB93: FALSE | AC93: TRUE | AD93: 1 | AE93: HIGH
A94: INFORMATION AND COMMUNICATION TECHNOLOGY | B94: MULTIMEDIA SERVICES | C94: GRAPHIC DESIGNERS | D94: CREATE AND DESIGN GRAPHICS | E94: VISUAL GRAPHIC DESIGN NC III | F94: With TR | G94: HIGH | H94: TRUE | I94: TRUE | J94: FALSE | K94: FALSE | L94: FALSE | M94: TRUE | N94: 1 | O94: HIGH | P94: TRUE | Q94: TRUE | R94: FALSE | S94: FALSE | T94: FALSE | U94: TRUE | V94: 1 | W94: HIGH | X94: TRUE | Y94: TRUE | Z94: FALSE | AA94: FALSE | AB94: FALSE | AC94: TRUE | AD94: 1 | AE94: HIGH
A95: INFORMATION AND COMMUNICATION TECHNOLOGY | B95: INFORMATION TECHNOLOGY SERVICES | C95: HARDWARE DEPLOYMENT | D95: INSTALLATION OF ICT INFRASTRUCTURE | E95: COMPUTER SYSTEMS SERVICING NC II | F95: With TR | G95: HIGH | H95: FALSE | I95: FALSE | J95: FALSE | K95: FALSE | L95: FALSE | M95: FALSE | P95: TRUE | Q95: TRUE | R95: FALSE | S95: FALSE | T95: TRUE | U95: FALSE | V95: 1.5 | W95: HIGH | X95: FALSE | Y95: FALSE | Z95: FALSE | AA95: FALSE | AB95: FALSE | AC95: FALSE
A96: INFORMATION AND COMMUNICATION TECHNOLOGY | B96: INFORMATION TECHNOLOGY SERVICES | C96: IT SKILLED INDIVIDUAL | D96: PROVIDE ICT SERVICES | E96: COMPUTER SYSTEMS SERVICING NC II | F96: With TR | G96: HIGH | H96: TRUE | I96: TRUE | J96: FALSE | K96: FALSE | L96: FALSE | M96: TRUE | N96: 1 | O96: HIGH | P96: TRUE | Q96: TRUE | R96: FALSE | S96: FALSE | T96: FALSE | U96: TRUE | V96: 1 | W96: HIGH | X96: TRUE | Y96: TRUE | Z96: FALSE | AA96: FALSE | AB96: FALSE | AC96: TRUE | AD96: 1 | AE96: HIGH
A97: INFORMATION AND COMMUNICATION TECHNOLOGY | B97: MULTIMEDIA SERVICES | C97: MASTER OF PHOTOSHOP | D97: CREATE AND DESIGN GRAPHICS | E97: VISUAL GRAPHIC DESIGN NC III | F97: With TR | G97: HIGH | H97: FALSE | I97: FALSE | J97: FALSE | K97: FALSE | L97: FALSE | M97: FALSE | P97: TRUE | Q97: TRUE | R97: FALSE | S97: FALSE | T97: TRUE | U97: FALSE | V97: 1.5 | W97: HIGH | X97: FALSE | Y97: FALSE | Z97: FALSE | AA97: FALSE | AB97: FALSE | AC97: FALSE
A98: INFORMATION AND COMMUNICATION TECHNOLOGY | B98: INFORMATION TECHNOLOGY SERVICES | C98: NETWORK ENGINEER AND FIBER OPTIC SPECIALIST | D98: MANAGE AND INSTALL PREMISES/OUTSIDE PLANT COPPER OR FIBER NETWORKS | E98: TELECOM OSP INSTALLATION (FIBER OPTIC CABLE) NC II | F98: With TR | G98: MEDIUM | H98: FALSE | I98: FALSE | J98: FALSE | K98: FALSE | L98: FALSE | M98: FALSE | P98: TRUE | Q98: TRUE | R98: FALSE | S98: TRUE | T98: FALSE | U98: FALSE | V98: 2 | W98: MEDIUM | X98: TRUE | Y98: TRUE | Z98: FALSE | AA98: TRUE | AB98: FALSE | AC98: FALSE | AD98: 2 | AE98: MEDIUM
A99: INFORMATION AND COMMUNICATION TECHNOLOGY | B99: INFORMATION TECHNOLOGY SERVICES | C99: SENIOR DRUPAL DEVELOPER | D99: CONCEPTUALIZE, DESIGN, DEPLOY AND MONITOR WEBSITE | E99: WEB DEVELOPMENT NC III | F99: With TR | G99: MEDIUM | H99: TRUE | I99: TRUE | J99: FALSE | K99: TRUE | L99: FALSE | M99: FALSE | N99: 2 | O99: MEDIUM | P99: TRUE | Q99: TRUE | R99: FALSE | S99: TRUE | T99: FALSE | U99: FALSE | V99: 2 | W99: MEDIUM | X99: TRUE | Y99: TRUE | Z99: FALSE | AA99: TRUE | AB99: FALSE | AC99: FALSE | AD99: 2 | AE99: MEDIUM
A100: INFORMATION AND COMMUNICATION TECHNOLOGY | B100: INFORMATION TECHNOLOGY SERVICES | C100: SENIOR SWIFT DEVELOPER | D100: CONCEPTUALIZE, DESIGN, DEPLOY AND MONITOR APPLICATIONS (EITHER WEB, DESKTOP OR MOBILE) | E100: WEB DEVELOPMENT NC III | F100: With TR | G100: HIGH | H100: TRUE | I100: TRUE | J100: FALSE | K100: FALSE | L100: FALSE | M100: TRUE | N100: 1 | O100: HIGH | P100: TRUE | Q100: TRUE | R100: FALSE | S100: FALSE | T100: FALSE | U100: TRUE | V100: 1 | W100: HIGH | X100: TRUE | Y100: TRUE | Z100: FALSE | AA100: FALSE | AB100: FALSE | AC100: TRUE | AD100: 1 | AE100: HIGH
A101: INFORMATION AND COMMUNICATION TECHNOLOGY | B101: E-COMMERCE | C101: SOCIAL MEDIA MANAGING | D101: MANAGE SOCIAL MEDIA ACCOUNT | E101: CONTENT CREATION (SOCIAL MEDIA) LEVEL III | F101: With TR | G101: HIGH | H101: TRUE | I101: TRUE | J101: FALSE | K101: FALSE | L101: TRUE | M101: FALSE | N101: 1.5 | O101: HIGH | P101: TRUE | Q101: TRUE | R101: FALSE | S101: FALSE | T101: FALSE | U101: TRUE | V101: 1 | W101: HIGH | X101: TRUE | Y101: TRUE | Z101: FALSE | AA101: FALSE | AB101: FALSE | AC101: TRUE | AD101: 1 | AE101: HIGH
A102: INFORMATION AND COMMUNICATION TECHNOLOGY | B102: INFORMATION TECHNOLOGY SERVICES | C102: STRUCTURED CABLING | D102: PROVIDE PREMISES CABLING (NETWORK) | E102: COMPUTER SYSTEMS SERVICING NC II | F102: With TR | G102: HIGH | H102: TRUE | I102: TRUE | J102: FALSE | K102: FALSE | L102: TRUE | M102: FALSE | N102: 1.5 | O102: HIGH | P102: TRUE | Q102: TRUE | R102: FALSE | S102: FALSE | T102: TRUE | U102: FALSE | V102: 1.5 | W102: HIGH | X102: TRUE | Y102: TRUE | Z102: FALSE | AA102: FALSE | AB102: TRUE | AC102: FALSE | AD102: 1.5 | AE102: HIGH
A103: INFORMATION AND COMMUNICATION TECHNOLOGY | B103: MULTIMEDIA SERVICES | C103: VIDEO EDITOR | D103: CREATE, ENHANCE, SEQUENCE AND EDIT VIDEOS | E103: FILM AND VIDEO POSTPRODUCTION NC III | F103: With TR | G103: HIGH | H103: TRUE | I103: TRUE | J103: FALSE | K103: FALSE | L103: TRUE | M103: FALSE | N103: 1.5 | O103: HIGH | P103: TRUE | Q103: TRUE | R103: FALSE | S103: FALSE | T103: TRUE | U103: FALSE | V103: 1.5 | W103: HIGH | X103: TRUE | Y103: TRUE | Z103: FALSE | AA103: FALSE | AB103: TRUE | AC103: FALSE | AD103: 1.5 | AE103: HIGH
A104: INFORMATION AND COMMUNICATION TECHNOLOGY | B104: CONTACT CENTER AND BPO | C104: VIRTUAL ASSISTANT DEVELOPING | D104: PROVIDE VIRTUAL CLERICAL SERVICES | E104: VIRTUAL ASSISTANT SERVICES LEVEL III | F104: With TR | G104: MEDIUM | H104: FALSE | I104: TRUE | J104: FALSE | K104: TRUE | L104: FALSE | M104: FALSE | N104: 2 | O104: MEDIUM | P104: FALSE | Q104: TRUE | R104: FALSE | S104: TRUE | T104: FALSE | U104: FALSE | V104: 2 | W104: MEDIUM | X104: FALSE | Y104: TRUE | Z104: FALSE | AA104: TRUE | AB104: FALSE | AC104: FALSE | AD104: 2 | AE104: MEDIUM
A105: INFORMATION AND COMMUNICATION TECHNOLOGY | B105: MULTIMEDIA SERVICES | C105: VISUAL GRAPHIC DESIGNER | D105: CREATE AND DESIGN GRAPHICS | E105: VISUAL GRAPHIC DESIGN NC III | F105: With TR | G105: HIGH | H105: TRUE | I105: TRUE | J105: FALSE | K105: FALSE | L105: FALSE | M105: TRUE | N105: 1 | O105: HIGH | P105: FALSE | Q105: FALSE | R105: FALSE | S105: FALSE | T105: FALSE | U105: FALSE | X105: TRUE | Y105: TRUE | Z105: FALSE | AA105: FALSE | AB105: FALSE | AC105: TRUE | AD105: 1 | AE105: HIGH
A106: INFORMATION AND COMMUNICATION TECHNOLOGY | B106: INFORMATION TECHNOLOGY SERVICES | C106: WEB DEVELOPER AND DESIGNER | D106: CONCEPTUALIZE, DESIGN, DEPLOY AND MONITOR WEBSITE | E106: WEB DEVELOPMENT NC III | F106: With TR | G106: MEDIUM | H106: TRUE | I106: TRUE | J106: FALSE | K106: TRUE | L106: FALSE | M106: FALSE | N106: 2 | O106: MEDIUM | P106: TRUE | Q106: TRUE | R106: FALSE | S106: TRUE | T106: FALSE | U106: FALSE | V106: 2 | W106: MEDIUM | X106: TRUE | Y106: TRUE | Z106: FALSE | AA106: TRUE | AB106: FALSE | AC106: FALSE | AD106: 2 | AE106: MEDIUM
A107: OTHERS | B107: FURNITURE/SOUVENIRS/UPCYCLING | C107: PRODUCT DESIGNER | D107: TO DESIGN PRODUCT OUT OF WOOD AND BAMBOO/SOUVENIR AND UPCYCLED PRODUCTS | E107: WOOD CARVING LEVEL II | F107: With CS | G107: HIGH | H107: TRUE | I107: TRUE | J107: FALSE | K107: FALSE | L107: FALSE | M107: TRUE | N107: 1 | O107: HIGH | P107: TRUE | Q107: TRUE | R107: FALSE | S107: FALSE | T107: FALSE | U107: TRUE | V107: 1 | W107: HIGH | X107: TRUE | Y107: TRUE | Z107: FALSE | AA107: FALSE | AB107: FALSE | AC107: TRUE | AD107: 1 | AE107: HIGH
A108: OTHERS | B108: LANGUAGE EDUCATION AND INSTRUCTION | C108: SKILL IN FOREIGN LANGUAGE | D108: TO TEACH ENGLISH LANGUAGE | E108: LANGUAGE B1 LEVEL | F108: With CS | G108: HIGH | H108: FALSE | I108: TRUE | J108: FALSE | K108: FALSE | L108: TRUE | M108: FALSE | N108: 1.5 | O108: HIGH | P108: FALSE | Q108: TRUE | R108: FALSE | S108: FALSE | T108: TRUE | U108: FALSE | V108: 1.5 | W108: HIGH | X108: FALSE | Y108: TRUE | Z108: FALSE | AA108: FALSE | AB108: TRUE | AC108: FALSE | AD108: 1.5 | AE108: HIGH
A109: OTHERS | B109: CULTURAL EXCHANGE AND INTERNATIONAL RELATION | C109: SKILL IN JAPANESE LANGUAGE | D109: TO STUDY AND WORK LOCAL/ABROAD | E109: LANGUAGE A1 LEVEL | F109: With CS | G109: HIGH | H109: TRUE | I109: TRUE | J109: FALSE | K109: FALSE | L109: TRUE | M109: FALSE | N109: 1.5 | O109: HIGH | P109: TRUE | Q109: TRUE | R109: FALSE | S109: FALSE | T109: TRUE | U109: FALSE | V109: 1.5 | W109: HIGH | X109: TRUE | Y109: TRUE | Z109: FALSE | AA109: FALSE | AB109: TRUE | AC109: FALSE | AD109: 1.5 | AE109: HIGH
A110: OTHERS | B110: LANGUAGE EDUCATION AND INSTRUCTION | C110: SKILL IN KOREAN LANGUAGE | D110: TO STUDY AND WORK LOCAL/ABROAD | E110: LANGUAGE A1 LEVEL | F110: With CS | G110: MEDIUM | H110: TRUE | I110: TRUE | J110: FALSE | K110: TRUE | L110: FALSE | M110: FALSE | N110: 2 | O110: MEDIUM | P110: TRUE | Q110: TRUE | R110: FALSE | S110: TRUE | T110: FALSE | U110: FALSE | V110: 2 | W110: MEDIUM | X110: TRUE | Y110: TRUE | Z110: FALSE | AA110: TRUE | AB110: FALSE | AC110: FALSE | AD110: 2 | AE110: MEDIUM
A111: OTHERS | B111: MARKETING | C111: SOCIAL MEDIA MANAGER/CONTENT CREATOR | D111: TO CREATE CURATE, AND ANALYZE SOCIAL MEDIA CONTENTS | E111: CONTENT CREATION (SOCIAL MEDIA) LEVEL III | F111: With CS | G111: MEDIUM | H111: FALSE | I111: TRUE | J111: FALSE | K111: TRUE | L111: FALSE | M111: FALSE | N111: 2 | O111: MEDIUM | P111: FALSE | Q111: TRUE | R111: FALSE | S111: TRUE | T111: FALSE | U111: FALSE | V111: 2 | W111: MEDIUM | X111: FALSE | Y111: TRUE | Z111: FALSE | AA111: TRUE | AB111: FALSE | AC111: FALSE | AD111: 2 | AE111: MEDIUM
A112: SOCIAL, COMMUNITY DEVELOPMENT AND OTHER SERVICES | B112: HAIRSTYLING AND HAIRCARE | C112: BEAUTICIAN SPECIALIST | D112: TO STYLE, CUT, COLOR AND TREAT HAIR | E112: HAIRDRESSING NC II | F112: With TR | G112: HIGH | H112: TRUE | I112: TRUE | J112: FALSE | K112: FALSE | L112: FALSE | M112: TRUE | N112: 1 | O112: HIGH | P112: FALSE | Q112: TRUE | R112: FALSE | S112: FALSE | T112: FALSE | U112: TRUE | V112: 1 | W112: HIGH | X112: TRUE | Y112: TRUE | Z112: FALSE | AA112: FALSE | AB112: FALSE | AC112: TRUE | AD112: 1 | AE112: HIGH
A113: SOCIAL, COMMUNITY DEVELOPMENT AND OTHER SERVICES | B113: COLLECTION AND DISBURSMENT | C113: BOOKKEEPING | D113: TO COLLECT AND MONITOR CASH FLOW/RECEIPT | E113: BOOKKEEPING NC III | F113: With TR | G113: HIGH | H113: TRUE | I113: TRUE | J113: FALSE | K113: FALSE | L113: TRUE | M113: FALSE | N113: 1.5 | O113: HIGH | P113: TRUE | Q113: TRUE | R113: FALSE | S113: FALSE | T113: TRUE | U113: FALSE | V113: 1.5 | W113: HIGH | X113: TRUE | Y113: TRUE | Z113: FALSE | AA113: FALSE | AB113: TRUE | AC113: FALSE | AD113: 1.5 | AE113: HIGH
A114: SOCIAL, COMMUNITY DEVELOPMENT AND OTHER SERVICES | B114: VIRTUAL ASSISTANT | C114: BOOKKEEPING | D114: TO ASSIST IN THE PREPARATION OF PAYROLLS AND FINANCIAL REPORTS | E114: VIRTUAL ASSISTANT SERVICES LEVEL III | F114: With CS | G114: MEDIUM | H114: FALSE | I114: TRUE | J114: FALSE | K114: TRUE | L114: FALSE | M114: FALSE | N114: 2 | O114: MEDIUM | P114: FALSE | Q114: TRUE | R114: FALSE | S114: TRUE | T114: FALSE | U114: FALSE | V114: 2 | W114: MEDIUM | X114: FALSE | Y114: TRUE | Z114: FALSE | AA114: TRUE | AB114: FALSE | AC114: FALSE | AD114: 2 | AE114: MEDIUM
A115: SOCIAL, COMMUNITY DEVELOPMENT AND OTHER SERVICES | B115: BASIC BRAZILIAN WAXING | C115: BRAZILIAN WAX | D115: TO CATER TO DIFFERENT CUSTOMER PREFERENCES AND NEEDS IN THE FIELD OF HAIR REMOVAL SERVICES | E115: BEAUTY CARE (SKIN CARE) SERVICES NC II | F115: With TR | G115: MEDIUM | H115: FALSE | I115: TRUE | J115: FALSE | K115: TRUE | L115: FALSE | M115: FALSE | N115: 2 | O115: MEDIUM | P115: FALSE | Q115: TRUE | R115: FALSE | S115: TRUE | T115: FALSE | U115: FALSE | V115: 2 | W115: MEDIUM | X115: FALSE | Y115: TRUE | Z115: FALSE | AA115: TRUE | AB115: FALSE | AC115: FALSE | AD115: 2 | AE115: MEDIUM
A116: SOCIAL, COMMUNITY DEVELOPMENT AND OTHER SERVICES | B116: SKINCARE AND FACIAL TREATMENT | C116: FACIAL | D116: TO EXFOLIATE AND REMOVE IMPURITIES, BLACKHEADS AND CLOGGED PORES OF SKIN | E116: BEAUTY CARE (SKIN CARE) SERVICES NC II | F116: With TR | G116: MEDIUM | H116: FALSE | I116: TRUE | J116: FALSE | K116: TRUE | L116: FALSE | M116: FALSE | N116: 2 | O116: MEDIUM | P116: FALSE | Q116: TRUE | R116: FALSE | S116: TRUE | T116: FALSE | U116: FALSE | V116: 2 | W116: MEDIUM | X116: FALSE | Y116: TRUE | Z116: FALSE | AA116: TRUE | AB116: FALSE | AC116: FALSE | AD116: 2 | AE116: MEDIUM
A117: SOCIAL, COMMUNITY DEVELOPMENT AND OTHER SERVICES | B117: FACIAL MASSAGE AND RELAXATION TREATMENTS | C117: FACIAL MASSAGE | D117: TO OFFER THERAPEUTIC MASSAGE AND RELAX FACIAL MUSCLES | E117: BEAUTY CARE (SKIN CARE) SERVICES NC II | F117: With TR | G117: MEDIUM | H117: FALSE | I117: TRUE | J117: FALSE | K117: TRUE | L117: FALSE | M117: FALSE | N117: 2 | O117: MEDIUM | P117: FALSE | Q117: TRUE | R117: FALSE | S117: TRUE | T117: FALSE | U117: FALSE | V117: 2 | W117: MEDIUM | X117: FALSE | Y117: TRUE | Z117: FALSE | AA117: TRUE | AB117: FALSE | AC117: FALSE | AD117: 2 | AE117: MEDIUM
... A148: TOURISM (HOTEL AND RESTAURANT) | B148: TRAVEL AND TOURS | C148: TOURISM PROMOTIONS SERVICES (ONLINE TRAVEL ADVISOR, ONLINE TOURISM PROMOTIONAL MATERIAL DEVELOPER) | D148: PROMOTE THE TOURISM INDUSTRY | E148: TOURISM PROMOTION SERVICES NC II | F148: With TR | G148: MEDIUM | H148: TRUE | I148: TRUE | J148: FALSE | K148: TRUE | L148: FALSE | M148: FALSE | N148: 2 | O148: MEDIUM | P148: TRUE | Q148: TRUE | R148: FALSE | S148: TRUE | T148: FALSE | U148: FALSE | V148: 2 | W148: MEDIUM | X148: TRUE | Y148: TRUE | Z148: FALSE | AA148: TRUE | AB148: FALSE | AC148: FALSE | AD148: 2 | AE148: MEDIUM
A149: TOURISM (HOTEL AND RESTAURANT) | B149: TRAVEL AND TOURS | C149: TRAVEL SERVICES (TRAVEL AGENTS) | D149: ASSISTS CLIENTS IN TRAVEL ITINERARY | E149: TRAVEL SERVICES NC II | F149: With TR | H149: FALSE | I149: FALSE | J149: FALSE | K149: FALSE | L149: FALSE | M149: FALSE | P149: FALSE | Q149: FALSE | R149: FALSE | S149: FALSE | T149: FALSE | U149: FALSE | X149: FALSE | Y149: FALSE | Z149: FALSE | AA149: FALSE | AB149: FALSE | AC149: FALSE
A150: CONSTRUCTION | B150: HEAVY EQUIPMENT | C150: FORKLIFT EQUIPMENT OPERATOR | D150: OPERATE FORKLIFT EQUIPMENT | E150: HEAVY EQUIPMENT OPERATION (FORKLIFT) NC II | F150: With TR | H150: FALSE | I150: FALSE | J150: FALSE | K150: FALSE | L150: FALSE | M150: FALSE | P150: FALSE | Q150: FALSE | R150: FALSE | S150: FALSE | T150: FALSE | U150: FALSE | X150: FALSE | Y150: FALSE | Z150: FALSE | AA150: FALSE | AB150: FALSE | AC150: FALSE
A151: METALS AND ENGINEERING | B151: WELDING | C151: MULTIPLE FILLET PASS WELDER | D151: WELD MULTIPLE FILLET PASS | E151: SHIELDED METAL ARC WELDING NC III | F151: With TR | H151: FALSE | I151: FALSE | J151: FALSE | K151: FALSE | L151: FALSE | M151: FALSE | P151: FALSE | Q151: FALSE | R151: FALSE | S151: FALSE | T151: FALSE | U151: FALSE | X151: FALSE | Y151: FALSE | Z151: FALSE | AA151: FALSE | AB151: FALSE | AC151: FALSE
A152: WHOLESALE AND RETAIL TRADING | B152: ENTREPRENUERSHIP | C152: HIGHER LEVEL ENTREPRENUER | D152: MANAGE OWN BUSINESS | E152: ENTREPRENEURSHIP LEVEL IV | F152: With CS | H152: FALSE | I152: FALSE | J152: FALSE | K152: FALSE | L152: FALSE | M152: FALSE | P152: FALSE | Q152: FALSE | R152: FALSE | S152: FALSE | T152: FALSE | U152: FALSE | X152: FALSE | Y152: FALSE | Z152: FALSE | AA152: FALSE | AB152: FALSE | AC152: FALSE
H153: FALSE | I153: FALSE | J153: FALSE | K153: FALSE | L153: FALSE | M153: FALSE | P153: FALSE | Q153: FALSE | R153: FALSE | S153: FALSE | T153: FALSE | U153: FALSE | X153: FALSE | Y153: FALSE | Z153: FALSE | AA153: FALSE | AB153: FALSE | AC153: FALSE
H154: FALSE | I154: FALSE | J154: FALSE | K154: FALSE | L154: FALSE | M154: FALSE | X154: FALSE | Y154: FALSE | Z154: FALSE | AA154: FALSE | AB154: FALSE | AC154: FALSE
H155: FALSE | I155: FALSE | J155: FALSE | K155: FALSE | L155: FALSE | M155: FALSE | X155: FALSE | Y155: FALSE | Z155: FALSE | AA155: FALSE | AB155: FALSE | AC155: FALSE
H156: FALSE | I156: FALSE | J156: FALSE | K156: FALSE | L156: FALSE | M156: FALSE | X156: FALSE | Y156: FALSE | Z156: FALSE | AA156: FALSE | AB156: FALSE | AC156: FALSE
H157: FALSE | I157: FALSE | J157: FALSE | K157: FALSE | L157: FALSE | M157: FALSE | X157: FALSE | Y157: FALSE | Z157: FALSE | AA157: FALSE | AB157: FALSE | AC157: FALSE
X158: FALSE | Y158: FALSE | Z158: FALSE | AA158: FALSE | AB158: FALSE | AC158: FALSE
X159: FALSE | Y159: FALSE | Z159: FALSE | AA159: FALSE | AB159: FALSE | AC159: FALSE
X160: FALSE | Y160: FALSE | Z160: FALSE | AA160: FALSE | AB160: FALSE | AC160: FALSE
X161: FALSE | Y161: FALSE | Z161: FALSE | AA161: FALSE | AB161: FALSE | AC161: FALSE
X162: FALSE | Y162: FALSE | Z162: FALSE | AA162: FALSE | AB162: FALSE | AC162: FALSE
X163: FALSE | Y163: FALSE | Z163: FALSE | AA163: FALSE | AB163: FALSE | AC163: FALSE
X164: FALSE | Y164: FALSE | Z164: FALSE | AA164: FALSE | AB164: FALSE | AC164: FALSE
X165: FALSE | Y165: FALSE | Z165: FALSE | AA165: FALSE | AB165: FALSE | AC165: FALSE
X166: FALSE | Y166: FALSE | Z166: FALSE | AA166: FALSE | AB166: FALSE | AC166: FALSE
X167: FALSE | Y167: FALSE | Z167: FALSE | AA167: FALSE | AB167: FALSE | AC167: FALSE
X168: FALSE | Y168: FALSE | Z168: FALSE | AA168: FALSE | AB168: FALSE | AC168: FALSE

Sheet BoholFinal
A1: Region | B1: REGION_VII
A2: Province | B2: BOHOL
A3: Number of Districts | B3: 3
A4: Sector | B4: Subsector/ Value Chain | C4: Job Requirement | D4: Tasks | E4: Program | F4: Type of Program (TR, CS, New and Emerging, Diploma Programs) | G4: Provincial Rank (Averaged Across Districts)
A6: DISTRICTS | I6: D1 | O6: D2 | W6: D3
A7: AGRICULTURE FORESTRY AND FISHERY | B7: CROP PRODUCTION | C7: AGRI CROPS PRODUCER | D7: PRODUCE SEEDS AND FERTILIZER | E7: AGRICULTURAL CROPS PRODUCTION NC II | F7: With TR | G7: HIGH | H7: 1 | I7: =IF(Bohol!H7=TRUE,"✓","") -> ✓ | J7: =IF(Bohol!I7=TRUE,"✓","") -> ✓ | K7: =IF(Bohol!J7=TRUE,"✓","") | L7: =IF(Bohol!K7=TRUE,"✓","") | M7: =IF(Bohol!L7=TRUE,"✓","") | N7: =IF(Bohol!M7=TRUE,"✓","") -> ✓ | O7: HIGH | P7: =IF(Bohol!P7=TRUE,"✓","") -> ✓ | Q7: =IF(Bohol!Q7=TRUE,"✓","") -> ✓ | R7: =IF(Bohol!R7=TRUE,"✓","") | S7: =IF(Bohol!S7=TRUE,"✓","") | T7: =IF(Bohol!T7=TRUE,"✓","") | U7: =IF(Bohol!U7=TRUE,"✓","") -> ✓ | V7: 1 | W7: HIGH | X7: =IF(Bohol!X7=TRUE,"✓","") -> ✓ | Y7: =IF(Bohol!Y7=TRUE,"✓","") -> ✓ | Z7: =IF(Bohol!Z7=TRUE,"✓","") | AA7: =IF(Bohol!AA7=TRUE,"✓","") | AB7: =IF(Bohol!AB7=TRUE,"✓","") | AC7: 1 | AD7: HIGH
A8: AGRICULTURE FORESTRY AND FISHERY | B8: FOOD PROCESSING | C8: ANIMAL BUTCHERING AND SLAUGHTERING | D8: PREPARE, HANDLE, STUN, SLAUGHTER, INSPECT, PROCES, COLLECT, STORE, DISPOSE AND LABEL MEAT | E8: SLAUGHTERING OPERATIONS (LARGE ANIMAL) NC II | F8: With TR | G8: HIGH | H8: 1.5 | I8: =IF(Bohol!H8=TRUE,"✓","") -> ✓ | J8: =IF(Bohol!I8=TRUE,"✓","") -> ✓ | K8: =IF(Bohol!J8=TRUE,"✓","") | L8: =IF(Bohol!K8=TRUE,"✓","") | M8: =IF(Bohol!L8=TRUE,"✓","") -> ✓ | N8: =IF(Bohol!M8=TRUE,"✓","") | O8: HIGH | P8: =IF(Bohol!P8=TRUE,"✓","") | Q8: =IF(Bohol!Q8=TRUE,"✓","") | R8: =IF(Bohol!R8=TRUE,"✓","") | S8: =IF(Bohol!S8=TRUE,"✓","") | T8: =IF(Bohol!T8=TRUE,"✓","") | U8: =IF(Bohol!U8=TRUE,"✓","") | X8: =IF(Bohol!X8=TRUE,"✓","") -> ✓ | Y8: =IF(Bohol!Y8=TRUE,"✓","") -> ✓ | Z8: =IF(Bohol!Z8=TRUE,"✓","") | AA8: =IF(Bohol!AA8=TRUE,"✓","") | AB8: =IF(Bohol!AB8=TRUE,"✓","") -> ✓ | AC8: 1.5 | AD8: HIGH
A9: AGRICULTURE FORESTRY AND FISHERY | B9: FISHERY | C9: BANGUS FRY PRODUCTION | D9: COLLECT AND INCUBATE EGG IN HATCHERY | E9: AQUACULTURE (HATCHERY OPERATION) NC II | F9: With TR | G9: HIGH | H9: 1 | I9: =IF(Bohol!H9=TRUE,"✓","") -> ✓ | J9: =IF(Bohol!I9=TRUE,"✓","") -> ✓ | K9: =IF(Bohol!J9=TRUE,"✓","") | L9: =IF(Bohol!K9=TRUE,"✓","") | M9: =IF(Bohol!L9=TRUE,"✓","") | N9: =IF(Bohol!M9=TRUE,"✓","") -> ✓ | O9: HIGH | P9: =IF(Bohol!P9=TRUE,"✓","") -> ✓ | Q9: =IF(Bohol!Q9=TRUE,"✓","") -> ✓ | R9: =IF(Bohol!R9=TRUE,"✓","") | S9: =IF(Bohol!S9=TRUE,"✓","") | T9: =IF(Bohol!T9=TRUE,"✓","") | U9: =IF(Bohol!U9=TRUE,"✓","") -> ✓ | V9: 1 | W9: HIGH | X9: =IF(Bohol!X9=TRUE,"✓","") -> ✓ | Y9: =IF(Bohol!Y9=TRUE,"✓","") -> ✓ | Z9: =IF(Bohol!Z9=TRUE,"✓","") | AA9: =IF(Bohol!AA9=TRUE,"✓","") | AB9: =IF(Bohol!AB9=TRUE,"✓","") | AC9: 1 | AD9: HIGH
A10: AGRICULTURE FORESTRY AND FISHERY | B10: AGRICULTURE FORESTRY AND FISHERY | C10: BEEKEEPING | D10: MANAGE BEEHIVE | E10: BEEKEEPING LEVEL II | F10: With TR | G10: MEDIUM | H10: 2 | I10: =IF(Bohol!H10=TRUE,"✓","") | J10: =IF(Bohol!I10=TRUE,"✓","") | K10: =IF(Bohol!J10=TRUE,"✓","") -> ✓ | L10: =IF(Bohol!K10=TRUE,"✓","") | M10: =IF(Bohol!L10=TRUE,"✓","") -> ✓ | N10: =IF(Bohol!M10=TRUE,"✓","") | O10: MEDIUM | P10: =IF(Bohol!P10=TRUE,"✓","") | Q10: =IF(Bohol!Q10=TRUE,"✓","") | R10: =IF(Bohol!R10=TRUE,"✓","") -> ✓ | S10: =IF(Bohol!S10=TRUE,"✓","") | T10: =IF(Bohol!T10=TRUE,"✓","") -> ✓ | U10: =IF(Bohol!U10=TRUE,"✓","") | V10: 2 | W10: MEDIUM | X10: =IF(Bohol!X10=TRUE,"✓","") | Y10: =IF(Bohol!Y10=TRUE,"✓","") | Z10: =IF(Bohol!Z10=TRUE,"✓","") -> ✓ | AA10: =IF(Bohol!AA10=TRUE,"✓","") | AB10: =IF(Bohol!AB10=TRUE,"✓","") -> ✓ | AC10: 2 | AD10: MEDIUM
A11: AGRICULTURE FORESTRY AND FISHERY | B11: FERRO CEMENT TANK | C11: BUILD FERRO CEMENT TANK | D11: DESIGN, PREPARE, FABRICATE, INSTALL, MIX AND MAINTAIN FERRO CEMENT CONSTRUCTION | E11: NONE | F11: New and Emerging | G11: HIGH | H11: 1 | I11: =IF(Bohol!H11=TRUE,"✓","") -> ✓ | J11: =IF(Bohol!I11=TRUE,"✓","") -> ✓ | K11: =IF(Bohol!J11=TRUE,"✓","") | L11: =IF(Bohol!K11=TRUE,"✓","") | M11: =IF(Bohol!L11=TRUE,"✓","") | N11: =IF(Bohol!M11=TRUE,"✓","") -> ✓ | O11: HIGH | P11: =IF(Bohol!P11=TRUE,"✓","") -> ✓ | Q11: =IF(Bohol!Q11=TRUE,"✓","") -> ✓ | R11: =IF(Bohol!R11=TRUE,"✓","") | S11: =IF(Bohol!S11=TRUE,"✓","") | T11: =IF(Bohol!T11=TRUE,"✓","") | U11: =IF(Bohol!U11=TRUE,"✓","") -> ✓ | V11: 1 | W11: HIGH | X11: =IF(Bohol!X11=TRUE,"✓","") -> ✓ | Y11: =IF(Bohol!Y11=TRUE,"✓","") -> ✓ | Z11: =IF(Bohol!Z11=TRUE,"✓","") | AA11: =IF(Bohol!AA11=TRUE,"✓","") | AB11: =IF(Bohol!AB11=TRUE,"✓","") | AC11: 1 | AD11: HIGH
A12: AGRICULTURE FORESTRY AND FISHERY | B12: CROP PRODUCTION | C12: CACAO PROCESSING | D12: PROCESS CACAO PRODUCTS AND BY PRODUCTS | E12: CACAO PRODUCTION LEVEL II | F12: With TR | G12: MEDIUM | H12: 2 | I12: =IF(Bohol!H12=TRUE,"✓","") | J12: =IF(Bohol!I12=TRUE,"✓","") | K12: =IF(Bohol!J12=TRUE,"✓","") -> ✓ | L12: =IF(Bohol!K12=TRUE,"✓","") | M12: =IF(Bohol!L12=TRUE,"✓","") -> ✓ | N12: =IF(Bohol!M12=TRUE,"✓","") | O12: MEDIUM | P12: =IF(Bohol!P12=TRUE,"✓","") | Q12: =IF(Bohol!Q12=TRUE,"✓","") | R12: =IF(Bohol!R12=TRUE,"✓","") | S12: =IF(Bohol!S12=TRUE,"✓","") | T12: =IF(Bohol!T12=TRUE,"✓","") | U12: =IF(Bohol!U12=TRUE,"✓","") | X12: =IF(Bohol!X12=TRUE,"✓","") | Y12: =IF(Bohol!Y12=TRUE,"✓","") | Z12: =IF(Bohol!Z12=TRUE,"✓","") -> ✓ | AA12: =IF(Bohol!AA12=TRUE,"✓","") | AB12: =IF(Bohol!AB12=TRUE,"✓","") -> ✓ | AC12: 2 | AD12: MEDIUM
A13: AGRICULTURE FORESTRY AND FISHERY | B13: ANIMAL HUSBANDRY AND LIVESTOCK PRODUCTION | C13: CHICKEN LAYER GROWER | D13: BROOD, HOUSE, FEED, MANAGE CHICKEN LAYER | E13: ANIMAL PRODUCTION (POULTRY-CHICKEN) NC II | F13: With TR | G13: HIGH | H13: 1 | I13: =IF(Bohol!H13=TRUE,"✓","") -> ✓ | J13: =IF(Bohol!I13=TRUE,"✓","") -> ✓ | K13: =IF(Bohol!J13=TRUE,"✓","") | L13: =IF(Bohol!K13=TRUE,"✓","") | M13: =IF(Bohol!L13=TRUE,"✓","") | N13: =IF(Bohol!M13=TRUE,"✓","") -> ✓ | O13: HIGH | P13: =IF(Bohol!P13=TRUE,"✓","") -> ✓ | Q13: =IF(Bohol!Q13=TRUE,"✓","") -> ✓ | R13: =IF(Bohol!R13=TRUE,"✓","") | S13: =IF(Bohol!S13=TRUE,"✓","") | T13: =IF(Bohol!T13=TRUE,"✓","") | U13: =IF(Bohol!U13=TRUE,"✓","") -> ✓ | V13: 1 | W13: HIGH | X13: =IF(Bohol!X13=TRUE,"✓","") -> ✓ | Y13: =IF(Bohol!Y13=TRUE,"✓","") -> ✓ | Z13: =IF(Bohol!Z13=TRUE,"✓","") | AA13: =IF(Bohol!AA13=TRUE,"✓","") | AB13: =IF(Bohol!AB13=TRUE,"✓","") | AC13: 1 | AD13: HIGH
A14: AGRICULTURE FORESTRY AND FISHERY | B14: ANIMAL HUSBANDRY AND LIVESTOCK PRODUCTION | C14: EGG PRODUCER | D14: COLLECT AND HANDLE EGG | E14: ANIMAL PRODUCTION (POULTRY-CHICKEN) NC II | F14: With TR | G14: HIGH | H14: 1 | I14: =IF(Bohol!H14=TRUE,"✓","") -> ✓ | J14: =IF(Bohol!I14=TRUE,"✓","") -> ✓ | K14: =IF(Bohol!J14=TRUE,"✓","") | L14: =IF(Bohol!K14=TRUE,"✓","") | M14: =IF(Bohol!L14=TRUE,"✓","") | N14: =IF(Bohol!M14=TRUE,"✓","") -> ✓ | O14: HIGH | P14: =IF(Bohol!P14=TRUE,"✓","") -> ✓ | Q14: =IF(Bohol!Q14=TRUE,"✓","") -> ✓ | R14: =IF(Bohol!R14=TRUE,"✓","") | S14: =IF(Bohol!S14=TRUE,"✓","") | T14: =IF(Bohol!T14=TRUE,"✓","") | U14: =IF(Bohol!U14=TRUE,"✓","") -> ✓ | V14: 1 | W14: HIGH | X14: =IF(Bohol!X14=TRUE,"✓","") -> ✓ | Y14: =IF(Bohol!Y14=TRUE,"✓","") -> ✓ | Z14: =IF(Bohol!Z14=TRUE,"✓","") | AA14: =IF(Bohol!AA14=TRUE,"✓","") | AB14: =IF(Bohol!AB14=TRUE,"✓","") | AC14: 1 | AD14: HIGH
A15: AGRICULTURE FORESTRY AND FISHERY | B15: CROP PRODUCTION | C15: FARM MACHINERIES OPERATIONS | D15: OPEARATE FARM MACHINERIES | E15: AGRICULTURAL MACHINERY OPERATION NC II | F15: With TR | G15: HIGH | H15: 1 | I15: =IF(Bohol!H15=TRUE,"✓","") -> ✓ | J15: =IF(Bohol!I15=TRUE,"✓","") -> ✓ | K15: =IF(Bohol!J15=TRUE,"✓","") | L15: =IF(Bohol!K15=TRUE,"✓","") | M15: =IF(Bohol!L15=TRUE,"✓","") | N15: =IF(Bohol!M15=TRUE,"✓","") -> ✓ | O15: HIGH | P15: =IF(Bohol!P15=TRUE,"✓","") -> ✓ | Q15: =IF(Bohol!Q15=TRUE,"✓","") -> ✓ | R15: =IF(Bohol!R15=TRUE,"✓","") | S15: =IF(Bohol!S15=TRUE,"✓","") | T15: =IF(Bohol!T15=TRUE,"✓","") | U15: =IF(Bohol!U15=TRUE,"✓","") -> ✓ | V15: 1 | W15: HIGH | X15: =IF(Bohol!X15=TRUE,"✓","") -> ✓ | Y15: =IF(Bohol!Y15=TRUE,"✓","") -> ✓ | Z15: =IF(Bohol!Z15=TRUE,"✓","") | AA15: =IF(Bohol!AA15=TRUE,"✓","") | AB15: =IF(Bohol!AB15=TRUE,"✓","") | AC15: 1 | AD15: HIGH
A16: AGRICULTURE FORESTRY AND FISHERY | B16: CROP PRODUCTION | C16: FARM MANAGEMENT & TECHNOLOGICAL AWARENESS | D16: TRAIN IN FARM MACHINERY | E16: AGRICULTURAL MACHINERY OPERATION NC II | F16: With TR | G16: MEDIUM | H16: 2 | I16: =IF(Bohol!H16=TRUE,"✓","") -> ✓ | J16: =IF(Bohol!I16=TRUE,"✓","") | K16: =IF(Bohol!J16=TRUE,"✓","") -> ✓ | L16: =IF(Bohol!K16=TRUE,"✓","") | M16: =IF(Bohol!L16=TRUE,"✓","") -> ✓ | N16: =IF(Bohol!M16=TRUE,"✓","") | O16: MEDIUM | P16: =IF(Bohol!P16=TRUE,"✓","") -> ✓ | Q16: =IF(Bohol!Q16=TRUE,"✓","") | R16: =IF(Bohol!R16=TRUE,"✓","") -> ✓ | S16: =IF(Bohol!S16=TRUE,"✓","") | T16: =IF(Bohol!T16=TRUE,"✓","") -> ✓ | U16: =IF(Bohol!U16=TRUE,"✓","") | V16: 2 | W16: MEDIUM | X16: =IF(Bohol!X16=TRUE,"✓","") -> ✓ | Y16: =IF(Bohol!Y16=TRUE,"✓","") | Z16: =IF(Bohol!Z16=TRUE,"✓","") -> ✓ | AA16: =IF(Bohol!AA16=TRUE,"✓","") | AB16: =IF(Bohol!AB16=TRUE,"✓","") -> ✓ | AC16: 2 | AD16: MEDIUM
A17: AGRICULTURE FORESTRY AND FISHERY | B17: CROP PRODUCTION | C17: FARM MECHANICS & OPERATORS | D17: REPAIR FARM EQUIPMENT | E17: NONE | F17: New and Emerging | G17: HIGH | I17: =IF(Bohol!H17=TRUE,"✓","") | J17: =IF(Bohol!I17=TRUE,"✓","") | K17: =IF(Bohol!J17=TRUE,"✓","") | L17: =IF(Bohol!K17=TRUE,"✓","") | M17: =IF(Bohol!L17=TRUE,"✓","") | N17: =IF(Bohol!M17=TRUE,"✓","") | P17: =IF(Bohol!P17=TRUE,"✓","") -> ✓ | Q17: =IF(Bohol!Q17=TRUE,"✓","") -> ✓ | R17: =IF(Bohol!R17=TRUE,"✓","") | S17: =IF(Bohol!S17=TRUE,"✓","") | T17: =IF(Bohol!T17=TRUE,"✓","") -> ✓ | U17: =IF(Bohol!U17=TRUE,"✓","") | V17: 1.5 | W17: HIGH | X17: =IF(Bohol!X17=TRUE,"✓","") -> ✓ | Y17: =IF(Bohol!Y17=TRUE,"✓","") -> ✓ | Z17: =IF(Bohol!Z17=TRUE,"✓","") | AA17: =IF(Bohol!AA17=TRUE,"✓","") | AB17: =IF(Bohol!AB17=TRUE,"✓","") -> ✓ | AC17: 1.5 | AD17: HIGH
A18: AGRICULTURE FORESTRY AND FISHERY | B18: FISHERIES | C18: FRESHWATER FISH GROWER | D18: COLLECT AND INCUBATE EGG IN HATCHERY | E18: AQUACULTURE (HATCHERY OPERATION) NC II | F18: With TR | G18: LOW | H18: 2.5 | I18: =IF(Bohol!H18=TRUE,"✓","") | J18: =IF(Bohol!I18=TRUE,"✓","") | K18: =IF(Bohol!J18=TRUE,"✓","") -> ✓ | L18: =IF(Bohol!K18=TRUE,"✓","") -> ✓ | M18: =IF(Bohol!L18=TRUE,"✓","") | N18: =IF(Bohol!M18=TRUE,"✓","") | O18: LOW | P18: =IF(Bohol!P18=TRUE,"✓","") | Q18: =IF(Bohol!Q18=TRUE,"✓","") | R18: =IF(Bohol!R18=TRUE,"✓","") -> ✓ | S18: =IF(Bohol!S18=TRUE,"✓","") -> ✓ | T18: =IF(Bohol!T18=TRUE,"✓","") | U18: =IF(Bohol!U18=TRUE,"✓","") | V18: 2.5 | W18: LOW | X18: =IF(Bohol!X18=TRUE,"✓","") | Y18: =IF(Bohol!Y18=TRUE,"✓","") | Z18: =IF(Bohol!Z18=TRUE,"✓","") -> ✓ | AA18: =IF(Bohol!AA18=TRUE,"✓","") -> ✓ | AB18: =IF(Bohol!AB18=TRUE,"✓","") | AC18: 2.5 | AD18: LOW
A19: AGRICULTURE FORESTRY AND FISHERY | B19: CROP PRODUCTION | C19: FRUITS, COCONUT TREES, UBI & CACAO PRODUCTION & PROCESSING | D19: UBI PRODUCTION AND PROCESSING | E19: NONE | F19: New and Emerging | G19: HIGH | H19: 1.5 | I19: =IF(Bohol!H19=TRUE,"✓","") -> ✓ | J19: =IF(Bohol!I19=TRUE,"✓","") -> ✓ | K19: =IF(Bohol!J19=TRUE,"✓","") | L19: =IF(Bohol!K19=TRUE,"✓","") | M19: =IF(Bohol!L19=TRUE,"✓","") -> ✓ | N19: =IF(Bohol!M19=TRUE,"✓","") | O19: HIGH | P19: =IF(Bohol!P19=TRUE,"✓","") -> ✓ | Q19: =IF(Bohol!Q19=TRUE,"✓","") -> ✓ | R19: =IF(Bohol!R19=TRUE,"✓","") | S19: =IF(Bohol!S19=TRUE,"✓","") | T19: =IF(Bohol!T19=TRUE,"✓","") -> ✓ | U19: =IF(Bohol!U19=TRUE,"✓","") | V19: 1.5 | W19: HIGH | X19: =IF(Bohol!X19=TRUE,"✓","") -> ✓ | Y19: =IF(Bohol!Y19=TRUE,"✓","") -> ✓ | Z19: =IF(Bohol!Z19=TRUE,"✓","") | AA19: =IF(Bohol!AA19=TRUE,"✓","") | AB19: =IF(Bohol!AB19=TRUE,"✓","") -> ✓ | AC19: 1.5 | AD19: HIGH
A20: AGRICULTURE FORESTRY AND FISHERY | B20: CROP PRODUCTION | C20: HEAVY EQUIPMENT OPERATOR (BACKHOE, GRADER) | D20: OPERATE BACKHOE AND GRADER FOR DIGGING WATER RESERVOIR | E20: HEAVY EQUIPMENT OPERATION (BACKHOE LOADER) NC II | F20: With TR | G20: HIGH | H20: 1 | I20: =IF(Bohol!H20=TRUE,"✓","") -> ✓ | J20: =IF(Bohol!I20=TRUE,"✓","") -> ✓ | K20: =IF(Bohol!J20=TRUE,"✓","") | L20: =IF(Bohol!K20=TRUE,"✓","") | M20: =IF(Bohol!L20=TRUE,"✓","") | N20: =IF(Bohol!M20=TRUE,"✓","") -> ✓ | O20: HIGH | P20: =IF(Bohol!P20=TRUE,"✓","") -> ✓ | Q20: =IF(Bohol!Q20=TRUE,"✓","") -> ✓ | R20: =IF(Bohol!R20=TRUE,"✓","") | S20: =IF(Bohol!S20=TRUE,"✓","") | T20: =IF(Bohol!T20=TRUE,"✓","") | U20: =IF(Bohol!U20=TRUE,"✓","") -> ✓ | V20: 1 | W20: HIGH | X20: =IF(Bohol!X20=TRUE,"✓","") -> ✓ | Y20: =IF(Bohol!Y20=TRUE,"✓","") -> ✓ | Z20: =IF(Bohol!Z20=TRUE,"✓","") | AA20: =IF(Bohol!AA20=TRUE,"✓","") | AB20: =IF(Bohol!AB20=TRUE,"✓","") | AC20: 1 | AD20: HIGH
A21: AGRICULTURE FORESTRY AND FISHERY | B21: CROP PRODUCTION | C21: HIGH /ORGANIC QUALITY SEEDS GROWER | D21: PRODUCE ORGANIC VEGETABLE SEEDS | E21: NONE | F21: New and Emerging | G21: HIGH | H21: 1 | I21: =IF(Bohol!H21=TRUE,"✓","") -> ✓ | J21: =IF(Bohol!I21=TRUE,"✓","") -> ✓ | K21: =IF(Bohol!J21=TRUE,"✓","") | L21: =IF(Bohol!K21=TRUE,"✓","") | M21: =IF(Bohol!L21=TRUE,"✓","") | N21: =IF(Bohol!M21=TRUE,"✓","") -> ✓ | O21: HIGH | P21: =IF(Bohol!P21=TRUE,"✓","") -> ✓ | Q21: =IF(Bohol!Q21=TRUE,"✓","") -> ✓ | R21: =IF(Bohol!R21=TRUE,"✓","") | S21: =IF(Bohol!S21=TRUE,"✓","") | T21: =IF(Bohol!T21=TRUE,"✓","") | U21: =IF(Bohol!U21=TRUE,"✓","") -> ✓ | V21: 1 | W21: HIGH | X21: =IF(Bohol!X21=TRUE,"✓","") -> ✓ | Y21: =IF(Bohol!Y21=TRUE,"✓","") -> ✓ | Z21: =IF(Bohol!Z21=TRUE,"✓","") | AA21: =IF(Bohol!AA21=TRUE,"✓","") | AB21: =IF(Bohol!AB21=TRUE,"✓","") | AC21: 1 | AD21: HIGH
A22: AGRICULTURE FORESTRY AND FISHERY | B22: CROP PRODUCTION | C22: HIGH QUALITY INBREED RICE GROWER | D22: RICE PRODUCTION SEED CERTIFICATION AND FARM MECHANIZATION | E22: NONE | F22: New and Emerging | G22: MEDIUM | H22: 2 | I22: =IF(Bohol!H22=TRUE,"✓","") -> ✓ | J22: =IF(Bohol!I22=TRUE,"✓","") | K22: =IF(Bohol!J22=TRUE,"✓","") -> ✓ | L22: =IF(Bohol!K22=TRUE,"✓","") | M22: =IF(Bohol!L22=TRUE,"✓","") -> ✓ | N22: =IF(Bohol!M22=TRUE,"✓","") | O22: MEDIUM | P22: =IF(Bohol!P22=TRUE,"✓","") | Q22: =IF(Bohol!Q22=TRUE,"✓","") | R22: =IF(Bohol!R22=TRUE,"✓","") -> ✓ | S22: =IF(Bohol!S22=TRUE,"✓","") | T22: =IF(Bohol!T22=TRUE,"✓","") -> ✓ | U22: =IF(Bohol!U22=TRUE,"✓","") | V22: 2 | W22: MEDIUM | X22: =IF(Bohol!X22=TRUE,"✓","") | Y22: =IF(Bohol!Y22=TRUE,"✓","") | Z22: =IF(Bohol!Z22=TRUE,"✓","") -> ✓ | AA22: =IF(Bohol!AA22=TRUE,"✓","") | AB22: =IF(Bohol!AB22=TRUE,"✓","") -> ✓ | AC22: 2 | AD22: MEDIUM
A23: AGRICULTURE FORESTRY AND FISHERY | B23: CROP PRODUCTION | C23: INTERCROPPING TECHNICIAN | D23: IDENTIFY COMPATIBLE CROPS WITH COCONUT | E23: NONE | F23: New and Emerging | G23: MEDIUM | H23: 2 | I23: =IF(Bohol!H23=TRUE,"✓","") -> ✓ | J23: =IF(Bohol!I23=TRUE,"✓","") | K23: =IF(Bohol!J23=TRUE,"✓","") -> ✓ | L23: =IF(Bohol!K23=TRUE,"✓","") | M23: =IF(Bohol!L23=TRUE,"✓","") -> ✓ | N23: =IF(Bohol!M23=TRUE,"✓","") | O23: MEDIUM | P23: =IF(Bohol!P23=TRUE,"✓","") | Q23: =IF(Bohol!Q23=TRUE,"✓","") | R23: =IF(Bohol!R23=TRUE,"✓","") -> ✓ | S23: =IF(Bohol!S23=TRUE,"✓","") | T23: =IF(Bohol!T23=TRUE,"✓","") -> ✓ | U23: =IF(Bohol!U23=TRUE,"✓","") | V23: 2 | W23: MEDIUM | X23: =IF(Bohol!X23=TRUE,"✓","") | Y23: =IF(Bohol!Y23=TRUE,"✓","") | Z23: =IF(Bohol!Z23=TRUE,"✓","") -> ✓ | AA23: =IF(Bohol!AA23=TRUE,"✓","") | AB23: =IF(Bohol!AB23=TRUE,"✓","") -> ✓ | AC23: 2 | AD23: MEDIUM
A24: AGRICULTURE FORESTRY AND FISHERY | B24: CROP PRODUCTION | C24: INTERGRATED COCONUT AND CASH CROPS PRODUCTION AND PROCESSING (BY PRODUCTS LIKE SHELL,DUST, COIR) | D24: PRODUCE COCONUT and PROCESS COCONUT PRDUCTS AND BY PRODUCTS | E24: COCONUT PRODUCTION LEVEL II | F24: With CS | G24: HIGH | H24: 1.5 | I24: =IF(Bohol!H24=TRUE,"✓","") -> ✓ | J24: =IF(Bohol!I24=TRUE,"✓","") -> ✓ | K24: =IF(Bohol!J24=TRUE,"✓","") | L24: =IF(Bohol!K24=TRUE,"✓","") | M24: =IF(Bohol!L24=TRUE,"✓","") -> ✓ | N24: =IF(Bohol!M24=TRUE,"✓","") | O24: HIGH | P24: =IF(Bohol!P24=TRUE,"✓","") -> ✓ | Q24: =IF(Bohol!Q24=TRUE,"✓","") -> ✓ | R24: =IF(Bohol!R24=TRUE,"✓","") | S24: =IF(Bohol!S24=TRUE,"✓","") | T24: =IF(Bohol!T24=TRUE,"✓","") -> ✓ | U24: =IF(Bohol!U24=TRUE,"✓","") | V24: 1.5 | W24: HIGH | X24: =IF(Bohol!X24=TRUE,"✓","") -> ✓ | Y24: =IF(Bohol!Y24=TRUE,"✓","") -> ✓ | Z24: =IF(Bohol!Z24=TRUE,"✓","") | AA24: =IF(Bohol!AA24=TRUE,"✓","") | AB24: =IF(Bohol!AB24=TRUE,"✓","") -> ✓ | AC24: 1.5 | AD24: HIGH
A25: AGRICULTURE FORESTRY AND FISHERY | B25: HORTICULTURE | C25: LANDSCAPE PLANTS (ORNAMENTAL AND CUT FLOWER) CULTURE, CARE AND MAINTENANCE | D25: PROPAGATE, PLANT CARE, MAINTAIN, LANDSCAPE AND MANAGE ORNAMENTAL PLANTS | E25: LANDSCAPE INSTALLATION AND MAINTENANCE (SOFTSCAPE) NC II | F25: With TR | G25: HIGH | H25: 1.5 | I25: =IF(Bohol!H25=TRUE,"✓","") -> ✓ | J25: =IF(Bohol!I25=TRUE,"✓","") -> ✓ | K25: =IF(Bohol!J25=TRUE,"✓","") | L25: =IF(Bohol!K25=TRUE,"✓","") | M25: =IF(Bohol!L25=TRUE,"✓","") -> ✓ | N25: =IF(Bohol!M25=TRUE,"✓","") | O25: HIGH | P25: =IF(Bohol!P25=TRUE,"✓","") -> ✓ | Q25: =IF(Bohol!Q25=TRUE,"✓","") -> ✓ | R25: =IF(Bohol!R25=TRUE,"✓","") | S25: =IF(Bohol!S25=TRUE,"✓","") | T25: =IF(Bohol!T25=TRUE,"✓","") -> ✓ | U25: =IF(Bohol!U25=TRUE,"✓","") | V25: 1.5 | W25: HIGH | X25: =IF(Bohol!X25=TRUE,"✓","") -> ✓ | Y25: =IF(Bohol!Y25=TRUE,"✓","") -> ✓ | Z25: =IF(Bohol!Z25=TRUE,"✓","") | AA25: =IF(Bohol!AA25=TRUE,"✓","") | AB25: =IF(Bohol!AB25=TRUE,"✓","") -> ✓ | AC25: 1.5 | AD25: HIGH
A26: AGRICULTURE FORESTRY AND FISHERY | B26: CROP PRODUCTION | C26: MAKE ORGANIC FERTILIZER & CONCOCTION | D26: PRODUCE ORGANIC FERTILIZER, SEEDS, RICE | E26: ORGANIC AGRICULTURE PRODUCTION NC II | F26: With TR | G26: HIGH | H26: 1 | I26: =IF(Bohol!H26=TRUE,"✓","") -> ✓ | J26: =IF(Bohol!I26=TRUE,"✓","") -> ✓ | K26: =IF(Bohol!J26=TRUE,"✓","") | L26: =IF(Bohol!K26=TRUE,"✓","") | M26: =IF(Bohol!L26=TRUE,"✓","") | N26: =IF(Bohol!M26=TRUE,"✓","") -> ✓ | O26: HIGH | P26: =IF(Bohol!P26=TRUE,"✓","") -> ✓ | Q26: =IF(Bohol!Q26=TRUE,"✓","") -> ✓ | R26: =IF(Bohol!R26=TRUE,"✓","") | S26: =IF(Bohol!S26=TRUE,"✓","") | T26: =IF(Bohol!T26=TRUE,"✓","") | U26: =IF(Bohol!U26=TRUE,"✓","") -> ✓ | V26: 1 | W26: HIGH | X26: =IF(Bohol!X26=TRUE,"✓","") -> ✓ | Y26: =IF(Bohol!Y26=TRUE,"✓","") -> ✓ | Z26: =IF(Bohol!Z26=TRUE,"✓","") | AA26: =IF(Bohol!AA26=TRUE,"✓","") | AB26: =IF(Bohol!AB26=TRUE,"✓","") | AC26: 1 | AD26: HIGH
A27: AGRICULTURE FORESTRY AND FISHERY | B27: CROP PRODUCTION | C27: MEDICINAL TEA PRODUCTION AND PROCESSING (TURMERIC,SALABAT,MORINGA,ETC.) | D27: PRODUCE AND PROCESS MEDICINAL PLANTS | E27: NONE | F27: New and Emerging | G27: HIGH | H27: 1 | I27: =IF(Bohol!H27=TRUE,"✓","") -> ✓ | J27: =IF(Bohol!I27=TRUE,"✓","") -> ✓ | K27: =IF(Bohol!J27=TRUE,"✓","") | L27: =IF(Bohol!K27=TRUE,"✓","") | M27: =IF(Bohol!L27=TRUE,"✓","") | N27: =IF(Bohol!M27=TRUE,"✓","") -> ✓ | O27: HIGH | P27: =IF(Bohol!P27=TRUE,"✓","") -> ✓ | Q27: =IF(Bohol!Q27=TRUE,"✓","") -> ✓ | R27: =IF(Bohol!R27=TRUE,"✓","") | S27: =IF(Bohol!S27=TRUE,"✓","") | T27: =IF(Bohol!T27=TRUE,"✓","") | U27: =IF(Bohol!U27=TRUE,"✓","") -> ✓ | V27: 1 | W27: HIGH | X27: =IF(Bohol!X27=TRUE,"✓","") -> ✓ | Y27: =IF(Bohol!Y27=TRUE,"✓","") -> ✓ | Z27: =IF(Bohol!Z27=TRUE,"✓","") | AA27: =IF(Bohol!AA27=TRUE,"✓","") | AB27: =IF(Bohol!AB27=TRUE,"✓","") | AC27: 1 | AD27: HIGH
A28: AGRICULTURE FORESTRY AND FISHERY | B28: AGRICULTURE | C28: REPAIR OF FARM MECHANICAL EQUIPMENT | D28: REPAIR FARM EQUIPMENT | E28: NONE | F28: New and Emerging | G28: HIGH | H28: 1 | I28: =IF(Bohol!H28=TRUE,"✓","") -> ✓ | J28: =IF(Bohol!I28=TRUE,"✓","") -> ✓ | K28: =IF(Bohol!J28=TRUE,"✓","") | L28: =IF(Bohol!K28=TRUE,"✓","") | M28: =IF(Bohol!L28=TRUE,"✓","") | N28: =IF(Bohol!M28=TRUE,"✓","") -> ✓ | O28: HIGH | P28: =IF(Bohol!P28=TRUE,"✓","") -> ✓ | Q28: =IF(Bohol!Q28=TRUE,"✓","") -> ✓ | R28: =IF(Bohol!R28=TRUE,"✓","") | S28: =IF(Bohol!S28=TRUE,"✓","") | T28: =IF(Bohol!T28=TRUE,"✓","") | U28: =IF(Bohol!U28=TRUE,"✓","") -> ✓ | V28: 1 | W28: HIGH | X28: =IF(Bohol!X28=TRUE,"✓","") -> ✓ | Y28: =IF(Bohol!Y28=TRUE,"✓","") -> ✓ | Z28: =IF(Bohol!Z28=TRUE,"✓","") | AA28: =IF(Bohol!AA28=TRUE,"✓","") | AB28: =IF(Bohol!AB28=TRUE,"✓","") | AC28: 1 | AD28: HIGH
A29: AGRICULTURE FORESTRY AND FISHERY | B29: CROP PRODUCTION | C29: RICE MACHINES OPERATORS | D29: OPERATE RICE MACHINERIES | E29: RICE MACHINERY OPERATIONS NC II | F29: With TR | G29: HIGH | H29: 1.5 | I29: =IF(Bohol!H29=TRUE,"✓","") | J29: =IF(Bohol!I29=TRUE,"✓","") -> ✓ | K29: =IF(Bohol!J29=TRUE,"✓","") | L29: =IF(Bohol!K29=TRUE,"✓","") | M29: =IF(Bohol!L29=TRUE,"✓","") -> ✓ | N29: =IF(Bohol!M29=TRUE,"✓","") | O29: HIGH | P29: =IF(Bohol!P29=TRUE,"✓","") | Q29: =IF(Bohol!Q29=TRUE,"✓","") -> ✓ | R29: =IF(Bohol!R29=TRUE,"✓","") | S29: =IF(Bohol!S29=TRUE,"✓","") | T29: =IF(Bohol!T29=TRUE,"✓","") -> ✓ | U29: =IF(Bohol!U29=TRUE,"✓","") | V29: 1.5 | W29: HIGH | X29: =IF(Bohol!X29=TRUE,"✓","") | Y29: =IF(Bohol!Y29=TRUE,"✓","") -> ✓ | Z29: =IF(Bohol!Z29=TRUE,"✓","") | AA29: =IF(Bohol!AA29=TRUE,"✓","") | AB29: =IF(Bohol!AB29=TRUE,"✓","") -> ✓ | AC29: 1.5 | AD29: HIGH
... A89: INFORMATION AND COMMUNICATION TECHNOLOGY | B89: CONTACT CENTER AND BPO | C89: CALL CENTER AGENTS | D89: ASSESS AND RESOLVE CLIENT CONCERN | E89: CONTACT CENTER SERVICES NC II | F89: With TR | G89: HIGH | H89: 1 | I89: =IF(Bohol!H89=TRUE,"✓","") -> ✓ | J89: =IF(Bohol!I89=TRUE,"✓","") -> ✓ | K89: =IF(Bohol!J89=TRUE,"✓","") | L89: =IF(Bohol!K89=TRUE,"✓","") | M89: =IF(Bohol!L89=TRUE,"✓","") | N89: =IF(Bohol!M89=TRUE,"✓","") -> ✓ | O89: HIGH | P89: =IF(Bohol!P89=TRUE,"✓","") -> ✓ | Q89: =IF(Bohol!Q89=TRUE,"✓","") -> ✓ | R89: =IF(Bohol!R89=TRUE,"✓","") | S89: =IF(Bohol!S89=TRUE,"✓","") | T89: =IF(Bohol!T89=TRUE,"✓","") | U89: =IF(Bohol!U89=TRUE,"✓","") -> ✓ | V89: 1 | W89: HIGH | X89: =IF(Bohol!X89=TRUE,"✓","") -> ✓ | Y89: =IF(Bohol!Y89=TRUE,"✓","") -> ✓ | Z89: =IF(Bohol!Z89=TRUE,"✓","") | AA89: =IF(Bohol!AA89=TRUE,"✓","") | AB89: =IF(Bohol!AB89=TRUE,"✓","") | AC89: 1 | AD89: HIGH
A90: INFORMATION AND COMMUNICATION TECHNOLOGY | B90: INFORMATION TECHNOLOGY SERVICES | C90: COMPUTER LITERATE AND PROFICIENT TO WINDOWS OS, APPLE OS, X, MS OFFICE AND GOOGLE APPLICATION | D90: PERFORM OFFICE APPLICATION SOFTWARES | E90: COMPUTER SYSTEMS SERVICING NC II | F90: With TR | G90: MEDIUM | I90: =IF(Bohol!H90=TRUE,"✓","") | J90: =IF(Bohol!I90=TRUE,"✓","") | K90: =IF(Bohol!J90=TRUE,"✓","") | L90: =IF(Bohol!K90=TRUE,"✓","") | M90: =IF(Bohol!L90=TRUE,"✓","") | N90: =IF(Bohol!M90=TRUE,"✓","") | P90: =IF(Bohol!P90=TRUE,"✓","") -> ✓ | Q90: =IF(Bohol!Q90=TRUE,"✓","") -> ✓ | R90: =IF(Bohol!R90=TRUE,"✓","") | S90: =IF(Bohol!S90=TRUE,"✓","") -> ✓ | T90: =IF(Bohol!T90=TRUE,"✓","") | U90: =IF(Bohol!U90=TRUE,"✓","") | V90: 2 | W90: MEDIUM | X90: =IF(Bohol!X90=TRUE,"✓","") -> ✓ | Y90: =IF(Bohol!Y90=TRUE,"✓","") -> ✓ | Z90: =IF(Bohol!Z90=TRUE,"✓","") | AA90: =IF(Bohol!AA90=TRUE,"✓","") -> ✓ | AB90: =IF(Bohol!AB90=TRUE,"✓","") | AC90: 2 | AD90: MEDIUM
A91: INFORMATION AND COMMUNICATION TECHNOLOGY | B91: CONTACT CENTER AND BPO | C91: CUSTOMER SERVICE REPRESENTATIVE | D91: ASSESS AND RESOLVE CUSTOMER CONCERN | E91: CONTACT CENTER SERVICES NC II | F91: With TR | G91: HIGH | H91: 1 | I91: =IF(Bohol!H91=TRUE,"✓","") -> ✓ | J91: =IF(Bohol!I91=TRUE,"✓","") -> ✓ | K91: =IF(Bohol!J91=TRUE,"✓","") | L91: =IF(Bohol!K91=TRUE,"✓","") | M91: =IF(Bohol!L91=TRUE,"✓","") | N91: =IF(Bohol!M91=TRUE,"✓","") -> ✓ | O91: HIGH | P91: =IF(Bohol!P91=TRUE,"✓","") -> ✓ | Q91: =IF(Bohol!Q91=TRUE,"✓","") -> ✓ | R91: =IF(Bohol!R91=TRUE,"✓","") | S91: =IF(Bohol!S91=TRUE,"✓","") | T91: =IF(Bohol!T91=TRUE,"✓","") | U91: =IF(Bohol!U91=TRUE,"✓","") -> ✓ | V91: 1 | W91: HIGH | X91: =IF(Bohol!X91=TRUE,"✓","") -> ✓ | Y91: =IF(Bohol!Y91=TRUE,"✓","") -> ✓ | Z91: =IF(Bohol!Z91=TRUE,"✓","") | AA91: =IF(Bohol!AA91=TRUE,"✓","") | AB91: =IF(Bohol!AB91=TRUE,"✓","") | AC91: 1 | AD91: HIGH
A92: INFORMATION AND COMMUNICATION TECHNOLOGY | B92: INFORMATION TECHNOLOGY SERVICES | C92: CYBER SECURITY | D92: MANAGE AND SECURE CYBERSPACE | E92: CYBER RISK ASSESSMENT LEVEL III | F92: With TR | G92: HIGH | I92: =IF(Bohol!H92=TRUE,"✓","") | J92: =IF(Bohol!I92=TRUE,"✓","") | K92: =IF(Bohol!J92=TRUE,"✓","") | L92: =IF(Bohol!K92=TRUE,"✓","") | M92: =IF(Bohol!L92=TRUE,"✓","") | N92: =IF(Bohol!M92=TRUE,"✓","") | P92: =IF(Bohol!P92=TRUE,"✓","") -> ✓ | Q92: =IF(Bohol!Q92=TRUE,"✓","") -> ✓ | R92: =IF(Bohol!R92=TRUE,"✓","") | S92: =IF(Bohol!S92=TRUE,"✓","") | T92: =IF(Bohol!T92=TRUE,"✓","") | U92: =IF(Bohol!U92=TRUE,"✓","") -> ✓ | V92: 1 | W92: HIGH | X92: =IF(Bohol!X92=TRUE,"✓","") | Y92: =IF(Bohol!Y92=TRUE,"✓","") | Z92: =IF(Bohol!Z92=TRUE,"✓","") | AA92: =IF(Bohol!AA92=TRUE,"✓","") | AB92: =IF(Bohol!AB92=TRUE,"✓","")
A93: INFORMATION AND COMMUNICATION TECHNOLOGY | B93: E-COMMERCE | C93: DATA ANALYST | D93: ANALYZE DATA HISTORICALS TO PROVIDE FORECAST | E93: DATA ANALYTICS LEVEL III | F93: With TR | G93: HIGH | H93: 1 | I93: =IF(Bohol!H93=TRUE,"✓","") -> ✓ | J93: =IF(Bohol!I93=TRUE,"✓","") -> ✓ | K93: =IF(Bohol!J93=TRUE,"✓","") | L93: =IF(Bohol!K93=TRUE,"✓","") | M93: =IF(Bohol!L93=TRUE,"✓","") | N93: =IF(Bohol!M93=TRUE,"✓","") -> ✓ | O93: HIGH | P93: =IF(Bohol!P93=TRUE,"✓","") -> ✓ | Q93: =IF(Bohol!Q93=TRUE,"✓","") -> ✓ | R93: =IF(Bohol!R93=TRUE,"✓","") | S93: =IF(Bohol!S93=TRUE,"✓","") | T93: =IF(Bohol!T93=TRUE,"✓","") | U93: =IF(Bohol!U93=TRUE,"✓","") -> ✓ | V93: 1 | W93: HIGH | X93: =IF(Bohol!X93=TRUE,"✓","") -> ✓ | Y93: =IF(Bohol!Y93=TRUE,"✓","") -> ✓ | Z93: =IF(Bohol!Z93=TRUE,"✓","") | AA93: =IF(Bohol!AA93=TRUE,"✓","") | AB93: =IF(Bohol!AB93=TRUE,"✓","") | AC93: 1 | AD93: HIGH
A94: INFORMATION AND COMMUNICATION TECHNOLOGY | B94: MULTIMEDIA SERVICES | C94: GRAPHIC DESIGNERS | D94: CREATE AND DESIGN GRAPHICS | E94: VISUAL GRAPHIC DESIGN NC III | F94: With TR | G94: HIGH | H94: 1 | I94: =IF(Bohol!H94=TRUE,"✓","") -> ✓ | J94: =IF(Bohol!I94=TRUE,"✓","") -> ✓ | K94: =IF(Bohol!J94=TRUE,"✓","") | L94: =IF(Bohol!K94=TRUE,"✓","") | M94: =IF(Bohol!L94=TRUE,"✓","") | N94: =IF(Bohol!M94=TRUE,"✓","") -> ✓ | O94: HIGH | P94: =IF(Bohol!P94=TRUE,"✓","") -> ✓ | Q94: =IF(Bohol!Q94=TRUE,"✓","") -> ✓ | R94: =IF(Bohol!R94=TRUE,"✓","") | S94: =IF(Bohol!S94=TRUE,"✓","") | T94: =IF(Bohol!T94=TRUE,"✓","") | U94: =IF(Bohol!U94=TRUE,"✓","") -> ✓ | V94: 1 | W94: HIGH | X94: =IF(Bohol!X94=TRUE,"✓","") -> ✓ | Y94: =IF(Bohol!Y94=TRUE,"✓","") -> ✓ | Z94: =IF(Bohol!Z94=TRUE,"✓","") | AA94: =IF(Bohol!AA94=TRUE,"✓","") | AB94: =IF(Bohol!AB94=TRUE,"✓","") | AC94: 1 | AD94: HIGH
A95: INFORMATION AND COMMUNICATION TECHNOLOGY | B95: INFORMATION TECHNOLOGY SERVICES | C95: HARDWARE DEPLOYMENT | D95: INSTALLATION OF ICT INFRASTRUCTURE | E95: COMPUTER SYSTEMS SERVICING NC II | F95: With TR | G95: HIGH | I95: =IF(Bohol!H95=TRUE,"✓","") | J95: =IF(Bohol!I95=TRUE,"✓","") | K95: =IF(Bohol!J95=TRUE,"✓","") | L95: =IF(Bohol!K95=TRUE,"✓","") | M95: =IF(Bohol!L95=TRUE,"✓","") | N95: =IF(Bohol!M95=TRUE,"✓","") | P95: =IF(Bohol!P95=TRUE,"✓","") -> ✓ | Q95: =IF(Bohol!Q95=TRUE,"✓","") -> ✓ | R95: =IF(Bohol!R95=TRUE,"✓","") | S95: =IF(Bohol!S95=TRUE,"✓","") | T95: =IF(Bohol!T95=TRUE,"✓","") -> ✓ | U95: =IF(Bohol!U95=TRUE,"✓","") | V95: 1.5 | W95: HIGH | X95: =IF(Bohol!X95=TRUE,"✓","") | Y95: =IF(Bohol!Y95=TRUE,"✓","") | Z95: =IF(Bohol!Z95=TRUE,"✓","") | AA95: =IF(Bohol!AA95=TRUE,"✓","") | AB95: =IF(Bohol!AB95=TRUE,"✓","")
A96: INFORMATION AND COMMUNICATION TECHNOLOGY | B96: INFORMATION TECHNOLOGY SERVICES | C96: IT SKILLED INDIVIDUAL | D96: PROVIDE ICT SERVICES | E96: COMPUTER SYSTEMS SERVICING NC II | F96: With TR | G96: HIGH | H96: 1 | I96: =IF(Bohol!H96=TRUE,"✓","") -> ✓ | J96: =IF(Bohol!I96=TRUE,"✓","") -> ✓ | K96: =IF(Bohol!J96=TRUE,"✓","") | L96: =IF(Bohol!K96=TRUE,"✓","") | M96: =IF(Bohol!L96=TRUE,"✓","") | N96: =IF(Bohol!M96=TRUE,"✓","") -> ✓ | O96: HIGH | P96: =IF(Bohol!P96=TRUE,"✓","") -> ✓ | Q96: =IF(Bohol!Q96=TRUE,"✓","") -> ✓ | R96: =IF(Bohol!R96=TRUE,"✓","") | S96: =IF(Bohol!S96=TRUE,"✓","") | T96: =IF(Bohol!T96=TRUE,"✓","") | U96: =IF(Bohol!U96=TRUE,"✓","") -> ✓ | V96: 1 | W96: HIGH | X96: =IF(Bohol!X96=TRUE,"✓","") -> ✓ | Y96: =IF(Bohol!Y96=TRUE,"✓","") -> ✓ | Z96: =IF(Bohol!Z96=TRUE,"✓","") | AA96: =IF(Bohol!AA96=TRUE,"✓","") | AB96: =IF(Bohol!AB96=TRUE,"✓","") | AC96: 1 | AD96: HIGH
A97: INFORMATION AND COMMUNICATION TECHNOLOGY | B97: MULTIMEDIA SERVICES | C97: MASTER OF PHOTOSHOP | D97: CREATE AND DESIGN GRAPHICS | E97: VISUAL GRAPHIC DESIGN NC III | F97: With TR | G97: HIGH | I97: =IF(Bohol!H97=TRUE,"✓","") | J97: =IF(Bohol!I97=TRUE,"✓","") | K97: =IF(Bohol!J97=TRUE,"✓","") | L97: =IF(Bohol!K97=TRUE,"✓","") | M97: =IF(Bohol!L97=TRUE,"✓","") | N97: =IF(Bohol!M97=TRUE,"✓","") | P97: =IF(Bohol!P97=TRUE,"✓","") -> ✓ | Q97: =IF(Bohol!Q97=TRUE,"✓","") -> ✓ | R97: =IF(Bohol!R97=TRUE,"✓","") | S97: =IF(Bohol!S97=TRUE,"✓","") | T97: =IF(Bohol!T97=TRUE,"✓","") -> ✓ | U97: =IF(Bohol!U97=TRUE,"✓","") | V97: 1.5 | W97: HIGH | X97: =IF(Bohol!X97=TRUE,"✓","") | Y97: =IF(Bohol!Y97=TRUE,"✓","") | Z97: =IF(Bohol!Z97=TRUE,"✓","") | AA97: =IF(Bohol!AA97=TRUE,"✓","") | AB97: =IF(Bohol!AB97=TRUE,"✓","")
A98: INFORMATION AND COMMUNICATION TECHNOLOGY | B98: INFORMATION TECHNOLOGY SERVICES | C98: NETWORK ENGINEER AND FIBER OPTIC SPECIALIST | D98: MANAGE AND INSTALL PREMISES/OUTSIDE PLANT COPPER OR FIBER NETWORKS | E98: TELECOM OSP INSTALLATION (FIBER OPTIC CABLE) NC II | F98: With TR | G98: MEDIUM | I98: =IF(Bohol!H98=TRUE,"✓","") | J98: =IF(Bohol!I98=TRUE,"✓","") | K98: =IF(Bohol!J98=TRUE,"✓","") | L98: =IF(Bohol!K98=TRUE,"✓","") | M98: =IF(Bohol!L98=TRUE,"✓","") | N98: =IF(Bohol!M98=TRUE,"✓","") | P98: =IF(Bohol!P98=TRUE,"✓","") -> ✓ | Q98: =IF(Bohol!Q98=TRUE,"✓","") -> ✓ | R98: =IF(Bohol!R98=TRUE,"✓","") | S98: =IF(Bohol!S98=TRUE,"✓","") -> ✓ | T98: =IF(Bohol!T98=TRUE,"✓","") | U98: =IF(Bohol!U98=TRUE,"✓","") | V98: 2 | W98: MEDIUM | X98: =IF(Bohol!X98=TRUE,"✓","") -> ✓ | Y98: =IF(Bohol!Y98=TRUE,"✓","") -> ✓ | Z98: =IF(Bohol!Z98=TRUE,"✓","") | AA98: =IF(Bohol!AA98=TRUE,"✓","") -> ✓ | AB98: =IF(Bohol!AB98=TRUE,"✓","") | AC98: 2 | AD98: MEDIUM
A99: INFORMATION AND COMMUNICATION TECHNOLOGY | B99: INFORMATION TECHNOLOGY SERVICES | C99: SENIOR DRUPAL DEVELOPER | D99: CONCEPTUALIZE, DESIGN, DEPLOY AND MONITOR WEBSITE | E99: WEB DEVELOPMENT NC III | F99: With TR | G99: MEDIUM | H99: 2 | I99: =IF(Bohol!H99=TRUE,"✓","") -> ✓ | J99: =IF(Bohol!I99=TRUE,"✓","") -> ✓ | K99: =IF(Bohol!J99=TRUE,"✓","") | L99: =IF(Bohol!K99=TRUE,"✓","") -> ✓ | M99: =IF(Bohol!L99=TRUE,"✓","") | N99: =IF(Bohol!M99=TRUE,"✓","") | O99: MEDIUM | P99: =IF(Bohol!P99=TRUE,"✓","") -> ✓ | Q99: =IF(Bohol!Q99=TRUE,"✓","") -> ✓ | R99: =IF(Bohol!R99=TRUE,"✓","") | S99: =IF(Bohol!S99=TRUE,"✓","") -> ✓ | T99: =IF(Bohol!T99=TRUE,"✓","") | U99: =IF(Bohol!U99=TRUE,"✓","") | V99: 2 | W99: MEDIUM | X99: =IF(Bohol!X99=TRUE,"✓","") -> ✓ | Y99: =IF(Bohol!Y99=TRUE,"✓","") -> ✓ | Z99: =IF(Bohol!Z99=TRUE,"✓","") | AA99: =IF(Bohol!AA99=TRUE,"✓","") -> ✓ | AB99: =IF(Bohol!AB99=TRUE,"✓","") | AC99: 2 | AD99: MEDIUM
A100: INFORMATION AND COMMUNICATION TECHNOLOGY | B100: INFORMATION TECHNOLOGY SERVICES | C100: SENIOR SWIFT DEVELOPER | D100: CONCEPTUALIZE, DESIGN, DEPLOY AND MONITOR APPLICATIONS (EITHER WEB, DESKTOP OR MOBILE) | E100: WEB DEVELOPMENT NC III | F100: With TR | G100: HIGH | H100: 1 | I100: =IF(Bohol!H100=TRUE,"✓","") -> ✓ | J100: =IF(Bohol!I100=TRUE,"✓","") -> ✓ | K100: =IF(Bohol!J100=TRUE,"✓","") | L100: =IF(Bohol!K100=TRUE,"✓","") | M100: =IF(Bohol!L100=TRUE,"✓","") | N100: =IF(Bohol!M100=TRUE,"✓","") -> ✓ | O100: HIGH | P100: =IF(Bohol!P100=TRUE,"✓","") -> ✓ | Q100: =IF(Bohol!Q100=TRUE,"✓","") -> ✓ | R100: =IF(Bohol!R100=TRUE,"✓","") | S100: =IF(Bohol!S100=TRUE,"✓","") | T100: =IF(Bohol!T100=TRUE,"✓","") | U100: =IF(Bohol!U100=TRUE,"✓","") -> ✓ | V100: 1 | W100: HIGH | X100: =IF(Bohol!X100=TRUE,"✓","") -> ✓ | Y100: =IF(Bohol!Y100=TRUE,"✓","") -> ✓ | Z100: =IF(Bohol!Z100=TRUE,"✓","") | AA100: =IF(Bohol!AA100=TRUE,"✓","") | AB100: =IF(Bohol!AB100=TRUE,"✓","") | AC100: 1 | AD100: HIGH
A101: INFORMATION AND COMMUNICATION TECHNOLOGY | B101: E-COMMERCE | C101: SOCIAL MEDIA MANAGING | D101: MANAGE SOCIAL MEDIA ACCOUNT | E101: CONTENT CREATION (SOCIAL MEDIA) LEVEL III | F101: With TR | G101: HIGH | H101: 1.5 | I101: =IF(Bohol!H101=TRUE,"✓","") -> ✓ | J101: =IF(Bohol!I101=TRUE,"✓","") -> ✓ | K101: =IF(Bohol!J101=TRUE,"✓","") | L101: =IF(Bohol!K101=TRUE,"✓","") | M101: =IF(Bohol!L101=TRUE,"✓","") -> ✓ | N101: =IF(Bohol!M101=TRUE,"✓","") | O101: HIGH | P101: =IF(Bohol!P101=TRUE,"✓","") -> ✓ | Q101: =IF(Bohol!Q101=TRUE,"✓","") -> ✓ | R101: =IF(Bohol!R101=TRUE,"✓","") | S101: =IF(Bohol!S101=TRUE,"✓","") | T101: =IF(Bohol!T101=TRUE,"✓","") | U101: =IF(Bohol!U101=TRUE,"✓","") -> ✓ | V101: 1 | W101: HIGH | X101: =IF(Bohol!X101=TRUE,"✓","") -> ✓ | Y101: =IF(Bohol!Y101=TRUE,"✓","") -> ✓ | Z101: =IF(Bohol!Z101=TRUE,"✓","") | AA101: =IF(Bohol!AA101=TRUE,"✓","") | AB101: =IF(Bohol!AB101=TRUE,"✓","") | AC101: 1 | AD101: HIGH
A102: INFORMATION AND COMMUNICATION TECHNOLOGY | B102: INFORMATION TECHNOLOGY SERVICES | C102: STRUCTURED CABLING | D102: PROVIDE PREMISES CABLING (NETWORK) | E102: COMPUTER SYSTEMS SERVICING NC II | F102: With TR | G102: HIGH | H102: 1.5 | I102: =IF(Bohol!H102=TRUE,"✓","") -> ✓ | J102: =IF(Bohol!I102=TRUE,"✓","") -> ✓ | K102: =IF(Bohol!J102=TRUE,"✓","") | L102: =IF(Bohol!K102=TRUE,"✓","") | M102: =IF(Bohol!L102=TRUE,"✓","") -> ✓ | N102: =IF(Bohol!M102=TRUE,"✓","") | O102: HIGH | P102: =IF(Bohol!P102=TRUE,"✓","") -> ✓ | Q102: =IF(Bohol!Q102=TRUE,"✓","") -> ✓ | R102: =IF(Bohol!R102=TRUE,"✓","") | S102: =IF(Bohol!S102=TRUE,"✓","") | T102: =IF(Bohol!T102=TRUE,"✓","") -> ✓ | U102: =IF(Bohol!U102=TRUE,"✓","") | V102: 1.5 | W102: HIGH | X102: =IF(Bohol!X102=TRUE,"✓","") -> ✓ | Y102: =IF(Bohol!Y102=TRUE,"✓","") -> ✓ | Z102: =IF(Bohol!Z102=TRUE,"✓","") | AA102: =IF(Bohol!AA102=TRUE,"✓","") | AB102: =IF(Bohol!AB102=TRUE,"✓","") -> ✓ | AC102: 1.5 | AD102: HIGH
A103: INFORMATION AND COMMUNICATION TECHNOLOGY | B103: MULTIMEDIA SERVICES | C103: VIDEO EDITOR | D103: CREATE, ENHANCE, SEQUENCE AND EDIT VIDEOS | E103: FILM AND VIDEO POSTPRODUCTION NC III | F103: With TR | G103: HIGH | H103: 1.5 | I103: =IF(Bohol!H103=TRUE,"✓","") -> ✓ | J103: =IF(Bohol!I103=TRUE,"✓","") -> ✓ | K103: =IF(Bohol!J103=TRUE,"✓","") | L103: =IF(Bohol!K103=TRUE,"✓","") | M103: =IF(Bohol!L103=TRUE,"✓","") -> ✓ | N103: =IF(Bohol!M103=TRUE,"✓","") | O103: HIGH | P103: =IF(Bohol!P103=TRUE,"✓","") -> ✓ | Q103: =IF(Bohol!Q103=TRUE,"✓","") -> ✓ | R103: =IF(Bohol!R103=TRUE,"✓","") | S103: =IF(Bohol!S103=TRUE,"✓","") | T103: =IF(Bohol!T103=TRUE,"✓","") -> ✓ | U103: =IF(Bohol!U103=TRUE,"✓","") | V103: 1.5 | W103: HIGH | X103: =IF(Bohol!X103=TRUE,"✓","") -> ✓ | Y103: =IF(Bohol!Y103=TRUE,"✓","") -> ✓ | Z103: =IF(Bohol!Z103=TRUE,"✓","") | AA103: =IF(Bohol!AA103=TRUE,"✓","") | AB103: =IF(Bohol!AB103=TRUE,"✓","") -> ✓ | AC103: 1.5 | AD103: HIGH
A104: INFORMATION AND COMMUNICATION TECHNOLOGY | B104: CONTACT CENTER AND BPO | C104: VIRTUAL ASSISTANT DEVELOPING | D104: PROVIDE VIRTUAL CLERICAL SERVICES | E104: VIRTUAL ASSISTANT SERVICES LEVEL III | F104: With TR | G104: MEDIUM | H104: 2 | I104: =IF(Bohol!H104=TRUE,"✓","") | J104: =IF(Bohol!I104=TRUE,"✓","") -> ✓ | K104: =IF(Bohol!J104=TRUE,"✓","") | L104: =IF(Bohol!K104=TRUE,"✓","") -> ✓ | M104: =IF(Bohol!L104=TRUE,"✓","") | N104: =IF(Bohol!M104=TRUE,"✓","") | O104: MEDIUM | P104: =IF(Bohol!P104=TRUE,"✓","") | Q104: =IF(Bohol!Q104=TRUE,"✓","") -> ✓ | R104: =IF(Bohol!R104=TRUE,"✓","") | S104: =IF(Bohol!S104=TRUE,"✓","") -> ✓ | T104: =IF(Bohol!T104=TRUE,"✓","") | U104: =IF(Bohol!U104=TRUE,"✓","") | V104: 2 | W104: MEDIUM | X104: =IF(Bohol!X104=TRUE,"✓","") | Y104: =IF(Bohol!Y104=TRUE,"✓","") -> ✓ | Z104: =IF(Bohol!Z104=TRUE,"✓","") | AA104: =IF(Bohol!AA104=TRUE,"✓","") -> ✓ | AB104: =IF(Bohol!AB104=TRUE,"✓","") | AC104: 2 | AD104: MEDIUM
A105: INFORMATION AND COMMUNICATION TECHNOLOGY | B105: MULTIMEDIA SERVICES | C105: VISUAL GRAPHIC DESIGNER | D105: CREATE AND DESIGN GRAPHICS | E105: VISUAL GRAPHIC DESIGN NC III | F105: With TR | G105: HIGH | H105: 1 | I105: =IF(Bohol!H105=TRUE,"✓","") -> ✓ | J105: =IF(Bohol!I105=TRUE,"✓","") -> ✓ | K105: =IF(Bohol!J105=TRUE,"✓","") | L105: =IF(Bohol!K105=TRUE,"✓","") | M105: =IF(Bohol!L105=TRUE,"✓","") | N105: =IF(Bohol!M105=TRUE,"✓","") -> ✓ | O105: HIGH | P105: =IF(Bohol!P105=TRUE,"✓","") | Q105: =IF(Bohol!Q105=TRUE,"✓","") | R105: =IF(Bohol!R105=TRUE,"✓","") | S105: =IF(Bohol!S105=TRUE,"✓","") | T105: =IF(Bohol!T105=TRUE,"✓","") | U105: =IF(Bohol!U105=TRUE,"✓","") | X105: =IF(Bohol!X105=TRUE,"✓","") -> ✓ | Y105: =IF(Bohol!Y105=TRUE,"✓","") -> ✓ | Z105: =IF(Bohol!Z105=TRUE,"✓","") | AA105: =IF(Bohol!AA105=TRUE,"✓","") | AB105: =IF(Bohol!AB105=TRUE,"✓","") | AC105: 1 | AD105: HIGH
A106: INFORMATION AND COMMUNICATION TECHNOLOGY | B106: INFORMATION TECHNOLOGY SERVICES | C106: WEB DEVELOPER AND DESIGNER | D106: CONCEPTUALIZE, DESIGN, DEPLOY AND MONITOR WEBSITE | E106: WEB DEVELOPMENT NC III | F106: With TR | G106: MEDIUM | H106: 2 | I106: =IF(Bohol!H106=TRUE,"✓","") -> ✓ | J106: =IF(Bohol!I106=TRUE,"✓","") -> ✓ | K106: =IF(Bohol!J106=TRUE,"✓","") | L106: =IF(Bohol!K106=TRUE,"✓","") -> ✓ | M106: =IF(Bohol!L106=TRUE,"✓","") | N106: =IF(Bohol!M106=TRUE,"✓","") | O106: MEDIUM | P106: =IF(Bohol!P106=TRUE,"✓","") -> ✓ | Q106: =IF(Bohol!Q106=TRUE,"✓","") -> ✓ | R106: =IF(Bohol!R106=TRUE,"✓","") | S106: =IF(Bohol!S106=TRUE,"✓","") -> ✓ | T106: =IF(Bohol!T106=TRUE,"✓","") | U106: =IF(Bohol!U106=TRUE,"✓","") | V106: 2 | W106: MEDIUM | X106: =IF(Bohol!X106=TRUE,"✓","") -> ✓ | Y106: =IF(Bohol!Y106=TRUE,"✓","") -> ✓ | Z106: =IF(Bohol!Z106=TRUE,"✓","") | AA106: =IF(Bohol!AA106=TRUE,"✓","") -> ✓ | AB106: =IF(Bohol!AB106=TRUE,"✓","") | AC106: 2 | AD106: MEDIUM
A107: OTHERS | B107: FURNITURE/SOUVENIRS/UPCYCLING | C107: PRODUCT DESIGNER | D107: TO DESIGN PRODUCT OUT OF WOOD AND BAMBOO/SOUVENIR AND UPCYCLED PRODUCTS | E107: WOOD CARVING LEVEL II | F107: With CS | G107: HIGH | H107: 1 | I107: =IF(Bohol!H107=TRUE,"✓","") -> ✓ | J107: =IF(Bohol!I107=TRUE,"✓","") -> ✓ | K107: =IF(Bohol!J107=TRUE,"✓","") | L107: =IF(Bohol!K107=TRUE,"✓","") | M107: =IF(Bohol!L107=TRUE,"✓","") | N107: =IF(Bohol!M107=TRUE,"✓","") -> ✓ | O107: HIGH | P107: =IF(Bohol!P107=TRUE,"✓","") -> ✓ | Q107: =IF(Bohol!Q107=TRUE,"✓","") -> ✓ | R107: =IF(Bohol!R107=TRUE,"✓","") | S107: =IF(Bohol!S107=TRUE,"✓","") | T107: =IF(Bohol!T107=TRUE,"✓","") | U107: =IF(Bohol!U107=TRUE,"✓","") -> ✓ | V107: 1 | W107: HIGH | X107: =IF(Bohol!X107=TRUE,"✓","") -> ✓ | Y107: =IF(Bohol!Y107=TRUE,"✓","") -> ✓ | Z107: =IF(Bohol!Z107=TRUE,"✓","") | AA107: =IF(Bohol!AA107=TRUE,"✓","") | AB107: =IF(Bohol!AB107=TRUE,"✓","") | AC107: 1 | AD107: HIGH
A108: OTHERS | B108: LANGUAGE EDUCATION AND INSTRUCTION | C108: SKILL IN FOREIGN LANGUAGE | D108: TO TEACH ENGLISH LANGUAGE | E108: LANGUAGE B1 LEVEL | F108: With CS | G108: HIGH | H108: 1.5 | I108: =IF(Bohol!H108=TRUE,"✓","") | J108: =IF(Bohol!I108=TRUE,"✓","") -> ✓ | K108: =IF(Bohol!J108=TRUE,"✓","") | L108: =IF(Bohol!K108=TRUE,"✓","") | M108: =IF(Bohol!L108=TRUE,"✓","") -> ✓ | N108: =IF(Bohol!M108=TRUE,"✓","") | O108: HIGH | P108: =IF(Bohol!P108=TRUE,"✓","") | Q108: =IF(Bohol!Q108=TRUE,"✓","") -> ✓ | R108: =IF(Bohol!R108=TRUE,"✓","") | S108: =IF(Bohol!S108=TRUE,"✓","") | T108: =IF(Bohol!T108=TRUE,"✓","") -> ✓ | U108: =IF(Bohol!U108=TRUE,"✓","") | V108: 1.5 | W108: HIGH | X108: =IF(Bohol!X108=TRUE,"✓","") | Y108: =IF(Bohol!Y108=TRUE,"✓","") -> ✓ | Z108: =IF(Bohol!Z108=TRUE,"✓","") | AA108: =IF(Bohol!AA108=TRUE,"✓","") | AB108: =IF(Bohol!AB108=TRUE,"✓","") -> ✓ | AC108: 1.5 | AD108: HIGH
A109: OTHERS | B109: CULTURAL EXCHANGE AND INTERNATIONAL RELATION | C109: SKILL IN JAPANESE LANGUAGE | D109: TO STUDY AND WORK LOCAL/ABROAD | E109: LANGUAGE A1 LEVEL | F109: With CS | G109: HIGH | H109: 1.5 | I109: =IF(Bohol!H109=TRUE,"✓","") -> ✓ | J109: =IF(Bohol!I109=TRUE,"✓","") -> ✓ | K109: =IF(Bohol!J109=TRUE,"✓","") | L109: =IF(Bohol!K109=TRUE,"✓","") | M109: =IF(Bohol!L109=TRUE,"✓","") -> ✓ | N109: =IF(Bohol!M109=TRUE,"✓","") | O109: HIGH | P109: =IF(Bohol!P109=TRUE,"✓","") -> ✓ | Q109: =IF(Bohol!Q109=TRUE,"✓","") -> ✓ | R109: =IF(Bohol!R109=TRUE,"✓","") | S109: =IF(Bohol!S109=TRUE,"✓","") | T109: =IF(Bohol!T109=TRUE,"✓","") -> ✓ | U109: =IF(Bohol!U109=TRUE,"✓","") | V109: 1.5 | W109: HIGH | X109: =IF(Bohol!X109=TRUE,"✓","") -> ✓ | Y109: =IF(Bohol!Y109=TRUE,"✓","") -> ✓ | Z109: =IF(Bohol!Z109=TRUE,"✓","") | AA109: =IF(Bohol!AA109=TRUE,"✓","") | AB109: =IF(Bohol!AB109=TRUE,"✓","") -> ✓ | AC109: 1.5 | AD109: HIGH
A110: OTHERS | B110: LANGUAGE EDUCATION AND INSTRUCTION | C110: SKILL IN KOREAN LANGUAGE | D110: TO STUDY AND WORK LOCAL/ABROAD | E110: LANGUAGE A1 LEVEL | F110: With CS | G110: MEDIUM | H110: 2 | I110: =IF(Bohol!H110=TRUE,"✓","") -> ✓ | J110: =IF(Bohol!I110=TRUE,"✓","") -> ✓ | K110: =IF(Bohol!J110=TRUE,"✓","") | L110: =IF(Bohol!K110=TRUE,"✓","") -> ✓ | M110: =IF(Bohol!L110=TRUE,"✓","") | N110: =IF(Bohol!M110=TRUE,"✓","") | O110: MEDIUM | P110: =IF(Bohol!P110=TRUE,"✓","") -> ✓ | Q110: =IF(Bohol!Q110=TRUE,"✓","") -> ✓ | R110: =IF(Bohol!R110=TRUE,"✓","") | S110: =IF(Bohol!S110=TRUE,"✓","") -> ✓ | T110: =IF(Bohol!T110=TRUE,"✓","") | U110: =IF(Bohol!U110=TRUE,"✓","") | V110: 2 | W110: MEDIUM | X110: =IF(Bohol!X110=TRUE,"✓","") -> ✓ | Y110: =IF(Bohol!Y110=TRUE,"✓","") -> ✓ | Z110: =IF(Bohol!Z110=TRUE,"✓","") | AA110: =IF(Bohol!AA110=TRUE,"✓","") -> ✓ | AB110: =IF(Bohol!AB110=TRUE,"✓","") | AC110: 2 | AD110: MEDIUM
A111: OTHERS | B111: MARKETING | C111: SOCIAL MEDIA MANAGER/CONTENT CREATOR | D111: TO CREATE CURATE, AND ANALYZE SOCIAL MEDIA CONTENTS | E111: CONTENT CREATION (SOCIAL MEDIA) LEVEL III | F111: With CS | G111: MEDIUM | H111: 2 | I111: =IF(Bohol!H111=TRUE,"✓","") | J111: =IF(Bohol!I111=TRUE,"✓","") -> ✓ | K111: =IF(Bohol!J111=TRUE,"✓","") | L111: =IF(Bohol!K111=TRUE,"✓","") -> ✓ | M111: =IF(Bohol!L111=TRUE,"✓","") | N111: =IF(Bohol!M111=TRUE,"✓","") | O111: MEDIUM | P111: =IF(Bohol!P111=TRUE,"✓","") | Q111: =IF(Bohol!Q111=TRUE,"✓","") -> ✓ | R111: =IF(Bohol!R111=TRUE,"✓","") | S111: =IF(Bohol!S111=TRUE,"✓","") -> ✓ | T111: =IF(Bohol!T111=TRUE,"✓","") | U111: =IF(Bohol!U111=TRUE,"✓","") | V111: 2 | W111: MEDIUM | X111: =IF(Bohol!X111=TRUE,"✓","") | Y111: =IF(Bohol!Y111=TRUE,"✓","") -> ✓ | Z111: =IF(Bohol!Z111=TRUE,"✓","") | AA111: =IF(Bohol!AA111=TRUE,"✓","") -> ✓ | AB111: =IF(Bohol!AB111=TRUE,"✓","") | AC111: 2 | AD111: MEDIUM
A112: SOCIAL, COMMUNITY DEVELOPMENT AND OTHER SERVICES | B112: HAIRSTYLING AND HAIRCARE | C112: BEAUTICIAN SPECIALIST | D112: TO STYLE, CUT, COLOR AND TREAT HAIR | E112: HAIRDRESSING NC II | F112: With TR | G112: HIGH | H112: 1 | I112: =IF(Bohol!H112=TRUE,"✓","") -> ✓ | J112: =IF(Bohol!I112=TRUE,"✓","") -> ✓ | K112: =IF(Bohol!J112=TRUE,"✓","") | L112: =IF(Bohol!K112=TRUE,"✓","") | M112: =IF(Bohol!L112=TRUE,"✓","") | N112: =IF(Bohol!M112=TRUE,"✓","") -> ✓ | O112: HIGH | P112: =IF(Bohol!P112=TRUE,"✓","") | Q112: =IF(Bohol!Q112=TRUE,"✓","") -> ✓ | R112: =IF(Bohol!R112=TRUE,"✓","") | S112: =IF(Bohol!S112=TRUE,"✓","") | T112: =IF(Bohol!T112=TRUE,"✓","") | U112: =IF(Bohol!U112=TRUE,"✓","") -> ✓ | V112: 1 | W112: HIGH | X112: =IF(Bohol!X112=TRUE,"✓","") -> ✓ | Y112: =IF(Bohol!Y112=TRUE,"✓","") -> ✓ | Z112: =IF(Bohol!Z112=TRUE,"✓","") | AA112: =IF(Bohol!AA112=TRUE,"✓","") | AB112: =IF(Bohol!AB112=TRUE,"✓","") | AC112: 1 | AD112: HIGH
A113: SOCIAL, COMMUNITY DEVELOPMENT AND OTHER SERVICES | B113: COLLECTION AND DISBURSMENT | C113: BOOKKEEPING | D113: TO COLLECT AND MONITOR CASH FLOW/RECEIPT | E113: BOOKKEEPING NC III | F113: With TR | G113: HIGH | H113: 1.5 | I113: =IF(Bohol!H113=TRUE,"✓","") -> ✓ | J113: =IF(Bohol!I113=TRUE,"✓","") -> ✓ | K113: =IF(Bohol!J113=TRUE,"✓","") | L113: =IF(Bohol!K113=TRUE,"✓","") | M113: =IF(Bohol!L113=TRUE,"✓","") -> ✓ | N113: =IF(Bohol!M113=TRUE,"✓","") | O113: HIGH | P113: =IF(Bohol!P113=TRUE,"✓","") -> ✓ | Q113: =IF(Bohol!Q113=TRUE,"✓","") -> ✓ | R113: =IF(Bohol!R113=TRUE,"✓","") | S113: =IF(Bohol!S113=TRUE,"✓","") | T113: =IF(Bohol!T113=TRUE,"✓","") -> ✓ | U113: =IF(Bohol!U113=TRUE,"✓","") | V113: 1.5 | W113: HIGH | X113: =IF(Bohol!X113=TRUE,"✓","") -> ✓ | Y113: =IF(Bohol!Y113=TRUE,"✓","") -> ✓ | Z113: =IF(Bohol!Z113=TRUE,"✓","") | AA113: =IF(Bohol!AA113=TRUE,"✓","") | AB113: =IF(Bohol!AB113=TRUE,"✓","") -> ✓ | AC113: 1.5 | AD113: HIGH
A114: SOCIAL, COMMUNITY DEVELOPMENT AND OTHER SERVICES | B114: VIRTUAL ASSISTANT | C114: BOOKKEEPING | D114: TO ASSIST IN THE PREPARATION OF PAYROLLS AND FINANCIAL REPORTS | E114: VIRTUAL ASSISTANT SERVICES LEVEL III | F114: With CS | G114: MEDIUM | H114: 2 | I114: =IF(Bohol!H114=TRUE,"✓","") | J114: =IF(Bohol!I114=TRUE,"✓","") -> ✓ | K114: =IF(Bohol!J114=TRUE,"✓","") | L114: =IF(Bohol!K114=TRUE,"✓","") -> ✓ | M114: =IF(Bohol!L114=TRUE,"✓","") | N114: =IF(Bohol!M114=TRUE,"✓","") | O114: MEDIUM | P114: =IF(Bohol!P114=TRUE,"✓","") | Q114: =IF(Bohol!Q114=TRUE,"✓","") -> ✓ | R114: =IF(Bohol!R114=TRUE,"✓","") | S114: =IF(Bohol!S114=TRUE,"✓","") -> ✓ | T114: =IF(Bohol!T114=TRUE,"✓","") | U114: =IF(Bohol!U114=TRUE,"✓","") | V114: 2 | W114: MEDIUM | X114: =IF(Bohol!X114=TRUE,"✓","") | Y114: =IF(Bohol!Y114=TRUE,"✓","") -> ✓ | Z114: =IF(Bohol!Z114=TRUE,"✓","") | AA114: =IF(Bohol!AA114=TRUE,"✓","") -> ✓ | AB114: =IF(Bohol!AB114=TRUE,"✓","") | AC114: 2 | AD114: MEDIUM
A115: SOCIAL, COMMUNITY DEVELOPMENT AND OTHER SERVICES | B115: BASIC BRAZILIAN WAXING | C115: BRAZILIAN WAX | D115: TO CATER TO DIFFERENT CUSTOMER PREFERENCES AND NEEDS IN THE FIELD OF HAIR REMOVAL SERVICES | E115: BEAUTY CARE (SKIN CARE) SERVICES NC II | F115: With TR | G115: MEDIUM | H115: 2 | I115: =IF(Bohol!H115=TRUE,"✓","") | J115: =IF(Bohol!I115=TRUE,"✓","") -> ✓ | K115: =IF(Bohol!J115=TRUE,"✓","") | L115: =IF(Bohol!K115=TRUE,"✓","") -> ✓ | M115: =IF(Bohol!L115=TRUE,"✓","") | N115: =IF(Bohol!M115=TRUE,"✓","") | O115: MEDIUM | P115: =IF(Bohol!P115=TRUE,"✓","") | Q115: =IF(Bohol!Q115=TRUE,"✓","") -> ✓ | R115: =IF(Bohol!R115=TRUE,"✓","") | S115: =IF(Bohol!S115=TRUE,"✓","") -> ✓ | T115: =IF(Bohol!T115=TRUE,"✓","") | U115: =IF(Bohol!U115=TRUE,"✓","") | V115: 2 | W115: MEDIUM | X115: =IF(Bohol!X115=TRUE,"✓","") | Y115: =IF(Bohol!Y115=TRUE,"✓","") -> ✓ | Z115: =IF(Bohol!Z115=TRUE,"✓","") | AA115: =IF(Bohol!AA115=TRUE,"✓","") -> ✓ | AB115: =IF(Bohol!AB115=TRUE,"✓","") | AC115: 2 | AD115: MEDIUM
A116: SOCIAL, COMMUNITY DEVELOPMENT AND OTHER SERVICES | B116: SKINCARE AND FACIAL TREATMENT | C116: FACIAL | D116: TO EXFOLIATE AND REMOVE IMPURITIES, BLACKHEADS AND CLOGGED PORES OF SKIN | E116: BEAUTY CARE (SKIN CARE) SERVICES NC II | F116: With TR | G116: MEDIUM | H116: 2 | I116: =IF(Bohol!H116=TRUE,"✓","") | J116: =IF(Bohol!I116=TRUE,"✓","") -> ✓ | K116: =IF(Bohol!J116=TRUE,"✓","") | L116: =IF(Bohol!K116=TRUE,"✓","") -> ✓ | M116: =IF(Bohol!L116=TRUE,"✓","") | N116: =IF(Bohol!M116=TRUE,"✓","") | O116: MEDIUM | P116: =IF(Bohol!P116=TRUE,"✓","") | Q116: =IF(Bohol!Q116=TRUE,"✓","") -> ✓ | R116: =IF(Bohol!R116=TRUE,"✓","") | S116: =IF(Bohol!S116=TRUE,"✓","") -> ✓ | T116: =IF(Bohol!T116=TRUE,"✓","") | U116: =IF(Bohol!U116=TRUE,"✓","") | V116: 2 | W116: MEDIUM | X116: =IF(Bohol!X116=TRUE,"✓","") | Y116: =IF(Bohol!Y116=TRUE,"✓","") -> ✓ | Z116: =IF(Bohol!Z116=TRUE,"✓","") | AA116: =IF(Bohol!AA116=TRUE,"✓","") -> ✓ | AB116: =IF(Bohol!AB116=TRUE,"✓","") | AC116: 2 | AD116: MEDIUM
A117: SOCIAL, COMMUNITY DEVELOPMENT AND OTHER SERVICES | B117: FACIAL MASSAGE AND RELAXATION TREATMENTS | C117: FACIAL MASSAGE | D117: TO OFFER THERAPEUTIC MASSAGE AND RELAX FACIAL MUSCLES | E117: BEAUTY CARE (SKIN CARE) SERVICES NC II | F117: With TR | G117: MEDIUM | H117: 2 | I117: =IF(Bohol!H117=TRUE,"✓","") | J117: =IF(Bohol!I117=TRUE,"✓","") -> ✓ | K117: =IF(Bohol!J117=TRUE,"✓","") | L117: =IF(Bohol!K117=TRUE,"✓","") -> ✓ | M117: =IF(Bohol!L117=TRUE,"✓","") | N117: =IF(Bohol!M117=TRUE,"✓","") | O117: MEDIUM | P117: =IF(Bohol!P117=TRUE,"✓","") | Q117: =IF(Bohol!Q117=TRUE,"✓","") -> ✓ | R117: =IF(Bohol!R117=TRUE,"✓","") | S117: =IF(Bohol!S117=TRUE,"✓","") -> ✓ | T117: =IF(Bohol!T117=TRUE,"✓","") | U117: =IF(Bohol!U117=TRUE,"✓","") | V117: 2 | W117: MEDIUM | X117: =IF(Bohol!X117=TRUE,"✓","") | Y117: =IF(Bohol!Y117=TRUE,"✓","") -> ✓ | Z117: =IF(Bohol!Z117=TRUE,"✓","") | AA117: =IF(Bohol!AA117=TRUE,"✓","") -> ✓ | AB117: =IF(Bohol!AB117=TRUE,"✓","") | AC117: 2 | AD117: MEDIUM
... A123: TOURISM (HOTEL AND RESTAURANT) | B123: FOOD AND BEVERAGES | C123: BARTENDING (BARTENDER) | D123: PREPARE FUSION OF DRINKS | E123: BARTENDING NC II | F123: With TR | G123: HIGH | H123: 1.5 | I123: =IF(Bohol!H123=TRUE,"✓","") -> ✓ | J123: =IF(Bohol!I123=TRUE,"✓","") -> ✓ | K123: =IF(Bohol!J123=TRUE,"✓","") | L123: =IF(Bohol!K123=TRUE,"✓","") | M123: =IF(Bohol!L123=TRUE,"✓","") -> ✓ | N123: =IF(Bohol!M123=TRUE,"✓","") | O123: HIGH | P123: =IF(Bohol!P123=TRUE,"✓","") -> ✓ | Q123: =IF(Bohol!Q123=TRUE,"✓","") -> ✓ | R123: =IF(Bohol!R123=TRUE,"✓","") | S123: =IF(Bohol!S123=TRUE,"✓","") | T123: =IF(Bohol!T123=TRUE,"✓","") -> ✓ | U123: =IF(Bohol!U123=TRUE,"✓","") | V123: 1.5 | W123: HIGH | X123: =IF(Bohol!X123=TRUE,"✓","") -> ✓ | Y123: =IF(Bohol!Y123=TRUE,"✓","") -> ✓ | Z123: =IF(Bohol!Z123=TRUE,"✓","") | AA123: =IF(Bohol!AA123=TRUE,"✓","") | AB123: =IF(Bohol!AB123=TRUE,"✓","") -> ✓ | AC123: 1.5 | AD123: HIGH
A124: TOURISM (HOTEL AND RESTAURANT) | B124: FOOD PRODUCTION | C124: COMMIS PASTRY BAKER | D124: ASSIST HIGHER LEVEL CHEF IN THE PREPARATION AND BAKING | E124: BREAD AND PASTRY PRODUCTION NC II | F124: With TR | G124: HIGH | H124: 1.5 | I124: =IF(Bohol!H124=TRUE,"✓","") -> ✓ | J124: =IF(Bohol!I124=TRUE,"✓","") -> ✓ | K124: =IF(Bohol!J124=TRUE,"✓","") | L124: =IF(Bohol!K124=TRUE,"✓","") | M124: =IF(Bohol!L124=TRUE,"✓","") -> ✓ | N124: =IF(Bohol!M124=TRUE,"✓","") | O124: HIGH | P124: =IF(Bohol!P124=TRUE,"✓","") -> ✓ | Q124: =IF(Bohol!Q124=TRUE,"✓","") -> ✓ | R124: =IF(Bohol!R124=TRUE,"✓","") | S124: =IF(Bohol!S124=TRUE,"✓","") | T124: =IF(Bohol!T124=TRUE,"✓","") -> ✓ | U124: =IF(Bohol!U124=TRUE,"✓","") | V124: 1.5 | X124: =IF(Bohol!X124=TRUE,"✓","") -> ✓ | Y124: =IF(Bohol!Y124=TRUE,"✓","") -> ✓ | Z124: =IF(Bohol!Z124=TRUE,"✓","") | AA124: =IF(Bohol!AA124=TRUE,"✓","") | AB124: =IF(Bohol!AB124=TRUE,"✓","") -> ✓ | AC124: 1.5 | AD124: HIGH
A125: TOURISM (HOTEL AND RESTAURANT) | B125: FOOD PRODUCTION | C125: COOK OR COMMIS | D125: PREPARE FOOD THAT IS SAFE TO BE SERVED | E125: COOKERY NC II | F125: With TR | G125: MEDIUM | H125: 2 | I125: =IF(Bohol!H125=TRUE,"✓","") -> ✓ | J125: =IF(Bohol!I125=TRUE,"✓","") -> ✓ | K125: =IF(Bohol!J125=TRUE,"✓","") | L125: =IF(Bohol!K125=TRUE,"✓","") -> ✓ | M125: =IF(Bohol!L125=TRUE,"✓","") | N125: =IF(Bohol!M125=TRUE,"✓","") | O125: MEDIUM | P125: =IF(Bohol!P125=TRUE,"✓","") -> ✓ | Q125: =IF(Bohol!Q125=TRUE,"✓","") -> ✓ | R125: =IF(Bohol!R125=TRUE,"✓","") | S125: =IF(Bohol!S125=TRUE,"✓","") -> ✓ | T125: =IF(Bohol!T125=TRUE,"✓","") | U125: =IF(Bohol!U125=TRUE,"✓","") | V125: 2 | X125: =IF(Bohol!X125=TRUE,"✓","") -> ✓ | Y125: =IF(Bohol!Y125=TRUE,"✓","") -> ✓ | Z125: =IF(Bohol!Z125=TRUE,"✓","") | AA125: =IF(Bohol!AA125=TRUE,"✓","") -> ✓ | AB125: =IF(Bohol!AB125=TRUE,"✓","") | AC125: 2 | AD125: MEDIUM
A126: TOURISM (HOTEL AND RESTAURANT) | B126: ACCOMMODATION | C126: DIGITAL MARKETING & PROMOTION TECHNOLOGY | D126: DEVELOP AND DESIGN PROMOTIONAL MATERIALS | E126: DIGITAL MARKETING LEVEL III | F126: With CS | G126: MEDIUM | H126: 2 | I126: =IF(Bohol!H126=TRUE,"✓","") -> ✓ | J126: =IF(Bohol!I126=TRUE,"✓","") -> ✓ | K126: =IF(Bohol!J126=TRUE,"✓","") | L126: =IF(Bohol!K126=TRUE,"✓","") -> ✓ | M126: =IF(Bohol!L126=TRUE,"✓","") | N126: =IF(Bohol!M126=TRUE,"✓","") | O126: MEDIUM | P126: =IF(Bohol!P126=TRUE,"✓","") -> ✓ | Q126: =IF(Bohol!Q126=TRUE,"✓","") -> ✓ | R126: =IF(Bohol!R126=TRUE,"✓","") | S126: =IF(Bohol!S126=TRUE,"✓","") -> ✓ | T126: =IF(Bohol!T126=TRUE,"✓","") | U126: =IF(Bohol!U126=TRUE,"✓","") | V126: 2 | X126: =IF(Bohol!X126=TRUE,"✓","") -> ✓ | Y126: =IF(Bohol!Y126=TRUE,"✓","") -> ✓ | Z126: =IF(Bohol!Z126=TRUE,"✓","") | AA126: =IF(Bohol!AA126=TRUE,"✓","") -> ✓ | AB126: =IF(Bohol!AB126=TRUE,"✓","") | AC126: 2 | AD126: MEDIUM
A127: TOURISM (HOTEL AND RESTAURANT) | B127: ACCOMMODATION AND TRAVEL SERVICES | C127: DRIVERS | D127: TRANSPORT GOODS OR PASSENGERS SAFELY FROM ONE PLACE TO ANOTHER | E127: DRIVING NC II | F127: With TR | G127: MEDIUM | H127: 2 | I127: =IF(Bohol!H127=TRUE,"✓","") -> ✓ | J127: =IF(Bohol!I127=TRUE,"✓","") -> ✓ | K127: =IF(Bohol!J127=TRUE,"✓","") | L127: =IF(Bohol!K127=TRUE,"✓","") -> ✓ | M127: =IF(Bohol!L127=TRUE,"✓","") | N127: =IF(Bohol!M127=TRUE,"✓","") | O127: MEDIUM | P127: =IF(Bohol!P127=TRUE,"✓","") -> ✓ | Q127: =IF(Bohol!Q127=TRUE,"✓","") -> ✓ | R127: =IF(Bohol!R127=TRUE,"✓","") | S127: =IF(Bohol!S127=TRUE,"✓","") -> ✓ | T127: =IF(Bohol!T127=TRUE,"✓","") | U127: =IF(Bohol!U127=TRUE,"✓","") | V127: 2 | X127: =IF(Bohol!X127=TRUE,"✓","") -> ✓ | Y127: =IF(Bohol!Y127=TRUE,"✓","") -> ✓ | Z127: =IF(Bohol!Z127=TRUE,"✓","") | AA127: =IF(Bohol!AA127=TRUE,"✓","") -> ✓ | AB127: =IF(Bohol!AB127=TRUE,"✓","") | AC127: 2 | AD127: MEDIUM
A128: TOURISM (HOTEL AND RESTAURANT) | B128: ACCOMMODATION | C128: ELECTRICIAN | D128: INSTALL, MAINTAIN AND REPAIR ELECTRICAL SYSTEM | E128: ELECTRICAL INSTALLATION AND MAINTENANCE NC II | F128: With TR | G128: MEDIUM | H128: 2 | I128: =IF(Bohol!H128=TRUE,"✓","") -> ✓ | J128: =IF(Bohol!I128=TRUE,"✓","") -> ✓ | K128: =IF(Bohol!J128=TRUE,"✓","") | L128: =IF(Bohol!K128=TRUE,"✓","") -> ✓ | M128: =IF(Bohol!L128=TRUE,"✓","") | N128: =IF(Bohol!M128=TRUE,"✓","") | O128: MEDIUM | P128: =IF(Bohol!P128=TRUE,"✓","") -> ✓ | Q128: =IF(Bohol!Q128=TRUE,"✓","") -> ✓ | R128: =IF(Bohol!R128=TRUE,"✓","") | S128: =IF(Bohol!S128=TRUE,"✓","") -> ✓ | T128: =IF(Bohol!T128=TRUE,"✓","") | U128: =IF(Bohol!U128=TRUE,"✓","") | V128: 2 | X128: =IF(Bohol!X128=TRUE,"✓","") -> ✓ | Y128: =IF(Bohol!Y128=TRUE,"✓","") -> ✓ | Z128: =IF(Bohol!Z128=TRUE,"✓","") | AA128: =IF(Bohol!AA128=TRUE,"✓","") -> ✓ | AB128: =IF(Bohol!AB128=TRUE,"✓","") | AC128: 2 | AD128: MEDIUM
A129: TOURISM (HOTEL AND RESTAURANT) | B129: ACCOMMODATION | C129: ELECTRONICS/SOUND SYTEM OPERATOR/TECHNICIAN | D129: INSTALL AND MAINTAIN ELECTRONIC DEVICES AND SYSTEM | E129: ELECTRONIC PRODUCTS ASSEMBLY AND SERVICING NC II | F129: With TR | G129: HIGH | H129: 1 | I129: =IF(Bohol!H129=TRUE,"✓","") -> ✓ | J129: =IF(Bohol!I129=TRUE,"✓","") -> ✓ | K129: =IF(Bohol!J129=TRUE,"✓","") | L129: =IF(Bohol!K129=TRUE,"✓","") | M129: =IF(Bohol!L129=TRUE,"✓","") | N129: =IF(Bohol!M129=TRUE,"✓","") -> ✓ | O129: HIGH | P129: =IF(Bohol!P129=TRUE,"✓","") -> ✓ | Q129: =IF(Bohol!Q129=TRUE,"✓","") -> ✓ | R129: =IF(Bohol!R129=TRUE,"✓","") | S129: =IF(Bohol!S129=TRUE,"✓","") | T129: =IF(Bohol!T129=TRUE,"✓","") | U129: =IF(Bohol!U129=TRUE,"✓","") -> ✓ | V129: 1 | X129: =IF(Bohol!X129=TRUE,"✓","") -> ✓ | Y129: =IF(Bohol!Y129=TRUE,"✓","") -> ✓ | Z129: =IF(Bohol!Z129=TRUE,"✓","") | AA129: =IF(Bohol!AA129=TRUE,"✓","") | AB129: =IF(Bohol!AB129=TRUE,"✓","") | AC129: 1 | AD129: HIGH
A130: TOURISM (HOTEL AND RESTAURANT) | B130: FOOD AND BEVERAGES | C130: FOOD AND BEVERAGE SERVICES ATTENDANT | D130: RENDER AN EFFICIENT SERVICES IN SERVING THE FOOD AND BEVERAGES | E130: FOOD AND BEVERAGE SERVICES NC II | F130: With TR | G130: MEDIUM | H130: 2 | I130: =IF(Bohol!H130=TRUE,"✓","") -> ✓ | J130: =IF(Bohol!I130=TRUE,"✓","") -> ✓ | K130: =IF(Bohol!J130=TRUE,"✓","") | L130: =IF(Bohol!K130=TRUE,"✓","") -> ✓ | M130: =IF(Bohol!L130=TRUE,"✓","") | N130: =IF(Bohol!M130=TRUE,"✓","") | O130: MEDIUM | P130: =IF(Bohol!P130=TRUE,"✓","") -> ✓ | Q130: =IF(Bohol!Q130=TRUE,"✓","") -> ✓ | R130: =IF(Bohol!R130=TRUE,"✓","") | S130: =IF(Bohol!S130=TRUE,"✓","") -> ✓ | T130: =IF(Bohol!T130=TRUE,"✓","") | U130: =IF(Bohol!U130=TRUE,"✓","") | V130: 2 | X130: =IF(Bohol!X130=TRUE,"✓","") -> ✓ | Y130: =IF(Bohol!Y130=TRUE,"✓","") -> ✓ | Z130: =IF(Bohol!Z130=TRUE,"✓","") | AA130: =IF(Bohol!AA130=TRUE,"✓","") -> ✓ | AB130: =IF(Bohol!AB130=TRUE,"✓","") | AC130: 2 | AD130: MEDIUM
A131: TOURISM (HOTEL AND RESTAURANT) | B131: FOOD AND BEVERAGES | C131: FOOD AND BEVERAGE SERVICES HIGHER QUALIFICATIONS (FBS SUPERVISOR/MANAGER) | D131: OVERSEE THE QUALITY OF SERVICE AND SAFETY OF THE PREPARED FOOD | E131: FOOD AND BEVERAGE SERVICES NC III | F131: With TR | G131: MEDIUM | H131: 2 | I131: =IF(Bohol!H131=TRUE,"✓","") -> ✓ | J131: =IF(Bohol!I131=TRUE,"✓","") -> ✓ | K131: =IF(Bohol!J131=TRUE,"✓","") | L131: =IF(Bohol!K131=TRUE,"✓","") -> ✓ | M131: =IF(Bohol!L131=TRUE,"✓","") | N131: =IF(Bohol!M131=TRUE,"✓","") | O131: MEDIUM | P131: =IF(Bohol!P131=TRUE,"✓","") -> ✓ | Q131: =IF(Bohol!Q131=TRUE,"✓","") -> ✓ | R131: =IF(Bohol!R131=TRUE,"✓","") | S131: =IF(Bohol!S131=TRUE,"✓","") -> ✓ | T131: =IF(Bohol!T131=TRUE,"✓","") | U131: =IF(Bohol!U131=TRUE,"✓","") | V131: 2 | X131: =IF(Bohol!X131=TRUE,"✓","") -> ✓ | Y131: =IF(Bohol!Y131=TRUE,"✓","") -> ✓ | Z131: =IF(Bohol!Z131=TRUE,"✓","") | AA131: =IF(Bohol!AA131=TRUE,"✓","") -> ✓ | AB131: =IF(Bohol!AB131=TRUE,"✓","") | AC131: 2 | AD131: MEDIUM
A132: TOURISM (HOTEL AND RESTAURANT) | B132: FOOD PRODUCTION | C132: FOOD PROCESSING (QUALITY CONTROLLER) | D132: CONTROL THE QUALITY OF THE FOOD | E132: FOOD PROCESSING NC II | F132: With TR | G132: MEDIUM | H132: 2 | I132: =IF(Bohol!H132=TRUE,"✓","") -> ✓ | J132: =IF(Bohol!I132=TRUE,"✓","") -> ✓ | K132: =IF(Bohol!J132=TRUE,"✓","") | L132: =IF(Bohol!K132=TRUE,"✓","") -> ✓ | M132: =IF(Bohol!L132=TRUE,"✓","") | N132: =IF(Bohol!M132=TRUE,"✓","") | O132: MEDIUM | P132: =IF(Bohol!P132=TRUE,"✓","") -> ✓ | Q132: =IF(Bohol!Q132=TRUE,"✓","") -> ✓ | R132: =IF(Bohol!R132=TRUE,"✓","") | S132: =IF(Bohol!S132=TRUE,"✓","") -> ✓ | T132: =IF(Bohol!T132=TRUE,"✓","") | U132: =IF(Bohol!U132=TRUE,"✓","") | V132: 2 | X132: =IF(Bohol!X132=TRUE,"✓","") -> ✓ | Y132: =IF(Bohol!Y132=TRUE,"✓","") -> ✓ | Z132: =IF(Bohol!Z132=TRUE,"✓","") | AA132: =IF(Bohol!AA132=TRUE,"✓","") -> ✓ | AB132: =IF(Bohol!AB132=TRUE,"✓","") | AC132: 2 | AD132: MEDIUM
A133: TOURISM (HOTEL AND RESTAURANT) | B133: ACCOMODATION | C133: FRONT OFFICE SERVICES HIGHER QUALIFICATIONS (FRONT OFFICE SUPERVISOR/MANAGER) | D133: OVERSEE THE EFFICIENCY/QUALITY OF THE OFFICES/ SERVICES | E133: FRONT OFFICE SERVICES NC III | F133: With TR | G133: MEDIUM | H133: 2 | I133: =IF(Bohol!H133=TRUE,"✓","") -> ✓ | J133: =IF(Bohol!I133=TRUE,"✓","") -> ✓ | K133: =IF(Bohol!J133=TRUE,"✓","") | L133: =IF(Bohol!K133=TRUE,"✓","") -> ✓ | M133: =IF(Bohol!L133=TRUE,"✓","") | N133: =IF(Bohol!M133=TRUE,"✓","") | O133: MEDIUM | P133: =IF(Bohol!P133=TRUE,"✓","") -> ✓ | Q133: =IF(Bohol!Q133=TRUE,"✓","") -> ✓ | R133: =IF(Bohol!R133=TRUE,"✓","") | S133: =IF(Bohol!S133=TRUE,"✓","") -> ✓ | T133: =IF(Bohol!T133=TRUE,"✓","") | U133: =IF(Bohol!U133=TRUE,"✓","") | V133: 2 | X133: =IF(Bohol!X133=TRUE,"✓","") -> ✓ | Y133: =IF(Bohol!Y133=TRUE,"✓","") -> ✓ | Z133: =IF(Bohol!Z133=TRUE,"✓","") | AA133: =IF(Bohol!AA133=TRUE,"✓","") -> ✓ | AB133: =IF(Bohol!AB133=TRUE,"✓","") | AC133: 2 | AD133: MEDIUM
A134: TOURISM (HOTEL AND RESTAURANT) | B134: ACCOMODATION | C134: HOUSEKEEPING SERVICES HIGHER QUALIFICATIONS (HOUSEKEEPING SUPERVISOR/MANAGER) | D134: OVERSEE/ EFFICIENT HOUSEKEEPING | E134: HOUSEKEEPING NC III | F134: With TR | G134: MEDIUM | H134: 2 | I134: =IF(Bohol!H134=TRUE,"✓","") -> ✓ | J134: =IF(Bohol!I134=TRUE,"✓","") -> ✓ | K134: =IF(Bohol!J134=TRUE,"✓","") | L134: =IF(Bohol!K134=TRUE,"✓","") -> ✓ | M134: =IF(Bohol!L134=TRUE,"✓","") | N134: =IF(Bohol!M134=TRUE,"✓","") | O134: MEDIUM | P134: =IF(Bohol!P134=TRUE,"✓","") -> ✓ | Q134: =IF(Bohol!Q134=TRUE,"✓","") -> ✓ | R134: =IF(Bohol!R134=TRUE,"✓","") | S134: =IF(Bohol!S134=TRUE,"✓","") -> ✓ | T134: =IF(Bohol!T134=TRUE,"✓","") | U134: =IF(Bohol!U134=TRUE,"✓","") | V134: 2 | X134: =IF(Bohol!X134=TRUE,"✓","") -> ✓ | Y134: =IF(Bohol!Y134=TRUE,"✓","") -> ✓ | Z134: =IF(Bohol!Z134=TRUE,"✓","") | AA134: =IF(Bohol!AA134=TRUE,"✓","") -> ✓ | AB134: =IF(Bohol!AB134=TRUE,"✓","") | AC134: 2 | AD134: MEDIUM
A135: TOURISM (HOTEL AND RESTAURANT) | B135: ACCOMMODATION | C135: LANGUAGES (NIHONGO & KOREAN) | D135: FACILITATE COMMUNICATION BETWEEN INDIVIDUALS WITH DIFFERENT LANGUAGES | E135: LANGUAGE A1 LEVEL | F135: With CS | G135: MEDIUM | H135: 2 | I135: =IF(Bohol!H135=TRUE,"✓","") -> ✓ | J135: =IF(Bohol!I135=TRUE,"✓","") -> ✓ | K135: =IF(Bohol!J135=TRUE,"✓","") | L135: =IF(Bohol!K135=TRUE,"✓","") -> ✓ | M135: =IF(Bohol!L135=TRUE,"✓","") | N135: =IF(Bohol!M135=TRUE,"✓","") | O135: MEDIUM | P135: =IF(Bohol!P135=TRUE,"✓","") -> ✓ | Q135: =IF(Bohol!Q135=TRUE,"✓","") -> ✓ | R135: =IF(Bohol!R135=TRUE,"✓","") | S135: =IF(Bohol!S135=TRUE,"✓","") -> ✓ | T135: =IF(Bohol!T135=TRUE,"✓","") | U135: =IF(Bohol!U135=TRUE,"✓","") | V135: 2 | X135: =IF(Bohol!X135=TRUE,"✓","") -> ✓ | Y135: =IF(Bohol!Y135=TRUE,"✓","") -> ✓ | Z135: =IF(Bohol!Z135=TRUE,"✓","") | AA135: =IF(Bohol!AA135=TRUE,"✓","") -> ✓ | AB135: =IF(Bohol!AB135=TRUE,"✓","") | AC135: 2 | AD135: MEDIUM
... A148: TOURISM (HOTEL AND RESTAURANT) | B148: TRAVEL AND TOURS | C148: TOURISM PROMOTIONS SERVICES (ONLINE TRAVEL ADVISOR, ONLINE TOURISM PROMOTIONAL MATERIAL DEVELOPER) | D148: PROMOTE THE TOURISM INDUSTRY | E148: TOURISM PROMOTION SERVICES NC II | F148: With TR | G148: MEDIUM | H148: 2 | I148: =IF(Bohol!H148=TRUE,"✓","") -> ✓ | J148: =IF(Bohol!I148=TRUE,"✓","") -> ✓ | K148: =IF(Bohol!J148=TRUE,"✓","") | L148: =IF(Bohol!K148=TRUE,"✓","") -> ✓ | M148: =IF(Bohol!L148=TRUE,"✓","") | N148: =IF(Bohol!M148=TRUE,"✓","") | O148: MEDIUM | P148: =IF(Bohol!P148=TRUE,"✓","") -> ✓ | Q148: =IF(Bohol!Q148=TRUE,"✓","") -> ✓ | R148: =IF(Bohol!R148=TRUE,"✓","") | S148: =IF(Bohol!S148=TRUE,"✓","") -> ✓ | T148: =IF(Bohol!T148=TRUE,"✓","") | U148: =IF(Bohol!U148=TRUE,"✓","") | V148: 2 | X148: =IF(Bohol!X148=TRUE,"✓","") -> ✓ | Y148: =IF(Bohol!Y148=TRUE,"✓","") -> ✓ | Z148: =IF(Bohol!Z148=TRUE,"✓","") | AA148: =IF(Bohol!AA148=TRUE,"✓","") -> ✓ | AB148: =IF(Bohol!AB148=TRUE,"✓","") | AC148: 2 | AD148: MEDIUM
A149: TOURISM (HOTEL AND RESTAURANT) | B149: TRAVEL AND TOURS | C149: TRAVEL SERVICES (TRAVEL AGENTS) | D149: ASSISTS CLIENTS IN TRAVEL ITINERARY | E149: TRAVEL SERVICES NC II | F149: With TR | I149: =IF(Bohol!H149=TRUE,"✓","") | J149: =IF(Bohol!I149=TRUE,"✓","") | K149: =IF(Bohol!J149=TRUE,"✓","") | L149: =IF(Bohol!K149=TRUE,"✓","") | M149: =IF(Bohol!L149=TRUE,"✓","") | N149: =IF(Bohol!M149=TRUE,"✓","") | P149: =IF(Bohol!P149=TRUE,"✓","") | Q149: =IF(Bohol!Q149=TRUE,"✓","") | R149: =IF(Bohol!R149=TRUE,"✓","") | S149: =IF(Bohol!S149=TRUE,"✓","") | T149: =IF(Bohol!T149=TRUE,"✓","") | U149: =IF(Bohol!U149=TRUE,"✓","") | X149: =IF(Bohol!X149=TRUE,"✓","") | Y149: =IF(Bohol!Y149=TRUE,"✓","") | Z149: =IF(Bohol!Z149=TRUE,"✓","") | AA149: =IF(Bohol!AA149=TRUE,"✓","") | AB149: =IF(Bohol!AB149=TRUE,"✓","")
A150: CONSTRUCTION | B150: HEAVY EQUIPMENT | C150: FORKLIFT EQUIPMENT OPERATOR | D150: OPERATE FORKLIFT EQUIPMENT | E150: HEAVY EQUIPMENT OPERATION (FORKLIFT) NC II | F150: With TR | I150: =IF(Bohol!H150=TRUE,"✓","") | J150: =IF(Bohol!I150=TRUE,"✓","") | K150: =IF(Bohol!J150=TRUE,"✓","") | L150: =IF(Bohol!K150=TRUE,"✓","") | M150: =IF(Bohol!L150=TRUE,"✓","") | N150: =IF(Bohol!M150=TRUE,"✓","") | P150: =IF(Bohol!P150=TRUE,"✓","") | Q150: =IF(Bohol!Q150=TRUE,"✓","") | R150: =IF(Bohol!R150=TRUE,"✓","") | S150: =IF(Bohol!S150=TRUE,"✓","") | T150: =IF(Bohol!T150=TRUE,"✓","") | U150: =IF(Bohol!U150=TRUE,"✓","") | X150: =IF(Bohol!X150=TRUE,"✓","") | Y150: =IF(Bohol!Y150=TRUE,"✓","") | Z150: =IF(Bohol!Z150=TRUE,"✓","") | AA150: =IF(Bohol!AA150=TRUE,"✓","") | AB150: =IF(Bohol!AB150=TRUE,"✓","")
A151: METALS AND ENGINEERING | B151: WELDING | C151: MULTIPLE FILLET PASS WELDER | D151: WELD MULTIPLE FILLET PASS | E151: SHIELDED METAL ARC WELDING NC III | F151: With TR | I151: =IF(Bohol!H151=TRUE,"✓","") | J151: =IF(Bohol!I151=TRUE,"✓","") | K151: =IF(Bohol!J151=TRUE,"✓","") | L151: =IF(Bohol!K151=TRUE,"✓","") | M151: =IF(Bohol!L151=TRUE,"✓","") | N151: =IF(Bohol!M151=TRUE,"✓","") | P151: =IF(Bohol!P151=TRUE,"✓","") | Q151: =IF(Bohol!Q151=TRUE,"✓","") | R151: =IF(Bohol!R151=TRUE,"✓","") | S151: =IF(Bohol!S151=TRUE,"✓","") | T151: =IF(Bohol!T151=TRUE,"✓","") | U151: =IF(Bohol!U151=TRUE,"✓","") | X151: =IF(Bohol!X151=TRUE,"✓","") | Y151: =IF(Bohol!Y151=TRUE,"✓","") | Z151: =IF(Bohol!Z151=TRUE,"✓","") | AA151: =IF(Bohol!AA151=TRUE,"✓","") | AB151: =IF(Bohol!AB151=TRUE,"✓","")
A152: WHOLESALE AND RETAIL TRADING | B152: ENTREPRENUERSHIP | C152: HIGHER LEVEL ENTREPRENUER | D152: MANAGE OWN BUSINESS | E152: ENTREPRENEURSHIP LEVEL IV | F152: With CS | I152: =IF(Bohol!I152=TRUE,"✓","") | J152: =IF(Bohol!J152=TRUE,"✓","") | K152: =IF(Bohol!K152=TRUE,"✓","") | L152: =IF(Bohol!L152=TRUE,"✓","") | M152: =IF(Bohol!M152=TRUE,"✓","") | P152: =IF(Bohol!P152=TRUE,"✓","") | Q152: =IF(Bohol!Q152=TRUE,"✓","") | R152: =IF(Bohol!R152=TRUE,"✓","") | S152: =IF(Bohol!S152=TRUE,"✓","") | T152: =IF(Bohol!T152=TRUE,"✓","") | U152: =IF(Bohol!U152=TRUE,"✓","") | X152: =IF(Bohol!X152=TRUE,"✓","") | Y152: =IF(Bohol!Y152=TRUE,"✓","") | Z152: =IF(Bohol!Z152=TRUE,"✓","") | AA152: =IF(Bohol!AA152=TRUE,"✓","") | AB152: =IF(Bohol!AB152=TRUE,"✓","")
I153: =IF(Bohol!I153=TRUE,"✓","") | J153: =IF(Bohol!J153=TRUE,"✓","") | K153: =IF(Bohol!K153=TRUE,"✓","") | L153: =IF(Bohol!L153=TRUE,"✓","") | M153: =IF(Bohol!M153=TRUE,"✓","") | P153: =IF(Bohol!P153=TRUE,"✓","") | Q153: =IF(Bohol!Q153=TRUE,"✓","") | R153: =IF(Bohol!R153=TRUE,"✓","") | S153: =IF(Bohol!S153=TRUE,"✓","") | T153: =IF(Bohol!T153=TRUE,"✓","") | U153: =IF(Bohol!U153=TRUE,"✓","") | X153: =IF(Bohol!X153=TRUE,"✓","") | Y153: =IF(Bohol!Y153=TRUE,"✓","") | Z153: =IF(Bohol!Z153=TRUE,"✓","") | AA153: =IF(Bohol!AA153=TRUE,"✓","") | AB153: =IF(Bohol!AB153=TRUE,"✓","")
I154: =IF(Bohol!I154=TRUE,"✓","") | J154: =IF(Bohol!J154=TRUE,"✓","") | K154: =IF(Bohol!K154=TRUE,"✓","") | L154: =IF(Bohol!L154=TRUE,"✓","") | M154: =IF(Bohol!M154=TRUE,"✓","") | P154: =IF(Bohol!P154=TRUE,"✓","") | Q154: =IF(Bohol!Q154=TRUE,"✓","") | R154: =IF(Bohol!R154=TRUE,"✓","") | S154: =IF(Bohol!S154=TRUE,"✓","") | T154: =IF(Bohol!T154=TRUE,"✓","") | U154: =IF(Bohol!U154=TRUE,"✓","") | X154: =IF(Bohol!X154=TRUE,"✓","") | Y154: =IF(Bohol!Y154=TRUE,"✓","") | Z154: =IF(Bohol!Z154=TRUE,"✓","") | AA154: =IF(Bohol!AA154=TRUE,"✓","") | AB154: =IF(Bohol!AB154=TRUE,"✓","")
I155: =IF(Bohol!I155=TRUE,"✓","") | J155: =IF(Bohol!J155=TRUE,"✓","") | K155: =IF(Bohol!K155=TRUE,"✓","") | L155: =IF(Bohol!L155=TRUE,"✓","") | M155: =IF(Bohol!M155=TRUE,"✓","") | P155: =IF(Bohol!P155=TRUE,"✓","") | Q155: =IF(Bohol!Q155=TRUE,"✓","") | R155: =IF(Bohol!R155=TRUE,"✓","") | S155: =IF(Bohol!S155=TRUE,"✓","") | T155: =IF(Bohol!T155=TRUE,"✓","") | U155: =IF(Bohol!U155=TRUE,"✓","") | X155: =IF(Bohol!X155=TRUE,"✓","") | Y155: =IF(Bohol!Y155=TRUE,"✓","") | Z155: =IF(Bohol!Z155=TRUE,"✓","") | AA155: =IF(Bohol!AA155=TRUE,"✓","") | AB155: =IF(Bohol!AB155=TRUE,"✓","")
I156: =IF(Bohol!I156=TRUE,"✓","") | J156: =IF(Bohol!J156=TRUE,"✓","") | K156: =IF(Bohol!K156=TRUE,"✓","") | L156: =IF(Bohol!L156=TRUE,"✓","") | M156: =IF(Bohol!M156=TRUE,"✓","") | P156: =IF(Bohol!P156=TRUE,"✓","") | Q156: =IF(Bohol!Q156=TRUE,"✓","") | R156: =IF(Bohol!R156=TRUE,"✓","") | S156: =IF(Bohol!S156=TRUE,"✓","") | T156: =IF(Bohol!T156=TRUE,"✓","") | U156: =IF(Bohol!U156=TRUE,"✓","") | X156: =IF(Bohol!X156=TRUE,"✓","") | Y156: =IF(Bohol!Y156=TRUE,"✓","") | Z156: =IF(Bohol!Z156=TRUE,"✓","") | AA156: =IF(Bohol!AA156=TRUE,"✓","") | AB156: =IF(Bohol!AB156=TRUE,"✓","")
I157: =IF(Bohol!I157=TRUE,"✓","") | J157: =IF(Bohol!J157=TRUE,"✓","") | K157: =IF(Bohol!K157=TRUE,"✓","") | L157: =IF(Bohol!L157=TRUE,"✓","") | M157: =IF(Bohol!M157=TRUE,"✓","") | P157: =IF(Bohol!P157=TRUE,"✓","") | Q157: =IF(Bohol!Q157=TRUE,"✓","") | R157: =IF(Bohol!R157=TRUE,"✓","") | S157: =IF(Bohol!S157=TRUE,"✓","") | T157: =IF(Bohol!T157=TRUE,"✓","") | U157: =IF(Bohol!U157=TRUE,"✓","") | X157: =IF(Bohol!X157=TRUE,"✓","") | Y157: =IF(Bohol!Y157=TRUE,"✓","") | Z157: =IF(Bohol!Z157=TRUE,"✓","") | AA157: =IF(Bohol!AA157=TRUE,"✓","") | AB157: =IF(Bohol!AB157=TRUE,"✓","")
H158: =IF(Bohol!H152=TRUE,"✓","")
H159: =IF(Bohol!H153=TRUE,"✓","")
H160: =IF(Bohol!H154=TRUE,"✓","")
H161: =IF(Bohol!H155=TRUE,"✓","")
H162: =IF(Bohol!H156=TRUE,"✓","")
H163: =IF(Bohol!H157=TRUE,"✓","")

Sheet Cebu
A1: Region | B1: REGION_VII
A2: Province | B2: CEBU
A3: Number of Districts | B3: 11
A4: Sector | B4: Subsector/ Value Chain | C4: Job Requirement | D4: Tasks | E4: Program | F4: Type of Program (TR, CS, New and Emerging, Diploma Programs) | G4: Provincial Rank (Averaged Across Districts)
H5: D1 | P5: D2 | AA5: D3 | AL5: D4 | AW5: D5 | BG5: D6 | BS5: D7 | CD5: D8 | CO5: D9 | CZ5: D10 | DK5: D11
A6: AGRICULTURE FORESTRY AND FISHERY | B6: CROP PRODUCTION | C6: BAMBOO FARM WORKER | D6: PLANT BAMBOO SEEDLINGS PERFORM MAINTENANCE OF BAMBOO FARM GENERAL FARM SUPPORT | E6: BAMBOO PRODUCTION NC II | F6: With TR | G6: HIGH | H6: FALSE | I6: FALSE | J6: FALSE | K6: FALSE | L6: FALSE | M6: FALSE | P6: FALSE | S6: FALSE | T6: FALSE | U6: FALSE | V6: FALSE | W6: FALSE | X6: FALSE | AA6: FALSE | AD6: FALSE | AE6: FALSE | AF6: FALSE | AG6: FALSE | AH6: FALSE | AI6: FALSE | AL6: FALSE | AO6: FALSE | AP6: FALSE | AQ6: FALSE | AR6: FALSE | AS6: FALSE | AT6: FALSE | AW6: FALSE | AZ6: TRUE | BA6: TRUE | BB6: TRUE | BC6: FALSE | BD6: FALSE | BE6: TRUE | BF6: 1.25 | BG6: HIGH | BH6: TRUE | BI6: REGION_VII|CEBU|Cebu, District 3|AGRICULTURE FORESTRY AND FISHERY|AGRICULTURAL SERVICES|BAMBOO GROWER||BAMBOO PRODUCTION NC II||With TR|HIGH | BK6: FALSE | BL6: FALSE | BM6: FALSE | BN6: FALSE | BO6: FALSE | BP6: FALSE | BS6: FALSE | BV6: FALSE | BW6: FALSE | BX6: FALSE | BY6: FALSE | BZ6: FALSE | CA6: FALSE | CD6: FALSE | CG6: FALSE | CH6: FALSE | CI6: FALSE | CJ6: FALSE | CK6: FALSE | CL6: FALSE | CO6: FALSE | CR6: FALSE | CS6: FALSE | CT6: FALSE | CU6: FALSE | CV6: FALSE | CW6: FALSE | CZ6: FALSE | DC6: FALSE | DD6: FALSE | DE6: FALSE | DF6: FALSE | DG6: FALSE | DH6: FALSE | DK6: FALSE | DN6: FALSE | DO6: FALSE | DP6: FALSE | DQ6: FALSE | DR6: FALSE | DS6: FALSE
A7: AGRICULTURE FORESTRY AND FISHERY | B7: AGRICULTURAL SERVICES | C7: BAMBOO GROWER | D7: PERFORM NURSERY OPERATION COLLECT PROPAGULES BAMBOO CULTIVIATION CARE AND MAINTAIN HARVESTING | E7: BAMBOO PRODUCTION NC II | F7: With TR | G7: HIGH | H7: TRUE | I7: TRUE | J7: TRUE | K7: FALSE | L7: FALSE | M7: TRUE | N7: 1.25 | O7: HIGH | P7: TRUE | Q7: REGION_VII|CEBU|Cebu City, District 1|AGRICULTURE FORESTRY AND FISHERY|AGRICULTURAL SERVICES|CACAO FARM TECHNCIAN||CACAO PRODUCTION LEVEL II||With CS|HIGH | S7: FALSE | T7: FALSE | U7: FALSE | V7: FALSE | W7: FALSE | X7: FALSE | AA7: FALSE | AD7: FALSE | AE7: FALSE | AF7: FALSE | AG7: FALSE | AH7: FALSE | AI7: FALSE | AL7: FALSE | AO7: FALSE | AP7: FALSE | AQ7: FALSE | AR7: FALSE | AS7: FALSE | AT7: FALSE | AW7: FALSE | AZ7: FALSE | BA7: FALSE | BB7: FALSE | BC7: FALSE | BD7: FALSE | BE7: FALSE | BH7: FALSE | BK7: FALSE | BL7: FALSE | BM7: FALSE | BN7: FALSE | BO7: FALSE | BP7: FALSE | BS7: FALSE | BV7: FALSE | BW7: FALSE | BX7: FALSE | BY7: FALSE | BZ7: FALSE | CA7: FALSE | CD7: FALSE | CG7: FALSE | CH7: FALSE | CI7: FALSE | CJ7: FALSE | CK7: FALSE | CL7: FALSE | CO7: FALSE | CR7: FALSE | CS7: FALSE | CT7: FALSE | CU7: FALSE | CV7: FALSE | CW7: FALSE | CZ7: FALSE | DC7: FALSE | DD7: FALSE | DE7: FALSE | DF7: FALSE | DG7: FALSE | DH7: FALSE | DK7: FALSE | DN7: FALSE | DO7: FALSE | DP7: FALSE | DQ7: FALSE | DR7: FALSE | DS7: FALSE
A8: AGRICULTURE FORESTRY AND FISHERY | B8: AGRICULTURAL SERVICES | C8: CACAO FARM TECHNCIAN | D8: NURSERY OPERATION & MANAGEMENT LAND PREPRATION PLANTING AND SEEDLINGS PLANT CARE & MAINTENANCE HARVEST / POST HARVEST ACTIVITIES | E8: CACAO PRODUCTION LEVEL II | F8: With CS | G8: HIGH | H8: TRUE | I8: TRUE | J8: TRUE | K8: FALSE | L8: FALSE | M8: TRUE | N8: 1.25 | O8: HIGH | P8: TRUE | Q8: REGION_VII|CEBU|Cebu City, District 1|AGRICULTURE FORESTRY AND FISHERY|AGRICULTURAL SERVICES|COCONUT FARM TECHNICIAN||COCONUT PRODUCTION LEVEL II||With CS|HIGH | S8: FALSE | T8: FALSE | U8: FALSE | V8: FALSE | W8: FALSE | X8: FALSE | AA8: FALSE | AD8: FALSE | AE8: FALSE | AF8: FALSE | AG8: FALSE | AH8: FALSE | AI8: FALSE | AL8: FALSE | AO8: FALSE | AP8: FALSE | AQ8: FALSE | AR8: FALSE | AS8: FALSE | AT8: FALSE | AW8: FALSE | AZ8: FALSE | BA8: FALSE | BB8: FALSE | BC8: FALSE | BD8: FALSE | BE8: FALSE | BH8: FALSE | BK8: FALSE | BL8: FALSE | BM8: FALSE | BN8: FALSE | BO8: FALSE | BP8: FALSE | BS8: FALSE | BV8: FALSE | BW8: FALSE | BX8: FALSE | BY8: FALSE | BZ8: FALSE | CA8: FALSE | CD8: FALSE | CG8: FALSE | CH8: FALSE | CI8: FALSE | CJ8: FALSE | CK8: FALSE | CL8: FALSE | CO8: FALSE | CR8: FALSE | CS8: FALSE | CT8: FALSE | CU8: FALSE | CV8: FALSE | CW8: FALSE | CZ8: FALSE | DC8: FALSE | DD8: FALSE | DE8: FALSE | DF8: FALSE | DG8: FALSE | DH8: FALSE | DK8: FALSE | DN8: FALSE | DO8: FALSE | DP8: FALSE | DQ8: FALSE | DR8: FALSE | DS8: FALSE
A9: AGRICULTURE FORESTRY AND FISHERY | B9: AGRICULTURAL SERVICES | C9: COCONUT FARM TECHNICIAN | D9: NURSERY DEVELOPMENT & MANAGEMENT LAND PREPARATION PLANT COCO SEEDLINGS PLANT CARE & MAINTENANCE HARVEST & POST HARVEST ACTIVITIES | E9: COCONUT PRODUCTION LEVEL II | F9: With CS | G9: HIGH | H9: TRUE | I9: TRUE | J9: TRUE | K9: TRUE | L9: FALSE | M9: FALSE | N9: 2.25 | O9: LOW | P9: TRUE | Q9: REGION_VII|CEBU|Cebu City, District 1|AGRICULTURE FORESTRY AND FISHERY|ANIMAL PRODUCTION|DAIRY RAISER||ANIMAL PRODUCTION (RUMINANTS) NC II||With TR|LOW | S9: TRUE | T9: TRUE | U9: TRUE | V9: TRUE | W9: FALSE | X9: FALSE | Y9: 2.25 | Z9: LOW | AA9: TRUE | AB9: REGION_VII|CEBU|Cebu City, District 2|AGRICULTURE FORESTRY AND FISHERY|ANIMAL PRODUCTION|DAIRY RAISER||ANIMAL PRODUCTION (RUMINANTS) NC II||With TR|LOW | AD9: TRUE | AE9: TRUE | AF9: TRUE | AG9: TRUE | AH9: FALSE | AI9: FALSE | AJ9: 2.25 | AK9: LOW | AL9: TRUE | AM9: REGION_VII|CEBU|Cebu, District 1|AGRICULTURE FORESTRY AND FISHERY|ANIMAL PRODUCTION|DAIRY RAISER||ANIMAL PRODUCTION (RUMINANTS) NC II||With TR|LOW | AO9: TRUE | AP9: TRUE | AQ9: TRUE | AR9: TRUE | AS9: FALSE | AT9: FALSE | AU9: 2.25 | AV9: LOW | AW9: TRUE | AX9: REGION_VII|CEBU|Cebu, District 2|AGRICULTURE FORESTRY AND FISHERY|ANIMAL PRODUCTION|DAIRY RAISER||ANIMAL PRODUCTION (RUMINANTS) NC II||With TR|LOW | AZ9: TRUE | BA9: TRUE | BB9: TRUE | BC9: FALSE | BD9: FALSE | BE9: TRUE | BF9: 1.25 | BG9: HIGH | BH9: TRUE | BI9: REGION_VII|CEBU|Cebu, District 3|AGRICULTURE FORESTRY AND FISHERY|ANIMAL PRODUCTION|DAIRY RAISER||ANIMAL PRODUCTION (RUMINANTS) NC II||With TR|HIGH | BK9: TRUE | BL9: TRUE | BM9: TRUE | BN9: TRUE | BO9: FALSE | BP9: FALSE | BQ9: 2.25 | BR9: LOW | BS9: TRUE | BT9: REGION_VII|CEBU|Cebu, District 4|AGRICULTURE FORESTRY AND FISHERY|ANIMAL PRODUCTION|DAIRY RAISER||ANIMAL PRODUCTION (RUMINANTS) NC II||With TR|LOW | BV9: TRUE | BW9: TRUE | BX9: TRUE | BY9: TRUE | BZ9: FALSE | CA9: FALSE | CB9: 2.25 | CC9: LOW | CD9: TRUE | CE9: REGION_VII|CEBU|Cebu, District 5|AGRICULTURE FORESTRY AND FISHERY|ANIMAL PRODUCTION|DAIRY RAISER||ANIMAL PRODUCTION (RUMINANTS) NC II||With TR|LOW | CG9: TRUE | CH9: TRUE | CI9: TRUE | CJ9: TRUE | CK9: FALSE | CL9: FALSE | CM9: 2.25 | CN9: LOW | CO9: TRUE | CP9: REGION_VII|CEBU|Cebu, District 6|AGRICULTURE FORESTRY AND FISHERY|ANIMAL PRODUCTION|DAIRY RAISER||ANIMAL PRODUCTION (RUMINANTS) NC II||With TR|LOW | CR9: TRUE | CS9: TRUE | CT9: TRUE | CU9: TRUE | CV9: FALSE | CW9: FALSE | CX9: 2.25 | CY9: LOW | CZ9: TRUE | DA9: REGION_VII|CEBU|Cebu, District 7|AGRICULTURE FORESTRY AND FISHERY|ANIMAL PRODUCTION|DAIRY RAISER||ANIMAL PRODUCTION (RUMINANTS) NC II||With TR|LOW | DC9: TRUE | DD9: TRUE | DE9: TRUE | DF9: TRUE | DG9: FALSE | DH9: FALSE | DI9: 2.25 | DJ9: LOW | DK9: TRUE | DL9: REGION_VII|CEBU|Lapu-Lapu City, Lone District|AGRICULTURE FORESTRY AND FISHERY|ANIMAL PRODUCTION|DAIRY RAISER||ANIMAL PRODUCTION (RUMINANTS) NC II||With TR|LOW | DN9: TRUE | DO9: TRUE | DP9: TRUE | DQ9: TRUE | DR9: FALSE | DS9: FALSE | DT9: 2.25 | DU9: LOW
A10: AGRICULTURE FORESTRY AND FISHERY | B10: ANIMAL PRODUCTION | C10: DAIRY RAISER | D10: RAISE DAIRY ANIMALS | E10: ANIMAL PRODUCTION (RUMINANTS) NC II | F10: With TR | G10: LOW | H10: TRUE | I10: TRUE | J10: TRUE | K10: TRUE | L10: FALSE | M10: FALSE | N10: 2.25 | O10: LOW | P10: TRUE | Q10: REGION_VII|CEBU|Cebu City, District 1|AGRICULTURE FORESTRY AND FISHERY|AGRI-TOURISM|FARM EXPERIENCE HOST||NO CORRESPONDING TVET PROGRAM||New and Emerging|LOW | S10: TRUE | T10: TRUE | U10: TRUE | V10: TRUE | W10: FALSE | X10: FALSE | Y10: 2.25 | Z10: LOW | AA10: TRUE | AB10: REGION_VII|CEBU|Cebu City, District 2|AGRICULTURE FORESTRY AND FISHERY|AGRI-TOURISM|FARM EXPERIENCE HOST||NO CORRESPONDING TVET PROGRAM||New and Emerging|LOW | AD10: TRUE | AE10: TRUE | AF10: TRUE | AG10: TRUE | AH10: FALSE | AI10: FALSE | AJ10: 2.25 | AK10: LOW | AL10: TRUE | AM10: REGION_VII|CEBU|Cebu, District 1|AGRICULTURE FORESTRY AND FISHERY|AGRI-TOURISM|FARM EXPERIENCE HOST||NO CORRESPONDING TVET PROGRAM||New and Emerging|LOW | AO10: TRUE | AP10: TRUE | AQ10: TRUE | AR10: TRUE | AS10: FALSE | AT10: FALSE | AU10: 2.25 | AV10: LOW | AW10: TRUE | AX10: REGION_VII|CEBU|Cebu, District 2|AGRICULTURE FORESTRY AND FISHERY|AGRI-TOURISM|FARM EXPERIENCE HOST||NO CORRESPONDING TVET PROGRAM||New and Emerging|LOW | AZ10: TRUE | BA10: TRUE | BB10: TRUE | BC10: TRUE | BD10: FALSE | BE10: FALSE | BF10: 2.25 | BG10: LOW | BH10: TRUE | BI10: REGION_VII|CEBU|Cebu, District 3|AGRICULTURE FORESTRY AND FISHERY|AGRI-TOURISM|FARM EXPERIENCE HOST||NO CORRESPONDING TVET PROGRAM||New and Emerging|LOW | BK10: TRUE | BL10: TRUE | BM10: TRUE | BN10: TRUE | BO10: FALSE | BP10: FALSE | BQ10: 2.25 | BR10: LOW | BS10: TRUE | BT10: REGION_VII|CEBU|Cebu, District 4|AGRICULTURE FORESTRY AND FISHERY|AGRI-TOURISM|FARM EXPERIENCE HOST||NO CORRESPONDING TVET PROGRAM||New and Emerging|LOW | BV10: TRUE | BW10: TRUE | BX10: TRUE | BY10: TRUE | BZ10: FALSE | CA10: FALSE | CB10: 2.25 | CC10: LOW | CD10: TRUE | CE10: REGION_VII|CEBU|Cebu, District 5|AGRICULTURE FORESTRY AND FISHERY|AGRI-TOURISM|FARM EXPERIENCE HOST||NO CORRESPONDING TVET PROGRAM||New and Emerging|LOW | CG10: TRUE | CH10: TRUE | CI10: TRUE | CJ10: TRUE | CK10: FALSE | CL10: FALSE | CM10: 2.25 | CN10: LOW | CO10: TRUE | CP10: REGION_VII|CEBU|Cebu, District 6|AGRICULTURE FORESTRY AND FISHERY|AGRI-TOURISM|FARM EXPERIENCE HOST||NO CORRESPONDING TVET PROGRAM||New and Emerging|LOW | CR10: TRUE | CS10: TRUE | CT10: TRUE | CU10: TRUE | CV10: FALSE | CW10: FALSE | CX10: 2.25 | CY10: LOW | CZ10: TRUE | DA10: REGION_VII|CEBU|Cebu, District 7|AGRICULTURE FORESTRY AND FISHERY|AGRI-TOURISM|FARM EXPERIENCE HOST||NO CORRESPONDING TVET PROGRAM||New and Emerging|LOW | DC10: TRUE | DD10: TRUE | DE10: TRUE | DF10: TRUE | DG10: FALSE | DH10: FALSE | DI10: 2.25 | DJ10: LOW | DK10: TRUE | DL10: REGION_VII|CEBU|Lapu-Lapu City, Lone District|AGRICULTURE FORESTRY AND FISHERY|AGRI-TOURISM|FARM EXPERIENCE HOST||NO CORRESPONDING TVET PROGRAM||New and Emerging|LOW | DN10: TRUE | DO10: TRUE | DP10: TRUE | DQ10: TRUE | DR10: FALSE | DS10: FALSE | DT10: 2.25 | DU10: LOW
A11: AGRICULTURE FORESTRY AND FISHERY | B11: AGRI-TOURISM | C11: FARM EXPERIENCE HOST | D11: MARKETING AND PROMOTION DISTRIBUTION AND BOOKING DELIVERY AND EXPERIENCE POST VISIT-ACTIVITIES SUPPORT ACTIVITIES | E11: NO CORRESPONDING TVET PROGRAM | F11: New and Emerging | G11: LOW | H11: TRUE | I11: TRUE | J11: TRUE | K11: TRUE | L11: FALSE | M11: FALSE | N11: 2.25 | O11: LOW | P11: TRUE | Q11: REGION_VII|CEBU|Cebu City, District 1|AGRICULTURE FORESTRY AND FISHERY|CROP PRODUCTION|FARM LEAD HAND||AGRICULTURAL CROPS PRODUCTION NC III||With TR|LOW | S11: TRUE | T11: TRUE | U11: TRUE | V11: TRUE | W11: FALSE | X11: FALSE | Y11: 2.25 | Z11: LOW | AA11: TRUE | AB11: REGION_VII|CEBU|Cebu City, District 2|AGRICULTURE FORESTRY AND FISHERY|CROP PRODUCTION|FARM LEAD HAND||AGRICULTURAL CROPS PRODUCTION NC III||With TR|LOW | AD11: TRUE | AE11: TRUE | AF11: TRUE | AG11: TRUE | AH11: FALSE | AI11: FALSE | AJ11: 2.25 | AK11: LOW | AL11: TRUE | AM11: REGION_VII|CEBU|Cebu, District 1|AGRICULTURE FORESTRY AND FISHERY|CROP PRODUCTION|FARM LEAD HAND||AGRICULTURAL CROPS PRODUCTION NC III||With TR|LOW | AO11: TRUE | AP11: TRUE | AQ11: TRUE | AR11: TRUE | AS11: FALSE | AT11: FALSE | AU11: 2.25 | AV11: LOW | AW11: TRUE | AX11: REGION_VII|CEBU|Cebu, District 2|AGRICULTURE FORESTRY AND FISHERY|CROP PRODUCTION|FARM LEAD HAND||AGRICULTURAL CROPS PRODUCTION NC III||With TR|LOW | AZ11: TRUE | BA11: TRUE | BB11: TRUE | BC11: FALSE | BD11: FALSE | BE11: TRUE | BF11: 1.25 | BG11: HIGH | BH11: TRUE | BI11: REGION_VII|CEBU|Cebu, District 3|AGRICULTURE FORESTRY AND FISHERY|CROP PRODUCTION|FARM LEAD HAND||AGRICULTURAL CROPS PRODUCTION NC III||With TR|HIGH | BK11: TRUE | BL11: TRUE | BM11: TRUE | BN11: FALSE | BO11: FALSE | BP11: TRUE | BQ11: 1.25 | BR11: HIGH | BS11: TRUE | BT11: REGION_VII|CEBU|Cebu, District 4|AGRICULTURE FORESTRY AND FISHERY|CROP PRODUCTION|FARM LEAD HAND||AGRICULTURAL CROPS PRODUCTION NC III||With TR|HIGH | BV11: TRUE | BW11: TRUE | BX11: TRUE | BY11: FALSE | BZ11: FALSE | CA11: TRUE | CB11: 1.25 | CC11: HIGH | CD11: TRUE | CE11: REGION_VII|CEBU|Cebu, District 5|AGRICULTURE FORESTRY AND FISHERY|CROP PRODUCTION|FARM LEAD HAND||AGRICULTURAL CROPS PRODUCTION NC III||With TR|HIGH | CG11: TRUE | CH11: TRUE | CI11: TRUE | CJ11: TRUE | CK11: FALSE | CL11: FALSE | CM11: 2.25 | CN11: LOW | CO11: TRUE | CP11: REGION_VII|CEBU|Cebu, District 6|AGRICULTURE FORESTRY AND FISHERY|CROP PRODUCTION|FARM LEAD HAND||AGRICULTURAL CROPS PRODUCTION NC III||With TR|LOW | CR11: TRUE | CS11: TRUE | CT11: TRUE | CU11: TRUE | CV11: FALSE | CW11: FALSE | CX11: 2.25 | CY11: LOW | CZ11: TRUE | DA11: REGION_VII|CEBU|Cebu, District 7|AGRICULTURE FORESTRY AND FISHERY|CROP PRODUCTION|FARM LEAD HAND||AGRICULTURAL CROPS PRODUCTION NC III||With TR|LOW | DC11: FALSE | DD11: FALSE | DE11: FALSE | DF11: FALSE | DG11: FALSE | DH11: FALSE | DK11: FALSE | DN11: FALSE | DO11: FALSE | DP11: FALSE | DQ11: FALSE | DR11: FALSE | DS11: FALSE
A12: AGRICULTURE FORESTRY AND FISHERY | B12: CROP PRODUCTION | C12: FARM LEAD HAND | D12: PREPARE AND IRRIGATE SOIL PLANT SEEDS FERTILIZE CROPS HARVEST CROPS MAINTAIN FARM PERFORM PEST CONTROL | E12: AGRICULTURAL CROPS PRODUCTION NC III | F12: With TR | G12: LOW | H12: FALSE | I12: FALSE | J12: FALSE | K12: FALSE | L12: FALSE | M12: FALSE | P12: FALSE | S12: FALSE | T12: FALSE | U12: FALSE | V12: FALSE | W12: FALSE | X12: FALSE | AA12: FALSE | AD12: FALSE | AE12: FALSE | AF12: FALSE | AG12: FALSE | AH12: FALSE | AI12: FALSE | AL12: FALSE | AO12: FALSE | AP12: FALSE | AQ12: FALSE | AR12: FALSE | AS12: FALSE | AT12: FALSE | AW12: FALSE | AZ12: TRUE | BA12: TRUE | BB12: TRUE | BC12: FALSE | BD12: FALSE | BE12: TRUE | BF12: 1.25 | BG12: HIGH | BH12: TRUE | BI12: REGION_VII|CEBU|Cebu, District 3|AGRICULTURE FORESTRY AND FISHERY|CROP PRODUCTION|FARM TECHNCIAN||COFFEE PRODUCTION LEVEL II||With CS|HIGH | BK12: FALSE | BL12: FALSE | BM12: FALSE | BN12: FALSE | BO12: FALSE | BP12: FALSE | BS12: FALSE | BV12: FALSE | BW12: FALSE | BX12: FALSE | BY12: FALSE | BZ12: FALSE | CA12: FALSE | CD12: FALSE | CG12: FALSE | CH12: FALSE | CI12: FALSE | CJ12: FALSE | CK12: FALSE | CL12: FALSE | CO12: FALSE | CR12: FALSE | CS12: FALSE | CT12: FALSE | CU12: FALSE | CV12: FALSE | CW12: FALSE | CZ12: FALSE | DC12: FALSE | DD12: FALSE | DE12: FALSE | DF12: FALSE | DG12: FALSE | DH12: FALSE | DK12: FALSE | DN12: FALSE | DO12: FALSE | DP12: FALSE | DQ12: FALSE | DR12: FALSE | DS12: FALSE
A13: AGRICULTURE FORESTRY AND FISHERY | B13: CROP PRODUCTION | C13: FARM TECHNCIAN | D13: PERFORM NURSERY OPERATION LAND PREPARATION POST HARVEST MANAGEMENT | E13: COFFEE PRODUCTION LEVEL II | F13: With CS | G13: HIGH | H13: TRUE | I13: TRUE | J13: TRUE | K13: TRUE | L13: FALSE | M13: FALSE | N13: 2.25 | O13: LOW | P13: TRUE | Q13: REGION_VII|CEBU|Cebu City, District 1|AGRICULTURE FORESTRY AND FISHERY|AGRICULTURAL SERVICES|FARM TECHNCIAN||ARTIFICIAL INSEMINATION (LARGE RUMINANTS) NC II||With TR|LOW | S13: TRUE | T13: TRUE | U13: TRUE | V13: TRUE | W13: FALSE | X13: FALSE | Y13: 2.25 | Z13: LOW | AA13: TRUE | AB13: REGION_VII|CEBU|Cebu City, District 2|AGRICULTURE FORESTRY AND FISHERY|AGRICULTURAL SERVICES|FARM TECHNCIAN||ARTIFICIAL INSEMINATION (LARGE RUMINANTS) NC II||With TR|LOW | AD13: TRUE | AE13: TRUE | AF13: TRUE | AG13: TRUE | AH13: FALSE | AI13: FALSE | AJ13: 2.25 | AK13: LOW | AL13: TRUE | AM13: REGION_VII|CEBU|Cebu, District 1|AGRICULTURE FORESTRY AND FISHERY|AGRICULTURAL SERVICES|FARM TECHNCIAN||ARTIFICIAL INSEMINATION (LARGE RUMINANTS) NC II||With TR|LOW | AO13: TRUE | AP13: TRUE | AQ13: TRUE | AR13: TRUE | AS13: FALSE | AT13: FALSE | AU13: 2.25 | AV13: LOW | AW13: TRUE | AX13: REGION_VII|CEBU|Cebu, District 2|AGRICULTURE FORESTRY AND FISHERY|AGRICULTURAL SERVICES|FARM TECHNCIAN||ARTIFICIAL INSEMINATION (LARGE RUMINANTS) NC II||With TR|LOW | AZ13: TRUE | BA13: TRUE | BB13: TRUE | BC13: TRUE | BD13: FALSE | BE13: FALSE | BF13: 2.25 | BG13: LOW | BH13: TRUE | BI13: REGION_VII|CEBU|Cebu, District 3|AGRICULTURE FORESTRY AND FISHERY|AGRICULTURAL SERVICES|FARM TECHNCIAN||ARTIFICIAL INSEMINATION (LARGE RUMINANTS) NC II||With TR|LOW | BK13: TRUE | BL13: TRUE | BM13: TRUE | BN13: TRUE | BO13: FALSE | BP13: FALSE | BQ13: 2.25 | BR13: LOW | BS13: TRUE | BT13: REGION_VII|CEBU|Cebu, District 4|AGRICULTURE FORESTRY AND FISHERY|AGRICULTURAL SERVICES|FARM TECHNCIAN||ARTIFICIAL INSEMINATION (LARGE RUMINANTS) NC II||With TR|LOW | BV13: TRUE | BW13: TRUE | BX13: TRUE | BY13: FALSE | BZ13: TRUE | CA13: FALSE | CB13: 1.75 | CC13: MEDIUM | CD13: TRUE | CE13: REGION_VII|CEBU|Cebu, District 5|AGRICULTURE FORESTRY AND FISHERY|AGRICULTURAL SERVICES|FARM TECHNCIAN||ARTIFICIAL INSEMINATION (LARGE RUMINANTS) NC II||With TR|MEDIUM | CG13: TRUE | CH13: TRUE | CI13: TRUE | CJ13: TRUE | CK13: FALSE | CL13: FALSE | CM13: 2.25 | CN13: LOW | CO13: TRUE | CP13: REGION_VII|CEBU|Cebu, District 6|AGRICULTURE FORESTRY AND FISHERY|AGRICULTURAL SERVICES|FARM TECHNCIAN||ARTIFICIAL INSEMINATION (LARGE RUMINANTS) NC II||With TR|LOW | CR13: TRUE | CS13: TRUE | CT13: TRUE | CU13: TRUE | CV13: FALSE | CW13: FALSE | CX13: 2.25 | CY13: LOW | CZ13: TRUE | DA13: REGION_VII|CEBU|Cebu, District 7|AGRICULTURE FORESTRY AND FISHERY|AGRICULTURAL SERVICES|FARM TECHNCIAN||ARTIFICIAL INSEMINATION (LARGE RUMINANTS) NC II||With TR|LOW | DC13: FALSE | DD13: FALSE | DE13: FALSE | DF13: FALSE | DG13: FALSE | DH13: FALSE | DK13: FALSE | DN13: FALSE | DO13: FALSE | DP13: FALSE | DQ13: FALSE | DR13: FALSE | DS13: FALSE
A14: AGRICULTURE FORESTRY AND FISHERY | B14: AGRICULTURAL SERVICES | C14: FARM TECHNCIAN | D14: SETUP AND INSTALLATION MONITORING AND MAINTENANCE OPERATION EMERGENCY RESPONSE | E14: ARTIFICIAL INSEMINATION (LARGE RUMINANTS) NC II | F14: With TR | G14: LOW | H14: TRUE | I14: TRUE | J14: TRUE | K14: TRUE | L14: FALSE | M14: FALSE | N14: 2.25 | O14: LOW | P14: TRUE | Q14: REGION_VII|CEBU|Cebu City, District 1|AGRICULTURE FORESTRY AND FISHERY|AGRICULTURAL SERVICES|FARM TECHNICIAN FOR BEEKEEPING||BEEKEEPING LEVEL II||With CS|LOW | S14: TRUE | T14: TRUE | U14: TRUE | V14: TRUE | W14: FALSE | X14: FALSE | Y14: 2.25 | Z14: LOW | AA14: TRUE | AB14: REGION_VII|CEBU|Cebu City, District 2|AGRICULTURE FORESTRY AND FISHERY|AGRICULTURAL SERVICES|FARM TECHNICIAN FOR BEEKEEPING||BEEKEEPING LEVEL II||With CS|LOW | AD14: FALSE | AE14: FALSE | AF14: FALSE | AG14: FALSE | AH14: FALSE | AI14: FALSE | AL14: FALSE | AO14: FALSE | AP14: FALSE | AQ14: FALSE | AR14: FALSE | AS14: FALSE | AT14: FALSE | AW14: FALSE | AZ14: FALSE | BA14: FALSE | BB14: FALSE | BC14: FALSE | BD14: FALSE | BE14: FALSE | BH14: FALSE | BK14: FALSE | BL14: FALSE | BM14: FALSE | BN14: FALSE | BO14: FALSE | BP14: FALSE | BS14: FALSE | BV14: TRUE | BW14: TRUE | BX14: TRUE | BY14: TRUE | BZ14: FALSE | CA14: FALSE | CB14: 2.25 | CC14: LOW | CD14: TRUE | CE14: REGION_VII|CEBU|Cebu, District 5|AGRICULTURE FORESTRY AND FISHERY|AGRICULTURAL SERVICES|FARM TECHNICIAN FOR BEEKEEPING||BEEKEEPING LEVEL II||With CS|LOW | CG14: FALSE | CH14: FALSE | CI14: FALSE | CJ14: FALSE | CK14: FALSE | CL14: FALSE | CO14: FALSE | CR14: FALSE | CS14: FALSE | CT14: FALSE | CU14: FALSE | CV14: FALSE | CW14: FALSE | CZ14: FALSE | DC14: FALSE | DD14: FALSE | DE14: FALSE | DF14: FALSE | DG14: FALSE | DH14: FALSE | DK14: FALSE | DN14: FALSE | DO14: FALSE | DP14: FALSE | DQ14: FALSE | DR14: FALSE | DS14: FALSE
A15: AGRICULTURE FORESTRY AND FISHERY | B15: AGRICULTURAL SERVICES | C15: FARM TECHNICIAN FOR BEEKEEPING | D15: FEEDING SUGAR SYRUP POLLEN PATTY IDENTIFYING PEST & DISEASES CARE AND MAINTAIN READING THE SIGNS OF HONEY FLOW PREPARING THE HIVES FOR HONEY FLOW HARVESTING & POST HARVEST | E15: BEEKEEPING LEVEL II | F15: With CS | G15: LOW | H15: TRUE | I15: TRUE | J15: TRUE | K15: TRUE | L15: FALSE | M15: FALSE | N15: 2.25 | O15: LOW | P15: TRUE | Q15: REGION_VII|CEBU|Cebu City, District 1|AGRICULTURE FORESTRY AND FISHERY|CROP PRODUCTION ANIMAL PRODUCTION|FARMER LEADER||AGROENTREPRENEURSHIP NC III||With TR|LOW | S15: TRUE | T15: TRUE | U15: TRUE | V15: TRUE | W15: FALSE | X15: FALSE | Y15: 2.25 | Z15: LOW | AA15: TRUE | AB15: REGION_VII|CEBU|Cebu City, District 2|AGRICULTURE FORESTRY AND FISHERY|CROP PRODUCTION ANIMAL PRODUCTION|FARMER LEADER||AGROENTREPRENEURSHIP NC III||With TR|LOW | AD15: TRUE | AE15: TRUE | AF15: TRUE | AG15: TRUE | AH15: FALSE | AI15: FALSE | AJ15: 2.25 | AK15: LOW | AL15: TRUE | AM15: REGION_VII|CEBU|Cebu, District 1|AGRICULTURE FORESTRY AND FISHERY|CROP PRODUCTION ANIMAL PRODUCTION|FARMER LEADER||AGROENTREPRENEURSHIP NC III||With TR|LOW | AO15: TRUE | AP15: TRUE | AQ15: TRUE | AR15: TRUE | AS15: FALSE | AT15: FALSE | AU15: 2.25 | AV15: LOW | AW15: TRUE | AX15: REGION_VII|CEBU|Cebu, District 2|AGRICULTURE FORESTRY AND FISHERY|CROP PRODUCTION ANIMAL PRODUCTION|FARMER LEADER||AGROENTREPRENEURSHIP NC III||With TR|LOW | AZ15: TRUE | BA15: TRUE | BB15: TRUE | BC15: FALSE | BD15: FALSE | BE15: TRUE | BF15: 1.25 | BG15: HIGH | BH15: TRUE | BI15: REGION_VII|CEBU|Cebu, District 3|AGRICULTURE FORESTRY AND FISHERY|CROP PRODUCTION ANIMAL PRODUCTION|FARMER LEADER||AGROENTREPRENEURSHIP NC III||With TR|HIGH | BK15: TRUE | BL15: TRUE | BM15: TRUE | BN15: TRUE | BO15: FALSE | BP15: FALSE | BQ15: 2.25 | BR15: LOW | BS15: TRUE | BT15: REGION_VII|CEBU|Cebu, District 4|AGRICULTURE FORESTRY AND FISHERY|CROP PRODUCTION ANIMAL PRODUCTION|FARMER LEADER||AGROENTREPRENEURSHIP NC III||With TR|LOW | BV15: TRUE | BW15: TRUE | BX15: TRUE | BY15: TRUE | BZ15: FALSE | CA15: FALSE | CB15: 2.25 | CC15: LOW | CD15: TRUE | CE15: REGION_VII|CEBU|Cebu, District 5|AGRICULTURE FORESTRY AND FISHERY|CROP PRODUCTION ANIMAL PRODUCTION|FARMER LEADER||AGROENTREPRENEURSHIP NC III||With TR|LOW | CG15: TRUE | CH15: TRUE | CI15: TRUE | CJ15: TRUE | CK15: FALSE | CL15: FALSE | CM15: 2.25 | CN15: LOW | CO15: TRUE | CP15: REGION_VII|CEBU|Cebu, District 6|AGRICULTURE FORESTRY AND FISHERY|CROP PRODUCTION ANIMAL PRODUCTION|FARMER LEADER||AGROENTREPRENEURSHIP NC III||With TR|LOW | CR15: TRUE | CS15: TRUE | CT15: TRUE | CU15: TRUE | CV15: FALSE | CW15: FALSE | CX15: 2.25 | CY15: LOW | CZ15: TRUE | DA15: REGION_VII|CEBU|Cebu, District 7|AGRICULTURE FORESTRY AND FISHERY|CROP PRODUCTION ANIMAL PRODUCTION|FARMER LEADER||AGROENTREPRENEURSHIP NC III||With TR|LOW | DC15: TRUE | DD15: TRUE | DE15: TRUE | DF15: TRUE | DG15: FALSE | DH15: FALSE | DI15: 2.25 | DJ15: LOW | DK15: TRUE | DL15: REGION_VII|CEBU|Lapu-Lapu City, Lone District|AGRICULTURE FORESTRY AND FISHERY|CROP PRODUCTION ANIMAL PRODUCTION|FARMER LEADER||AGROENTREPRENEURSHIP NC III||With TR|LOW | DN15: TRUE | DO15: TRUE | DP15: TRUE | DQ15: TRUE | DR15: FALSE | DS15: FALSE | DT15: 2.25 | DU15: LOW
A16: AGRICULTURE FORESTRY AND FISHERY | B16: CROP PRODUCTION ANIMAL PRODUCTION | C16: FARMER LEADER | D16: ASSIGN TASKS TO FARMERS IMPLEMENT FINANCIAL MANAGEMENT ENSURE PRODUCT SUPPLY | E16: AGROENTREPRENEURSHIP NC III | F16: With TR | G16: LOW | H16: TRUE | I16: TRUE | J16: TRUE | K16: TRUE | L16: FALSE | M16: FALSE | N16: 2.25 | O16: LOW | P16: TRUE | Q16: REGION_VII|CEBU|Cebu City, District 1|AGRICULTURE FORESTRY AND FISHERY|CROP PRODUCTION AGRICULTURAL SERVICES|FARMER/GROWER||AGRICULTURAL CROPS PRODUCTION NC II||With TR|LOW | S16: TRUE | T16: TRUE | U16: TRUE | V16: TRUE | W16: FALSE | X16: FALSE | Y16: 2.25 | Z16: LOW | AA16: TRUE | AB16: REGION_VII|CEBU|Cebu City, District 2|AGRICULTURE FORESTRY AND FISHERY|CROP PRODUCTION AGRICULTURAL SERVICES|FARMER/GROWER||AGRICULTURAL CROPS PRODUCTION NC II||With TR|LOW | AD16: TRUE | AE16: TRUE | AF16: TRUE | AG16: TRUE | AH16: FALSE | AI16: FALSE | AJ16: 2.25 | AK16: LOW | AL16: TRUE | AM16: REGION_VII|CEBU|Cebu, District 1|AGRICULTURE FORESTRY AND FISHERY|CROP PRODUCTION AGRICULTURAL SERVICES|FARMER/GROWER||AGRICULTURAL CROPS PRODUCTION NC II||With TR|LOW | AO16: TRUE | AP16: TRUE | AQ16: TRUE | AR16: FALSE | AS16: FALSE | AT16: TRUE | AU16: 1.25 | AV16: HIGH | AW16: TRUE | AX16: REGION_VII|CEBU|Cebu, District 2|AGRICULTURE FORESTRY AND FISHERY|CROP PRODUCTION AGRICULTURAL SERVICES|FARMER/GROWER||AGRICULTURAL CROPS PRODUCTION NC II||With TR|HIGH | AZ16: TRUE | BA16: TRUE | BB16: TRUE | BC16: FALSE | BD16: FALSE | BE16: TRUE | BF16: 1.25 | BG16: HIGH | BH16: TRUE | BI16: REGION_VII|CEBU|Cebu, District 3|AGRICULTURE FORESTRY AND FISHERY|CROP PRODUCTION AGRICULTURAL SERVICES|FARMER/GROWER||AGRICULTURAL CROPS PRODUCTION NC II||With TR|HIGH | BK16: TRUE | BL16: TRUE | BM16: TRUE | BN16: FALSE | BO16: TRUE | BP16: FALSE | BQ16: 1.75 | BR16: MEDIUM | BS16: TRUE | BT16: REGION_VII|CEBU|Cebu, District 4|AGRICULTURE FORESTRY AND FISHERY|CROP PRODUCTION AGRICULTURAL SERVICES|FARMER/GROWER||AGRICULTURAL CROPS PRODUCTION NC II||With TR|MEDIUM | BV16: TRUE | BW16: TRUE | BX16: TRUE | BY16: FALSE | BZ16: FALSE | CA16: TRUE | CB16: 1.25 | CC16: HIGH | CD16: TRUE | CE16: REGION_VII|CEBU|Cebu, District 5|AGRICULTURE FORESTRY AND FISHERY|CROP PRODUCTION AGRICULTURAL SERVICES|FARMER/GROWER||AGRICULTURAL CROPS PRODUCTION NC II||With TR|HIGH | CG16: TRUE | CH16: TRUE | CI16: TRUE | CJ16: FALSE | CK16: FALSE | CL16: TRUE | CM16: 1.25 | CN16: HIGH | CO16: TRUE | CP16: REGION_VII|CEBU|Cebu, District 6|AGRICULTURE FORESTRY AND FISHERY|CROP PRODUCTION AGRICULTURAL SERVICES|FARMER/GROWER||AGRICULTURAL CROPS PRODUCTION NC II||With TR|HIGH | CR16: TRUE | CS16: TRUE | CT16: TRUE | CU16: FALSE | CV16: TRUE | CW16: FALSE | CX16: 1.75 | CY16: MEDIUM | CZ16: TRUE | DA16: REGION_VII|CEBU|Cebu, District 7|AGRICULTURE FORESTRY AND FISHERY|CROP PRODUCTION AGRICULTURAL SERVICES|FARMER/GROWER||AGRICULTURAL CROPS PRODUCTION NC II||With TR|MEDIUM | DC16: TRUE | DD16: TRUE | DE16: TRUE | DF16: FALSE | DG16: FALSE | DH16: TRUE | DI16: 1.25 | DJ16: HIGH | DK16: TRUE | DL16: REGION_VII|CEBU|Lapu-Lapu City, Lone District|AGRICULTURE FORESTRY AND FISHERY|CROP PRODUCTION AGRICULTURAL SERVICES|FARMER/GROWER||AGRICULTURAL CROPS PRODUCTION NC II||With TR|HIGH | DN16: TRUE | DO16: TRUE | DP16: TRUE | DQ16: FALSE | DR16: FALSE | DS16: TRUE | DT16: 1.25 | DU16: HIGH
A17: AGRICULTURE FORESTRY AND FISHERY | B17: CROP PRODUCTION AGRICULTURAL SERVICES | C17: FARMER/GROWER | D17: PLANT CROPS | E17: AGRICULTURAL CROPS PRODUCTION NC II | F17: With TR | G17: HIGH | H17: TRUE | I17: TRUE | J17: TRUE | K17: TRUE | L17: FALSE | M17: FALSE | N17: 2.25 | O17: LOW | P17: TRUE | Q17: REGION_VII|CEBU|Cebu City, District 1|AGRICULTURE FORESTRY AND FISHERY|SUPPORT AGRICULTURAL SERVICES|FISH HANDLER||FISHPORT/WHARF OPERATION NC I||With TR|LOW | S17: TRUE | T17: TRUE | U17: TRUE | V17: TRUE | W17: FALSE | X17: FALSE | Y17: 2.25 | Z17: LOW | AA17: TRUE | AB17: REGION_VII|CEBU|Cebu City, District 2|AGRICULTURE FORESTRY AND FISHERY|SUPPORT AGRICULTURAL SERVICES|FISH HANDLER||FISHPORT/WHARF OPERATION NC I||With TR|LOW | AD17: FALSE | AE17: FALSE | AF17: FALSE | AG17: FALSE | AH17: FALSE | AI17: FALSE | AL17: FALSE | AO17: FALSE | AP17: FALSE | AQ17: FALSE | AR17: FALSE | AS17: FALSE | AT17: FALSE | AW17: FALSE | AZ17: TRUE | BA17: TRUE | BB17: TRUE | BC17: TRUE | BD17: FALSE | BE17: FALSE | BF17: 2.25 | BG17: LOW | BH17: TRUE | BI17: REGION_VII|CEBU|Cebu, District 3|AGRICULTURE FORESTRY AND FISHERY|SUPPORT AGRICULTURAL SERVICES|FISH HANDLER||FISHPORT/WHARF OPERATION NC I||With TR|LOW | BK17: TRUE | BL17: TRUE | BM17: TRUE | BN17: TRUE | BO17: FALSE | BP17: FALSE | BQ17: 2.25 | BR17: LOW | BS17: TRUE | BT17: REGION_VII|CEBU|Cebu, District 4|AGRICULTURE FORESTRY AND FISHERY|SUPPORT AGRICULTURAL SERVICES|FISH HANDLER||FISHPORT/WHARF OPERATION NC I||With TR|LOW | BV17: FALSE | BW17: FALSE | BX17: FALSE | BY17: FALSE | BZ17: FALSE | CA17: FALSE | CD17: FALSE | CG17: FALSE | CH17: FALSE | CI17: FALSE | CJ17: FALSE | CK17: FALSE | CL17: FALSE | CO17: FALSE | CR17: FALSE | CS17: FALSE | CT17: FALSE | CU17: FALSE | CV17: FALSE | CW17: FALSE | CZ17: FALSE | DC17: FALSE | DD17: FALSE | DE17: FALSE | DF17: FALSE | DG17: FALSE | DH17: FALSE | DK17: FALSE | DN17: TRUE | DO17: TRUE | DP17: TRUE | DQ17: TRUE | DR17: FALSE | DS17: FALSE | DT17: 2.25 | DU17: LOW
A18: AGRICULTURE FORESTRY AND FISHERY | B18: SUPPORT AGRICULTURAL SERVICES | C18: FISH HANDLER | D18: CLASSIFY FISH AND FISH PRODUCTS UNLOAD AND LOAD FISH AND FISH PRODUCTS | E18: FISHPORT/WHARF OPERATION NC I | F18: With TR | G18: LOW | H18: FALSE | I18: FALSE | J18: FALSE | K18: FALSE | L18: FALSE | M18: FALSE | P18: FALSE | S18: FALSE | T18: FALSE | U18: FALSE | V18: FALSE | W18: FALSE | X18: FALSE | AA18: FALSE | AD18: FALSE | AE18: FALSE | AF18: FALSE | AG18: FALSE | AH18: FALSE | AI18: FALSE | AL18: FALSE | AO18: FALSE | AP18: FALSE | AQ18: FALSE | AR18: FALSE | AS18: FALSE | AT18: FALSE | AW18: FALSE | AZ18: FALSE | BA18: FALSE | BB18: FALSE | BC18: FALSE | BD18: FALSE | BE18: FALSE | BH18: FALSE | BK18: TRUE | BL18: TRUE | BM18: TRUE | BN18: TRUE | BO18: FALSE | BP18: FALSE | BQ18: 2.25 | BR18: LOW | BS18: TRUE | BT18: REGION_VII|CEBU|Cebu, District 4|AGRICULTURE FORESTRY AND FISHERY|SUPPORT AGRICULTURAL SERVICES|FISHERMAN||FISH CAPTURE NC II||With TR|LOW | BV18: TRUE | BW18: TRUE | BX18: TRUE | BY18: TRUE | BZ18: FALSE | CA18: FALSE | CB18: 2.25 | CC18: LOW | CD18: TRUE | CE18: REGION_VII|CEBU|Cebu, District 5|AGRICULTURE FORESTRY AND FISHERY|SUPPORT AGRICULTURAL SERVICES|FISHERMAN||FISH CAPTURE NC II||With TR|LOW | CG18: FALSE | CH18: FALSE | CI18: FALSE | CJ18: FALSE | CK18: FALSE | CL18: FALSE | CO18: FALSE | CR18: FALSE | CS18: FALSE | CT18: FALSE | CU18: FALSE | CV18: FALSE | CW18: FALSE | CZ18: FALSE | DC18: TRUE | DD18: TRUE | DE18: TRUE | DF18: TRUE | DG18: FALSE | DH18: FALSE | DI18: 2.25 | DJ18: LOW | DK18: TRUE | DL18: REGION_VII|CEBU|Lapu-Lapu City, Lone District|AGRICULTURE FORESTRY AND FISHERY|SUPPORT AGRICULTURAL SERVICES|FISHERMAN||FISH CAPTURE NC II||With TR|LOW | DN18: FALSE | DO18: FALSE | DP18: FALSE | DQ18: FALSE | DR18: FALSE | DS18: FALSE
A19: AGRICULTURE FORESTRY AND FISHERY | B19: SUPPORT AGRICULTURAL SERVICES | C19: FISHERMAN | D19: MAINTAIN FISHING VESSEL PERFORM FISHING TASKS | E19: FISH CAPTURE NC II | F19: With TR | G19: LOW | H19: FALSE | I19: FALSE | J19: FALSE | K19: FALSE | L19: FALSE | M19: FALSE | P19: FALSE | S19: FALSE | T19: FALSE | U19: FALSE | V19: FALSE | W19: FALSE | X19: FALSE | AA19: FALSE | AD19: FALSE | AE19: FALSE | AF19: FALSE | AG19: FALSE | AH19: FALSE | AI19: FALSE | AL19: FALSE | AO19: FALSE | AP19: FALSE | AQ19: FALSE | AR19: FALSE | AS19: FALSE | AT19: FALSE | AW19: FALSE | AZ19: FALSE | BA19: FALSE | BB19: FALSE | BC19: FALSE | BD19: FALSE | BE19: FALSE | BH19: FALSE | BK19: TRUE | BL19: TRUE | BM19: TRUE | BN19: TRUE | BO19: FALSE | BP19: FALSE | BQ19: 2.25 | BR19: LOW | BS19: TRUE | BT19: REGION_VII|CEBU|Cebu, District 4|AGRICULTURE FORESTRY AND FISHERY|SUPPORT AGRICULTURAL SERVICES|FISHING GEAR TECHNICIAN||FISHING GEAR REPAIR AND MAINTENANCE NC III||With TR|LOW | BV19: TRUE | BW19: TRUE | BX19: TRUE | BY19: TRUE | BZ19: FALSE | CA19: FALSE | CB19: 2.25 | CC19: LOW | CD19: TRUE | CE19: REGION_VII|CEBU|Cebu, District 5|AGRICULTURE FORESTRY AND FISHERY|SUPPORT AGRICULTURAL SERVICES|FISHING GEAR TECHNICIAN||FISHING GEAR REPAIR AND MAINTENANCE NC III||With TR|LOW | CG19: FALSE | CH19: FALSE | CI19: FALSE | CJ19: FALSE | CK19: FALSE | CL19: FALSE | CO19: FALSE | CR19: FALSE | CS19: FALSE | CT19: FALSE | CU19: FALSE | CV19: FALSE | CW19: FALSE | CZ19: FALSE | DC19: TRUE | DD19: TRUE | DE19: TRUE | DF19: TRUE | DG19: FALSE | DH19: FALSE | DI19: 2.25 | DJ19: LOW | DK19: TRUE | DL19: REGION_VII|CEBU|Lapu-Lapu City, Lone District|AGRICULTURE FORESTRY AND FISHERY|SUPPORT AGRICULTURAL SERVICES|FISHING GEAR TECHNICIAN||FISHING GEAR REPAIR AND MAINTENANCE NC III||With TR|LOW | DN19: FALSE | DO19: FALSE | DP19: FALSE | DQ19: FALSE | DR19: FALSE | DS19: FALSE
A20: AGRICULTURE FORESTRY AND FISHERY | B20: SUPPORT AGRICULTURAL SERVICES | C20: FISHING GEAR TECHNICIAN | D20: MAINTAIN AND REPAIR VARIOUS TYPE OF FISHING GEAR NET MENDING | E20: FISHING GEAR REPAIR AND MAINTENANCE NC III | F20: With TR | G20: LOW | H20: TRUE | I20: TRUE | J20: TRUE | K20: TRUE | L20: FALSE | M20: FALSE | N20: 2.25 | O20: LOW | P20: TRUE | Q20: REGION_VII|CEBU|Cebu City, District 1|AGRICULTURE FORESTRY AND FISHERY|SUPPORT AGRICULTURAL SERVICES|FRUIT/VEGETABLE VENDOR||AGROENTREPRENEURSHIP NC II||With TR|LOW | S20: TRUE | T20: TRUE | U20: TRUE | V20: TRUE | W20: FALSE | X20: FALSE | Y20: 2.25 | Z20: LOW | AA20: TRUE | AB20: REGION_VII|CEBU|Cebu City, District 2|AGRICULTURE FORESTRY AND FISHERY|SUPPORT AGRICULTURAL SERVICES|FRUIT/VEGETABLE VENDOR||AGROENTREPRENEURSHIP NC II||With TR|LOW | AD20: TRUE | AE20: TRUE | AF20: TRUE | AG20: FALSE | AH20: TRUE | AI20: FALSE | AJ20: 1.75 | AK20: MEDIUM | AL20: TRUE | AM20: REGION_VII|CEBU|Cebu, District 1|AGRICULTURE FORESTRY AND FISHERY|SUPPORT AGRICULTURAL SERVICES|FRUIT/VEGETABLE VENDOR||AGROENTREPRENEURSHIP NC II||With TR|MEDIUM | AO20: TRUE | AP20: TRUE | AQ20: TRUE | AR20: TRUE | AS20: FALSE | AT20: FALSE | AU20: 2.25 | AV20: LOW | AW20: TRUE | AX20: REGION_VII|CEBU|Cebu, District 2|AGRICULTURE FORESTRY AND FISHERY|SUPPORT AGRICULTURAL SERVICES|FRUIT/VEGETABLE VENDOR||AGROENTREPRENEURSHIP NC II||With TR|LOW | AZ20: TRUE | BA20: TRUE | BB20: TRUE | BC20: FALSE | BD20: TRUE | BE20: FALSE | BF20: 1.75 | BG20: MEDIUM | BH20: TRUE | BI20: REGION_VII|CEBU|Cebu, District 3|AGRICULTURE FORESTRY AND FISHERY|SUPPORT AGRICULTURAL SERVICES|FRUIT/VEGETABLE VENDOR||AGROENTREPRENEURSHIP NC II||With TR|MEDIUM | BK20: TRUE | BL20: TRUE | BM20: TRUE | BN20: FALSE | BO20: TRUE | BP20: FALSE | BQ20: 1.75 | BR20: MEDIUM | BS20: TRUE | BT20: REGION_VII|CEBU|Cebu, District 4|AGRICULTURE FORESTRY AND FISHERY|SUPPORT AGRICULTURAL SERVICES|FRUIT/VEGETABLE VENDOR||AGROENTREPRENEURSHIP NC II||With TR|MEDIUM | BV20: TRUE | BW20: TRUE | BX20: TRUE | BY20: TRUE | BZ20: FALSE | CA20: FALSE | CB20: 2.25 | CC20: LOW | CD20: TRUE | CE20: REGION_VII|CEBU|Cebu, District 5|AGRICULTURE FORESTRY AND FISHERY|SUPPORT AGRICULTURAL SERVICES|FRUIT/VEGETABLE VENDOR||AGROENTREPRENEURSHIP NC II||With TR|LOW | CG20: TRUE | CH20: TRUE | CI20: TRUE | CJ20: TRUE | CK20: FALSE | CL20: FALSE | CM20: 2.25 | CN20: LOW | CO20: TRUE | CP20: REGION_VII|CEBU|Cebu, District 6|AGRICULTURE FORESTRY AND FISHERY|SUPPORT AGRICULTURAL SERVICES|FRUIT/VEGETABLE VENDOR||AGROENTREPRENEURSHIP NC II||With TR|LOW | CR20: TRUE | CS20: TRUE | CT20: TRUE | CU20: TRUE | CV20: FALSE | CW20: FALSE | CX20: 2.25 | CY20: LOW | CZ20: TRUE | DA20: REGION_VII|CEBU|Cebu, District 7|AGRICULTURE FORESTRY AND FISHERY|SUPPORT AGRICULTURAL SERVICES|FRUIT/VEGETABLE VENDOR||AGROENTREPRENEURSHIP NC II||With TR|LOW | DC20: TRUE | DD20: TRUE | DE20: TRUE | DF20: TRUE | DG20: FALSE | DH20: FALSE | DI20: 2.25 | DJ20: LOW | DK20: TRUE | DL20: REGION_VII|CEBU|Lapu-Lapu City, Lone District|AGRICULTURE FORESTRY AND FISHERY|SUPPORT AGRICULTURAL SERVICES|FRUIT/VEGETABLE VENDOR||AGROENTREPRENEURSHIP NC II||With TR|LOW | DN20: TRUE | DO20: TRUE | DP20: TRUE | DQ20: TRUE | DR20: FALSE | DS20: FALSE | DT20: 2.25 | DU20: LOW
A21: AGRICULTURE FORESTRY AND FISHERY | B21: SUPPORT AGRICULTURAL SERVICES | C21: FRUIT/VEGETABLE VENDOR | D21: SELL FRUITS AND VEGETABLES STORE AND HANDLE PRODUCE SORT AND DISPLAY PRODUCTS MONITOR INVENTORY OF PRODUCTS | E21: AGROENTREPRENEURSHIP NC II | F21: With TR | G21: LOW | H21: TRUE | I21: TRUE | J21: TRUE | K21: FALSE | L21: TRUE | M21: FALSE | N21: 1.75 | O21: MEDIUM | P21: TRUE | Q21: REGION_VII|CEBU|Cebu City, District 1|AGRICULTURE FORESTRY AND FISHERY|ANIMAL PRODUCTION|HATCHERY TECHNICIAN||ANIMAL PRODUCTION (POULTRY-CHICKEN) NC II||With TR|MEDIUM | S21: TRUE | T21: TRUE | U21: TRUE | V21: TRUE | W21: FALSE | X21: FALSE | Y21: 2.25 | Z21: LOW | AA21: TRUE | AB21: REGION_VII|CEBU|Cebu City, District 2|AGRICULTURE FORESTRY AND FISHERY|ANIMAL PRODUCTION|HATCHERY TECHNICIAN||ANIMAL PRODUCTION (POULTRY-CHICKEN) NC II||With TR|LOW | AD21: TRUE | AE21: TRUE | AF21: TRUE | AG21: FALSE | AH21: TRUE | AI21: FALSE | AJ21: 1.75 | AK21: MEDIUM | AL21: TRUE | AM21: REGION_VII|CEBU|Cebu, District 1|AGRICULTURE FORESTRY AND FISHERY|ANIMAL PRODUCTION|HATCHERY TECHNICIAN||ANIMAL PRODUCTION (POULTRY-CHICKEN) NC II||With TR|MEDIUM | AO21: TRUE | AP21: TRUE | AQ21: TRUE | AR21: TRUE | AS21: FALSE | AT21: FALSE | AU21: 2.25 | AV21: LOW | AW21: TRUE | AX21: REGION_VII|CEBU|Cebu, District 2|AGRICULTURE FORESTRY AND FISHERY|ANIMAL PRODUCTION|HATCHERY TECHNICIAN||ANIMAL PRODUCTION (POULTRY-CHICKEN) NC II||With TR|LOW | AZ21: TRUE | BA21: TRUE | BB21: TRUE | BC21: FALSE | BD21: FALSE | BE21: TRUE | BF21: 1.25 | BG21: HIGH | BH21: TRUE | BI21: REGION_VII|CEBU|Cebu, District 3|AGRICULTURE FORESTRY AND FISHERY|ANIMAL PRODUCTION|HATCHERY TECHNICIAN||ANIMAL PRODUCTION (POULTRY-CHICKEN) NC II||With TR|HIGH | BK21: TRUE | BL21: TRUE | BM21: TRUE | BN21: TRUE | BO21: FALSE | BP21: FALSE | BQ21: 2.25 | BR21: LOW | BS21: TRUE | BT21: REGION_VII|CEBU|Cebu, District 4|AGRICULTURE FORESTRY AND FISHERY|ANIMAL PRODUCTION|HATCHERY TECHNICIAN||ANIMAL PRODUCTION (POULTRY-CHICKEN) NC II||With TR|LOW | BV21: TRUE | BW21: TRUE | BX21: TRUE | BY21: TRUE | BZ21: FALSE | CA21: FALSE | CB21: 2.25 | CC21: LOW | CD21: TRUE | CE21: REGION_VII|CEBU|Cebu, District 5|AGRICULTURE FORESTRY AND FISHERY|ANIMAL PRODUCTION|HATCHERY TECHNICIAN||ANIMAL PRODUCTION (POULTRY-CHICKEN) NC II||With TR|LOW | CG21: TRUE | CH21: TRUE | CI21: TRUE | CJ21: FALSE | CK21: TRUE | CL21: FALSE | CM21: 1.75 | CN21: MEDIUM | CO21: TRUE | CP21: REGION_VII|CEBU|Cebu, District 6|AGRICULTURE FORESTRY AND FISHERY|ANIMAL PRODUCTION|HATCHERY TECHNICIAN||ANIMAL PRODUCTION (POULTRY-CHICKEN) NC II||With TR|MEDIUM | CR21: TRUE | CS21: TRUE | CT21: TRUE | CU21: TRUE | CV21: FALSE | CW21: FALSE | CX21: 2.25 | CY21: LOW | CZ21: TRUE | DA21: REGION_VII|CEBU|Cebu, District 7|AGRICULTURE FORESTRY AND FISHERY|ANIMAL PRODUCTION|HATCHERY TECHNICIAN||ANIMAL PRODUCTION (POULTRY-CHICKEN) NC II||With TR|LOW | DC21: TRUE | DD21: TRUE | DE21: TRUE | DF21: TRUE | DG21: FALSE | DH21: FALSE | DI21: 2.25 | DJ21: LOW | DK21: TRUE | DL21: REGION_VII|CEBU|Lapu-Lapu City, Lone District|AGRICULTURE FORESTRY AND FISHERY|ANIMAL PRODUCTION|HATCHERY TECHNICIAN||ANIMAL PRODUCTION (POULTRY-CHICKEN) NC II||With TR|LOW | DN21: TRUE | DO21: TRUE | DP21: TRUE | DQ21: FALSE | DR21: TRUE | DS21: FALSE | DT21: 1.75 | DU21: MEDIUM
A22: AGRICULTURE FORESTRY AND FISHERY | B22: ANIMAL PRODUCTION | C22: HATCHERY TECHNICIAN | D22: PERFORM PRE-LAY AND LAYING ACTIVITIES IN POULTRY OPERATIONS | E22: ANIMAL PRODUCTION (POULTRY-CHICKEN) NC II | F22: With TR | G22: LOW | H22: TRUE | I22: TRUE | J22: TRUE | K22: TRUE | L22: FALSE | M22: FALSE | N22: 2.25 | O22: LOW | P22: TRUE | Q22: REGION_VII|CEBU|Cebu City, District 1|AGRICULTURE FORESTRY AND FISHERY|CROP PRODUCTION|HORTICULTURE AIDE||HORTICULTURE NC III||With TR|LOW | S22: TRUE | T22: TRUE | U22: TRUE | V22: TRUE | W22: FALSE | X22: FALSE | Y22: 2.25 | Z22: LOW | AA22: TRUE | AB22: REGION_VII|CEBU|Cebu City, District 2|AGRICULTURE FORESTRY AND FISHERY|CROP PRODUCTION|HORTICULTURE AIDE||HORTICULTURE NC III||With TR|LOW | AD22: TRUE | AE22: TRUE | AF22: TRUE | AG22: TRUE | AH22: FALSE | AI22: FALSE | AJ22: 2.25 | AK22: LOW | AL22: TRUE | AM22: REGION_VII|CEBU|Cebu, District 1|AGRICULTURE FORESTRY AND FISHERY|CROP PRODUCTION|HORTICULTURE AIDE||HORTICULTURE NC III||With TR|LOW | AO22: TRUE | AP22: TRUE | AQ22: TRUE | AR22: TRUE | AS22: FALSE | AT22: FALSE | AU22: 2.25 | AV22: LOW | AW22: TRUE | AX22: REGION_VII|CEBU|Cebu, District 2|AGRICULTURE FORESTRY AND FISHERY|CROP PRODUCTION|HORTICULTURE AIDE||HORTICULTURE NC III||With TR|LOW | AZ22: TRUE | BA22: TRUE | BB22: TRUE | BC22: TRUE | BD22: FALSE | BE22: FALSE | BF22: 2.25 | BG22: LOW | BH22: TRUE | BI22: REGION_VII|CEBU|Cebu, District 3|AGRICULTURE FORESTRY AND FISHERY|CROP PRODUCTION|HORTICULTURE AIDE||HORTICULTURE NC III||With TR|LOW | BK22: TRUE | BL22: TRUE | BM22: TRUE | BN22: TRUE | BO22: FALSE | BP22: FALSE | BQ22: 2.25 | BR22: LOW | BS22: TRUE | BT22: REGION_VII|CEBU|Cebu, District 4|AGRICULTURE FORESTRY AND FISHERY|CROP PRODUCTION|HORTICULTURE AIDE||HORTICULTURE NC III||With TR|LOW | BV22: TRUE | BW22: TRUE | BX22: TRUE | BY22: TRUE | BZ22: FALSE | CA22: FALSE | CB22: 2.25 | CC22: LOW | CD22: TRUE | CE22: REGION_VII|CEBU|Cebu, District 5|AGRICULTURE FORESTRY AND FISHERY|CROP PRODUCTION|HORTICULTURE AIDE||HORTICULTURE NC III||With TR|LOW | CG22: FALSE | CH22: FALSE | CI22: FALSE | CJ22: FALSE | CK22: FALSE | CL22: FALSE | CO22: FALSE | CR22: FALSE | CS22: FALSE | CT22: FALSE | CU22: FALSE | CV22: FALSE | CW22: FALSE | CZ22: FALSE | DC22: FALSE | DD22: FALSE | DE22: FALSE | DF22: FALSE | DG22: FALSE | DH22: FALSE | DK22: FALSE | DN22: TRUE | DO22: TRUE | DP22: TRUE | DQ22: TRUE | DR22: FALSE | DS22: FALSE | DT22: 2.25 | DU22: LOW
A23: AGRICULTURE FORESTRY AND FISHERY | B23: CROP PRODUCTION | C23: HORTICULTURE AIDE | D23: PROVIDE GENERAL SUPPORT IN HORTICULTURE PROJECTS ASSIST IN RECORD-KEEPING AND REPORTING PLANT GROWTH PROGRESS | E23: HORTICULTURE NC III | F23: With TR | G23: LOW | H23: TRUE | I23: TRUE | J23: TRUE | K23: FALSE | L23: TRUE | M23: FALSE | N23: 1.75 | O23: MEDIUM | P23: TRUE | Q23: REGION_VII|CEBU|Cebu City, District 1|AGRICULTURE FORESTRY AND FISHERY|CROP PRODUCTION|ORGANIC AGRICULTURE FARMER||ORGANIC AGRICULTURE PRODUCTION NC II||With TR|MEDIUM | S23: TRUE | T23: TRUE | U23: TRUE | V23: FALSE | W23: TRUE | X23: FALSE | Y23: 1.75 | Z23: MEDIUM | AA23: TRUE | AB23: REGION_VII|CEBU|Cebu City, District 2|AGRICULTURE FORESTRY AND FISHERY|CROP PRODUCTION|ORGANIC AGRICULTURE FARMER||ORGANIC AGRICULTURE PRODUCTION NC II||With TR|MEDIUM | AD23: TRUE | AE23: TRUE | AF23: TRUE | AG23: FALSE | AH23: TRUE | AI23: FALSE | AJ23: 1.75 | AK23: MEDIUM | AL23: TRUE | AM23: REGION_VII|CEBU|Cebu, District 1|AGRICULTURE FORESTRY AND FISHERY|CROP PRODUCTION|ORGANIC AGRICULTURE FARMER||ORGANIC AGRICULTURE PRODUCTION NC II||With TR|MEDIUM | AO23: TRUE | AP23: TRUE | AQ23: TRUE | AR23: FALSE | AS23: TRUE | AT23: FALSE | AU23: 1.75 | AV23: MEDIUM | AW23: TRUE | AX23: REGION_VII|CEBU|Cebu, District 2|AGRICULTURE FORESTRY AND FISHERY|CROP PRODUCTION|ORGANIC AGRICULTURE FARMER||ORGANIC AGRICULTURE PRODUCTION NC II||With TR|MEDIUM | AZ23: TRUE | BA23: TRUE | BB23: TRUE | BC23: FALSE | BD23: TRUE | BE23: FALSE | BF23: 1.75 | BG23: MEDIUM | BH23: TRUE | BI23: REGION_VII|CEBU|Cebu, District 3|AGRICULTURE FORESTRY AND FISHERY|CROP PRODUCTION|ORGANIC AGRICULTURE FARMER||ORGANIC AGRICULTURE PRODUCTION NC II||With TR|MEDIUM | BK23: TRUE | BL23: TRUE | BM23: TRUE | BN23: FALSE | BO23: TRUE | BP23: FALSE | BQ23: 1.75 | BR23: MEDIUM | BS23: TRUE | BT23: REGION_VII|CEBU|Cebu, District 4|AGRICULTURE FORESTRY AND FISHERY|CROP PRODUCTION|ORGANIC AGRICULTURE FARMER||ORGANIC AGRICULTURE PRODUCTION NC II||With TR|MEDIUM | BV23: TRUE | BW23: TRUE | BX23: TRUE | BY23: FALSE | BZ23: TRUE | CA23: FALSE | CB23: 1.75 | CC23: MEDIUM | CD23: TRUE | CE23: REGION_VII|CEBU|Cebu, District 5|AGRICULTURE FORESTRY AND FISHERY|CROP PRODUCTION|ORGANIC AGRICULTURE FARMER||ORGANIC AGRICULTURE PRODUCTION NC II||With TR|MEDIUM | CG23: TRUE | CH23: TRUE | CI23: TRUE | CJ23: TRUE | CK23: FALSE | CL23: FALSE | CM23: 2.25 | CN23: LOW | CO23: TRUE | CP23: REGION_VII|CEBU|Cebu, District 6|AGRICULTURE FORESTRY AND FISHERY|CROP PRODUCTION|ORGANIC AGRICULTURE FARMER||ORGANIC AGRICULTURE PRODUCTION NC II||With TR|LOW | CR23: TRUE | CS23: TRUE | CT23: TRUE | CU23: FALSE | CV23: TRUE | CW23: FALSE | CX23: 1.75 | CY23: MEDIUM | CZ23: TRUE | DA23: REGION_VII|CEBU|Cebu, District 7|AGRICULTURE FORESTRY AND FISHERY|CROP PRODUCTION|ORGANIC AGRICULTURE FARMER||ORGANIC AGRICULTURE PRODUCTION NC II||With TR|MEDIUM | DC23: TRUE | DD23: TRUE | DE23: TRUE | DF23: TRUE | DG23: FALSE | DH23: FALSE | DI23: 2.25 | DJ23: LOW | DK23: TRUE | DL23: REGION_VII|CEBU|Lapu-Lapu City, Lone District|AGRICULTURE FORESTRY AND FISHERY|CROP PRODUCTION|ORGANIC AGRICULTURE FARMER||ORGANIC AGRICULTURE PRODUCTION NC II||With TR|LOW | DN23: TRUE | DO23: TRUE | DP23: TRUE | DQ23: TRUE | DR23: FALSE | DS23: FALSE | DT23: 2.25 | DU23: LOW
A24: AGRICULTURE FORESTRY AND FISHERY | B24: CROP PRODUCTION | C24: ORGANIC AGRICULTURE FARMER | D24: PRODUCE ORGANIC CROPS AND VEGETABLES RAISE ORGANIC HOGS AND CHICKEN | E24: ORGANIC AGRICULTURE PRODUCTION NC II | F24: With TR | G24: MEDIUM | H24: TRUE | I24: TRUE | J24: TRUE | K24: TRUE | L24: FALSE | M24: FALSE | N24: 2.25 | O24: LOW | P24: TRUE | Q24: REGION_VII|CEBU|Cebu City, District 1|AGRICULTURE FORESTRY AND FISHERY|CROP PRODUCTION SUPPORT AGRICULTURAL SERVICES|PEST CONTROL TECHNICIAN||PEST MANAGEMENT (VEGETABLES) NC II||With TR|LOW | S24: TRUE | T24: TRUE | U24: TRUE | V24: TRUE | W24: FALSE | X24: FALSE | Y24: 2.25 | Z24: LOW | AA24: TRUE | AB24: REGION_VII|CEBU|Cebu City, District 2|AGRICULTURE FORESTRY AND FISHERY|CROP PRODUCTION SUPPORT AGRICULTURAL SERVICES|PEST CONTROL TECHNICIAN||PEST MANAGEMENT (VEGETABLES) NC II||With TR|LOW | AD24: TRUE | AE24: TRUE | AF24: TRUE | AG24: TRUE | AH24: FALSE | AI24: FALSE | AJ24: 2.25 | AK24: LOW | AL24: TRUE | AM24: REGION_VII|CEBU|Cebu, District 1|AGRICULTURE FORESTRY AND FISHERY|CROP PRODUCTION SUPPORT AGRICULTURAL SERVICES|PEST CONTROL TECHNICIAN||PEST MANAGEMENT (VEGETABLES) NC II||With TR|LOW | AO24: TRUE | AP24: TRUE | AQ24: TRUE | AR24: TRUE | AS24: FALSE | AT24: FALSE | AU24: 2.25 | AV24: LOW | AW24: TRUE | AX24: REGION_VII|CEBU|Cebu, District 2|AGRICULTURE FORESTRY AND FISHERY|CROP PRODUCTION SUPPORT AGRICULTURAL SERVICES|PEST CONTROL TECHNICIAN||PEST MANAGEMENT (VEGETABLES) NC II||With TR|LOW | AZ24: TRUE | BA24: TRUE | BB24: TRUE | BC24: TRUE | BD24: FALSE | BE24: FALSE | BF24: 2.25 | BG24: LOW | BH24: TRUE | BI24: REGION_VII|CEBU|Cebu, District 3|AGRICULTURE FORESTRY AND FISHERY|CROP PRODUCTION SUPPORT AGRICULTURAL SERVICES|PEST CONTROL TECHNICIAN||PEST MANAGEMENT (VEGETABLES) NC II||With TR|LOW | BK24: TRUE | BL24: TRUE | BM24: TRUE | BN24: TRUE | BO24: FALSE | BP24: FALSE | BQ24: 2.25 | BR24: LOW | BS24: TRUE | BT24: REGION_VII|CEBU|Cebu, District 4|AGRICULTURE FORESTRY AND FISHERY|CROP PRODUCTION SUPPORT AGRICULTURAL SERVICES|PEST CONTROL TECHNICIAN||PEST MANAGEMENT (VEGETABLES) NC II||With TR|LOW | BV24: TRUE | BW24: TRUE | BX24: TRUE | BY24: TRUE | BZ24: FALSE | CA24: FALSE | CB24: 2.25 | CC24: LOW | CD24: TRUE | CE24: REGION_VII|CEBU|Cebu, District 5|AGRICULTURE FORESTRY AND FISHERY|CROP PRODUCTION SUPPORT AGRICULTURAL SERVICES|PEST CONTROL TECHNICIAN||PEST MANAGEMENT (VEGETABLES) NC II||With TR|LOW | CG24: TRUE | CH24: TRUE | CI24: TRUE | CJ24: TRUE | CK24: FALSE | CL24: FALSE | CM24: 2.25 | CN24: LOW | CO24: TRUE | CP24: REGION_VII|CEBU|Cebu, District 6|AGRICULTURE FORESTRY AND FISHERY|CROP PRODUCTION SUPPORT AGRICULTURAL SERVICES|PEST CONTROL TECHNICIAN||PEST MANAGEMENT (VEGETABLES) NC II||With TR|LOW | CR24: TRUE | CS24: TRUE | CT24: TRUE | CU24: FALSE | CV24: FALSE | CW24: FALSE | CZ24: TRUE | DA24: REGION_VII|CEBU|Cebu, District 7|AGRICULTURE FORESTRY AND FISHERY|CROP PRODUCTION SUPPORT AGRICULTURAL SERVICES|PEST CONTROL TECHNICIAN||PEST MANAGEMENT (VEGETABLES) NC II||With TR| | DC24: TRUE | DD24: TRUE | DE24: TRUE | DF24: TRUE | DG24: FALSE | DH24: FALSE | DI24: 2.25 | DJ24: LOW | DK24: TRUE | DL24: REGION_VII|CEBU|Lapu-Lapu City, Lone District|AGRICULTURE FORESTRY AND FISHERY|CROP PRODUCTION SUPPORT AGRICULTURAL SERVICES|PEST CONTROL TECHNICIAN||PEST MANAGEMENT (VEGETABLES) NC II||With TR|LOW | DN24: TRUE | DO24: TRUE | DP24: TRUE | DQ24: TRUE | DR24: FALSE | DS24: FALSE | DT24: 2.25 | DU24: LOW
A25: AGRICULTURE FORESTRY AND FISHERY | B25: CROP PRODUCTION SUPPORT AGRICULTURAL SERVICES | C25: PEST CONTROL TECHNICIAN | D25: MONITOR PEST POPULATION IMPLEMENT PEST MANAGEMENT STRATEGIES | E25: PEST MANAGEMENT (VEGETABLES) NC II | F25: With TR | G25: LOW | H25: FALSE | I25: FALSE | J25: FALSE | K25: FALSE | L25: FALSE | M25: FALSE | P25: FALSE | S25: TRUE | T25: TRUE | U25: TRUE | V25: TRUE | W25: FALSE | X25: FALSE | Y25: 2.25 | Z25: LOW | AA25: TRUE | AB25: REGION_VII|CEBU|Cebu City, District 2|AGRICULTURE FORESTRY AND FISHERY|ANIMAL PRODUCTION|RABBIT RAISER||NO CORRESPONDING TVET PROGRAM||New and Emerging|LOW | AD25: TRUE | AE25: TRUE | AF25: TRUE | AG25: TRUE | AH25: FALSE | AI25: FALSE | AJ25: 2.25 | AK25: LOW | AL25: TRUE | AM25: REGION_VII|CEBU|Cebu, District 1|AGRICULTURE FORESTRY AND FISHERY|ANIMAL PRODUCTION|RABBIT RAISER||NO CORRESPONDING TVET PROGRAM||New and Emerging|LOW | AO25: FALSE | AP25: FALSE | AQ25: FALSE | AR25: FALSE | AS25: FALSE | AT25: FALSE | AW25: FALSE | AZ25: FALSE | BA25: FALSE | BB25: FALSE | BC25: FALSE | BD25: FALSE | BE25: FALSE | BH25: FALSE | BK25: FALSE | BL25: FALSE | BM25: FALSE | BN25: FALSE | BO25: FALSE | BP25: FALSE | BS25: FALSE | BV25: TRUE | BW25: TRUE | BX25: TRUE | BY25: TRUE | BZ25: FALSE | CA25: FALSE | CB25: 2.25 | CC25: LOW | CD25: TRUE | CE25: REGION_VII|CEBU|Cebu, District 5|AGRICULTURE FORESTRY AND FISHERY|ANIMAL PRODUCTION|RABBIT RAISER||NO CORRESPONDING TVET PROGRAM||New and Emerging|LOW | CG25: FALSE | CH25: FALSE | CI25: FALSE | CJ25: FALSE | CK25: FALSE | CL25: FALSE | CO25: FALSE | CR25: FALSE | CS25: FALSE | CT25: FALSE | CU25: FALSE | CV25: FALSE | CW25: FALSE | CZ25: FALSE | DC25: FALSE | DD25: FALSE | DE25: FALSE | DF25: FALSE | DG25: FALSE | DH25: FALSE | DK25: FALSE | DN25: FALSE | DO25: FALSE | DP25: FALSE | DQ25: FALSE | DR25: FALSE | DS25: FALSE
A26: AGRICULTURE FORESTRY AND FISHERY | B26: ANIMAL PRODUCTION | C26: RABBIT RAISER | D26: FEED RABBITS MANAGE BREEDING MONITOR THE HEALTH AND BEHAVIOR | E26: NO CORRESPONDING TVET PROGRAM | F26: New and Emerging | G26: LOW | H26: FALSE | I26: FALSE | J26: FALSE | K26: FALSE | L26: FALSE | M26: FALSE | P26: FALSE | S26: FALSE | T26: FALSE | U26: FALSE | V26: FALSE | W26: FALSE | X26: FALSE | AA26: FALSE | AD26: FALSE | AE26: FALSE | AF26: FALSE | AG26: FALSE | AH26: FALSE | AI26: FALSE | AL26: FALSE | AO26: FALSE | AP26: FALSE | AQ26: FALSE | AR26: FALSE | AS26: FALSE | AT26: FALSE | AW26: FALSE | AZ26: FALSE | BA26: FALSE | BB26: FALSE | BC26: FALSE | BD26: FALSE | BE26: FALSE | BH26: FALSE | BK26: FALSE | BL26: FALSE | BM26: FALSE | BN26: FALSE | BO26: FALSE | BP26: FALSE | BS26: FALSE | BV26: TRUE | BW26: TRUE | BX26: TRUE | BY26: TRUE | BZ26: FALSE | CA26: FALSE | CB26: 2.25 | CC26: LOW | CD26: TRUE | CE26: REGION_VII|CEBU|Cebu, District 5|AGRICULTURE FORESTRY AND FISHERY|AGRICULTURAL SERVICES|SMART IRRIGATORS||NO CORRESPONDING TVET PROGRAM||New and Emerging|LOW | CG26: FALSE | CH26: FALSE | CI26: FALSE | CJ26: FALSE | CK26: FALSE | CL26: FALSE | CO26: FALSE | CR26: FALSE | CS26: FALSE | CT26: FALSE | CU26: FALSE | CV26: FALSE | CW26: FALSE | CZ26: FALSE | DC26: FALSE | DD26: FALSE | DE26: FALSE | DF26: FALSE | DG26: FALSE | DH26: FALSE | DK26: FALSE | DN26: FALSE | DO26: FALSE | DP26: FALSE | DQ26: FALSE | DR26: FALSE | DS26: FALSE
A27: AGRICULTURE FORESTRY AND FISHERY | B27: AGRICULTURAL SERVICES | C27: SMART IRRIGATORS | D27: INSTALL SMART IRRIGATION CONTOLLERS, TIMERS AND SENSORS PROGRAM AND CONFIGURE IRRIGATION CONTROLS IDENTIFY AND REPAIR ISSUES ENSURE ALL INSTALLATIONS COMPLY WITH THE RIHGULATIONS | E27: NO CORRESPONDING TVET PROGRAM | F27: New and Emerging | G27: LOW | H27: FALSE | I27: FALSE | J27: FALSE | K27: FALSE | L27: FALSE | M27: FALSE | P27: FALSE | S27: FALSE | T27: FALSE | U27: FALSE | V27: FALSE | W27: FALSE | X27: FALSE | AA27: FALSE | AD27: TRUE | AE27: TRUE | AF27: TRUE | AG27: TRUE | AH27: FALSE | AI27: FALSE | AJ27: 2.25 | AK27: LOW | AL27: TRUE | AM27: REGION_VII|CEBU|Cebu, District 1|AGRICULTURE FORESTRY AND FISHERY|ANIMAL PRODUCTION|SWINE RAISER||ANIMAL PRODUCTION (SWINE) NC II||With TR|LOW | AO27: FALSE | AP27: FALSE | AQ27: FALSE | AR27: FALSE | AS27: FALSE | AT27: FALSE | AW27: FALSE | AZ27: TRUE | BA27: TRUE | BB27: TRUE | BC27: FALSE | BD27: TRUE | BE27: FALSE | BF27: 1.75 | BG27: MEDIUM | BH27: TRUE | BI27: REGION_VII|CEBU|Cebu, District 3|AGRICULTURE FORESTRY AND FISHERY|ANIMAL PRODUCTION|SWINE RAISER||ANIMAL PRODUCTION (SWINE) NC II||With TR|MEDIUM | BK27: TRUE | BL27: TRUE | BM27: TRUE | BN27: TRUE | BO27: FALSE | BP27: FALSE | BQ27: 2.25 | BR27: LOW | BS27: TRUE | BT27: REGION_VII|CEBU|Cebu, District 4|AGRICULTURE FORESTRY AND FISHERY|ANIMAL PRODUCTION|SWINE RAISER||ANIMAL PRODUCTION (SWINE) NC II||With TR|LOW | BV27: FALSE | BW27: FALSE | BX27: FALSE | BY27: FALSE | BZ27: FALSE | CA27: FALSE | CD27: FALSE | CG27: FALSE | CH27: FALSE | CI27: FALSE | CJ27: FALSE | CK27: FALSE | CL27: FALSE | CO27: FALSE | CR27: FALSE | CS27: FALSE | CT27: FALSE | CU27: FALSE | CV27: FALSE | CW27: FALSE | CZ27: FALSE | DC27: FALSE | DD27: FALSE | DE27: FALSE | DF27: FALSE | DG27: FALSE | DH27: FALSE | DK27: FALSE | DN27: FALSE | DO27: FALSE | DP27: FALSE | DQ27: FALSE | DR27: FALSE | DS27: FALSE
A28: AGRICULTURE FORESTRY AND FISHERY | B28: ANIMAL PRODUCTION | C28: SWINE RAISER | D28: RAISE SWINE FROM BIRTH TO FINISHER | E28: ANIMAL PRODUCTION (SWINE) NC II | F28: With TR | G28: LOW | H28: TRUE | I28: TRUE | J28: TRUE | K28: TRUE | L28: FALSE | M28: FALSE | N28: 2.25 | O28: LOW | P28: TRUE | Q28: REGION_VII|CEBU|Cebu City, District 1|AGRICULTURE FORESTRY AND FISHERY|SUPPORT AGRICULTURAL SERVICES|VETERINARY TECHNICIAN||ANIMAL HEALTH CARE AND MANAGEMENT NC III||With TR|LOW | S28: TRUE | T28: TRUE | U28: TRUE | V28: TRUE | W28: FALSE | X28: FALSE | Y28: 2.25 | Z28: LOW | AA28: TRUE | AB28: REGION_VII|CEBU|Cebu City, District 2|AGRICULTURE FORESTRY AND FISHERY|SUPPORT AGRICULTURAL SERVICES|VETERINARY TECHNICIAN||ANIMAL HEALTH CARE AND MANAGEMENT NC III||With TR|LOW | AD28: FALSE | AE28: FALSE | AF28: FALSE | AG28: FALSE | AH28: FALSE | AI28: FALSE | AL28: FALSE | AO28: FALSE | AP28: FALSE | AQ28: FALSE | AR28: FALSE | AS28: FALSE | AT28: FALSE | AW28: FALSE | AZ28: FALSE | BA28: FALSE | BB28: FALSE | BC28: FALSE | BD28: FALSE | BE28: FALSE | BH28: FALSE | BK28: FALSE | BL28: FALSE | BM28: FALSE | BN28: FALSE | BO28: FALSE | BP28: FALSE | BS28: FALSE | BV28: FALSE | BW28: FALSE | BX28: FALSE | BY28: FALSE | BZ28: FALSE | CA28: FALSE | CD28: FALSE | CG28: FALSE | CH28: FALSE | CI28: FALSE | CJ28: FALSE | CK28: FALSE | CL28: FALSE | CO28: FALSE | CR28: FALSE | CS28: FALSE | CT28: FALSE | CU28: FALSE | CV28: FALSE | CW28: FALSE | CZ28: FALSE | DC28: TRUE | DD28: TRUE | DE28: TRUE | DF28: TRUE | DG28: FALSE | DH28: FALSE | DI28: 2.25 | DJ28: LOW | DK28: TRUE | DL28: REGION_VII|CEBU|Lapu-Lapu City, Lone District|AGRICULTURE FORESTRY AND FISHERY|SUPPORT AGRICULTURAL SERVICES|VETERINARY TECHNICIAN||ANIMAL HEALTH CARE AND MANAGEMENT NC III||With TR|LOW | DN28: TRUE | DO28: TRUE | DP28: TRUE | DQ28: TRUE | DR28: FALSE | DS28: FALSE | DT28: 2.25 | DU28: LOW
A29: AGRICULTURE FORESTRY AND FISHERY | B29: SUPPORT AGRICULTURAL SERVICES | C29: VETERINARY TECHNICIAN | D29: ASSIST VETERINARIANS DURING EXAMINATIONS, SURGERIES, AND TREATMENTS PERFORM DIAGNOSTIC TESTS ADMINISTER MEDICATION | E29: ANIMAL HEALTH CARE AND MANAGEMENT NC III | F29: With TR | G29: LOW | H29: TRUE | I29: TRUE | J29: TRUE | K29: TRUE | L29: FALSE | M29: FALSE | N29: 2.25 | O29: LOW | P29: TRUE | Q29: REGION_VII|CEBU|Cebu City, District 1|AUTOMOTIVE AND LAND TRANSPORTATION|DESIGN AND DEVELOPMENT| _x000D_ _x000D_ AUTOMOTIVE PAINTER (SINGLE STAGE PAINTING)||AUTOMOTIVE BODY PAINTING/FINISHING NC III||With TR|LOW | S29: TRUE | T29: TRUE | U29: TRUE | V29: TRUE | W29: FALSE | X29: FALSE | Y29: 2.25 | Z29: LOW | AA29: TRUE | AB29: REGION_VII|CEBU|Cebu City, District 2|AUTOMOTIVE AND LAND TRANSPORTATION|DESIGN AND DEVELOPMENT| _x000D_ _x000D_ AUTOMOTIVE PAINTER (SINGLE STAGE PAINTING)||AUTOMOTIVE BODY PAINTING/FINISHING NC III||With TR|LOW | AD29: TRUE | AE29: TRUE | AF29: TRUE | AG29: TRUE | AH29: FALSE | AI29: FALSE | AJ29: 2.25 | AK29: LOW | AL29: TRUE | AM29: REGION_VII|CEBU|Cebu, District 1|AUTOMOTIVE AND LAND TRANSPORTATION|DESIGN AND DEVELOPMENT| _x000D_ _x000D_ AUTOMOTIVE PAINTER (SINGLE STAGE PAINTING)||AUTOMOTIVE BODY PAINTING/FINISHING NC III||With TR|LOW | AO29: FALSE | AP29: FALSE | AQ29: FALSE | AR29: FALSE | AS29: TRUE | AT29: FALSE | AW29: FALSE | AZ29: TRUE | BA29: TRUE | BB29: TRUE | BC29: FALSE | BD29: TRUE | BE29: FALSE | BF29: 1.75 | BG29: MEDIUM | BH29: TRUE | BI29: REGION_VII|CEBU|Cebu, District 3|AUTOMOTIVE AND LAND TRANSPORTATION|DESIGN AND DEVELOPMENT| _x000D_ _x000D_ AUTOMOTIVE PAINTER (SINGLE STAGE PAINTING)||AUTOMOTIVE BODY PAINTING/FINISHING NC III||With TR|MEDIUM | BK29: TRUE | BL29: TRUE | BM29: TRUE | BN29: TRUE | BO29: FALSE | BP29: FALSE | BQ29: 2.25 | BR29: LOW | BS29: TRUE | BT29: REGION_VII|CEBU|Cebu, District 4|AUTOMOTIVE AND LAND TRANSPORTATION|DESIGN AND DEVELOPMENT| _x000D_ _x000D_ AUTOMOTIVE PAINTER (SINGLE STAGE PAINTING)||AUTOMOTIVE BODY PAINTING/FINISHING NC III||With TR|LOW | BV29: TRUE | BW29: TRUE | BX29: TRUE | BY29: TRUE | BZ29: FALSE | CA29: FALSE | CB29: 2.25 | CC29: LOW | CD29: TRUE | CE29: REGION_VII|CEBU|Cebu, District 5|AUTOMOTIVE AND LAND TRANSPORTATION|DESIGN AND DEVELOPMENT| _x000D_ _x000D_ AUTOMOTIVE PAINTER (SINGLE STAGE PAINTING)||AUTOMOTIVE BODY PAINTING/FINISHING NC III||With TR|LOW | CG29: FALSE | CH29: FALSE | CI29: FALSE | CJ29: FALSE | CK29: FALSE | CL29: FALSE | CO29: FALSE | CR29: TRUE | CS29: TRUE | CT29: TRUE | CU29: TRUE | CV29: FALSE | CW29: FALSE | CX29: 2.25 | CY29: LOW | CZ29: TRUE | DA29: REGION_VII|CEBU|Cebu, District 7|AUTOMOTIVE AND LAND TRANSPORTATION|DESIGN AND DEVELOPMENT| _x000D_ _x000D_ AUTOMOTIVE PAINTER (SINGLE STAGE PAINTING)||AUTOMOTIVE BODY PAINTING/FINISHING NC III||With TR|LOW | DC29: TRUE | DD29: TRUE | DE29: TRUE | DF29: FALSE | DG29: TRUE | DH29: FALSE | DI29: 1.75 | DJ29: MEDIUM | DK29: TRUE | DL29: REGION_VII|CEBU|Lapu-Lapu City, Lone District|AUTOMOTIVE AND LAND TRANSPORTATION|DESIGN AND DEVELOPMENT| _x000D_ _x000D_ AUTOMOTIVE PAINTER (SINGLE STAGE PAINTING)||AUTOMOTIVE BODY PAINTING/FINISHING NC III||With TR|MEDIUM | DN29: TRUE | DO29: TRUE | DP29: TRUE | DQ29: FALSE | DR29: TRUE | DS29: FALSE | DT29: 1.75 | DU29: MEDIUM
A30: AUTOMOTIVE AND LAND TRANSPORTATION | B30: DESIGN AND DEVELOPMENT | C30: _x000D_ _x000D_ AUTOMOTIVE PAINTER (SINGLE STAGE PAINTING) | D30: PERFORM PEARL COLOR MATCHING SPRAY THREE-STAGE PEARL OR MICA COLOR PAINT | E30: AUTOMOTIVE BODY PAINTING/FINISHING NC III | F30: With TR | G30: LOW | H30: TRUE | I30: TRUE | J30: TRUE | K30: FALSE | L30: FALSE | M30: TRUE | N30: 1.25 | O30: HIGH | P30: TRUE | Q30: REGION_VII|CEBU|Cebu City, District 1|AUTOMOTIVE AND LAND TRANSPORTATION|AUTOMOTIVE AND LAND TRANSPORTATION|AUTO BODY REPAIR TECHNICIAN||AUTOMOTIVE SERVICING (CHASSIS REPAIR) NC II||With TR|HIGH | S30: TRUE | T30: TRUE | U30: TRUE | V30: FALSE | W30: FALSE | X30: TRUE | Y30: 1.25 | Z30: HIGH | AA30: TRUE | AB30: REGION_VII|CEBU|Cebu City, District 2|AUTOMOTIVE AND LAND TRANSPORTATION|AUTOMOTIVE AND LAND TRANSPORTATION|AUTO BODY REPAIR TECHNICIAN||AUTOMOTIVE SERVICING (CHASSIS REPAIR) NC II||With TR|HIGH | AD30: TRUE | AE30: TRUE | AF30: TRUE | AG30: FALSE | AH30: TRUE | AI30: FALSE | AJ30: 1.75 | AK30: MEDIUM | AL30: TRUE | AM30: REGION_VII|CEBU|Cebu, District 1|AUTOMOTIVE AND LAND TRANSPORTATION|AUTOMOTIVE AND LAND TRANSPORTATION|AUTO BODY REPAIR TECHNICIAN||AUTOMOTIVE SERVICING (CHASSIS REPAIR) NC II||With TR|MEDIUM | AO30: TRUE | AP30: TRUE | AQ30: TRUE | AR30: FALSE | AS30: TRUE | AT30: FALSE | AU30: 1.75 | AV30: MEDIUM | AW30: TRUE | AX30: REGION_VII|CEBU|Cebu, District 2|AUTOMOTIVE AND LAND TRANSPORTATION|AUTOMOTIVE AND LAND TRANSPORTATION|AUTO BODY REPAIR TECHNICIAN||AUTOMOTIVE SERVICING (CHASSIS REPAIR) NC II||With TR|MEDIUM | AZ30: TRUE | BA30: TRUE | BB30: TRUE | BC30: FALSE | BD30: TRUE | BE30: FALSE | BF30: 1.75 | BG30: MEDIUM | BH30: TRUE | BI30: REGION_VII|CEBU|Cebu, District 3|AUTOMOTIVE AND LAND TRANSPORTATION|AUTOMOTIVE AND LAND TRANSPORTATION|AUTO BODY REPAIR TECHNICIAN||AUTOMOTIVE SERVICING (CHASSIS REPAIR) NC II||With TR|MEDIUM | BK30: TRUE | BL30: TRUE | BM30: TRUE | BN30: FALSE | BO30: TRUE | BP30: FALSE | BQ30: 1.75 | BR30: MEDIUM | BS30: TRUE | BT30: REGION_VII|CEBU|Cebu, District 4|AUTOMOTIVE AND LAND TRANSPORTATION|AUTOMOTIVE AND LAND TRANSPORTATION|AUTO BODY REPAIR TECHNICIAN||AUTOMOTIVE SERVICING (CHASSIS REPAIR) NC II||With TR|MEDIUM | BV30: TRUE | BW30: TRUE | BX30: TRUE | BY30: FALSE | BZ30: TRUE | CA30: FALSE | CB30: 1.75 | CC30: MEDIUM | CD30: TRUE | CE30: REGION_VII|CEBU|Cebu, District 5|AUTOMOTIVE AND LAND TRANSPORTATION|AUTOMOTIVE AND LAND TRANSPORTATION|AUTO BODY REPAIR TECHNICIAN||AUTOMOTIVE SERVICING (CHASSIS REPAIR) NC II||With TR|MEDIUM | CG30: TRUE | CH30: TRUE | CI30: TRUE | CJ30: FALSE | CK30: TRUE | CL30: FALSE | CM30: 1.75 | CN30: MEDIUM | CO30: TRUE | CP30: REGION_VII|CEBU|Cebu, District 6|AUTOMOTIVE AND LAND TRANSPORTATION|AUTOMOTIVE AND LAND TRANSPORTATION|AUTO BODY REPAIR TECHNICIAN||AUTOMOTIVE SERVICING (CHASSIS REPAIR) NC II||With TR|MEDIUM | CR30: TRUE | CS30: TRUE | CT30: TRUE | CU30: FALSE | CV30: TRUE | CW30: FALSE | CX30: 1.75 | CY30: MEDIUM | CZ30: TRUE | DA30: REGION_VII|CEBU|Cebu, District 7|AUTOMOTIVE AND LAND TRANSPORTATION|AUTOMOTIVE AND LAND TRANSPORTATION|AUTO BODY REPAIR TECHNICIAN||AUTOMOTIVE SERVICING (CHASSIS REPAIR) NC II||With TR|MEDIUM | DC30: TRUE | DD30: TRUE | DE30: TRUE | DF30: FALSE | DG30: TRUE | DH30: FALSE | DI30: 1.75 | DJ30: MEDIUM | DK30: TRUE | DL30: REGION_VII|CEBU|Lapu-Lapu City, Lone District|AUTOMOTIVE AND LAND TRANSPORTATION|AUTOMOTIVE AND LAND TRANSPORTATION|AUTO BODY REPAIR TECHNICIAN||AUTOMOTIVE SERVICING (CHASSIS REPAIR) NC II||With TR|MEDIUM | DN30: TRUE | DO30: TRUE | DP30: TRUE | DQ30: FALSE | DR30: TRUE | DS30: FALSE | DT30: 1.75 | DU30: MEDIUM
A31: AUTOMOTIVE AND LAND TRANSPORTATION | B31: AUTOMOTIVE AND LAND TRANSPORTATION | C31: AUTO BODY REPAIR TECHNICIAN | D31: REPAIRING DAMAGE TO THE BODY OF THE VEHICLE AND WASHING AND PAINTING THE VEHICLE’S EXTERIOR._x000D_ PREPARES VEHICLES FOR BODY REPAIR WORK._x000D_ | E31: AUTOMOTIVE SERVICING (CHASSIS REPAIR) NC II | F31: With TR | G31: MEDIUM | H31: TRUE | I31: TRUE | J31: TRUE | K31: FALSE | L31: TRUE | M31: FALSE | N31: 1.75 | O31: MEDIUM | P31: TRUE | Q31: REGION_VII|CEBU|Cebu City, District 1|AUTOMOTIVE AND LAND TRANSPORTATION|AFTERSALES & SERVICE (MAINTENANCE)|AUTO ELECTRICIAN||AUTOMOTIVE SERVICING (ELECTRICAL REPAIR) NC II||With TR|MEDIUM | S31: TRUE | T31: TRUE | U31: TRUE | V31: FALSE | W31: TRUE | X31: FALSE | Y31: 1.75 | Z31: MEDIUM | AA31: TRUE | AB31: REGION_VII|CEBU|Cebu City, District 2|AUTOMOTIVE AND LAND TRANSPORTATION|AFTERSALES & SERVICE (MAINTENANCE)|AUTO ELECTRICIAN||AUTOMOTIVE SERVICING (ELECTRICAL REPAIR) NC II||With TR|MEDIUM | AD31: TRUE | AE31: TRUE | AF31: TRUE | AG31: FALSE | AH31: TRUE | AI31: FALSE | AJ31: 1.75 | AK31: MEDIUM | AL31: TRUE | AM31: REGION_VII|CEBU|Cebu, District 1|AUTOMOTIVE AND LAND TRANSPORTATION|AFTERSALES & SERVICE (MAINTENANCE)|AUTO ELECTRICIAN||AUTOMOTIVE SERVICING (ELECTRICAL REPAIR) NC II||With TR|MEDIUM | AO31: TRUE | AP31: TRUE | AQ31: TRUE | AR31: FALSE | AS31: TRUE | AT31: FALSE | AU31: 1.75 | AV31: MEDIUM | AW31: TRUE | AX31: REGION_VII|CEBU|Cebu, District 2|AUTOMOTIVE AND LAND TRANSPORTATION|AFTERSALES & SERVICE (MAINTENANCE)|AUTO ELECTRICIAN||AUTOMOTIVE SERVICING (ELECTRICAL REPAIR) NC II||With TR|MEDIUM | AZ31: TRUE | BA31: TRUE | BB31: TRUE | BC31: FALSE | BD31: TRUE | BE31: FALSE | BF31: 1.75 | BG31: MEDIUM | BH31: TRUE | BI31: REGION_VII|CEBU|Cebu, District 3|AUTOMOTIVE AND LAND TRANSPORTATION|AFTERSALES & SERVICE (MAINTENANCE)|AUTO ELECTRICIAN||AUTOMOTIVE SERVICING (ELECTRICAL REPAIR) NC II||With TR|MEDIUM | BK31: TRUE | BL31: TRUE | BM31: TRUE | BN31: FALSE | BO31: TRUE | BP31: FALSE | BQ31: 1.75 | BR31: MEDIUM | BS31: TRUE | BT31: REGION_VII|CEBU|Cebu, District 4|AUTOMOTIVE AND LAND TRANSPORTATION|AFTERSALES & SERVICE (MAINTENANCE)|AUTO ELECTRICIAN||AUTOMOTIVE SERVICING (ELECTRICAL REPAIR) NC II||With TR|MEDIUM | BV31: TRUE | BW31: TRUE | BX31: TRUE | BY31: FALSE | BZ31: TRUE | CA31: FALSE | CB31: 1.75 | CC31: MEDIUM | CD31: TRUE | CE31: REGION_VII|CEBU|Cebu, District 5|AUTOMOTIVE AND LAND TRANSPORTATION|AFTERSALES & SERVICE (MAINTENANCE)|AUTO ELECTRICIAN||AUTOMOTIVE SERVICING (ELECTRICAL REPAIR) NC II||With TR|MEDIUM | CG31: TRUE | CH31: TRUE | CI31: TRUE | CJ31: FALSE | CK31: TRUE | CL31: FALSE | CM31: 1.75 | CN31: MEDIUM | CO31: TRUE | CP31: REGION_VII|CEBU|Cebu, District 6|AUTOMOTIVE AND LAND TRANSPORTATION|AFTERSALES & SERVICE (MAINTENANCE)|AUTO ELECTRICIAN||AUTOMOTIVE SERVICING (ELECTRICAL REPAIR) NC II||With TR|MEDIUM | CR31: TRUE | CS31: TRUE | CT31: TRUE | CU31: FALSE | CV31: TRUE | CW31: FALSE | CX31: 1.75 | CY31: MEDIUM | CZ31: TRUE | DA31: REGION_VII|CEBU|Cebu, District 7|AUTOMOTIVE AND LAND TRANSPORTATION|AFTERSALES & SERVICE (MAINTENANCE)|AUTO ELECTRICIAN||AUTOMOTIVE SERVICING (ELECTRICAL REPAIR) NC II||With TR|MEDIUM | DC31: TRUE | DD31: TRUE | DE31: TRUE | DF31: FALSE | DG31: TRUE | DH31: FALSE | DI31: 1.75 | DJ31: MEDIUM | DK31: TRUE | DL31: REGION_VII|CEBU|Lapu-Lapu City, Lone District|AUTOMOTIVE AND LAND TRANSPORTATION|AFTERSALES & SERVICE (MAINTENANCE)|AUTO ELECTRICIAN||AUTOMOTIVE SERVICING (ELECTRICAL REPAIR) NC II||With TR|MEDIUM | DN31: TRUE | DO31: TRUE | DP31: TRUE | DQ31: FALSE | DR31: TRUE | DS31: FALSE | DT31: 1.75 | DU31: MEDIUM
A32: AUTOMOTIVE AND LAND TRANSPORTATION | B32: AFTERSALES & SERVICE (MAINTENANCE) | C32: AUTO ELECTRICIAN | D32: DIAGNOSE AND REPAIR ELECTRICAL FAULTS AND ISSUES IN VEHICLES_x000D_ INSTALL, MAINTAIN, AND REPAIR ELECTRICAL COMPONENTS SUCH AS BATTERIES, ALTERNATORS, STARTERS, AND LIGHTING SYSTEMS_x000D_ PERFORM ELECTRICAL SYSTEM TESTING AND TROUBLESHOOTING_x000D_ ADVISE CUSTOMERS ON NECESSARY REPAIRS AND MAINTENANCE_x000D_ COMPLY WITH ALL RELEVANT SAFETY STANDARDS AND REGULATIONS_x000D_ MAINTAIN DETAILED RECORDS OF WORK COMPLETED_x000D_ ASSIST WITH THE MAINTENANCE AND UPKEEP OF THE WORKSHOP AND TOOLS_x000D_ | E32: AUTOMOTIVE SERVICING (ELECTRICAL REPAIR) NC II | F32: With TR | G32: MEDIUM | H32: TRUE | I32: TRUE | J32: TRUE | K32: FALSE | L32: FALSE | M32: TRUE | N32: 1.25 | O32: HIGH | P32: TRUE | Q32: REGION_VII|CEBU|Cebu City, District 1|AUTOMOTIVE AND LAND TRANSPORTATION|AUTOMOTIVE AND LAND TRANSPORTATION|AUTOMOTIVE AIRCON TECHNICIAN||AUTOMOTIVE SERVICING NC III||With TR|HIGH | S32: TRUE | T32: TRUE | U32: TRUE | V32: FALSE | W32: TRUE | X32: FALSE | Y32: 1.75 | Z32: MEDIUM | AA32: TRUE | AB32: REGION_VII|CEBU|Cebu City, District 2|AUTOMOTIVE AND LAND TRANSPORTATION|AUTOMOTIVE AND LAND TRANSPORTATION|AUTOMOTIVE AIRCON TECHNICIAN||AUTOMOTIVE SERVICING NC III||With TR|MEDIUM | AD32: TRUE | AE32: TRUE | AF32: TRUE | AG32: FALSE | AH32: TRUE | AI32: FALSE | AJ32: 1.75 | AK32: MEDIUM | AL32: TRUE | AM32: REGION_VII|CEBU|Cebu, District 1|AUTOMOTIVE AND LAND TRANSPORTATION|AUTOMOTIVE AND LAND TRANSPORTATION|AUTOMOTIVE AIRCON TECHNICIAN||AUTOMOTIVE SERVICING NC III||With TR|MEDIUM | AO32: TRUE | AP32: TRUE | AQ32: TRUE | AR32: FALSE | AS32: TRUE | AT32: FALSE | AU32: 1.75 | AV32: MEDIUM | AW32: TRUE | AX32: REGION_VII|CEBU|Cebu, District 2|AUTOMOTIVE AND LAND TRANSPORTATION|AUTOMOTIVE AND LAND TRANSPORTATION|AUTOMOTIVE AIRCON TECHNICIAN||AUTOMOTIVE SERVICING NC III||With TR|MEDIUM | AZ32: TRUE | BA32: TRUE | BB32: TRUE | BC32: FALSE | BD32: TRUE | BE32: FALSE | BF32: 1.75 | BG32: MEDIUM | BH32: TRUE | BI32: REGION_VII|CEBU|Cebu, District 3|AUTOMOTIVE AND LAND TRANSPORTATION|AUTOMOTIVE AND LAND TRANSPORTATION|AUTOMOTIVE AIRCON TECHNICIAN||AUTOMOTIVE SERVICING NC III||With TR|MEDIUM | BK32: TRUE | BL32: TRUE | BM32: TRUE | BN32: FALSE | BO32: FALSE | BP32: TRUE | BQ32: 1.25 | BR32: HIGH | BS32: TRUE | BT32: REGION_VII|CEBU|Cebu, District 4|AUTOMOTIVE AND LAND TRANSPORTATION|AUTOMOTIVE AND LAND TRANSPORTATION|AUTOMOTIVE AIRCON TECHNICIAN||AUTOMOTIVE SERVICING NC III||With TR|HIGH | BV32: TRUE | BW32: TRUE | BX32: TRUE | BY32: FALSE | BZ32: TRUE | CA32: FALSE | CB32: 1.75 | CC32: MEDIUM | CD32: TRUE | CE32: REGION_VII|CEBU|Cebu, District 5|AUTOMOTIVE AND LAND TRANSPORTATION|AUTOMOTIVE AND LAND TRANSPORTATION|AUTOMOTIVE AIRCON TECHNICIAN||AUTOMOTIVE SERVICING NC III||With TR|MEDIUM | CG32: TRUE | CH32: TRUE | CI32: TRUE | CJ32: FALSE | CK32: TRUE | CL32: FALSE | CM32: 1.75 | CN32: MEDIUM | CO32: TRUE | CP32: REGION_VII|CEBU|Cebu, District 6|AUTOMOTIVE AND LAND TRANSPORTATION|AUTOMOTIVE AND LAND TRANSPORTATION|AUTOMOTIVE AIRCON TECHNICIAN||AUTOMOTIVE SERVICING NC III||With TR|MEDIUM | CR32: TRUE | CS32: TRUE | CT32: TRUE | CU32: FALSE | CV32: TRUE | CW32: FALSE | CX32: 1.75 | CY32: MEDIUM | CZ32: TRUE | DA32: REGION_VII|CEBU|Cebu, District 7|AUTOMOTIVE AND LAND TRANSPORTATION|AUTOMOTIVE AND LAND TRANSPORTATION|AUTOMOTIVE AIRCON TECHNICIAN||AUTOMOTIVE SERVICING NC III||With TR|MEDIUM | DC32: TRUE | DD32: TRUE | DE32: TRUE | DF32: FALSE | DG32: TRUE | DH32: FALSE | DI32: 1.75 | DJ32: MEDIUM | DK32: TRUE | DL32: REGION_VII|CEBU|Lapu-Lapu City, Lone District|AUTOMOTIVE AND LAND TRANSPORTATION|AUTOMOTIVE AND LAND TRANSPORTATION|AUTOMOTIVE AIRCON TECHNICIAN||AUTOMOTIVE SERVICING NC III||With TR|MEDIUM | DN32: TRUE | DO32: TRUE | DP32: TRUE | DQ32: FALSE | DR32: TRUE | DS32: FALSE | DT32: 1.75 | DU32: MEDIUM
A33: AUTOMOTIVE AND LAND TRANSPORTATION | B33: AUTOMOTIVE AND LAND TRANSPORTATION | C33: AUTOMOTIVE AIRCON TECHNICIAN | D33: INSTALLS AND REPAIRS AUTOMOTIVE AIR-CONDITIONING UNITS: BOLTS COMPRESSOR TO ENGINE BLOCK AND INSTALLS DRIVING PULLEY ON FRONT END OF CRANKSHAFT._x000D_ PLACES FAN BELT ON PULLEYS, ADJUSTS TENSION, AND TIGHTENS BOLTS._x000D_ BOLTS EVAPORATOR UNIT UNDER DASHBOARD OR IN TRUNK._x000D_ WELDS OR BOLTS MOUNTING BRACKETS TO AUTOMOBILE FRAME._x000D_ DRILLS HOLES THROUGH INTERIOR PANELS, THREADS HOSES THROUGH HOLES AND CONNECTS HOSES TO COMPRESSOR, EVAPORATOR, AND COOL-AIR OUTLET._x000D_ FILLS COMPRESSOR WITH REFRIGERANT AND STARTS UNIT._x000D_ MEASURES COMPRESSOR PRESSURE TO DETERMINE EFFICIENCY OF COMPRESSOR, USING GAUGE._x000D_ REMOVES FAULTY UNITS FROM VEHICLES, DISASSEMBLES THEM, AND REPLACES WORN AND BROKEN PARTS AND FLUID IN UNIT._x000D_ MAKES ELECTRICAL CONNECTIONS AS REQUIRED._x000D_ MAY SPECIALIZE IN INSTALLATION OF AUTOMOTIVE AIR-CONDITIONING UNITS AND BE DESIGNATED AUTOMOTIVE AIR-CONDITIONER INSTALLER._x000D_ | E33: AUTOMOTIVE SERVICING NC III | F33: With TR | G33: MEDIUM | H33: TRUE | I33: TRUE | J33: TRUE | K33: FALSE | L33: TRUE | M33: FALSE | N33: 1.75 | O33: MEDIUM | P33: TRUE | Q33: REGION_VII|CEBU|Cebu City, District 1|AUTOMOTIVE AND LAND TRANSPORTATION|AUTOMOTIVE AND LAND TRANSPORTATION|AUTOMOTIVE ELECTRICIAN||AUTOMOTIVE ELECTRICAL ASSEMBLY NC III||With TR|MEDIUM | S33: TRUE | T33: TRUE | U33: TRUE | V33: FALSE | W33: TRUE | X33: FALSE | Y33: 1.75 | Z33: MEDIUM | AA33: TRUE | AB33: REGION_VII|CEBU|Cebu City, District 2|AUTOMOTIVE AND LAND TRANSPORTATION|AUTOMOTIVE AND LAND TRANSPORTATION|AUTOMOTIVE ELECTRICIAN||AUTOMOTIVE ELECTRICAL ASSEMBLY NC III||With TR|MEDIUM | AD33: TRUE | AE33: TRUE | AF33: TRUE | AG33: FALSE | AH33: TRUE | AI33: FALSE | AJ33: 1.75 | AK33: MEDIUM | AL33: TRUE | AM33: REGION_VII|CEBU|Cebu, District 1|AUTOMOTIVE AND LAND TRANSPORTATION|AUTOMOTIVE AND LAND TRANSPORTATION|AUTOMOTIVE ELECTRICIAN||AUTOMOTIVE ELECTRICAL ASSEMBLY NC III||With TR|MEDIUM | AO33: TRUE | AP33: TRUE | AQ33: TRUE | AR33: FALSE | AS33: TRUE | AT33: FALSE | AU33: 1.75 | AV33: MEDIUM | AW33: TRUE | AX33: REGION_VII|CEBU|Cebu, District 2|AUTOMOTIVE AND LAND TRANSPORTATION|AUTOMOTIVE AND LAND TRANSPORTATION|AUTOMOTIVE ELECTRICIAN||AUTOMOTIVE ELECTRICAL ASSEMBLY NC III||With TR|MEDIUM | AZ33: TRUE | BA33: TRUE | BB33: TRUE | BC33: FALSE | BD33: TRUE | BE33: FALSE | BF33: 1.75 | BG33: MEDIUM | BH33: TRUE | BI33: REGION_VII|CEBU|Cebu, District 3|AUTOMOTIVE AND LAND TRANSPORTATION|AUTOMOTIVE AND LAND TRANSPORTATION|AUTOMOTIVE ELECTRICIAN||AUTOMOTIVE ELECTRICAL ASSEMBLY NC III||With TR|MEDIUM | BK33: TRUE | BL33: TRUE | BM33: TRUE | BN33: FALSE | BO33: TRUE | BP33: FALSE | BQ33: 1.75 | BR33: MEDIUM | BS33: TRUE | BT33: REGION_VII|CEBU|Cebu, District 4|AUTOMOTIVE AND LAND TRANSPORTATION|AUTOMOTIVE AND LAND TRANSPORTATION|AUTOMOTIVE ELECTRICIAN||AUTOMOTIVE ELECTRICAL ASSEMBLY NC III||With TR|MEDIUM | BV33: TRUE | BW33: TRUE | BX33: TRUE | BY33: FALSE | BZ33: TRUE | CA33: FALSE | CB33: 1.75 | CC33: MEDIUM | CD33: TRUE | CE33: REGION_VII|CEBU|Cebu, District 5|AUTOMOTIVE AND LAND TRANSPORTATION|AUTOMOTIVE AND LAND TRANSPORTATION|AUTOMOTIVE ELECTRICIAN||AUTOMOTIVE ELECTRICAL ASSEMBLY NC III||With TR|MEDIUM | CG33: TRUE | CH33: TRUE | CI33: TRUE | CJ33: FALSE | CK33: TRUE | CL33: FALSE | CM33: 1.75 | CN33: MEDIUM | CO33: TRUE | CP33: REGION_VII|CEBU|Cebu, District 6|AUTOMOTIVE AND LAND TRANSPORTATION|AUTOMOTIVE AND LAND TRANSPORTATION|AUTOMOTIVE ELECTRICIAN||AUTOMOTIVE ELECTRICAL ASSEMBLY NC III||With TR|MEDIUM | CR33: TRUE | CS33: TRUE | CT33: TRUE | CU33: FALSE | CV33: TRUE | CW33: FALSE | CX33: 1.75 | CY33: MEDIUM | CZ33: TRUE | DA33: REGION_VII|CEBU|Cebu, District 7|AUTOMOTIVE AND LAND TRANSPORTATION|AUTOMOTIVE AND LAND TRANSPORTATION|AUTOMOTIVE ELECTRICIAN||AUTOMOTIVE ELECTRICAL ASSEMBLY NC III||With TR|MEDIUM | DC33: TRUE | DD33: TRUE | DE33: TRUE | DF33: FALSE | DG33: TRUE | DH33: FALSE | DI33: 1.75 | DJ33: MEDIUM | DK33: TRUE | DL33: REGION_VII|CEBU|Lapu-Lapu City, Lone District|AUTOMOTIVE AND LAND TRANSPORTATION|AUTOMOTIVE AND LAND TRANSPORTATION|AUTOMOTIVE ELECTRICIAN||AUTOMOTIVE ELECTRICAL ASSEMBLY NC III||With TR|MEDIUM | DN33: TRUE | DO33: TRUE | DP33: TRUE | DQ33: FALSE | DR33: TRUE | DS33: FALSE | DT33: 1.75 | DU33: MEDIUM
A34: AUTOMOTIVE AND LAND TRANSPORTATION | B34: AUTOMOTIVE AND LAND TRANSPORTATION | C34: AUTOMOTIVE ELECTRICIAN | D34: INSTALLING NEW VEHICLE WIRING SYSTEMS._x000D_ INSTALLING AND TROUBLESHOOTING IMMOBILIZER AND ALARM SYSTEMS._x000D_ GATHERING INFORMATION FROM CUSTOMERS ABOUT ISSUES WITH THEIR ELECTRICAL SYSTEM._x000D_ DIAGNOSING ELECTRICAL ISSUES AND PROPOSING A COURSE OF ACTION._x000D_ REPAIRING AND REPLACING FAULTY WIRING OR ELECTRICAL SYSTEMS._x000D_ SERVICING OF ELECTRICAL AUTOMOTIVE PARTS._x000D_ SERVICING AND REPAIRING ELECTRICAL SYSTEMS._x000D_ | E34: AUTOMOTIVE ELECTRICAL ASSEMBLY NC III | F34: With TR | G34: MEDIUM | H34: TRUE | I34: TRUE | J34: TRUE | K34: FALSE | L34: TRUE | M34: FALSE | N34: 1.75 | O34: MEDIUM | P34: TRUE | Q34: REGION_VII|CEBU|Cebu City, District 1|AUTOMOTIVE AND LAND TRANSPORTATION|AUTOMOTIVE AND LAND TRANSPORTATION|AUTOMOTIVE MECHANIC||AUTOMOTIVE MECHANICAL ASSEMBLY NC II||With TR|MEDIUM | S34: TRUE | T34: TRUE | U34: TRUE | V34: FALSE | W34: TRUE | X34: FALSE | Y34: 1.75 | Z34: MEDIUM | AA34: TRUE | AB34: REGION_VII|CEBU|Cebu City, District 2|AUTOMOTIVE AND LAND TRANSPORTATION|AUTOMOTIVE AND LAND TRANSPORTATION|AUTOMOTIVE MECHANIC||AUTOMOTIVE MECHANICAL ASSEMBLY NC II||With TR|MEDIUM | AD34: TRUE | AE34: TRUE | AF34: TRUE | AG34: TRUE | AH34: FALSE | AI34: FALSE | AJ34: 2.25 | AK34: LOW | AL34: TRUE | AM34: REGION_VII|CEBU|Cebu, District 1|AUTOMOTIVE AND LAND TRANSPORTATION|AUTOMOTIVE AND LAND TRANSPORTATION|AUTOMOTIVE MECHANIC||AUTOMOTIVE MECHANICAL ASSEMBLY NC II||With TR|LOW | AO34: TRUE | AP34: TRUE | AQ34: TRUE | AR34: FALSE | AS34: TRUE | AT34: FALSE | AU34: 1.75 | AV34: MEDIUM | AW34: TRUE | AX34: REGION_VII|CEBU|Cebu, District 2|AUTOMOTIVE AND LAND TRANSPORTATION|AUTOMOTIVE AND LAND TRANSPORTATION|AUTOMOTIVE MECHANIC||AUTOMOTIVE MECHANICAL ASSEMBLY NC II||With TR|MEDIUM | AZ34: TRUE | BA34: TRUE | BB34: TRUE | BC34: FALSE | BD34: TRUE | BE34: FALSE | BF34: 1.75 | BG34: MEDIUM | BH34: TRUE | BI34: REGION_VII|CEBU|Cebu, District 3|AUTOMOTIVE AND LAND TRANSPORTATION|AUTOMOTIVE AND LAND TRANSPORTATION|AUTOMOTIVE MECHANIC||AUTOMOTIVE MECHANICAL ASSEMBLY NC II||With TR|MEDIUM | BK34: TRUE | BL34: TRUE | BM34: TRUE | BN34: FALSE | BO34: TRUE | BP34: FALSE | BQ34: 1.75 | BR34: MEDIUM | BS34: TRUE | BT34: REGION_VII|CEBU|Cebu, District 4|AUTOMOTIVE AND LAND TRANSPORTATION|AUTOMOTIVE AND LAND TRANSPORTATION|AUTOMOTIVE MECHANIC||AUTOMOTIVE MECHANICAL ASSEMBLY NC II||With TR|MEDIUM | BV34: TRUE | BW34: TRUE | BX34: TRUE | BY34: FALSE | BZ34: TRUE | CA34: FALSE | CB34: 1.75 | CC34: MEDIUM | CD34: TRUE | CE34: REGION_VII|CEBU|Cebu, District 5|AUTOMOTIVE AND LAND TRANSPORTATION|AUTOMOTIVE AND LAND TRANSPORTATION|AUTOMOTIVE MECHANIC||AUTOMOTIVE MECHANICAL ASSEMBLY NC II||With TR|MEDIUM | CG34: TRUE | CH34: TRUE | CI34: TRUE | CJ34: FALSE | CK34: TRUE | CL34: FALSE | CM34: 1.75 | CN34: MEDIUM | CO34: TRUE | CP34: REGION_VII|CEBU|Cebu, District 6|AUTOMOTIVE AND LAND TRANSPORTATION|AUTOMOTIVE AND LAND TRANSPORTATION|AUTOMOTIVE MECHANIC||AUTOMOTIVE MECHANICAL ASSEMBLY NC II||With TR|MEDIUM | CR34: TRUE | CS34: TRUE | CT34: TRUE | CU34: FALSE | CV34: TRUE | CW34: FALSE | CX34: 1.75 | CY34: MEDIUM | CZ34: TRUE | DA34: REGION_VII|CEBU|Cebu, District 7|AUTOMOTIVE AND LAND TRANSPORTATION|AUTOMOTIVE AND LAND TRANSPORTATION|AUTOMOTIVE MECHANIC||AUTOMOTIVE MECHANICAL ASSEMBLY NC II||With TR|MEDIUM | DC34: TRUE | DD34: TRUE | DE34: TRUE | DF34: FALSE | DG34: TRUE | DH34: FALSE | DI34: 1.75 | DJ34: MEDIUM | DK34: TRUE | DL34: REGION_VII|CEBU|Lapu-Lapu City, Lone District|AUTOMOTIVE AND LAND TRANSPORTATION|AUTOMOTIVE AND LAND TRANSPORTATION|AUTOMOTIVE MECHANIC||AUTOMOTIVE MECHANICAL ASSEMBLY NC II||With TR|MEDIUM | DN34: TRUE | DO34: TRUE | DP34: TRUE | DQ34: FALSE | DR34: TRUE | DS34: FALSE | DT34: 1.75 | DU34: MEDIUM
A35: AUTOMOTIVE AND LAND TRANSPORTATION | B35: AUTOMOTIVE AND LAND TRANSPORTATION | C35: AUTOMOTIVE MECHANIC | D35: PERFORMING TEST DRIVERS, INSPECTIONS, AND OTHER DIAGNOSTIC TESTS ON VEHICLES TO IDENTIFY WHERE PROBLEMS EXISTS AND DETERMINE WHICH PARTS NEED TO BE REPAIRED OR REPLACED._x000D_ COMPLETING PREVENTATIVE MAINTENANCE ON VEHICLES, SUCH AS PERFORMING OIL CHANGES, FLUSHING AND REPLACING FLUIDS, AND REPLACING BRAKES._x000D_ GENERATING TIMELINES AND ESTIMATES FOR REPAIRS AND DISCUSSING OPTIONS WITH CLIENTS._x000D_ INSPECTING INTERNAL SYSTEMS AND CONTROLS TO ENSURE THE VEHICLE IS OPERATING PROPERLY AND IN COMPLIANCE WITH STATE REGULATIONS._x000D_ USING SHOP EQUIPMENT AS INSTRUCTED, PERFORMING REGULAR MAINTENANCE AND REPAIRS AS NEEDED._x000D_ USING MANUAL AND COMPUTERIZED DIAGNOSTIC METHODS TO IDENTIFY POTENTIAL PROBLEMS IN A CAR_x000D_ EXPLAINING MECHANICAL PROBLEMS AND POSSIBLE SOLUTIONS TO CLIENTS_x000D_ PLANNING WORK AND TESTING PROCEDURES USING CHARTS, EXPERIENCE AND OTHER ORGANIZATIONAL METHODS_x000D_ TESTING PARTS AND SYSTEMS TO ENSURE THEY WORK CORRECTLY_x000D_ ENSURING ALL CRITICAL PARTS ARE CHECKED AND TESTED_x000D_ PERFORMING BASIC AUTOMOTIVE CARE, INCLUDING CHANGING OIL AND ROTATING TIRES_x000D_ REPAIRING OR REPLACING WORN, OLD OR DEFECTIVE PARTS OF A CAR_x000D_ | E35: AUTOMOTIVE MECHANICAL ASSEMBLY NC II | F35: With TR | G35: MEDIUM | H35: TRUE | I35: TRUE | J35: TRUE | K35: FALSE | L35: TRUE | M35: FALSE | N35: 1.75 | O35: MEDIUM | P35: TRUE | Q35: REGION_VII|CEBU|Cebu City, District 1|AUTOMOTIVE AND LAND TRANSPORTATION|AUTOMOTIVE AND LAND TRANSPORTATION|AUTOMOTIVE PAINTER||AUTOMOTIVE BODY PAINTING/FINISHING NC I||With TR|MEDIUM | S35: TRUE | T35: TRUE | U35: TRUE | V35: FALSE | W35: TRUE | X35: FALSE | Y35: 1.75 | Z35: MEDIUM | AA35: TRUE | AB35: REGION_VII|CEBU|Cebu City, District 2|AUTOMOTIVE AND LAND TRANSPORTATION|AUTOMOTIVE AND LAND TRANSPORTATION|AUTOMOTIVE PAINTER||AUTOMOTIVE BODY PAINTING/FINISHING NC I||With TR|MEDIUM | AD35: TRUE | AE35: TRUE | AF35: TRUE | AG35: FALSE | AH35: TRUE | AI35: FALSE | AJ35: 1.75 | AK35: MEDIUM | AL35: TRUE | AM35: REGION_VII|CEBU|Cebu, District 1|AUTOMOTIVE AND LAND TRANSPORTATION|AUTOMOTIVE AND LAND TRANSPORTATION|AUTOMOTIVE PAINTER||AUTOMOTIVE BODY PAINTING/FINISHING NC I||With TR|MEDIUM | AO35: TRUE | AP35: TRUE | AQ35: TRUE | AR35: FALSE | AS35: TRUE | AT35: FALSE | AU35: 1.75 | AV35: MEDIUM | AW35: TRUE | AX35: REGION_VII|CEBU|Cebu, District 2|AUTOMOTIVE AND LAND TRANSPORTATION|AUTOMOTIVE AND LAND TRANSPORTATION|AUTOMOTIVE PAINTER||AUTOMOTIVE BODY PAINTING/FINISHING NC I||With TR|MEDIUM | AZ35: TRUE | BA35: TRUE | BB35: TRUE | BC35: FALSE | BD35: TRUE | BE35: FALSE | BF35: 1.75 | BG35: MEDIUM | BH35: TRUE | BI35: REGION_VII|CEBU|Cebu, District 3|AUTOMOTIVE AND LAND TRANSPORTATION|AUTOMOTIVE AND LAND TRANSPORTATION|AUTOMOTIVE PAINTER||AUTOMOTIVE BODY PAINTING/FINISHING NC I||With TR|MEDIUM | BK35: TRUE | BL35: TRUE | BM35: TRUE | BN35: FALSE | BO35: TRUE | BP35: FALSE | BQ35: 1.75 | BR35: MEDIUM | BS35: TRUE | BT35: REGION_VII|CEBU|Cebu, District 4|AUTOMOTIVE AND LAND TRANSPORTATION|AUTOMOTIVE AND LAND TRANSPORTATION|AUTOMOTIVE PAINTER||AUTOMOTIVE BODY PAINTING/FINISHING NC I||With TR|MEDIUM | BV35: TRUE | BW35: TRUE | BX35: TRUE | BY35: FALSE | BZ35: TRUE | CA35: FALSE | CB35: 1.75 | CC35: MEDIUM | CD35: TRUE | CE35: REGION_VII|CEBU|Cebu, District 5|AUTOMOTIVE AND LAND TRANSPORTATION|AUTOMOTIVE AND LAND TRANSPORTATION|AUTOMOTIVE PAINTER||AUTOMOTIVE BODY PAINTING/FINISHING NC I||With TR|MEDIUM | CG35: TRUE | CH35: TRUE | CI35: TRUE | CJ35: FALSE | CK35: TRUE | CL35: FALSE | CM35: 1.75 | CN35: MEDIUM | CO35: TRUE | CP35: REGION_VII|CEBU|Cebu, District 6|AUTOMOTIVE AND LAND TRANSPORTATION|AUTOMOTIVE AND LAND TRANSPORTATION|AUTOMOTIVE PAINTER||AUTOMOTIVE BODY PAINTING/FINISHING NC I||With TR|MEDIUM | CR35: TRUE | CS35: TRUE | CT35: TRUE | CU35: FALSE | CV35: TRUE | CW35: FALSE | CX35: 1.75 | CY35: MEDIUM | CZ35: TRUE | DA35: REGION_VII|CEBU|Cebu, District 7|AUTOMOTIVE AND LAND TRANSPORTATION|AUTOMOTIVE AND LAND TRANSPORTATION|AUTOMOTIVE PAINTER||AUTOMOTIVE BODY PAINTING/FINISHING NC I||With TR|MEDIUM | DC35: TRUE | DD35: TRUE | DE35: TRUE | DF35: FALSE | DG35: TRUE | DH35: FALSE | DI35: 1.75 | DJ35: MEDIUM | DK35: TRUE | DL35: REGION_VII|CEBU|Lapu-Lapu City, Lone District|AUTOMOTIVE AND LAND TRANSPORTATION|AUTOMOTIVE AND LAND TRANSPORTATION|AUTOMOTIVE PAINTER||AUTOMOTIVE BODY PAINTING/FINISHING NC I||With TR|MEDIUM | DN35: TRUE | DO35: TRUE | DP35: TRUE | DQ35: FALSE | DR35: TRUE | DS35: FALSE | DT35: 1.75 | DU35: MEDIUM
A36: AUTOMOTIVE AND LAND TRANSPORTATION | B36: AUTOMOTIVE AND LAND TRANSPORTATION | C36: AUTOMOTIVE PAINTER | D36: FILLS SMALL DENTS AND SCRATCHES WITH BODY FILLER AND CLEANS AND PREPARES SURFACES TO ENSURE PAINT AND OTHER FINISHES WILL ADHERE PROPERLY_x000D_ MAY PREPARE COST ESTIMATES OF LABOR AND MATERIALS FOR PENDING AUTOMOTIVE PAINT JOBS_x000D_ COLOR BLENDING INTO ADJACENT PANELS FOR A BETTER COLOR MATCH TO EXISTING VEHICLE PAINT_x000D_ MIX AND SPRAY PAINT AND PRIMER PER WORK INSTRUCTIONS_x000D_ CLEAN PANELS IN PREPARATION FOR PAINTING AND PRIMING_x000D_ MAINTAIN SPRAY EQUIPMENT_x000D_ SELECT APPROPRIATE PAINT OR MIX PAINTS USING AUTOMATED PAINT MIXING EQUIPMENT_x000D_ | E36: AUTOMOTIVE BODY PAINTING/FINISHING NC I | F36: With TR | G36: MEDIUM | H36: TRUE | I36: TRUE | J36: TRUE | K36: FALSE | L36: FALSE | M36: TRUE | N36: 1.25 | O36: HIGH | P36: TRUE | Q36: REGION_VII|CEBU|Cebu City, District 1|AUTOMOTIVE AND LAND TRANSPORTATION|AFTERSALES & SERVICE (MAINTENANCE)|AUTOMOTIVE TECHNICIAN||AUTOMOTIVE SERVICING NC I||With TR|HIGH | S36: TRUE | T36: TRUE | U36: TRUE | V36: FALSE | W36: TRUE | X36: FALSE | Y36: 1.75 | Z36: MEDIUM | AA36: TRUE | AB36: REGION_VII|CEBU|Cebu City, District 2|AUTOMOTIVE AND LAND TRANSPORTATION|AFTERSALES & SERVICE (MAINTENANCE)|AUTOMOTIVE TECHNICIAN||AUTOMOTIVE SERVICING NC I||With TR|MEDIUM | AD36: TRUE | AE36: TRUE | AF36: TRUE | AG36: FALSE | AH36: TRUE | AI36: FALSE | AJ36: 1.75 | AK36: MEDIUM | AL36: TRUE | AM36: REGION_VII|CEBU|Cebu, District 1|AUTOMOTIVE AND LAND TRANSPORTATION|AFTERSALES & SERVICE (MAINTENANCE)|AUTOMOTIVE TECHNICIAN||AUTOMOTIVE SERVICING NC I||With TR|MEDIUM | AO36: TRUE | AP36: TRUE | AQ36: TRUE | AR36: FALSE | AS36: TRUE | AT36: FALSE | AU36: 1.75 | AV36: MEDIUM | AW36: TRUE | AX36: REGION_VII|CEBU|Cebu, District 2|AUTOMOTIVE AND LAND TRANSPORTATION|AFTERSALES & SERVICE (MAINTENANCE)|AUTOMOTIVE TECHNICIAN||AUTOMOTIVE SERVICING NC I||With TR|MEDIUM | AZ36: TRUE | BA36: TRUE | BB36: TRUE | BC36: FALSE | BD36: TRUE | BE36: FALSE | BF36: 1.75 | BG36: MEDIUM | BH36: TRUE | BI36: REGION_VII|CEBU|Cebu, District 3|AUTOMOTIVE AND LAND TRANSPORTATION|AFTERSALES & SERVICE (MAINTENANCE)|AUTOMOTIVE TECHNICIAN||AUTOMOTIVE SERVICING NC I||With TR|MEDIUM | BK36: TRUE | BL36: TRUE | BM36: TRUE | BN36: FALSE | BO36: FALSE | BP36: TRUE | BQ36: 1.25 | BR36: HIGH | BS36: TRUE | BT36: REGION_VII|CEBU|Cebu, District 4|AUTOMOTIVE AND LAND TRANSPORTATION|AFTERSALES & SERVICE (MAINTENANCE)|AUTOMOTIVE TECHNICIAN||AUTOMOTIVE SERVICING NC I||With TR|HIGH | BV36: TRUE | BW36: TRUE | BX36: TRUE | BY36: FALSE | BZ36: TRUE | CA36: FALSE | CB36: 1.75 | CC36: MEDIUM | CD36: TRUE | CE36: REGION_VII|CEBU|Cebu, District 5|AUTOMOTIVE AND LAND TRANSPORTATION|AFTERSALES & SERVICE (MAINTENANCE)|AUTOMOTIVE TECHNICIAN||AUTOMOTIVE SERVICING NC I||With TR|MEDIUM | CG36: TRUE | CH36: TRUE | CI36: TRUE | CJ36: FALSE | CK36: TRUE | CL36: FALSE | CM36: 1.75 | CN36: MEDIUM | CO36: TRUE | CP36: REGION_VII|CEBU|Cebu, District 6|AUTOMOTIVE AND LAND TRANSPORTATION|AFTERSALES & SERVICE (MAINTENANCE)|AUTOMOTIVE TECHNICIAN||AUTOMOTIVE SERVICING NC I||With TR|MEDIUM | CR36: TRUE | CS36: TRUE | CT36: TRUE | CU36: FALSE | CV36: TRUE | CW36: FALSE | CX36: 1.75 | CY36: MEDIUM | CZ36: TRUE | DA36: REGION_VII|CEBU|Cebu, District 7|AUTOMOTIVE AND LAND TRANSPORTATION|AFTERSALES & SERVICE (MAINTENANCE)|AUTOMOTIVE TECHNICIAN||AUTOMOTIVE SERVICING NC I||With TR|MEDIUM | DC36: TRUE | DD36: TRUE | DE36: TRUE | DF36: FALSE | DG36: TRUE | DH36: FALSE | DI36: 1.75 | DJ36: MEDIUM | DK36: TRUE | DL36: REGION_VII|CEBU|Lapu-Lapu City, Lone District|AUTOMOTIVE AND LAND TRANSPORTATION|AFTERSALES & SERVICE (MAINTENANCE)|AUTOMOTIVE TECHNICIAN||AUTOMOTIVE SERVICING NC I||With TR|MEDIUM | DN36: TRUE | DO36: TRUE | DP36: TRUE | DQ36: FALSE | DR36: TRUE | DS36: FALSE | DT36: 1.75 | DU36: MEDIUM
A37: AUTOMOTIVE AND LAND TRANSPORTATION | B37: AFTERSALES & SERVICE (MAINTENANCE) | C37: AUTOMOTIVE TECHNICIAN | D37: PERFORM REPARI AND PREVENTIVE MAINTENANCE OF VEHICLES CONDUCT EXTENSIVE DIAGNOSTIC PROCEDURES PROVIDE ACCURATE REPAIR RECOMMENDATIONS | E37: AUTOMOTIVE SERVICING NC I | F37: With TR | G37: MEDIUM | H37: TRUE | I37: TRUE | J37: TRUE | K37: FALSE | L37: FALSE | M37: TRUE | N37: 1.25 | O37: HIGH | P37: TRUE | Q37: REGION_VII|CEBU|Cebu City, District 1|AUTOMOTIVE AND LAND TRANSPORTATION|AUTOMOTIVE AND LAND TRANSPORTATION|DISPATCHER (BOOKING/TRIP CONTROLLER) ||NO CORRESPONDING TVET PROGRAM||New and Emerging|HIGH | S37: TRUE | T37: TRUE | U37: TRUE | V37: FALSE | W37: FALSE | X37: TRUE | Y37: 1.25 | Z37: HIGH | AA37: TRUE | AB37: REGION_VII|CEBU|Cebu City, District 2|AUTOMOTIVE AND LAND TRANSPORTATION|AUTOMOTIVE AND LAND TRANSPORTATION|DISPATCHER (BOOKING/TRIP CONTROLLER) ||NO CORRESPONDING TVET PROGRAM||New and Emerging|HIGH | AD37: TRUE | AE37: TRUE | AF37: TRUE | AG37: FALSE | AH37: FALSE | AI37: TRUE | AJ37: 1.25 | AK37: HIGH | AL37: TRUE | AM37: REGION_VII|CEBU|Cebu, District 1|AUTOMOTIVE AND LAND TRANSPORTATION|AUTOMOTIVE AND LAND TRANSPORTATION|DISPATCHER (BOOKING/TRIP CONTROLLER) ||NO CORRESPONDING TVET PROGRAM||New and Emerging|HIGH | AO37: TRUE | AP37: TRUE | AQ37: TRUE | AR37: TRUE | AS37: FALSE | AT37: FALSE | AU37: 2.25 | AV37: LOW | AW37: TRUE | AX37: REGION_VII|CEBU|Cebu, District 2|AUTOMOTIVE AND LAND TRANSPORTATION|AUTOMOTIVE AND LAND TRANSPORTATION|DISPATCHER (BOOKING/TRIP CONTROLLER) ||NO CORRESPONDING TVET PROGRAM||New and Emerging|LOW | AZ37: TRUE | BA37: TRUE | BB37: TRUE | BC37: TRUE | BD37: FALSE | BE37: FALSE | BF37: 2.25 | BG37: LOW | BH37: TRUE | BI37: REGION_VII|CEBU|Cebu, District 3|AUTOMOTIVE AND LAND TRANSPORTATION|AUTOMOTIVE AND LAND TRANSPORTATION|DISPATCHER (BOOKING/TRIP CONTROLLER) ||NO CORRESPONDING TVET PROGRAM||New and Emerging|LOW | BK37: TRUE | BL37: TRUE | BM37: TRUE | BN37: TRUE | BO37: FALSE | BP37: FALSE | BQ37: 2.25 | BR37: LOW | BS37: TRUE | BT37: REGION_VII|CEBU|Cebu, District 4|AUTOMOTIVE AND LAND TRANSPORTATION|AUTOMOTIVE AND LAND TRANSPORTATION|DISPATCHER (BOOKING/TRIP CONTROLLER) ||NO CORRESPONDING TVET PROGRAM||New and Emerging|LOW | BV37: TRUE | BW37: TRUE | BX37: TRUE | BY37: TRUE | BZ37: FALSE | CA37: FALSE | CB37: 2.25 | CC37: LOW | CD37: TRUE | CE37: REGION_VII|CEBU|Cebu, District 5|AUTOMOTIVE AND LAND TRANSPORTATION|AUTOMOTIVE AND LAND TRANSPORTATION|DISPATCHER (BOOKING/TRIP CONTROLLER) ||NO CORRESPONDING TVET PROGRAM||New and Emerging|LOW | CG37: TRUE | CH37: TRUE | CI37: TRUE | CJ37: TRUE | CK37: FALSE | CL37: FALSE | CM37: 2.25 | CN37: LOW | CO37: TRUE | CP37: REGION_VII|CEBU|Cebu, District 6|AUTOMOTIVE AND LAND TRANSPORTATION|AUTOMOTIVE AND LAND TRANSPORTATION|DISPATCHER (BOOKING/TRIP CONTROLLER) ||NO CORRESPONDING TVET PROGRAM||New and Emerging|LOW | CR37: TRUE | CS37: TRUE | CT37: TRUE | CU37: TRUE | CV37: FALSE | CW37: FALSE | CX37: 2.25 | CY37: LOW | CZ37: TRUE | DA37: REGION_VII|CEBU|Cebu, District 7|AUTOMOTIVE AND LAND TRANSPORTATION|AUTOMOTIVE AND LAND TRANSPORTATION|DISPATCHER (BOOKING/TRIP CONTROLLER) ||NO CORRESPONDING TVET PROGRAM||New and Emerging|LOW | DC37: TRUE | DD37: TRUE | DE37: TRUE | DF37: FALSE | DG37: FALSE | DH37: TRUE | DI37: 1.25 | DJ37: HIGH | DK37: TRUE | DL37: REGION_VII|CEBU|Lapu-Lapu City, Lone District|AUTOMOTIVE AND LAND TRANSPORTATION|AUTOMOTIVE AND LAND TRANSPORTATION|DISPATCHER (BOOKING/TRIP CONTROLLER) ||NO CORRESPONDING TVET PROGRAM||New and Emerging|HIGH | DN37: TRUE | DO37: TRUE | DP37: TRUE | DQ37: FALSE | DR37: FALSE | DS37: TRUE | DT37: 1.25 | DU37: HIGH
A38: AUTOMOTIVE AND LAND TRANSPORTATION | B38: AUTOMOTIVE AND LAND TRANSPORTATION | C38: DISPATCHER (BOOKING/TRIP CONTROLLER) | D38: RECORDS BOOKINGS RECEIVED FROM CLIENTS._x000D_ ASSIGNS/PLOT SCHEDULES OF TRUCKS BASED ON BOOKINGS._x000D_ PREPARES WAYBILL AND GATE PASS FOR THE TRUCKS._x000D_ DISPATCHES TRUCKS AS THEY LEAVE THE BASE._x000D_ ENSURES THAT TRUCKS LEAVE AND ARRIVE AT THE HOME BASE ON SCHEDULED TIME._x000D_ MONITOR DRIVERS’ AND TRUCK HELPER’S COMPLIANCE TO SCHEDULE TRIPS._x000D_ MAINTAINS A SUMMARY OF BOOKINGS, SERVED/UNSERVED TRIPS AND CANCELLED TRIPS._x000D_ | E38: NO CORRESPONDING TVET PROGRAM | F38: New and Emerging | G38: LOW | H38: TRUE | I38: TRUE | J38: TRUE | K38: FALSE | L38: FALSE | M38: TRUE | N38: 1.25 | O38: HIGH | P38: TRUE | Q38: REGION_VII|CEBU|Cebu City, District 1|AUTOMOTIVE AND LAND TRANSPORTATION|AUTOMOTIVE AND LAND TRANSPORTATION|DRIVER||DRIVING NC II||With TR|HIGH | S38: TRUE | T38: TRUE | U38: TRUE | V38: FALSE | W38: FALSE | X38: TRUE | Y38: 1.25 | Z38: HIGH | AA38: TRUE | AB38: REGION_VII|CEBU|Cebu City, District 2|AUTOMOTIVE AND LAND TRANSPORTATION|AUTOMOTIVE AND LAND TRANSPORTATION|DRIVER||DRIVING NC II||With TR|HIGH | AD38: TRUE | AE38: TRUE | AF38: TRUE | AG38: FALSE | AH38: FALSE | AI38: TRUE | AJ38: 1.25 | AK38: HIGH | AL38: TRUE | AM38: REGION_VII|CEBU|Cebu, District 1|AUTOMOTIVE AND LAND TRANSPORTATION|AUTOMOTIVE AND LAND TRANSPORTATION|DRIVER||DRIVING NC II||With TR|HIGH | AO38: TRUE | AP38: TRUE | AQ38: TRUE | AR38: FALSE | AS38: FALSE | AT38: TRUE | AU38: 1.25 | AV38: HIGH | AW38: TRUE | AX38: REGION_VII|CEBU|Cebu, District 2|AUTOMOTIVE AND LAND TRANSPORTATION|AUTOMOTIVE AND LAND TRANSPORTATION|DRIVER||DRIVING NC II||With TR|HIGH | AZ38: TRUE | BA38: TRUE | BB38: TRUE | BC38: FALSE | BD38: FALSE | BE38: TRUE | BF38: 1.25 | BG38: HIGH | BH38: TRUE | BI38: REGION_VII|CEBU|Cebu, District 3|AUTOMOTIVE AND LAND TRANSPORTATION|AUTOMOTIVE AND LAND TRANSPORTATION|DRIVER||DRIVING NC II||With TR|HIGH | BK38: TRUE | BL38: TRUE | BM38: TRUE | BN38: FALSE | BO38: TRUE | BP38: TRUE | BQ38: 1.75 | BR38: MEDIUM | BS38: TRUE | BT38: REGION_VII|CEBU|Cebu, District 4|AUTOMOTIVE AND LAND TRANSPORTATION|AUTOMOTIVE AND LAND TRANSPORTATION|DRIVER||DRIVING NC II||With TR|MEDIUM | BV38: TRUE | BW38: TRUE | BX38: TRUE | BY38: FALSE | BZ38: FALSE | CA38: TRUE | CB38: 1.25 | CC38: HIGH | CD38: TRUE | CE38: REGION_VII|CEBU|Cebu, District 5|AUTOMOTIVE AND LAND TRANSPORTATION|AUTOMOTIVE AND LAND TRANSPORTATION|DRIVER||DRIVING NC II||With TR|HIGH | CG38: TRUE | CH38: TRUE | CI38: TRUE | CJ38: FALSE | CK38: TRUE | CL38: FALSE | CM38: 1.75 | CN38: MEDIUM | CO38: TRUE | CP38: REGION_VII|CEBU|Cebu, District 6|AUTOMOTIVE AND LAND TRANSPORTATION|AUTOMOTIVE AND LAND TRANSPORTATION|DRIVER||DRIVING NC II||With TR|MEDIUM | CR38: TRUE | CS38: TRUE | CT38: TRUE | CU38: FALSE | CV38: TRUE | CW38: FALSE | CX38: 1.75 | CY38: MEDIUM | CZ38: TRUE | DA38: REGION_VII|CEBU|Cebu, District 7|AUTOMOTIVE AND LAND TRANSPORTATION|AUTOMOTIVE AND LAND TRANSPORTATION|DRIVER||DRIVING NC II||With TR|MEDIUM | DC38: TRUE | DD38: TRUE | DE38: TRUE | DF38: FALSE | DG38: FALSE | DH38: TRUE | DI38: 1.25 | DJ38: HIGH | DK38: TRUE | DL38: REGION_VII|CEBU|Lapu-Lapu City, Lone District|AUTOMOTIVE AND LAND TRANSPORTATION|AUTOMOTIVE AND LAND TRANSPORTATION|DRIVER||DRIVING NC II||With TR|HIGH | DN38: TRUE | DO38: TRUE | DP38: TRUE | DQ38: FALSE | DR38: FALSE | DS38: TRUE | DT38: 1.25 | DU38: HIGH
A39: AUTOMOTIVE AND LAND TRANSPORTATION | B39: AUTOMOTIVE AND LAND TRANSPORTATION | C39: DRIVER | D39: TRANSPORT CLIENTS AND/OR PACKAGES TO AND FROM DESTINATIONS_x000D_ ARRIVE AT DESTINATIONS ON SCHEDULE_x000D_ ENSURE THAT THE VEHICLE IS ALWAYS FUELED AND READY FOR USE_x000D_ ARRANGE FOR VEHICLE REPAIRS AS NEEDED_x000D_ | E39: DRIVING NC II | F39: With TR | G39: HIGH | H39: TRUE | I39: TRUE | J39: TRUE | K39: FALSE | L39: TRUE | M39: FALSE | N39: 1.75 | O39: MEDIUM | P39: TRUE | Q39: REGION_VII|CEBU|Cebu City, District 1|AUTOMOTIVE AND LAND TRANSPORTATION|AFTERSALES & SERVICE (MAINTENANCE)|ENGINE TECHNICIAN||AUTOMOTIVE SERVICING (ENGINE REPAIR) NC II||With TR|MEDIUM | S39: TRUE | T39: TRUE | U39: TRUE | V39: FALSE | W39: TRUE | X39: FALSE | Y39: 1.75 | Z39: MEDIUM | AA39: TRUE | AB39: REGION_VII|CEBU|Cebu City, District 2|AUTOMOTIVE AND LAND TRANSPORTATION|AFTERSALES & SERVICE (MAINTENANCE)|ENGINE TECHNICIAN||AUTOMOTIVE SERVICING (ENGINE REPAIR) NC II||With TR|MEDIUM | AD39: TRUE | AE39: TRUE | AF39: TRUE | AG39: FALSE | AH39: TRUE | AI39: FALSE | AJ39: 1.75 | AK39: MEDIUM | AL39: TRUE | AM39: REGION_VII|CEBU|Cebu, District 1|AUTOMOTIVE AND LAND TRANSPORTATION|AFTERSALES & SERVICE (MAINTENANCE)|ENGINE TECHNICIAN||AUTOMOTIVE SERVICING (ENGINE REPAIR) NC II||With TR|MEDIUM | AO39: TRUE | AP39: TRUE | AQ39: TRUE | AR39: FALSE | AS39: TRUE | AT39: FALSE | AU39: 1.75 | AV39: MEDIUM | AW39: TRUE | AX39: REGION_VII|CEBU|Cebu, District 2|AUTOMOTIVE AND LAND TRANSPORTATION|AFTERSALES & SERVICE (MAINTENANCE)|ENGINE TECHNICIAN||AUTOMOTIVE SERVICING (ENGINE REPAIR) NC II||With TR|MEDIUM | AZ39: TRUE | BA39: TRUE | BB39: TRUE | BC39: FALSE | BD39: TRUE | BE39: FALSE | BF39: 1.75 | BG39: MEDIUM | BH39: TRUE | BI39: REGION_VII|CEBU|Cebu, District 3|AUTOMOTIVE AND LAND TRANSPORTATION|AFTERSALES & SERVICE (MAINTENANCE)|ENGINE TECHNICIAN||AUTOMOTIVE SERVICING (ENGINE REPAIR) NC II||With TR|MEDIUM | BK39: TRUE | BL39: TRUE | BM39: TRUE | BN39: FALSE | BO39: TRUE | BP39: FALSE | BQ39: 1.75 | BR39: MEDIUM | BS39: TRUE | BT39: REGION_VII|CEBU|Cebu, District 4|AUTOMOTIVE AND LAND TRANSPORTATION|AFTERSALES & SERVICE (MAINTENANCE)|ENGINE TECHNICIAN||AUTOMOTIVE SERVICING (ENGINE REPAIR) NC II||With TR|MEDIUM | BV39: TRUE | BW39: TRUE | BX39: TRUE | BY39: FALSE | BZ39: TRUE | CA39: FALSE | CB39: 1.75 | CC39: MEDIUM | CD39: TRUE | CE39: REGION_VII|CEBU|Cebu, District 5|AUTOMOTIVE AND LAND TRANSPORTATION|AFTERSALES & SERVICE (MAINTENANCE)|ENGINE TECHNICIAN||AUTOMOTIVE SERVICING (ENGINE REPAIR) NC II||With TR|MEDIUM | CG39: TRUE | CH39: TRUE | CI39: TRUE | CJ39: FALSE | CK39: TRUE | CL39: FALSE | CM39: 1.75 | CN39: MEDIUM | CO39: TRUE | CP39: REGION_VII|CEBU|Cebu, District 6|AUTOMOTIVE AND LAND TRANSPORTATION|AFTERSALES & SERVICE (MAINTENANCE)|ENGINE TECHNICIAN||AUTOMOTIVE SERVICING (ENGINE REPAIR) NC II||With TR|MEDIUM | CR39: TRUE | CS39: TRUE | CT39: TRUE | CU39: FALSE | CV39: TRUE | CW39: FALSE | CX39: 1.75 | CY39: MEDIUM | CZ39: TRUE | DA39: REGION_VII|CEBU|Cebu, District 7|AUTOMOTIVE AND LAND TRANSPORTATION|AFTERSALES & SERVICE (MAINTENANCE)|ENGINE TECHNICIAN||AUTOMOTIVE SERVICING (ENGINE REPAIR) NC II||With TR|MEDIUM | DC39: TRUE | DD39: TRUE | DE39: TRUE | DF39: FALSE | DG39: TRUE | DH39: FALSE | DI39: 1.75 | DJ39: MEDIUM | DK39: TRUE | DL39: REGION_VII|CEBU|Lapu-Lapu City, Lone District|AUTOMOTIVE AND LAND TRANSPORTATION|AFTERSALES & SERVICE (MAINTENANCE)|ENGINE TECHNICIAN||AUTOMOTIVE SERVICING (ENGINE REPAIR) NC II||With TR|MEDIUM | DN39: TRUE | DO39: TRUE | DP39: TRUE | DQ39: FALSE | DR39: TRUE | DS39: FALSE | DT39: 1.75 | DU39: MEDIUM
A40: AUTOMOTIVE AND LAND TRANSPORTATION | B40: AFTERSALES & SERVICE (MAINTENANCE) | C40: ENGINE TECHNICIAN | D40: DIAGNOSE AND REPAIR ENGINE COOLING AND LUBRICATION SYSTEM DIAGNOSE AND REPAIR INTAKE AND EXHAUST SYSTEM DIAGNOSE AND OVERHAUL ENGINE MECHANICAL SYSTEM | E40: AUTOMOTIVE SERVICING (ENGINE REPAIR) NC II | F40: With TR | G40: MEDIUM | H40: TRUE | I40: TRUE | J40: TRUE | K40: FALSE | L40: TRUE | M40: FALSE | N40: 1.75 | O40: MEDIUM | P40: TRUE | Q40: REGION_VII|CEBU|Cebu City, District 1|AUTOMOTIVE AND LAND TRANSPORTATION|AUTOMOTIVE AND LAND TRANSPORTATION|PASSENGER ASSISTANT OFFICER (CONDUCTOR)||NO CORRESPONDING TVET PROGRAM||New and Emerging|MEDIUM | S40: TRUE | T40: TRUE | U40: TRUE | V40: FALSE | W40: TRUE | X40: FALSE | Y40: 1.75 | Z40: MEDIUM | AA40: TRUE | AB40: REGION_VII|CEBU|Cebu City, District 2|AUTOMOTIVE AND LAND TRANSPORTATION|AUTOMOTIVE AND LAND TRANSPORTATION|PASSENGER ASSISTANT OFFICER (CONDUCTOR)||NO CORRESPONDING TVET PROGRAM||New and Emerging|MEDIUM | AD40: TRUE | AE40: TRUE | AF40: TRUE | AG40: FALSE | AH40: TRUE | AI40: FALSE | AJ40: 1.75 | AK40: MEDIUM | AL40: TRUE | AM40: REGION_VII|CEBU|Cebu, District 1|AUTOMOTIVE AND LAND TRANSPORTATION|AUTOMOTIVE AND LAND TRANSPORTATION|PASSENGER ASSISTANT OFFICER (CONDUCTOR)||NO CORRESPONDING TVET PROGRAM||New and Emerging|MEDIUM | AO40: TRUE | AP40: TRUE | AQ40: TRUE | AR40: TRUE | AS40: FALSE | AT40: FALSE | AU40: 2.25 | AV40: LOW | AW40: TRUE | AX40: REGION_VII|CEBU|Cebu, District 2|AUTOMOTIVE AND LAND TRANSPORTATION|AUTOMOTIVE AND LAND TRANSPORTATION|PASSENGER ASSISTANT OFFICER (CONDUCTOR)||NO CORRESPONDING TVET PROGRAM||New and Emerging|LOW | AZ40: TRUE | BA40: TRUE | BB40: TRUE | BC40: TRUE | BD40: FALSE | BE40: FALSE | BF40: 2.25 | BG40: LOW | BH40: TRUE | BI40: REGION_VII|CEBU|Cebu, District 3|AUTOMOTIVE AND LAND TRANSPORTATION|AUTOMOTIVE AND LAND TRANSPORTATION|PASSENGER ASSISTANT OFFICER (CONDUCTOR)||NO CORRESPONDING TVET PROGRAM||New and Emerging|LOW | BK40: TRUE | BL40: TRUE | BM40: TRUE | BN40: TRUE | BO40: FALSE | BP40: FALSE | BQ40: 2.25 | BR40: LOW | BS40: TRUE | BT40: REGION_VII|CEBU|Cebu, District 4|AUTOMOTIVE AND LAND TRANSPORTATION|AUTOMOTIVE AND LAND TRANSPORTATION|PASSENGER ASSISTANT OFFICER (CONDUCTOR)||NO CORRESPONDING TVET PROGRAM||New and Emerging|LOW | BV40: TRUE | BW40: TRUE | BX40: TRUE | BY40: TRUE | BZ40: FALSE | CA40: FALSE | CB40: 2.25 | CC40: LOW | CD40: TRUE | CE40: REGION_VII|CEBU|Cebu, District 5|AUTOMOTIVE AND LAND TRANSPORTATION|AUTOMOTIVE AND LAND TRANSPORTATION|PASSENGER ASSISTANT OFFICER (CONDUCTOR)||NO CORRESPONDING TVET PROGRAM||New and Emerging|LOW | CG40: TRUE | CH40: TRUE | CI40: TRUE | CJ40: TRUE | CK40: FALSE | CL40: FALSE | CM40: 2.25 | CN40: LOW | CO40: TRUE | CP40: REGION_VII|CEBU|Cebu, District 6|AUTOMOTIVE AND LAND TRANSPORTATION|AUTOMOTIVE AND LAND TRANSPORTATION|PASSENGER ASSISTANT OFFICER (CONDUCTOR)||NO CORRESPONDING TVET PROGRAM||New and Emerging|LOW | CR40: TRUE | CS40: TRUE | CT40: TRUE | CU40: TRUE | CV40: FALSE | CW40: FALSE | CX40: 2.25 | CY40: LOW | CZ40: TRUE | DA40: REGION_VII|CEBU|Cebu, District 7|AUTOMOTIVE AND LAND TRANSPORTATION|AUTOMOTIVE AND LAND TRANSPORTATION|PASSENGER ASSISTANT OFFICER (CONDUCTOR)||NO CORRESPONDING TVET PROGRAM||New and Emerging|LOW | DC40: TRUE | DD40: TRUE | DE40: TRUE | DF40: TRUE | DG40: TRUE | DH40: FALSE | DI40: 2.25 | DJ40: LOW | DK40: TRUE | DL40: REGION_VII|CEBU|Lapu-Lapu City, Lone District|AUTOMOTIVE AND LAND TRANSPORTATION|AUTOMOTIVE AND LAND TRANSPORTATION|PASSENGER ASSISTANT OFFICER (CONDUCTOR)||NO CORRESPONDING TVET PROGRAM||New and Emerging|LOW | DN40: TRUE | DO40: TRUE | DP40: TRUE | DQ40: FALSE | DR40: TRUE | DS40: FALSE | DT40: 1.75 | DU40: MEDIUM
