Workbook

Sheet Read Me
A1: TVET Landscape EDA & Leads: NCR & Region IV-A (CALABARZON)
A2: Source: NCR4A_TVET.xlsx (TESDA registry extract). JF + Angela
A5: WHAT THIS DATASET IS
A6: Grain | B6: One row = institution x city x qualification x role (training and/or assessment).
A7: Roles | B7: Is_Development=1: delivers training (drives Enrolled, Graduates). Is_Assessment=1: accredited assessment venue (drives Assessed, Certified). A row can be both.
A8: Coverage | B8: 2 regions, 1,085 unique institutions, 155 qualifications, 3,327 records after cleaning.
A10: DATA CLEANING APPLIED
A11: Duplicates removed | B11: 738 exact full-row duplicates dropped (mostly assessment rows double-listed in the export). 4,065 raw rows -> 3,327 clean.
A12: Construction flag | B12: Built-environment trades flagged: SMAW/GMAW/GTAW/FCAW welding, Electrical Installation, Masonry, Carpentry, Plumbing, Tile Setting, Heavy Equipment Operation, Scaffolding, Pipefitting, Reinforcing Steel, Rigging, Formwork. Automotive painting excluded (vehicle, not building).
A14: HOW CENTRES ARE RANKED
A15: Primary metric | B15: Enrolled = training throughput (scale of the teaching business).
A16: Quality signals | B16: Grad Rate = Graduates / Enrolled. Cert Rate = Certified / Assessed. Both can exceed 100% because a cohort graduating/certifying this period may have enrolled earlier, and assessment includes walk-in RPL candidates.
A18: KEY TAKEAWAYS
A19: 1 | B19: The market splits into two businesses: training (Enrolled/Graduates) and assessment/certification (Assessed/Certified). Many high-volume players are assessment-heavy, which is more asset-light.
A20: 2 | B20: NCR leaders skew to BPO-adjacent and service trades (call center, computer servicing, caregiving, food). 4A leaders skew to manufacturing-linked and trade skills.
A21: 3 | B21: Construction trades = 15.8% of all training enrolment, but certification volume (72.5k) far exceeds training enrolment (30.6k): the trades assessment/RPL business is larger than the training business.
A22: 4 | B22: Welding (SMAW I+II) and Electrical Installation are the deepest construction pools by both demand and number of providers (130+ centres each), i.e. competitive. Heavy Equipment, Scaffolding and Plumbing are thinner provider markets with high certification pull.

Sheet Top Centers - NCR
A1: Top TVET Centers for NCR | C1: Filter
A2: 546 institutions. Ranked by training Enrolled. Rates shown as formulas (recompute live). | C2: =>3 Quals | E2: =>100 graduates | H2: =>5 trainers
A4: Rank | B4: Institution | C4: Quals | D4: Enrolled | E4: Graduates | F4: Assessed | G4: Certified | H4: Trainers | I4: Grad Rate | J4: Cert Rate | K4: 1 | L4: Primary Research Notes (JF Inputs) | M4: Updated FB in the Past Year | N4: Congratulate their Graduates of the Current Year? | O4: Updated Google Maps | P4: Responded to Student Inquiry? | Q4: Website? | R4: Website Link | S4: Decision | T4: First Name | U4: Last Name | V4: Title | W4: Email of Contact | X4: Has a LMS | Y4: When is next course starting | Z4: How much is it? | AA4: Can I get scholarship? | AB4: How do I apply? | AC4: 2 | AD4: Phone number contact | AE4: Email Contact | AF4: 3 | AG4: Number of Yes | AH4: Number of Institutions that have At Least 3 Yes
A5: 1 | B5: PHILIPPINE CALL CENTER INSTITUTE INC. | C5: 3 | D5: 2741 | E5: 3191 | F5: 0 | G5: 0 | H5: 20 | I5: =IF(D5=0,"-",E5/D5) -> 1.1641737 | J5: =IF(F5=0,"-",G5/F5) -> - | K5: 1 | L5: Facebook page, last update 2024. Called both numbers, no response. | M5: No | N5: No | O5: No | P5: No | Q5: No | AG5: {=SUMPRODUCT(--(M5:Q5="YES"))} -> 0 | AH5: =COUNTIF($AG$5:AG5, ">=3") -> 0
A6: 2 | B6: TESDA Women's Center | C6: 18 | D6: 2422 | E6: 2491 | F6: 0 | G6: 0 | H6: 25 | I6: =IF(D6=0,"-",E6/D6) -> 1.0284889 | J6: =IF(F6=0,"-",G6/F6) -> - | K6: 1 | L6: Has a webpage and Facebook page. | M6: Yes | N6: Yes | O6: Yes | P6: Yes | Q6: Yes | R6: https://twc.tesda.gov.ph/ | S6: Yes | T6: Gerrelen | U6: Balbin | V6: Senior TESD Specialist, Unit Head (Training Management Unit) | W6: gdbalbin@tesda.gov.ph | X6: Yes | Y6: N/A | Z6: N/A | AA6: N/A | AB6: N/A | AD6: (02) 8817-2650 / (02) 8817-2651 | AE6: twc@tesda.gov.ph | AG6: {=SUMPRODUCT(--(M6:Q6="YES"))} -> 5 | AH6: =COUNTIF($AG$5:AG6, ">=3") -> 1
A7: 3 | B7: UNITED INTERNATIONAL MARITIME TRAINING AND ASSESSMENT CENTER INC. | C7: 7 | D7: 2126 | E7: 325 | F7: 5627 | G7: 5549 | H7: 16 | I7: =IF(D7=0,"-",E7/D7) -> 0.15286924 | J7: =IF(F7=0,"-",G7/F7) -> 0.98613826 | K7: 1 | L7: Facebook has student photos, but the phone number given does not work. They have a website. There, the number does work. Wala pong bread and pastry. No TESDA scholarship. Ships NC III for 27 days for 1495 USD. They ask for Form 137, 138,and Transcript of Records. Pwede mag apply ng online. Sales@unpc.com.ph. | M7: No | N7: No | O7: Yes | P7: Yes | Q7: Yes | R7: https://www.umtc.com.ph/ | S7: Yes | Y7: None (Waiting for full batch) | Z7: 1495 USD | AA7: No (No TESDA scholarship currently) | AB7: Online (Email the Requirements) | AG7: {=SUMPRODUCT(--(M7:Q7="YES"))} -> 3 | AH7: =COUNTIF($AG$5:AG7, ">=3") -> 2
A8: 4 | B8: CARENET HEALTHCARE INSTITUTE INC. | C8: 3 | D8: 2114 | E8: 2193 | F8: 1221 | G8: 1205 | H8: 19 | I8: =IF(D8=0,"-",E8/D8) -> 1.0373699 | J8: =IF(F8=0,"-",G8/F8) -> 0.98689599 | K8: 1 | L8: Facebook page is actually an account, not a page. | M8: No | N8: No | O8: Yes | P8: No | Q8: No | AG8: {=SUMPRODUCT(--(M8:Q8="YES"))} -> 1 | AH8: =COUNTIF($AG$5:AG8, ">=3") -> 2
A9: 5 | B9: TECHVOC SKILLS INC. | C9: 4 | D9: 2028 | E9: 1917 | F9: 817 | G9: 812 | H9: 12 | I9: =IF(D9=0,"-",E9/D9) -> 0.94526627 | J9: =IF(F9=0,"-",G9/F9) -> 0.99388005 | K9: 1 | L9: They have a message channel that just posts whenver there is a new opening or program. They responded very quickly when I messaged them on Facebook. They even have a Tiktok with 2000 followers. | M9: Yes | N9: Yes | O9: Yes | P9: Yes | Q9: No | S9: Yes | T9: Melody | U9: Cruz | V9: School Head | Y9: N/A | Z9: N/A | AA9: N/A | AB9: N/A | AD9: N/A | AE9: techvoc_skills.incorporated@yahoo.com | AG9: {=SUMPRODUCT(--(M9:Q9="YES"))} -> 4 | AH9: =COUNTIF($AG$5:AG9, ">=3") -> 3
A10: 6 | B10: PHILIPPINE SCHOOL FOR TECHNOLOGY DEVELOPMENT AND INNOVATION INC. | C10: 12 | D10: 1831 | E10: 1972 | F10: 1666 | G10: 1658 | H10: 9 | I10: =IF(D10=0,"-",E10/D10) -> 1.0770071 | J10: =IF(F10=0,"-",G10/F10) -> 0.99519808 | K10: 1 | L10: Facebook was updated last April 14. No phone number and email is provided. | M10: Yes | N10: Yes | O10: Yes | P10: No | Q10: No | AG10: {=SUMPRODUCT(--(M10:Q10="YES"))} -> 3 | AH10: =COUNTIF($AG$5:AG10, ">=3") -> 4
A11: 7 | B11: UNO CAREGIVER AND DOMESTIC MNGT TRAINING, INC. | C11: 13 | D11: 1722 | E11: 1703 | F11: 1978 | G11: 1935 | H11: 27 | I11: =IF(D11=0,"-",E11/D11) -> 0.98896632 | J11: =IF(F11=0,"-",G11/F11) -> 0.97826087 | L11: They have a Tiktok. I tried calling them thrice. They never picked up. For the Caregiving NC II, there is no tentative. Php 26,000 in installment basis. Merong TESDA scholarship pero walang starting date. Drop by. | M11: Yes | N11: Yes | O11: Yes | P11: Yes | Q11: No | S11: Yes | Y11: None (Pending TESDA funding) | Z11: Php 26,000 | AA11: Yes (Waitlist) | AB11: Onsite (Walk-in application) | AD11: (02) 8687 6250 | AE11: uno.training88@gmail.com | AG11: {=SUMPRODUCT(--(M11:Q11="YES"))} -> 4 | AH11: =COUNTIF($AG$5:AG11, ">=3") -> 5
A12: 8 | B12: PSAA INTERNATIONAL ACADEMY INC. | C12: 16 | D12: 1476 | E12: 1169 | F12: 3929 | G12: 3894 | H12: 20 | I12: =IF(D12=0,"-",E12/D12) -> 0.79200542 | J12: =IF(F12=0,"-",G12/F12) -> 0.99109188 | K12: 1 | L12: Has a Facebook page but webpage does not work anymore. Called, no response. | M12: Yes | N12: Yes | O12: Yes | P12: Yes | Q12: Yes | R12: https://psaamanilatvet.com/ | S12: Yes | T12: Riza | U12: Sorima-Matias | V12: Training Director | W12: N/A | Y12: N/A | Z12: N/A | AA12: N/A | AB12: N/A | AD12: 0920 859 3752 | AE12: psaamanila@hotmail.com | AG12: {=SUMPRODUCT(--(M12:Q12="YES"))} -> 5 | AH12: =COUNTIF($AG$5:AG12, ">=3") -> 6
A13: 9 | B13: POWER LINK CENTER FOR ADVANCED TECHNICAL SKILLS DEVELOPMENT INC. | C13: 5 | D13: 1468 | E13: 1214 | F13: 0 | G13: 0 | H13: 19 | I13: =IF(D13=0,"-",E13/D13) -> 0.82697548 | J13: =IF(F13=0,"-",G13/F13) -> - | K13: 1 | L13: Facebook page was updated last June 19. There is Barista, Cookery. They offer scholarships and the such, but there is no voucher right now. They need 15 to 20 candidates. It is unsure when it will start. Fill up an application. Voucher for the scholarship. | M13: Yes | N13: No | O13: Yes | P13: Yes | Q13: Yes | R13: https://powerlink3.wixsite.com/powerlinkgroup | S13: 3rd Priority | Y13: None (Waiting for full batch) | Z13: None (Pending TESDA funding) | AA13: Yes (Waitlist) | AB13: Onsite (Walk-in application) | AD13: 0969 306 4698 | AE13: powerlink0615@gmail.com | AG13: {=SUMPRODUCT(--(M13:Q13="YES"))} -> 4 | AH13: =COUNTIF($AG$5:AG13, ">=3") -> 7
A14: 11 | B14: MAGSAYSAY CENTER FOR HOSPITALITY AND CULINARY ARTS, INC. | C14: 4 | D14: 1384 | E14: 1675 | F14: 0 | G14: 0 | H14: 15 | I14: =IF(D14=0,"-",E14/D14) -> 1.2102601 | J14: =IF(F14=0,"-",G14/F14) -> - | K14: 1 | L14: Already a partner, no need to review | M14: Yes | N14: Yes | O14: Yes | P14: Yes | Q14: No | S14: N/A | Y14: N/A | Z14: N/A | AA14: N/A | AB14: N/A | AG14: {=SUMPRODUCT(--(M14:Q14="YES"))} -> 4 | AH14: =COUNTIF($AG$5:AG14, ">=3") -> 8
A15: 12 | B15: RMC EAGLES TRAINING AND ASSESSMENT CENTER INC. | C15: 3 | D15: 1377 | E15: 1318 | F15: 1012 | G15: 1010 | H15: 6 | I15: =IF(D15=0,"-",E15/D15) -> 0.95715323 | J15: =IF(F15=0,"-",G15/F15) -> 0.99802372 | L15: Facebook page was updated last June 11. There is registration link in the recent Facebook post to register. They are waiting for the notice to proceed from TESDA so that they can start orientation. For the regular, there is no assessment for the cyber threat monitoring NC I. For the regular, it is 16 days. The price was not said to me, and when they said to look at the registration form, it doesn't even say the price either. | M15: Yes | N15: Yes | O15: Yes | P15: Yes | Q15: No | Y15: None (Pending TESDA funding) | Z15: None (For scheduling) | AA15: Yes (Waitlist) | AB15: FB (Use registration link) | AD15: 0905 418 0148 | AE15: rmceagles3@gmail.com | AG15: {=SUMPRODUCT(--(M15:Q15="YES"))} -> 4 | AH15: =COUNTIF($AG$5:AG15, ">=3") -> 9
A16: 13 | B16: ASIANTOUCH INTERNATIONAL TRAINING INSTITUTE, INC. | C16: 5 | D16: 1369 | E16: 1006 | F16: 1294 | G16: 1289 | H16: 12 | I16: =IF(D16=0,"-",E16/D16) -> 0.73484295 | J16: =IF(F16=0,"-",G16/F16) -> 0.99613601 | K16: 1 | L16: Facebook page was last updated in 2025, but the phone number does not work. | M16: No | N16: No | O16: Yes | P16: No | Q16: No | AG16: {=SUMPRODUCT(--(M16:Q16="YES"))} -> 1 | AH16: =COUNTIF($AG$5:AG16, ">=3") -> 9
A17: 14 | B17: NATIONAL INSTITUTE FOR TECHNICAL AND VOCATIONAL CAREERS, INC. | C17: 3 | D17: 1311 | E17: 1374 | F17: 0 | G17: 0 | H17: 11 | I17: =IF(D17=0,"-",E17/D17) -> 1.0480549 | J17: =IF(F17=0,"-",G17/F17) -> - | K17: 1 | L17: Facebook was updated last 2019, and the phone numbers given do not work. | M17: No | N17: No | O17: No | P17: No | Q17: No | AG17: {=SUMPRODUCT(--(M17:Q17="YES"))} -> 0 | AH17: =COUNTIF($AG$5:AG17, ">=3") -> 9
A18: 16 | B18: PHILIPPINE ACADEMY FOR TECHNICAL AND VOCATIONAL SKILLS, INC. | C18: 4 | D18: 1231 | E18: 1026 | F18: 0 | G18: 0 | H18: 13 | I18: =IF(D18=0,"-",E18/D18) -> 0.83346872 | J18: =IF(F18=0,"-",G18/F18) -> - | K18: 1 | L18: Their landline number is not even updated. | M18: No | N18: No | O18: Yes | P18: No | Q18: No | AG18: {=SUMPRODUCT(--(M18:Q18="YES"))} -> 1 | AH18: =COUNTIF($AG$5:AG18, ">=3") -> 9
A19: 17 | B19: CAPT. WILIJADO P. ABUID FOUNDATION, INC. | C19: 4 | D19: 1227 | E19: 345 | F19: 4261 | G19: 4254 | H19: 6 | I19: =IF(D19=0,"-",E19/D19) -> 0.28117359 | J19: =IF(F19=0,"-",G19/F19) -> 0.99835719 | K19: 1 | AG19: {=SUMPRODUCT(--(M19:Q19="YES"))} -> 0 | AH19: =COUNTIF($AG$5:AG19, ">=3") -> 9
A20: 19 | B20: B AND B ACADEMY FOR SKILLS TRAINING AND ASSESSMENT INC. | C20: 7 | D20: 1178 | E20: 1446 | F20: 1372 | G20: 1334 | H20: 9 | I20: =IF(D20=0,"-",E20/D20) -> 1.2275042 | J20: =IF(F20=0,"-",G20/F20) -> 0.97230321 | K20: 1 | L20: Facebook was updated last June 23. | M20: Yes | N20: Yes | O20: Yes | P20: No | Q20: No | AD20: 0956 432 9868 | AE20: bbacademypasig@gmail.com | AG20: {=SUMPRODUCT(--(M20:Q20="YES"))} -> 3 | AH20: =COUNTIF($AG$5:AG20, ">=3") -> 10
A21: 21 | B21: MILESTONE TECHNOLOGICAL INSTITUTE, INC. | C21: 5 | D21: 1089 | E21: 970 | F21: 0 | G21: 0 | H21: 14 | I21: =IF(D21=0,"-",E21/D21) -> 0.89072544 | J21: =IF(F21=0,"-",G21/F21) -> - | K21: 1 | L21: They have a wordpress. However, when I asked on the Java programming course, they said that it's not currently available since there are currently no scholarships. | M21: Yes | N21: Yes | O21: Yes | P21: Yes | Q21: Yes | R21: https://mtivalenzuela.wordpress.com/?fbclid=IwY2xjawS79edleHRuA2FlbQIxMABicmlkETF5V0pSQ3Y2RzltTzJOcnVnc3J0YwZhcHBfaWQQMjIyMDM5MTc4ODIwMDg5MgABHt0O_Y9j0jQTXKv1oxd1Fu3dQssYM3hmiiWsYsvMSxal3hLrXq4TLgvaa0DH_aem_LJ0TYP3wfSv9mKSm77KLSQ | S21: Yes | X21: Yes | Y21: None (Pending TESDA funding) | Z21: None (Pending TESDA funding) | AA21: No (No TESDA scholarship currently) | AB21: Online (WordPress site for inquiries) | AD21: (02) 8553-8078 | AE21: mti.developer.ph@gmail.com | AG21: {=SUMPRODUCT(--(M21:Q21="YES"))} -> 5 | AH21: =COUNTIF($AG$5:AG21, ">=3") -> 11
A22: 22 | B22: REGIONAL TRAINING CENTER - NCR | C22: 12 | D22: 1059 | E22: 1438 | F22: 1405 | G22: 1346 | H22: 12 | I22: =IF(D22=0,"-",E22/D22) -> 1.3578848 | J22: =IF(F22=0,"-",G22/F22) -> 0.95800712 | K22: 1 | L22: The regional training center does not have its own Facebook page for developmental acitivites. It is combined with the main Facebook page. However, their website does tell on how to apply. | M22: Yes | N22: No | O22: Yes | P22: Yes | Q22: Yes | R22: https://rtcncr.com/ | S22: Yes | T22: Jerry | U22: Taroy | V22: Supervising TESD Specialist, Head – Training, Research, Assessment and Extension Unit (TREAU) | Y22: N/A | Z22: N/A | AA22: N/A | AB22: N/A | AD22: 0968 852 8204 | AE22: rtcncr@tesda.gov.ph | AG22: {=SUMPRODUCT(--(M22:Q22="YES"))} -> 4 | AH22: =COUNTIF($AG$5:AG22, ">=3") -> 12
A23: 23 | B23: QTEK TRAINING AND ASSESSMENT CENTER INC. | C23: 5 | D23: 1048 | E23: 906 | F23: 492 | G23: 487 | H23: 11 | I23: =IF(D23=0,"-",E23/D23) -> 0.86450382 | J23: =IF(F23=0,"-",G23/F23) -> 0.9898374 | K23: 1 | L23: Facebook was updated last July 3. They accepted my call, but they ended it when I asked about scholarships. | M23: Yes | N23: Yes | O23: Yes | P23: Yes | Q23: Yes | R23: http://www.qtekcenter.com/site/page/content | S23: 3rd Priority (For the courses, it is difficult to work with construction) | Y23: N/A | Z23: N/A | AA23: N/A | AB23: N/A | AD23: 0917 300 5827 | AE23: mcobinayug@qtekcenter.com | AG23: {=SUMPRODUCT(--(M23:Q23="YES"))} -> 5 | AH23: =COUNTIF($AG$5:AG23, ">=3") -> 13
A24: 25 | B24: MECHATRONICS TECHNOLOGIES CORP. | C24: 9 | D24: 992 | E24: 957 | F24: 1187 | G24: 1149 | H24: 11 | I24: =IF(D24=0,"-",E24/D24) -> 0.96471774 | J24: =IF(F24=0,"-",G24/F24) -> 0.96798652 | K24: 1 | L24: Facebook was updated last June 25. They also have a website. The landline number does not work, but the phone number does. | M24: Yes | N24: Yes | O24: Yes | P24: Yes | Q24: Yes | R24: https://www.mechatronicstechnologiescorp.com/?fbclid=IwY2xjawS7-FRleHRuA2FlbQIxMABicmlkETF5V0pSQ3Y2RzltTzJOcnVnc3J0YwZhcHBfaWQQMjIyMDM5MTc4ODIwMDg5MgABHgOEcKonPcyX34lk0-T79l9To5TiXmsiLxDTW94WhhoSFaJ87Uav6eHa-KJj_aem_4cikKUbg9_O5qQenqa8UCg | S24: Yes | T24: Xerxes Gamaliel | U24: Itao | V24: Managing Director | W24: N/A | X24: No | Y24: N/A | Z24: N/A | AA24: N/A | AB24: N/A | AD24: 0975 293 7418 | AE24: mechatronicstechnologiescorp@yahoo.com | AG24: {=SUMPRODUCT(--(M24:Q24="YES"))} -> 5 | AH24: =COUNTIF($AG$5:AG24, ">=3") -> 14
A25: 26 | B25: DON BOSCO YOUTH CENTER-TONDO INC. | C25: 9 | D25: 991 | E25: 1117 | F25: 0 | G25: 0 | H25: 11 | I25: =IF(D25=0,"-",E25/D25) -> 1.1271443 | J25: =IF(F25=0,"-",G25/F25) -> - | K25: 1 | L25: Facebook was updated last June 30. They also have a nice website. | M25: Yes | N25: Yes | O25: Yes | P25: No | Q25: Yes | R25: https://www.donboscoyouthcenter.online/ | S25: N/A | AD25: 0949 103 8045 | AE25: donboscoyouthcentertvet@gmail.com | AG25: {=SUMPRODUCT(--(M25:Q25="YES"))} -> 4 | AH25: =COUNTIF($AG$5:AG25, ">=3") -> 15
A26: 27 | B26: SOCIO INTER SKILLS TRAINING ACADEMY (SISTA) INC. | C26: 4 | D26: 988 | E26: 841 | F26: 802 | G26: 801 | H26: 7 | I26: =IF(D26=0,"-",E26/D26) -> 0.85121457 | J26: =IF(F26=0,"-",G26/F26) -> 0.99875312 | K26: 1 | L26: Facebook page was updated last July 2. | M26: Yes | N26: Yes | O26: Yes | P26: No | Q26: Yes | R26: https://www.sista.com.ph/ | S26: Yes | AD26: 0962 246 4473 | AE26: sociointerskills@gmail.com | AG26: {=SUMPRODUCT(--(M26:Q26="YES"))} -> 4 | AH26: =COUNTIF($AG$5:AG26, ">=3") -> 16
A27: 28 | B27: Top Choice Training Institute and Assessment Center | C27: 3 | D27: 963 | E27: 897 | F27: 0 | G27: 0 | H27: 10 | I27: =IF(D27=0,"-",E27/D27) -> 0.93146417 | J27: =IF(F27=0,"-",G27/F27) -> - | K27: 1 | L27: Facebook was updated lasy July 3. The website provided did not work. For the phone call, they were very insightful because they even said on how to actually register. They asked also for my name and said that I can register in the center or message more in WhatsApp. | M27: Yes | N27: No | O27: Yes | P27: Yes | Q27: No | Y27: N/A | Z27: N/A | AA27: N/A | AB27: Onsite / WhatsApp (Register at center or message for assistance) | AD27: 0918 927 1980 | AE27: topchoicetraining24@gmail.com | AG27: {=SUMPRODUCT(--(M27:Q27="YES"))} -> 3 | AH27: =COUNTIF($AG$5:AG27, ">=3") -> 17
A28: 29 | B28: BOWLINE TRAINING & ASSESSMENT CENTER, INC. | C28: 3 | D28: 900 | E28: 731 | F28: 0 | G28: 0 | H28: 6 | I28: =IF(D28=0,"-",E28/D28) -> 0.81222222 | J28: =IF(F28=0,"-",G28/F28) -> - | K28: 1 | AG28: {=SUMPRODUCT(--(M28:Q28="YES"))} -> 0 | AH28: =COUNTIF($AG$5:AG28, ">=3") -> 17
A29: 30 | B29: ARAYA SKILLS DEVELOPMENT INSTITUTE, CORP. | C29: 3 | D29: 900 | E29: 668 | F29: 0 | G29: 0 | H29: 6 | I29: =IF(D29=0,"-",E29/D29) -> 0.74222222 | J29: =IF(F29=0,"-",G29/F29) -> - | K29: 1 | AG29: {=SUMPRODUCT(--(M29:Q29="YES"))} -> 0 | AH29: =COUNTIF($AG$5:AG29, ">=3") -> 17
A30: 31 | B30: Quezon City Lingkod Bayan Skills Development Center | C30: 6 | D30: 882 | E30: 868 | F30: 0 | G30: 0 | H30: 10 | I30: =IF(D30=0,"-",E30/D30) -> 0.98412698 | J30: =IF(F30=0,"-",G30/F30) -> - | K30: 1 | L30: Their Facebook is not even the first result. It's called Tesda Ncr Qclbsdc, so it's just a lost list of acronyms huhuhuhu. Also, calling is not an option. They prefer if you just go there. As a commenter said, "Mas mabilis ang transaction sa QC Lingkod Bayan Center kung personal kayo pupunta sa office nila" | M30: No | N30: No | O30: Yes | P30: No | Q30: No | AG30: {=SUMPRODUCT(--(M30:Q30="YES"))} -> 1 | AH30: =COUNTIF($AG$5:AG30, ">=3") -> 17
A31: 32 | B31: HORIZONS INSTITUTE OF TECHNOLOGY CORPORATION | C31: 8 | D31: 859 | E31: 895 | F31: 1770 | G31: 1756 | H31: 7 | I31: =IF(D31=0,"-",E31/D31) -> 1.0419092 | J31: =IF(F31=0,"-",G31/F31) -> 0.9920904 | K31: 1 | L31: Facebook page was updated last July 7. They did not accept my call. | M31: Yes | N31: Yes | O31: Yes | P31: No | Q31: No | AD31: 0968 776 0024 | AE31: hitacc.am@gmail.com | AG31: {=SUMPRODUCT(--(M31:Q31="YES"))} -> 3 | AH31: =COUNTIF($AG$5:AG31, ">=3") -> 18
A32: 34 | B32: SLDM COLLEGES OF QUEZON CITY, INC. | C32: 5 | D32: 833 | E32: 844 | F32: 0 | G32: 0 | H32: 8 | I32: =IF(D32=0,"-",E32/D32) -> 1.0132053 | J32: =IF(F32=0,"-",G32/F32) -> - | K32: 1 | L32: Facebook was last updated June 30. They actually had to transfer me. To register, we would have to go to Facebook of the training and assessment center of lakewood school of alabang. There would be a link that gives the registration link and they would give me a list of requirements. Aside of the list requirements, certificate of indigency (no need for medical since this is replacement of the medical). | M32: Yes | N32: Yes | O32: Yes | P32: No | Q32: No | AD32: 0967 375 4257 | AE32: sldmcollegesofqc2014@gmail.com | AG32: {=SUMPRODUCT(--(M32:Q32="YES"))} -> 3 | AH32: =COUNTIF($AG$5:AG32, ">=3") -> 19
A33: 35 | B33: RIGHT FOCUS TRAINING CENTER, INC. | C33: 6 | D33: 821 | E33: 764 | F33: 547 | G33: 543 | H33: 8 | I33: =IF(D33=0,"-",E33/D33) -> 0.93057247 | J33: =IF(F33=0,"-",G33/F33) -> 0.99268739 | K33: 1 | L33: Facebook was last updated June 25. They also have an Instagram where they posted last June 11. | M33: Yes | N33: Yes | O33: Yes | P33: No | Q33: Yes | R33: https://www.rightfocustrainingcenter.com/ | S33: Yes | AD33: 0981 792 9222 | AE33: rftc.socmed@gmail.com | AG33: {=SUMPRODUCT(--(M33:Q33="YES"))} -> 4 | AH33: =COUNTIF($AG$5:AG33, ">=3") -> 20
A34: 36 | B34: MUNTIPARLASTAPAT DISTRICT TRAINING AND ASSESSMENT CENTER | C34: 6 | D34: 812 | E34: 1035 | F34: 1018 | G34: 976 | H34: 10 | I34: =IF(D34=0,"-",E34/D34) -> 1.2746305 | J34: =IF(F34=0,"-",G34/F34) -> 0.95874263 | K34: 1 | L34: Facebook was updated last July 2. The district training center does not have their own website, and the phone numbers given do not work. Still, I will just include a phone number for completion's sake. However, they do have a Forms to register: https://docs.google.com/forms/d/e/1FAIpQLSezk8jlUcjy0xn-x7dg1agnQHsxHzhmO0TqGaZCNuBZKQXvew/viewform | M34: Yes | N34: No | O34: Yes | P34: No | Q34: No | AD34: 0917 845 8926 | AE34: mdtac@tesda.gov.ph | AG34: {=SUMPRODUCT(--(M34:Q34="YES"))} -> 2 | AH34: =COUNTIF($AG$5:AG34, ">=3") -> 20
A35: 37 | B35: TESDA-NAVOTAAS TRAINING INSTITUTE | C35: 11 | D35: 811 | E35: 983 | F35: 791 | G35: 782 | H35: 10 | I35: =IF(D35=0,"-",E35/D35) -> 1.2120838 | J35: =IF(F35=0,"-",G35/F35) -> 0.988622 | K35: 1 | L35: Facebook was updated last May. The district's landline does not work, but I'll include it anyways. They do have a Forms: https://forms.gle/gpkjhHgY3i8MGiLy8 | M35: Yes | N35: No | O35: Yes | P35: No | Q35: No | AD35: (02) 8292-2183 | AE35: tnti@tesda.gov.ph | AG35: {=SUMPRODUCT(--(M35:Q35="YES"))} -> 2 | AH35: =COUNTIF($AG$5:AG35, ">=3") -> 20
A36: 38 | B36: TRIDENT-ASSESSMENT AND TECHNICAL TRAINING CENTER INC. | C36: 6 | D36: 788 | E36: 695 | F36: 2801 | G36: 2801 | H36: 5 | I36: =IF(D36=0,"-",E36/D36) -> 0.8819797 | J36: =IF(F36=0,"-",G36/F36) -> 1 | K36: 1 | AG36: {=SUMPRODUCT(--(M36:Q36="YES"))} -> 0 | AH36: =COUNTIF($AG$5:AG36, ">=3") -> 20
A37: 39 | B37: APLUS TECHNICAL AND VOCATIONAL SCHOOL INC. | C37: 3 | D37: 777 | E37: 727 | F37: 0 | G37: 0 | H37: 9 | I37: =IF(D37=0,"-",E37/D37) -> 0.93564994 | J37: =IF(F37=0,"-",G37/F37) -> - | K37: 1 | L37: Facebook was updated last May 14, but the post was just 'Amen!🧚‍♂️' When I called the phone number, they said that I should just go to the actual location for more questions. They did not want to answer on how to register on the phone. | M37: Yes | N37: No | O37: Yes | P37: Yes | Q37: No | Y37: N/A | Z37: N/A | AA37: N/A | AB37: Onsite (Walk-in application) | AD37: 0915 800 1270 | AE37: N/A | AG37: {=SUMPRODUCT(--(M37:Q37="YES"))} -> 3 | AH37: =COUNTIF($AG$5:AG37, ">=3") -> 21
A38: 42 | B38: GATEWAYS INSTITUTE OF SCIENCE & TECHNOLOGY, INC. (Mandaluyong) | C38: 4 | D38: 761 | E38: 719 | F38: 0 | G38: 0 | H38: 6 | I38: =IF(D38=0,"-",E38/D38) -> 0.94480946 | J38: =IF(F38=0,"-",G38/F38) -> - | K38: 1 | AG38: {=SUMPRODUCT(--(M38:Q38="YES"))} -> 0 | AH38: =COUNTIF($AG$5:AG38, ">=3") -> 21
A39: 43 | B39: APHRODITE TRAINING AND ASSESSMENT CENTER INC. | C39: 3 | D39: 757 | E39: 661 | F39: 204 | G39: 204 | H39: 6 | I39: =IF(D39=0,"-",E39/D39) -> 0.87318362 | J39: =IF(F39=0,"-",G39/F39) -> 1 | K39: 1 | AG39: {=SUMPRODUCT(--(M39:Q39="YES"))} -> 0 | AH39: =COUNTIF($AG$5:AG39, ">=3") -> 21
A40: 44 | B40: HEADSTART TRAINING CENTER CORP. | C40: 4 | D40: 751 | E40: 251 | F40: 214 | G40: 214 | H40: 9 | I40: =IF(D40=0,"-",E40/D40) -> 0.33422104 | J40: =IF(F40=0,"-",G40/F40) -> 1 | K40: 1 | L40: Facebook was last updated June 23. The number provided could not be completed at dial. | M40: Yes | N40: Yes | O40: Yes | P40: No | Q40: No | AD40: 0968 447 1790 | AE40: headstartcenter1@gmail.com | AG40: {=SUMPRODUCT(--(M40:Q40="YES"))} -> 3 | AH40: =COUNTIF($AG$5:AG40, ">=3") -> 22
A41: 48 | B41: ACADEMY ASIA SCHOOL OF TECHNOLOGY AND THE ARTS, INC. | C41: 6 | D41: 720 | E41: 644 | F41: 0 | G41: 0 | H41: 7 | I41: =IF(D41=0,"-",E41/D41) -> 0.89444444 | J41: =IF(F41=0,"-",G41/F41) -> - | K41: 1 | L41: Facebook page was updated last June 25. No TESDA courses right now. But there is a registration link in the Facebook page. We can register there so that once TESDA gives scholarship. Instead, they suggested to just enroll regularly. With tuition, they will just be assessed. The tuition will be of the Professional Certificate of Culinary Art (where it leads to the Cookery NC II) is of four months with the duration ours of 270 hours with 300 hours of OJT from 8 AM to 5 PM thrice a week. Afterwards, there is a program inclusion with local partnerships para maging OJT. For the payment, there is two options of cash payment with Php 65,000 with 10% discount. The second option is monthly payment of an initial payment of Php 25,000 (monthly of Php 10,000). | M41: Yes | N41: Yes | O41: Yes | P41: Yes | Q41: Yes | R41: http://academyasia.ph/ | S41: Yes | T41: N/A | U41: N/A | V41: N/A | W41: N/A | Y41: None (Pending TESDA funding) | Z41: ₱65,000 (Training; Professional Certificate in Culinary Art → Cookery NC II) | AA41: Yes (Waitlist) | AB41: Online (Register via FB link for updates or enroll regularly) | AD41: 0917 882 2742 | AE41: academy.asia@gmail.com | AG41: {=SUMPRODUCT(--(M41:Q41="YES"))} -> 5 | AH41: =COUNTIF($AG$5:AG41, ">=3") -> 23
A42: 50 | B42: RCTI TRAINING AND ASSESSMENT CORP. | C42: 7 | D42: 717 | E42: 633 | F42: 2356 | G42: 2349 | H42: 8 | I42: =IF(D42=0,"-",E42/D42) -> 0.88284519 | J42: =IF(F42=0,"-",G42/F42) -> 0.99702886 | K42: 1 | L42: Facebook was updated last July 8. There is a tentative schedule with a weekend schedule for someone brand new for the barista (no sure date). Onsite registration only. Message in Facebook for the contact and the such so that they are added in the line-up. No TESDA scholarship, only regular training. For regular training of Php 8,000. 1,200 for the assessment. | M42: Yes | N42: Yes | O42: Yes | P42: Yes | Q42: Yes | R42: https://www.rcti-elearning.com/?fbclid=IwY2xjawS8M1lleHRuA2FlbQIxMABicmlkETF1MlN4bjJpVkN6a2xHNENDc3J0YwZhcHBfaWQQMjIyMDM5MTc4ODIwMDg5MgABHsse20a-kx8qQZzgBEtMPjDQWQVaDKiODPt1be4_bNNBVzZ_htwzsLhcjn6F_aem_BpN-2npgquSQzmI1bA_K7A | S42: 2nd Priority | X42: Yes | AG42: {=SUMPRODUCT(--(M42:Q42="YES"))} -> 5 | AH42: =COUNTIF($AG$5:AG42, ">=3") -> 24
A43: 49 | B43: FINE INTERNATIONAL TRAINING CENTER, INC. | C43: 7 | D43: 717 | E43: 620 | F43: 858 | G43: 835 | H43: 11 | I43: =IF(D43=0,"-",E43/D43) -> 0.86471409 | J43: =IF(F43=0,"-",G43/F43) -> 0.97319347 | K43: 1 | L43: Facebook was updated last July 3. They also have a nice website. | M43: Yes | N43: Yes | O43: Yes | P43: No | Q43: Yes | R43: https://finetraining.co/ | S43: Yes | T43: N/A | U43: N/A | V43: N/A | X43: Yes | AD43: 0921 576 9341 | AE43: admin@fineitc.com | AG43: {=SUMPRODUCT(--(M43:Q43="YES"))} -> 4 | AH43: =COUNTIF($AG$5:AG43, ">=3") -> 25
A44: 51 | B44: TAGUIG MANPOWER TRAINING AND ASSESSMENT CENTER (TMTC) | C44: 6 | D44: 714 | E44: 930 | F44: 706 | G44: 704 | H44: 13 | I44: =IF(D44=0,"-",E44/D44) -> 1.302521 | J44: =IF(F44=0,"-",G44/F44) -> 0.99716714 | K44: 1 | L44: Facebook was updated lst June 30, very recent. | M44: Yes | N44: Yes | O44: Yes | P44: No | Q44: No | AD44: 0908 813 7226 | AE44: None | AG44: {=SUMPRODUCT(--(M44:Q44="YES"))} -> 3 | AH44: =COUNTIF($AG$5:AG44, ">=3") -> 26
A45: 52 | B45: SMI INSTITUTE INC. | C45: 6 | D45: 645 | E45: 749 | F45: 0 | G45: 0 | H45: 12 | I45: =IF(D45=0,"-",E45/D45) -> 1.1612403 | J45: =IF(F45=0,"-",G45/F45) -> - | K45: 1 | L45: Facebook was updated last May 3. No phone number available. They also have a website, but it is not secure. | M45: Yes | N45: Yes | O45: Yes | P45: No | Q45: Yes | R45: https://smitracked.cloud/ | S45: Yes | T45: Cristina | U45: Aplasca | V45: N/A | AE45: smiacademicenter@gmail.com | AG45: {=SUMPRODUCT(--(M45:Q45="YES"))} -> 4 | AH45: =COUNTIF($AG$5:AG45, ">=3") -> 27
A46: 53 | B46: HUMAN RESOURCE DEVELOPMENT CENTER (HRDC) | C46: 4 | D46: 625 | E46: 588 | F46: 0 | G46: 0 | H46: 5 | I46: =IF(D46=0,"-",E46/D46) -> 0.9408 | J46: =IF(F46=0,"-",G46/F46) -> - | K46: 1 | AG46: {=SUMPRODUCT(--(M46:Q46="YES"))} -> 0 | AH46: =COUNTIF($AG$5:AG46, ">=3") -> 27
A47: 56 | B47: SEA GEM TRAINING AND ASSESSMENT CENTER, INC. | C47: 4 | D47: 597 | E47: 492 | F47: 0 | G47: 0 | H47: 11 | I47: =IF(D47=0,"-",E47/D47) -> 0.8241206 | J47: =IF(F47=0,"-",G47/F47) -> - | K47: 1 | L47: Facebook was updated last June 16. They said to go to the location for registration. | M47: Yes | N47: Yes | O47: Yes | P47: Yes | Q47: No | S47: 2nd Priority | Y47: N/A | Z47: N/A | AA47: N/A | AB47: Onsite (Walk-in application) | AD47: (02) 8252 1192 | AG47: {=SUMPRODUCT(--(M47:Q47="YES"))} -> 4 | AH47: =COUNTIF($AG$5:AG47, ">=3") -> 28
A48: 57 | B48: PASAY-MAKATI DISTRICT TRAINING AND ASSESSMENT CENTER (PMDTAC) | C48: 8 | D48: 550 | E48: 584 | F48: 648 | G48: 610 | H48: 9 | I48: =IF(D48=0,"-",E48/D48) -> 1.0618182 | J48: =IF(F48=0,"-",G48/F48) -> 0.94135802 | K48: 1 | L48: They do not have their own facebook since they are just combined with the main TESDA page. Moreover, the last time they were posted about was September 24, 2024. | M48: No | N48: No | O48: Yes | P48: No | Q48: No | AG48: {=SUMPRODUCT(--(M48:Q48="YES"))} -> 1 | AH48: =COUNTIF($AG$5:AG48, ">=3") -> 28
A49: 58 | B49: INTERNATIONAL TRAINING CENTER AND HOSPITALITY INSTITUTE, INC. | C49: 6 | D49: 540 | E49: 663 | F49: 1222 | G49: 1212 | H49: 8 | I49: =IF(D49=0,"-",E49/D49) -> 1.2277778 | J49: =IF(F49=0,"-",G49/F49) -> 0.99181669 | K49: 1 | L49: There are no more scholarships available, but 16000 tuition fee, 2000 deductible for registration for housekeeping. The registration has to be done onsite. They spoke to me in English. | M49: Yes | N49: Yes | O49: Yes | P49: Yes | R49: https://itchi-asia.com/ | S49: Yes | Y49: None (Waiting for full batch) | Z49: ₱16,000 (Training; Housekeeping NC II) | AA49: None (No available scholarship slots) | AB49: Onsite (Register at center; ₱2,000 deductible for reservation) | AD49: 0947 484 5312 | AE49: info@itchi-asia.com | AG49: {=SUMPRODUCT(--(M49:Q49="YES"))} -> 4 | AH49: =COUNTIF($AG$5:AG49, ">=3") -> 29
A50: 59 | B50: SEAMAC INTERNATIONAL TRAINING INSTITUTE, INC. | C50: 8 | D50: 536 | E50: 476 | F50: 1025 | G50: 1013 | H50: 7 | I50: =IF(D50=0,"-",E50/D50) -> 0.8880597 | J50: =IF(F50=0,"-",G50/F50) -> 0.98829268 | K50: 1 | L50: Facebook page was updated last July 1. For Electrical Installation and Maintenance NC II, it is currently ongoing. For the regular training, there is a minimum amount of people needed. It would Php 14,500 for over 25 days. This includes only training. The assessment fee is Php 1,849. To register, we can just message on Facebook to fill up and register. There is only online payment available. | M50: Yes | N50: Yes | O50: Yes | P50: Yes | Q50: Yes | R50: https://seamactraining.com/ | S50: 2nd Priority | T50: N/A | U50: N/A | V50: N/A | W50: N/A | X50: No | Y50: Ongoing (25-day training; minimum batch required) | Z50: ₱14,500 + ₱1,849 (Training + Assessment; Electrical Installation and Maintenance NC II) | AA50: No (No available scholarship slots) | AB50: FB (Fill out form + pay online) | AD50: 02 8736 7885 | AE50: seamactraining@yahoo.com | AG50: {=SUMPRODUCT(--(M50:Q50="YES"))} -> 5 | AH50: =COUNTIF($AG$5:AG50, ">=3") -> 30
A51: 62 | B51: FPTI-PUNLAAN SCHOOL | C51: 5 | D51: 526 | E51: 571 | F51: 0 | G51: 0 | H51: 6 | I51: =IF(D51=0,"-",E51/D51) -> 1.0855513 | J51: =IF(F51=0,"-",G51/F51) -> - | K51: 1 | AG51: {=SUMPRODUCT(--(M51:Q51="YES"))} -> 0 | AH51: =COUNTIF($AG$5:AG51, ">=3") -> 30
A52: 63 | B52: CENTRAL INSTITUTE OF TECHNOLOGY OF QUEZON CITY, INC. | C52: 4 | D52: 516 | E52: 427 | F52: 0 | G52: 0 | H52: 6 | I52: =IF(D52=0,"-",E52/D52) -> 0.82751938 | J52: =IF(F52=0,"-",G52/F52) -> - | K52: 1 | AG52: {=SUMPRODUCT(--(M52:Q52="YES"))} -> 0 | AH52: =COUNTIF($AG$5:AG52, ">=3") -> 30
A53: 67 | B53: ST. CATHERINE INSTITUTE OF TECHNOLOGY, INC. | C53: 11 | D53: 498 | E53: 730 | F53: 0 | G53: 0 | H53: 12 | I53: =IF(D53=0,"-",E53/D53) -> 1.4658635 | J53: =IF(F53=0,"-",G53/F53) -> - | K53: 1 | L53: Facebook was updated last May 22. When I called, I asked first on when is the next enrollment. They asked specifically for which course, so I just said on SMAW NC III. They suggested to me for registration that I go physically to their offices. | M53: Yes | N53: No | O53: Yes | P53: Yes | Q53: No | Y53: N/A | Z53: N/A | AA53: N/A | AB53: Onsite (Walk-in application) | AD53: 0918 529 2561 | AE53: stcatherineinstituteoftechnology@yahoo.com | AG53: {=SUMPRODUCT(--(M53:Q53="YES"))} -> 3 | AH53: =COUNTIF($AG$5:AG53, ">=3") -> 31
A54: 69 | B54: CENTER FOR BARISTA AND TOURISM ACADEMY TRAINING AND ASSESSMENT, INC. | C54: 4 | D54: 497 | E54: 521 | F54: 0 | G54: 0 | H54: 8 | I54: =IF(D54=0,"-",E54/D54) -> 1.0482897 | J54: =IF(F54=0,"-",G54/F54) -> - | K54: 1 | L54: Facebook was updated last July 8. This is for the Barista NC I. Next available on July 9 to 25. For scholarship, the enrollment is closed right now since it is not available. For the paid training, Php 27,490 with training and assessment. They accept online enrollment through the website page and facebook page. | M54: Yes | N54: Yes | O54: Yes | P54: Yes | Q54: Yes | R54: https://centerforbarista.com/ | S54: 2nd Priority | T54: Deejae | U54: Juanta | V54: Founder | X54: Yes | Y54: July 9–25 | Z54: ₱27,490 (Training + Assessment; Barista NC I) | AA54: None (No available scholarship slots) | AB54: Online (Website or FB enrollment) | AD54: 0945 217 5697 | AE54: training.cfb@gmail.com | AG54: {=SUMPRODUCT(--(M54:Q54="YES"))} -> 5 | AH54: =COUNTIF($AG$5:AG54, ">=3") -> 32
A55: 71 | B55: Miesha Training Academy and Assessment Center, Inc. | C55: 6 | D55: 480 | E55: 581 | F55: 0 | G55: 0 | H55: 10 | I55: =IF(D55=0,"-",E55/D55) -> 1.2104167 | J55: =IF(F55=0,"-",G55/F55) -> - | K55: 1 | L55: Facebook was updated last June 30. | M55: Yes | N55: No | O55: Yes | P55: No | Q55: No | AD55: 0912 801 0310 | AE55: miesha.inc@gmail.com | AG55: {=SUMPRODUCT(--(M55:Q55="YES"))} -> 2 | AH55: =COUNTIF($AG$5:AG55, ">=3") -> 32
A56: 72 | B56: CPDC TRAINING & TESTING CORP. | C56: 3 | D56: 477 | E56: 555 | F56: 0 | G56: 0 | H56: 7 | I56: =IF(D56=0,"-",E56/D56) -> 1.163522 | J56: =IF(F56=0,"-",G56/F56) -> - | K56: 1 | L56: The Facebook page was last updated on July 8. The tentative start date is within this month, contingent upon the completion of the participant list; however, the exact schedule remains indefinite. Applicants may also opt for regular training. It should be noted that there is a limited absorptive capacity for TESDA scholars, and those who are not accommodated may be placed in a waiting list or considered for the regular program. The fee for the regular training is Php 29,727.17. Registration must be completed onsite, as certain documents require physical signatures. | M56: Yes | N56: Yes | O56: Yes | P56: Yes | Q56: No | Y56: Tentative (Within this month; waiting for full batch) | Z56: ₱29,727.17 (Training; Regular program) | AA56: Yes (Waitlist) | AB56: Onsite (Walk-in application) | AD56: 0917 133 0793 | AE56: cpdcorp@gmail.com | AG56: {=SUMPRODUCT(--(M56:Q56="YES"))} -> 4 | AH56: =COUNTIF($AG$5:AG56, ">=3") -> 33
A57: 73 | B57: COLLEGE OF SAINT AMATIEL INC. | C57: 9 | D57: 465 | E57: 637 | F57: 1125 | G57: 1120 | H57: 6 | I57: =IF(D57=0,"-",E57/D57) -> 1.3698925 | J57: =IF(F57=0,"-",G57/F57) -> 0.99555556 | K57: 1 | AG57: {=SUMPRODUCT(--(M57:Q57="YES"))} -> 0 | AH57: =COUNTIF($AG$5:AG57, ">=3") -> 33
A58: 74 | B58: TECHNO DEVELOPMENT CENTER OF THE PHILIPPINES, INC. | C58: 4 | D58: 454 | E58: 399 | F58: 0 | G58: 0 | H58: 5 | I58: =IF(D58=0,"-",E58/D58) -> 0.87885463 | J58: =IF(F58=0,"-",G58/F58) -> - | K58: 1 | AG58: {=SUMPRODUCT(--(M58:Q58="YES"))} -> 0 | AH58: =COUNTIF($AG$5:AG58, ">=3") -> 33
A59: 76 | B59: ASIAN ENTREPRENEURS TECHNOLOGICAL INSTITUTE, INC. | C59: 3 | D59: 452 | E59: 491 | F59: 0 | G59: 0 | H59: 5 | I59: =IF(D59=0,"-",E59/D59) -> 1.0862832 | J59: =IF(F59=0,"-",G59/F59) -> - | K59: 1 | AG59: {=SUMPRODUCT(--(M59:Q59="YES"))} -> 0 | AH59: =COUNTIF($AG$5:AG59, ">=3") -> 33
A60: 77 | B60: SOUTHERN LUZON TECHNOLOGICAL COLLEGE FOUNDATION, INC. | C60: 8 | D60: 451 | E60: 838 | F60: 678 | G60: 592 | H60: 7 | I60: =IF(D60=0,"-",E60/D60) -> 1.8580931 | J60: =IF(F60=0,"-",G60/F60) -> 0.87315634 | K60: 1 | L60: Facebook page was updated last July 1. The website provided more details in the TESDA programs. https://sltcfi.com/page.php?page=tran | M60: Yes | N60: Yes | O60: Yes | P60: No | Q60: Yes | R60: https://pasig.sltcfi.com/ | S60: Yes | AD60: 0995 111 4651 | AE60: registrar@sltcfi.com | AG60: {=SUMPRODUCT(--(M60:Q60="YES"))} -> 4 | AH60: =COUNTIF($AG$5:AG60, ">=3") -> 34
A61: 82 | B61: MILLENNIUM PROPERTIES AND BROKERAGE INCORPORATED - ASTORIA CULINARY & HOSPITALITY INSTITUTE | C61: 5 | D61: 431 | E61: 310 | F61: 0 | G61: 0 | H61: 7 | I61: =IF(D61=0,"-",E61/D61) -> 0.71925754 | J61: =IF(F61=0,"-",G61/F61) -> - | K61: 1 | L61: Facebook page was updated last July 3. They did not accept my call. The posts are not really for the TESDA branch. It is more on the SHS branch. | M61: Yes | N61: Yes | O61: Yes | P61: No | Q61: Yes | R61: https://astoriaculinaryandhospitalityinstitute.com/ | S61: Yes | X61: Yes | AD61: 0920 958 2032 | AE61: training@astoriaplaza.com | AG61: {=SUMPRODUCT(--(M61:Q61="YES"))} -> 4 | AH61: =COUNTIF($AG$5:AG61, ">=3") -> 35
A62: 83 | B62: St. Bernadette College of Alabang | C62: 5 | D62: 430 | E62: 302 | F62: 0 | G62: 0 | H62: 7 | I62: =IF(D62=0,"-",E62/D62) -> 0.70232558 | J62: =IF(F62=0,"-",G62/F62) -> - | K62: 1 | AG62: {=SUMPRODUCT(--(M62:Q62="YES"))} -> 0 | AH62: =COUNTIF($AG$5:AG62, ">=3") -> 35
A63: 85 | B63: ACADEMY FOR INTERNATIONAL CULINARY ARTS, INC. | C63: 3 | D63: 426 | E63: 489 | F63: 0 | G63: 0 | H63: 6 | I63: =IF(D63=0,"-",E63/D63) -> 1.1478873 | J63: =IF(F63=0,"-",G63/F63) -> - | K63: 1 | AG63: {=SUMPRODUCT(--(M63:Q63="YES"))} -> 0 | AH63: =COUNTIF($AG$5:AG63, ">=3") -> 35
A64: 87 | B64: ASIA SOURCE ICOLLEGE INC. | C64: 3 | D64: 415 | E64: 329 | F64: 0 | G64: 0 | H64: 7 | I64: =IF(D64=0,"-",E64/D64) -> 0.79277108 | J64: =IF(F64=0,"-",G64/F64) -> - | K64: 1 | L64: Facebook page was updated last July 6. There are two branches of Pasig and Taguig. I called the Pasig branch since that is the came up when I searched for the Facebook page. For the Bookkeeping NC III, they are offering the regular program na may bayad with Php 12,000 of only training. The assessment fee is Php 841. The regular program would be starting when the 10 slots are occupied. I would be the first one in line for the Bookkeeping (I would have to find nine other people). Regular program lahat sa TESDA. There are no TESDA scholarships right now. To register, kailangan onsite to pass requirements in the officem so it needs onsite. | M64: Yes | N64: Yes | O64: Yes | P64: Yes | Q64: Yes | R64: https://www.asiasourceicollege.edu.ph/ | S64: 2nd Priority | T64: Jethro | U64: Orejuela | V64: School Director | W64: N/A | Y64: None (Waiting for full batch) | Z64: ₱12,000 + ₱841 (Training + Assessment; Bookkeeping NC III) | AA64: None (No available scholarship slots) | AB64: Onsite (Submit requirements at office) | AD64: 0961 743 0541 | AE64: asic2014@asiasourceicollege.edu.ph | AG64: {=SUMPRODUCT(--(M64:Q64="YES"))} -> 5 | AH64: =COUNTIF($AG$5:AG64, ">=3") -> 36
A65: 92 | B65: INTEGRATED INNOVATION AND HOSPITALITY COLLEGES, INC. | C65: 7 | D65: 388 | E65: 552 | F65: 999 | G65: 997 | H65: 5 | I65: =IF(D65=0,"-",E65/D65) -> 1.4226804 | J65: =IF(F65=0,"-",G65/F65) -> 0.997998 | K65: 1 | AG65: {=SUMPRODUCT(--(M65:Q65="YES"))} -> 0 | AH65: =COUNTIF($AG$5:AG65, ">=3") -> 36
A66: 96 | B66: LA SALLE GREENHILLS, INC. | C66: 6 | D66: 376 | E66: 337 | F66: 0 | G66: 0 | H66: 8 | I66: =IF(D66=0,"-",E66/D66) -> 0.8962766 | J66: =IF(F66=0,"-",G66/F66) -> - | K66: 1 | L66: Facebook page was updated last June 20. They did not accept my call. | M66: Yes | N66: Yes | O66: Yes | P66: No | Q66: Yes | R66: https://www.lsgh.edu.ph/ | S66: 3rd Priority | AD66: 02 8723 4055 | AE66: is.apae@lsgh.edu.ph | AG66: {=SUMPRODUCT(--(M66:Q66="YES"))} -> 4 | AH66: =COUNTIF($AG$5:AG66, ">=3") -> 37
A67: 97 | B67: PASIG CITY INSTITUTE OF SCIENCE AND TECHNOLOGY | C67: 3 | D67: 373 | E67: 367 | F67: 0 | G67: 0 | H67: 5 | I67: =IF(D67=0,"-",E67/D67) -> 0.98391421 | J67: =IF(F67=0,"-",G67/F67) -> - | K67: 1 | AG67: {=SUMPRODUCT(--(M67:Q67="YES"))} -> 0 | AH67: =COUNTIF($AG$5:AG67, ">=3") -> 37
A68: 99 | B68: Stars and Rainbow Academy, Inc. | C68: 4 | D68: 369 | E68: 287 | F68: 0 | G68: 0 | H68: 6 | I68: =IF(D68=0,"-",E68/D68) -> 0.77777778 | J68: =IF(F68=0,"-",G68/F68) -> - | K68: 1 | AG68: {=SUMPRODUCT(--(M68:Q68="YES"))} -> 0 | AH68: =COUNTIF($AG$5:AG68, ">=3") -> 37
A69: 101 | B69: Laborlink Technical Institute Corporation | C69: 3 | D69: 357 | E69: 449 | F69: 0 | G69: 0 | H69: 5 | I69: =IF(D69=0,"-",E69/D69) -> 1.2577031 | J69: =IF(F69=0,"-",G69/F69) -> - | K69: 1 | AG69: {=SUMPRODUCT(--(M69:Q69="YES"))} -> 0 | AH69: =COUNTIF($AG$5:AG69, ">=3") -> 37
A70: 105 | C70: 9 | D70: 327 | E70: 199 | F70: 54 | G70: 54 | H70: 9 | I70: =IF(D70=0,"-",E70/D70) -> 0.60856269 | J70: =IF(F70=0,"-",G70/F70) -> 1 | K70: 1 | L70: N/A | M70: No | N70: No | O70: No | P70: No | AG70: {=SUMPRODUCT(--(M70:Q70="YES"))} -> 0 | AH70: =COUNTIF($AG$5:AG70, ">=3") -> 37
A71: 107 | B71: CENTER FOR ASIAN CULINARY STUDIES INC. | C71: 4 | D71: 320 | E71: 341 | F71: 215 | G71: 215 | H71: 12 | I71: =IF(D71=0,"-",E71/D71) -> 1.065625 | J71: =IF(F71=0,"-",G71/F71) -> 1 | K71: 1 | L71: Facebook was updated last July 1. They also have a very nice website. Scholarships are being provided by Vikings Hospitality program. First step of application is to reserve a slot, which has Php 5,000 or Php 10,000 of the reservation, depending on the program. They are likely to have a very good reputation. | M71: Yes | N71: Yes | O71: Yes | P71: Yes | Q71: Yes | R71: https://centerforasianculinarystudies.com/ | S71: Yes | T71: Eugenio; Eliseo | U71: Gonzalez; De Guzman | V71: Culinary Arts Director; Pastry Arts Director | W71: N/A | X71: No | Y71: N/A | Z71: Php 40,000 | AA71: Yes (Not through TESDA but through Vikings Hospitality Program) | AB71: Online (Reserve slot via website + pay ₱5,000–₱10,000) | AD71: 0977 347 3277 | AE71: cacschef@gmail.com | AG71: {=SUMPRODUCT(--(M71:Q71="YES"))} -> 5 | AH71: =COUNTIF($AG$5:AG71, ">=3") -> 38
A72: 113 | B72: COLEGIO DE SAN GABRIEL ARCANGEL OF CALOOCAN, INC. | C72: 5 | D72: 295 | E72: 346 | F72: 0 | G72: 0 | H72: 6 | I72: =IF(D72=0,"-",E72/D72) -> 1.1728814 | J72: =IF(F72=0,"-",G72/F72) -> - | K72: 1 | AG72: {=SUMPRODUCT(--(M72:Q72="YES"))} -> 0 | AH72: =COUNTIF($AG$5:AG72, ">=3") -> 38
A73: 114 | B73: MARY GRACE INTERNATIONAL EDUCATION INC. | C73: 4 | D73: 292 | E73: 278 | F73: 172 | G73: 170 | H73: 5 | I73: =IF(D73=0,"-",E73/D73) -> 0.95205479 | J73: =IF(F73=0,"-",G73/F73) -> 0.98837209 | K73: 1 | AG73: {=SUMPRODUCT(--(M73:Q73="YES"))} -> 0 | AH73: =COUNTIF($AG$5:AG73, ">=3") -> 38
A74: 115 | B74: PAMANTASAN NG LUNGSOD NG MARIKINA | C74: 4 | D74: 291 | E74: 452 | F74: 0 | G74: 0 | H74: 7 | I74: =IF(D74=0,"-",E74/D74) -> 1.5532646 | J74: =IF(F74=0,"-",G74/F74) -> - | K74: 1 | L74: Facebook page was updated last June 15. When I called the phone number provided in the their webpage, the background noise was so loud that I could not hear anything from the service agent. | M74: Yes | N74: No | O74: Yes | P74: No | Q74: Yes | R74: https://plmar.edu.ph/ | AD74: 02 7369 7277 | AE74: plmarikina2003@yahoo.com.ph | AG74: {=SUMPRODUCT(--(M74:Q74="YES"))} -> 3 | AH74: =COUNTIF($AG$5:AG74, ">=3") -> 39
A75: 122 | B75: BLUERIDGE PACIFIC INSTITUTE, INC. | C75: 3 | D75: 270 | E75: 161 | F75: 0 | G75: 0 | H75: 6 | I75: =IF(D75=0,"-",E75/D75) -> 0.5962963 | J75: =IF(F75=0,"-",G75/F75) -> - | K75: 1 | AG75: {=SUMPRODUCT(--(M75:Q75="YES"))} -> 0 | AH75: =COUNTIF($AG$5:AG75, ">=3") -> 39
A76: 123 | B76: SACRED HEART TECHNICAL & VOCATIONAL ASSESSMENT CENTER INC. | C76: 4 | D76: 268 | E76: 417 | F76: 1174 | G76: 1173 | H76: 6 | I76: =IF(D76=0,"-",E76/D76) -> 1.5559701 | J76: =IF(F76=0,"-",G76/F76) -> 0.99914821 | K76: 1 | AG76: {=SUMPRODUCT(--(M76:Q76="YES"))} -> 0 | AH76: =COUNTIF($AG$5:AG76, ">=3") -> 39
A77: 124 | B77: PHILIPPINE CENTER FOR CREATIVE IMAGING, INC. | C77: 4 | D77: 267 | E77: 215 | F77: 160 | G77: 143 | H77: 5 | I77: =IF(D77=0,"-",E77/D77) -> 0.80524345 | J77: =IF(F77=0,"-",G77/F77) -> 0.89375 | K77: 1 | AG77: {=SUMPRODUCT(--(M77:Q77="YES"))} -> 0 | AH77: =COUNTIF($AG$5:AG77, ">=3") -> 39
A78: 127 | B78: GLOBAL CULINARY & HOSPITALITY ACADEMY, INC. | C78: 3 | D78: 253 | E78: 215 | F78: 0 | G78: 0 | H78: 6 | I78: =IF(D78=0,"-",E78/D78) -> 0.84980237 | J78: =IF(F78=0,"-",G78/F78) -> - | K78: 1 | AG78: {=SUMPRODUCT(--(M78:Q78="YES"))} -> 0 | AH78: =COUNTIF($AG$5:AG78, ">=3") -> 39
A79: 126 | B79: ST. PETER VELLE TECHNICAL TRAINING CENTER, INC. | C79: 17 | D79: 253 | E79: 223 | F79: 5730 | G79: 5675 | H79: 5 | I79: =IF(D79=0,"-",E79/D79) -> 0.88142292 | J79: =IF(F79=0,"-",G79/F79) -> 0.9904014 | K79: 1 | AG79: {=SUMPRODUCT(--(M79:Q79="YES"))} -> 0 | AH79: =COUNTIF($AG$5:AG79, ">=3") -> 39
A80: 142 | B80: GLOBAL CENTER OF EDUCATION MANAGEMENT SCIENCE AND TECHNOLOGY CORP. | C80: 6 | D80: 230 | E80: 180 | F80: 273 | G80: 272 | H80: 6 | I80: =IF(D80=0,"-",E80/D80) -> 0.7826087 | J80: =IF(F80=0,"-",G80/F80) -> 0.996337 | K80: 1 | AG80: {=SUMPRODUCT(--(M80:Q80="YES"))} -> 0 | AH80: =COUNTIF($AG$5:AG80, ">=3") -> 39
A81: 145 | B81: Asia Source College of Arts and Technology, Inc. | C81: 4 | D81: 228 | E81: 255 | F81: 0 | G81: 0 | H81: 5 | I81: =IF(D81=0,"-",E81/D81) -> 1.1184211 | J81: =IF(F81=0,"-",G81/F81) -> - | K81: 1 | AG81: {=SUMPRODUCT(--(M81:Q81="YES"))} -> 0 | AH81: =COUNTIF($AG$5:AG81, ">=3") -> 39
A82: 153 | B82: ST. LOUISE DE MARILLAC INTERNATIONAL FOUNDATION, INC. | C82: 6 | D82: 215 | E82: 213 | F82: 762 | G82: 762 | H82: 5 | I82: =IF(D82=0,"-",E82/D82) -> 0.99069767 | J82: =IF(F82=0,"-",G82/F82) -> 1 | K82: 1 | AG82: {=SUMPRODUCT(--(M82:Q82="YES"))} -> 0 | AH82: =COUNTIF($AG$5:AG82, ">=3") -> 39
A83: 164 | B83: Lakewood School of Alabang, Inc. | C83: 7 | D83: 202 | E83: 240 | F83: 0 | G83: 0 | H83: 9 | I83: =IF(D83=0,"-",E83/D83) -> 1.1881188 | J83: =IF(F83=0,"-",G83/F83) -> - | K83: 1 | L83: Facebook was last updated June 30. They actually had to transfer me. To register, we would have to go to Facebook of the training and assessment center of lakewood school of alabang. There would be a link that gives the registration link and they would give me a list of requirements. Aside of the list requirements, certificate of indigency (no need for medical. This is replacement of the medical). | M83: Yes | N83: Yes | O83: Yes | P83: Yes | Q83: No | S83: 2nd Priority | Y83: N/A | Z83: N/A | AA83: N/A | AB83: Online (Use registration link and complete requirements) | AD83: (02) 8550 2260 | AE83: lakewoodschoolofalabang@gmail.com | AG83: {=SUMPRODUCT(--(M83:Q83="YES"))} -> 4 | AH83: =COUNTIF($AG$5:AG83, ">=3") -> 40
A84: 173 | B84: Integrated Innovation and Hospitality Colleges, Inc. | C84: 3 | D84: 180 | E84: 328 | F84: 0 | G84: 0 | H84: 5 | I84: =IF(D84=0,"-",E84/D84) -> 1.8222222 | J84: =IF(F84=0,"-",G84/F84) -> - | K84: 1 | AG84: {=SUMPRODUCT(--(M84:Q84="YES"))} -> 0 | AH84: =COUNTIF($AG$5:AG84, ">=3") -> 40
A85: 175 | B85: Infotech Institute of Arts and Sciences, Inc. | C85: 5 | D85: 179 | E85: 182 | F85: 0 | G85: 0 | H85: 5 | I85: =IF(D85=0,"-",E85/D85) -> 1.0167598 | J85: =IF(F85=0,"-",G85/F85) -> - | K85: 1 | AG85: {=SUMPRODUCT(--(M85:Q85="YES"))} -> 0 | AH85: =COUNTIF($AG$5:AG85, ">=3") -> 40
A86: 178 | B86: DON BOSCO TECHNICAL COLLEGE, INC. | C86: 4 | D86: 177 | E86: 119 | F86: 0 | G86: 0 | H86: 5 | I86: =IF(D86=0,"-",E86/D86) -> 0.67231638 | J86: =IF(F86=0,"-",G86/F86) -> - | K86: 1 | L86: Already a partner, no need to review | AG86: {=SUMPRODUCT(--(M86:Q86="YES"))} -> 0 | AH86: =COUNTIF($AG$5:AG86, ">=3") -> 40
A87: 199 | B87: ASIAN CHRISTIAN THEOLOGICAL SCHOOL & COLLEGES INC. | C87: 5 | D87: 148 | E87: 156 | F87: 43 | G87: 43 | H87: 5 | I87: =IF(D87=0,"-",E87/D87) -> 1.0540541 | J87: =IF(F87=0,"-",G87/F87) -> 1 | K87: 1 | AG87: {=SUMPRODUCT(--(M87:Q87="YES"))} -> 0 | AH87: =COUNTIF($AG$5:AG87, ">=3") -> 40
A88: 213 | B88: Lyceum of ALabang | C88: 4 | D88: 128 | E88: 101 | F88: 0 | G88: 0 | H88: 6 | I88: =IF(D88=0,"-",E88/D88) -> 0.7890625 | J88: =IF(F88=0,"-",G88/F88) -> - | K88: 1 | AG88: {=SUMPRODUCT(--(M88:Q88="YES"))} -> 0 | AH88: =COUNTIF($AG$5:AG88, ">=3") -> 40
A89: 40 | B89: ST. MICHAEL CAREER FOCUSED ENHANCEMENT, INC. | C89: 2 | D89: 766 | E89: 445 | F89: 0 | G89: 0 | H89: 12 | I89: =IF(D89=0,"-",E89/D89) -> 0.58093995 | J89: =IF(F89=0,"-",G89/F89) -> - | AH89: =COUNTIF($AG$5:AG89, ">=3") -> 40
A90: 117 | B90: RASE TRAINING AND ASSESSMENT CENTER INC. | C90: 4 | D90: 287 | E90: 0 | F90: 0 | G90: 0 | H90: 9 | I90: =IF(D90=0,"-",E90/D90) -> 0 | J90: =IF(F90=0,"-",G90/F90) -> - | AH90: =COUNTIF($AG$5:AG90, ">=3") -> 40
A91: 18 | B91: SOUTHERN INSTITUTE OF MARITIME STUDIES-MANILA INC. | C91: 2 | D91: 1200 | E91: 1169 | F91: 0 | G91: 0 | H91: 8 | I91: =IF(D91=0,"-",E91/D91) -> 0.97416667 | J91: =IF(F91=0,"-",G91/F91) -> - | AH91: =COUNTIF($AG$5:AG91, ">=3") -> 40
A92: 33 | B92: MYCHEST SKILLS INSTITUTE CORP. | C92: 2 | D92: 858 | E92: 782 | F92: 0 | G92: 0 | H92: 7 | I92: =IF(D92=0,"-",E92/D92) -> 0.91142191 | J92: =IF(F92=0,"-",G92/F92) -> - | AH92: =COUNTIF($AG$5:AG92, ">=3") -> 40
A93: 64 | B93: CENTER FOR INTERNATIONAL INDUSTRIES COMPETENCE CORP. | C93: 2 | D93: 507 | E93: 757 | F93: 0 | G93: 0 | H93: 7 | I93: =IF(D93=0,"-",E93/D93) -> 1.4930966 | J93: =IF(F93=0,"-",G93/F93) -> - | AH93: =COUNTIF($AG$5:AG93, ">=3") -> 40
A94: 128 | B94: CARENET HEALTHCARE INSTITUTE, INC. | C94: 2 | D94: 252 | E94: 173 | F94: 0 | G94: 0 | H94: 7 | I94: =IF(D94=0,"-",E94/D94) -> 0.68650794 | J94: =IF(F94=0,"-",G94/F94) -> - | AH94: =COUNTIF($AG$5:AG94, ">=3") -> 40
A95: 15 | B95: HYPER YOUNG INSTITUTE OF TECHNOLOGY INC. | C95: 1 | D95: 1256 | E95: 1238 | F95: 969 | G95: 908 | H95: 6 | I95: =IF(D95=0,"-",E95/D95) -> 0.98566879 | J95: =IF(F95=0,"-",G95/F95) -> 0.9370485 | AH95: =COUNTIF($AG$5:AG95, ">=3") -> 40
A96: 20 | B96: TRIPLE K'S EAST CAPITOL KITCHEN CORP. DOING BUSINESS UNDER THE NAME AND STYLE OF SPICES AND HERBS TR | C96: 2 | D96: 1149 | E96: 1298 | F96: 1108 | G96: 1100 | H96: 6 | I96: =IF(D96=0,"-",E96/D96) -> 1.129678 | J96: =IF(F96=0,"-",G96/F96) -> 0.99277978 | AH96: =COUNTIF($AG$5:AG96, ">=3") -> 40
A97: 24 | B97: A1VENTURES TECHNICAL AND VOCATIONAL ACADEMY INC. | C97: 2 | D97: 1021 | E97: 913 | F97: 0 | G97: 0 | H97: 6 | I97: =IF(D97=0,"-",E97/D97) -> 0.89422135 | J97: =IF(F97=0,"-",G97/F97) -> - | AH97: =COUNTIF($AG$5:AG97, ">=3") -> 40
A98: 47 | B98: MINDBANK TRAINING & SKILLS CORPORATION | C98: 2 | D98: 727 | E98: 685 | F98: 0 | G98: 0 | H98: 6 | I98: =IF(D98=0,"-",E98/D98) -> 0.94222834 | J98: =IF(F98=0,"-",G98/F98) -> - | AH98: =COUNTIF($AG$5:AG98, ">=3") -> 40
A99: 60 | B99: CABALEN TRAINING INSTITUTE CORP. | C99: 2 | D99: 528 | E99: 477 | F99: 456 | G99: 455 | H99: 6 | I99: =IF(D99=0,"-",E99/D99) -> 0.90340909 | J99: =IF(F99=0,"-",G99/F99) -> 0.99780702 | AH99: =COUNTIF($AG$5:AG99, ">=3") -> 40
A100: 65 | B100: MARANATHA TECHNOLOGICAL INSTITUTE AND TRAINING CENTER CORPORATION | C100: 2 | D100: 503 | E100: 460 | F100: 0 | G100: 0 | H100: 6 | I100: =IF(D100=0,"-",E100/D100) -> 0.91451292 | J100: =IF(F100=0,"-",G100/F100) -> - | AH100: =COUNTIF($AG$5:AG100, ">=3") -> 40
... A187: 230 | B187: WORLD CITI, INC. DOING BUSINESS UNDER THE NAME AND STYLE OF WORLD CITI COLLEGES AND WORLD CITI MEDIC | C187: 2 | D187: 113 | E187: 168 | F187: 0 | G187: 0 | H187: 3 | I187: =IF(D187=0,"-",E187/D187) -> 1.4867257 | J187: =IF(F187=0,"-",G187/F187) -> - | AH187: =COUNTIF($AG$5:AG187, ">=3") -> 40
...

Sheet Top Centers - 4A
A1: Top TVET Centres: 4A | C1: Filter
A2: Top TVET Centers for 4A
A3: 543 institutions. Ranked by training Enrolled. Rates shown as formulas (recompute live). | C3: =>3 Quals | E3: =>100 graduates | H3: =>5 trainers
A5: Rank | B5: Institution | C5: Quals | D5: Enrolled | E5: Graduates | F5: Assessed | G5: Certified | H5: Trainers | I5: Grad Rate | J5: Cert Rate | K5: 1 | L5: Primary Research Notes (JF Inputs) | M5: Updated FB in the Past Year | N5: Congratulate their Graduates of the Current Year? | O5: Updated Google Maps | P5: Responded to Student Inquiry? | Q5: Website? | R5: Website Link | S5: Decision | T5: 2 | U5: When is next course starting | V5: How much is it? | W5: Can I get scholarship? | X5: How do I apply? | Y5: 3 | Z5: Phone number contact | AA5: Email Contact | AB5: 4 | AC5: Number of Yes | AD5: Number of Institutions that have At Least 3 Yes
A6: 451 | B6: JACOBO Z. GONZALES MEMORIAL SCHOOL OF ARTS AND TRADES | C6: 38 | D6: 0 | E6: 0 | F6: 5399 | G6: 5191 | H6: 0 | I6: =IF(D6=0,"-",E6/D6) -> - | J6: =IF(F6=0,"-",G6/F6) -> 0.96147435 | K6: 1
A7: 463 | B7: REGIONAL TRAINING CENTER-CALABARZON | C7: 30 | D7: 0 | E7: 0 | F7: 3190 | G7: 2723 | H7: 0 | I7: =IF(D7=0,"-",E7/D7) -> - | J7: =IF(F7=0,"-",G7/F7) -> 0.85360502 | K7: 1 | AG7: =COUNTIF(P7:P21, "YES") -> 5
A8: 462 | B8: QUEZON NATIONAL AGRICULTURAL SCHOOL | C8: 20 | D8: 0 | E8: 0 | F8: 2670 | G8: 2703 | H8: 0 | I8: =IF(D8=0,"-",E8/D8) -> - | J8: =IF(F8=0,"-",G8/F8) -> 1.0123596 | K8: 1
A9: 3 | B9: ADAO LEARNING INSTITUTE INC. | C9: 5 | D9: 2146 | E9: 1945 | F9: 1403 | G9: 1363 | H9: 24 | I9: =IF(D9=0,"-",E9/D9) -> 0.90633737 | J9: =IF(F9=0,"-",G9/F9) -> 0.97148967 | L9: Scholarship available is Carpenter available on July 20 and 30. NCs for assessment can vary, but training is all scholarship provided. | M9: Yes | N9: Yes | O9: Yes | P9: Yes | Q9: No | S9: 2nd Priority | T9: 2 | U9: July 20 and 30 | V9: N/A | W9: Yes | X9: N/A | Z9: 0916 397 7290 | AA9: adaolearninginstituteinc@gmail.com | AC9: {=SUMPRODUCT(--(M9:Q9="YES"))} -> 4 | AD9: =COUNTIF($AC$7:AC9, ">=3") -> 1
A10: 2 | B10: THE BIG FIVE TRAINING AND ASSESSMENT CENTER INC. | C10: 5 | D10: 2170 | E10: 1695 | F10: 1548 | G10: 1733 | H10: 14 | I10: =IF(D10=0,"-",E10/D10) -> 0.78110599 | J10: =IF(F10=0,"-",G10/F10) -> 1.119509 | L10: As of right now, there is no scholarship given by TESDA, but there is regular training (with a training fee of Php 10_000). To enroll, we need to go to the office physically. To be able to start, they need to be fully booked, so as of right now, we just need to wait. Facebook was updated last June 30. | M10: Yes | N10: Yes | O10: Yes | P10: Yes | Q10: No | S10: 2nd Priority | T10: 2 | U10: None (Waiting for full batch) | V10: Php 10,000 (Regular training) | W10: No (No TESDA scholarship currently) | X10: Onsite (Waitlist until class is full) | Z10: 0908 655 2653 | AA10: thebigfivetraining2018@gmail.com | AC10: {=SUMPRODUCT(--(M10:Q10="YES"))} -> 4 | AD10: =COUNTIF($AC$7:AC10, ">=3") -> 2
A11: 11 | B11: Colegio de Santo Cristo De Burgos Corporation | C11: 5 | D11: 1107 | E11: 1187 | F11: 0 | G11: 0 | H11: 11 | I11: =IF(D11=0,"-",E11/D11) -> 1.0722674 | J11: =IF(F11=0,"-",G11/F11) -> - | L11: Facebook page was updated last June 23. | M11: Yes | N11: Yes | O11: Yes | P11: No | Q11: Yes | R11: https://cdscdb.edu.ph/ | S11: Yes | T11: 2 | Z11: 0917 538 1515 | AA11: colegiodesantocristodeburgos@gmail.com | AC11: {=SUMPRODUCT(--(M11:Q11="YES"))} -> 4 | AD11: =COUNTIF($AC$7:AC11, ">=3") -> 3
A12: 411 | B12: LYCEUM OF THE PHILIPPINES UNIVERSITY - BATANGAS, INC. | C12: 14 | D12: 0 | E12: 0 | F12: 2650 | G12: 2626 | H12: 0 | I12: =IF(D12=0,"-",E12/D12) -> - | J12: =IF(F12=0,"-",G12/F12) -> 0.9909434 | K12: 1
A13: 524 | B13: CSTC COLLEGE OF SCIENCES, TECHNOLOGY AND COMMUNICATIONS, INC. | C13: 14 | D13: 0 | E13: 0 | F13: 2709 | G13: 2694 | H13: 0 | I13: =IF(D13=0,"-",E13/D13) -> - | J13: =IF(F13=0,"-",G13/F13) -> 0.9944629 | K13: 1
A14: 16 | B14: RENAISSANCE SCHOOL OF SCIENCE AND TECHNOLOGY INC | C14: 11 | D14: 842 | E14: 1182 | F14: 0 | G14: 0 | H14: 17 | I14: =IF(D14=0,"-",E14/D14) -> 1.4038005 | J14: =IF(F14=0,"-",G14/F14) -> - | L14: Facebook page was updated last July 1. The phone number does not work. | M14: Yes | N14: Yes | O14: Yes | P14: No | Q14: Yes | R14: https://learnatrsst.org/home.php | S14: 2nd Priority | T14: 2 | Z14: 0919 084 0826 | AA14: renaissance.oic@gmail.com | AC14: {=SUMPRODUCT(--(M14:Q14="YES"))} -> 4 | AD14: =COUNTIF($AC$7:AC14, ">=3") -> 4
A15: 402 | B15: UNIVERSITY OF BATANGAS, INC. | C15: 12 | D15: 0 | E15: 0 | F15: 561 | G15: 560 | H15: 0 | I15: =IF(D15=0,"-",E15/D15) -> - | J15: =IF(F15=0,"-",G15/F15) -> 0.99821747 | K15: 1
A16: 7 | B16: AUTOZONE DRIVING SCHOOLINC. | C16: 5 | D16: 1237 | E16: 1141 | F16: 0 | G16: 0 | H16: 10 | I16: =IF(D16=0,"-",E16/D16) -> 0.92239289 | J16: =IF(F16=0,"-",G16/F16) -> - | L16: The Facebook page was last updated on July 2, 2026. The institution also has a webpage; however, upon accessing it, it was flagged as not secure. It should be noted that there are two versions of the site, “Autozone” and “Autozone TESDA,” but the latter appears to be outdated. For the Pedro branch, there are currently no available scholarship slots. However, SMAW NC I training remains open in this branch. To apply or inquire, applicants are advised to search for “Autozone TESDA” and coordinate through their official channels. For Driving NC II, the institution is currently accepting applicants for a waitlist. They require applicants to indicate whether they already have a student permit or driver’s license. According to the staff, there is already a long lineup with multiple batches scheduled. Under the scholarship program, training is free. For private enrollment, the cost is Php 5,500 per trainee, with an additional Php 1,034 for assessment. To apply for the scholarship, applicants must visit the site in person and bring a valid license and a 1×1 photo. Additional requirements will be requested once the training schedule is confirmed. For private training, a minimum of ten students is required to open a class. | M16: Yes | N16: No | O16: Yes | P16: Yes | Q16: Yes | R16: https://autozone.driving.com.ph/ | S16: No | T16: 2 | U16: None (Waiting for full batch) | V16: Php 5,500 + Php 1,034 assessment (Regular Training) | W16: Limited (No slots for Pedro branch; free if available) | X16: Onsite (Walk-in; waitlist for Driving NC II) | Z16: 028 400 2430 | AA16: autozone.trainingcenter@gmail.com | AC16: {=SUMPRODUCT(--(M16:Q16="YES"))} -> 4 | AD16: =COUNTIF($AC$7:AC16, ">=3") -> 5
A17: 6 | B17: Computer Site Ins. Inc. | C17: 3 | D17: 1321 | E17: 1112 | F17: 0 | G17: 0 | H17: 13 | I17: =IF(D17=0,"-",E17/D17) -> 0.84178653 | J17: =IF(F17=0,"-",G17/F17) -> - | L17: No TESDA scholarship as of right now. You cannot pay for a TESDA course either. It really has to be through TESDA scholarship. If you want to be apply to pay, you would have to go through the two-year courses. To apply, you have to drop-by and fill up to the location. Facebook was last updated July 3. | M17: Yes | N17: No | O17: Yes | P17: Yes | Q17: Yes | R17: https://baldestamon2004.neocities.org/ | S17: No | T17: 2 | U17: None (Pending TESDA funding) | V17: N/A (TESDA only; paid via 2-year courses) | W17: No (No TESDA scholarship currently) | X17: Onsite (Walk-in application) | Z17: 0942 422 0165 | AA17: comsite19882000@yahoo.com | AC17: {=SUMPRODUCT(--(M17:Q17="YES"))} -> 4 | AD17: =COUNTIF($AC$7:AC17, ">=3") -> 6
A18: 209 | B18: C HEO TRAINING AND ASSESSMENT CENTER, INC. | C18: 11 | D18: 82 | E18: 53 | F18: 1306 | G18: 1064 | H18: 2 | I18: =IF(D18=0,"-",E18/D18) -> 0.64634146 | J18: =IF(F18=0,"-",G18/F18) -> 0.81470138 | K18: 1
A19: 15 | B19: LUCENA TECHNOLOGICAL INSTITUTE INCORPORATED | C19: 3 | D19: 848 | E19: 1102 | F19: 805 | G19: 788 | H19: 24 | I19: =IF(D19=0,"-",E19/D19) -> 1.2995283 | J19: =IF(F19=0,"-",G19/F19) -> 0.97888199 | L19: They do not have any budget yet, so no TESDA offered courses. Once they have a budget, they call those who registered. To register, you just have to message the page. For the phone number, it's not readily available in the Facebook page. You would have to go to the TESDA page. | M19: Yes | N19: Yes | O19: Yes | P19: Yes | Q19: No | S19: 2nd Priority | T19: 2 | U19: None (Pending TESDA funding) | V19: None (Pending TESDA funding) | W19: Yes | X19: Online (Facebook Message) | Z19: (042) 784 2334 | AA19: LucenaTech@gmail.com | AC19: {=SUMPRODUCT(--(M19:Q19="YES"))} -> 4 | AD19: =COUNTIF($AC$7:AC19, ">=3") -> 7
A20: 348 | B20: ACETAC INSTITUTE OF TECHNOLOGY INC. | C20: 10 | D20: 23 | E20: 30 | F20: 2412 | G20: 2689 | H20: 1 | I20: =IF(D20=0,"-",E20/D20) -> 1.3043478 | J20: =IF(F20=0,"-",G20/F20) -> 1.1148425 | K20: 1
A21: 416 | B21: PROVINCIAL TECHNICAL EDUCATION AND SKILLS DEVELOPMENT CENTER (PTESDC) - TAYTAY | C21: 10 | D21: 0 | E21: 0 | F21: 1055 | G21: 907 | H21: 0 | I21: =IF(D21=0,"-",E21/D21) -> - | J21: =IF(F21=0,"-",G21/F21) -> 0.85971564 | K21: 1
A22: 456 | B22: RENAISSANCE SCHOOL OF SCIENCE AND TECHNOLOGY INC. | C22: 10 | D22: 0 | E22: 0 | F22: 2588 | G22: 2486 | H22: 0 | I22: =IF(D22=0,"-",E22/D22) -> - | J22: =IF(F22=0,"-",G22/F22) -> 0.96058733 | K22: 1
A23: 458 | B23: RIZAL PROVINCIAL TECHNICAL EDUCATION AND SKILLS DEVELOPMENT CENTER - CAINTA | C23: 10 | D23: 0 | E23: 0 | F23: 810 | G23: 686 | H23: 0 | I23: =IF(D23=0,"-",E23/D23) -> - | J23: =IF(F23=0,"-",G23/F23) -> 0.84691358 | K23: 1
A24: 525 | B24: SISTERS OF MARY TECHNICAL EDUCATION INSTITUTE CAVITE, INC. - BOYSTOWN | C24: 10 | D24: 0 | E24: 0 | F24: 454 | G24: 442 | H24: 0 | I24: =IF(D24=0,"-",E24/D24) -> - | J24: =IF(F24=0,"-",G24/F24) -> 0.97356828 | K24: 1
A25: 535 | B25: BANAHAW TECHNOLOGICAL COLLEGE, INC. | C25: 10 | D25: 0 | E25: 0 | F25: 1985 | G25: 1907 | H25: 0 | I25: =IF(D25=0,"-",E25/D25) -> - | J25: =IF(F25=0,"-",G25/F25) -> 0.96070529 | K25: 1
A26: 9 | B26: DIVINE MERCY INTERNATIONAL INSTITUTE INC. | C26: 5 | D26: 1167 | E26: 1099 | F26: 0 | G26: 0 | H26: 18 | I26: =IF(D26=0,"-",E26/D26) -> 0.94173093 | J26: =IF(F26=0,"-",G26/F26) -> - | L26: The number provided in the TESDA Webpage was apparently incorrect. I will still include it for completeness, but they don't even provide an email. The Facebook page was updated last July 1. | M26: Yes | N26: Yes | O26: Yes | P26: No | Q26: No | S26: 2nd Priority | T26: 2 | Z26: (046) 512 3522 | AC26: {=SUMPRODUCT(--(M26:Q26="YES"))} -> 3 | AD26: =COUNTIF($AC$7:AC26, ">=3") -> 8
A27: 12 | B27: SYNERGY ASSESSMENT & TRAINING CENTER | C27: 4 | D27: 971 | E27: 1034 | F27: 0 | G27: 0 | H27: 15 | I27: =IF(D27=0,"-",E27/D27) -> 1.0648816 | J27: =IF(F27=0,"-",G27/F27) -> - | L27: The number provided in the TESDA Webpage was apparently incorrect. They currently have welding courses, lahat may scholarship. They only have scholarship. Umaabot pa ng 13K. To apply, get a registration form in the onsite office of the national ID, birth certificate, and the such. Once they applied and once the instituion gets the funding from TESDA for the scholarships, they will just call the scholars. | M27: Yes | N27: Yes | O27: Yes | P27: Yes | Q27: No | S27: 3rd Priority | T27: 2 | U27: None (Pending TESDA funding) | V27: Free (Scholarship), Php 13,000 (Regular) | W27: Yes | X27: Onsite (Waitlist until class is full) | Z27: 043 756 2564 | AA27: synergyassessment_trainingcenter@yahoo.com | AC27: {=SUMPRODUCT(--(M27:Q27="YES"))} -> 4 | AD27: =COUNTIF($AC$7:AC27, ">=3") -> 9
A28: 25 | B28: Regional Training Center - CALABARZON | C28: 18 | D28: 715 | E28: 871 | F28: 0 | G28: 0 | H28: 22 | I28: =IF(D28=0,"-",E28/D28) -> 1.2181818 | J28: =IF(F28=0,"-",G28/F28) -> - | L28: They are very active in their Facebook page, where they last uploaded July 3. They also have a very pretty website, which was the first result. 0917 124 6624 | M28: Yes | N28: Yes | O28: Yes | P28: Yes | Q28: Yes | R28: https://tesdartccalabarzon.com/ | S28: Yes | T28: 2 | U28: N/A | V28: N/A | W28: N/A | X28: N/A | Z28: (043) 781 9379 | AA28: rtcbatangas@tesda.gov.ph | AC28: {=SUMPRODUCT(--(M28:Q28="YES"))} -> 5 | AD28: =COUNTIF($AC$7:AC28, ">=3") -> 10
A29: 17 | B29: SP CASTRO CONSTRUCTION SERVICES | C29: 4 | D29: 825 | E29: 773 | F29: 0 | G29: 0 | H29: 9 | I29: =IF(D29=0,"-",E29/D29) -> 0.9369697 | J29: =IF(F29=0,"-",G29/F29) -> - | L29: This specializes as a construction company, so when you search it up, it shows their offices in Pasig, not the school in Quezon. The Facebook for the school was updated last May 9, 2024. The phone number does not work. | M29: No | N29: No | O29: No | P29: No | Q29: Yes | R29: https://www.spcastro.com/ | S29: 2nd Priority | T29: 2 | AC29: {=SUMPRODUCT(--(M29:Q29="YES"))} -> 1 | AD29: =COUNTIF($AC$7:AC29, ">=3") -> 10
A30: 13 | B30: ST. MARK SKILLS TRAINING INSTITUTE INC. | C30: 7 | D30: 940 | E30: 768 | F30: 986 | G30: 982 | H30: 13 | I30: =IF(D30=0,"-",E30/D30) -> 0.81702128 | J30: =IF(F30=0,"-",G30/F30) -> 0.9959432 | L30: Facebook was updated last July 3. | M30: Yes | N30: Yes | O30: Yes | P30: No | Q30: No | T30: 2 | Z30: 0948 051 1340 | AA30: st.mark.institute2022@gmail.com | AC30: {=SUMPRODUCT(--(M30:Q30="YES"))} -> 3 | AD30: =COUNTIF($AC$7:AC30, ">=3") -> 11
A31: 19 | B31: EXCELSIOR CENTER FOR EXCELLENCE INC. | C31: 3 | D31: 765 | E31: 766 | F31: 0 | G31: 0 | H31: 13 | I31: =IF(D31=0,"-",E31/D31) -> 1.0013072 | J31: =IF(F31=0,"-",G31/F31) -> - | L31: Facebook page is just a group chat. It is filled with questions if a TESDA course is now available. The latest question was from June 27. Even though the Facebook is technically updated, I don't trust it. The phone number provided in the TESDA Webpage does not work. | M31: No | N31: No | O31: Yes | P31: No | Q31: No | T31: 2 | AC31: {=SUMPRODUCT(--(M31:Q31="YES"))} -> 1 | AD31: =COUNTIF($AC$7:AC31, ">=3") -> 11
A32: 395 | B32: LYCEUM OF THE PHILIPPINES UNIVERSITY, INC. - CAVITE | C32: 9 | D32: 0 | E32: 0 | F32: 391 | G32: 391 | H32: 0 | I32: =IF(D32=0,"-",E32/D32) -> - | J32: =IF(F32=0,"-",G32/F32) -> 1
A33: 428 | B33: TESDA PROVINCIAL TRAINING CENTER - ROSARIO | C33: 9 | D33: 0 | E33: 0 | F33: 1415 | G33: 1335 | H33: 0 | I33: =IF(D33=0,"-",E33/D33) -> - | J33: =IF(F33=0,"-",G33/F33) -> 0.9434629
A34: 513 | B34: COLEGIO DE SANTO CRISTO DE BURGOS CORPORATION | C34: 9 | D34: 0 | E34: 0 | F34: 1702 | G34: 1647 | H34: 0 | I34: =IF(D34=0,"-",E34/D34) -> - | J34: =IF(F34=0,"-",G34/F34) -> 0.96768508
A35: 31 | B35: KAMELO MANPOWER SKILLS DEVELOPMENT CENTER INC. | C35: 4 | D35: 595 | E35: 737 | F35: 0 | G35: 0 | H35: 11 | I35: =IF(D35=0,"-",E35/D35) -> 1.2386555 | J35: =IF(F35=0,"-",G35/F35) -> - | L35: The Facebook page does not readily provide the institution’s contact details, such as the phone number and email. These had to be located within the posts. The page was last updated on July 6. https://www.facebook.com/photo?fbid=2250178522472942&set=a.210535573103924 At present, there are no available scholarships. For paid training, applicants must wait for the availability of a trainer. The fee for SMAW NC I is Php 35,000. To apply, applicants are required to proceed onsite and coordinate directly with the institution for further instructions. | M35: Yes | N35: Yes | O35: Yes | P35: Yes | Q35: No | S35: 3rd Priority | T35: 2 | U35: None (Waiting for trainer availability) | V35: Php 35,000 (SMAW NC I) | W35: No (No scholarship currently) | X35: Onsite (Walk-in application) | Z35: 0946 502 9079 | AA35: kamelo.batangas@gmail.com | AC35: {=SUMPRODUCT(--(M35:Q35="YES"))} -> 4 | AD35: =COUNTIF($AC$7:AC35, ">=3") -> 12
A36: 26 | B36: RUBIKS MANPOWER TRAINING CENTER INC. | C36: 5 | D36: 711 | E36: 716 | F36: 1168 | G36: 1141 | H36: 12 | I36: =IF(D36=0,"-",E36/D36) -> 1.0070323 | J36: =IF(F36=0,"-",G36/F36) -> 0.97688356 | L36: Facebook page was updated last July 3, 2014. | M36: No | N36: No | O36: Yes | P36: No | Q36: No | T36: 2 | AC36: {=SUMPRODUCT(--(M36:Q36="YES"))} -> 1 | AD36: =COUNTIF($AC$7:AC36, ">=3") -> 12
A37: 32 | B37: Skillful Training and Assessment Center Inc. | C37: 3 | D37: 594 | E37: 715 | F37: 0 | G37: 0 | H37: 7 | I37: =IF(D37=0,"-",E37/D37) -> 1.2037037 | J37: =IF(F37=0,"-",G37/F37) -> - | T37: 2 | AC37: {=SUMPRODUCT(--(M37:Q37="YES"))} -> 0 | AD37: =COUNTIF($AC$7:AC37, ">=3") -> 12
A38: 400 | B38: TOYOTA MOTOR PHILIPPINES SCHOOL OF TECHNOLOGY, INC. | C38: 8 | D38: 0 | E38: 0 | F38: 2876 | G38: 2871 | H38: 0 | I38: =IF(D38=0,"-",E38/D38) -> - | J38: =IF(F38=0,"-",G38/F38) -> 0.99826147
A39: 422 | B39: OLIVAREZ COLLEGE - TAGAYTAY, INC. | C39: 8 | D39: 0 | E39: 0 | F39: 1253 | G39: 1130 | H39: 0 | I39: =IF(D39=0,"-",E39/D39) -> - | J39: =IF(F39=0,"-",G39/F39) -> 0.90183559
A40: 436 | B40: TESDA PROVINCIAL TRAINING CENTER - PALIPARAN | C40: 8 | D40: 0 | E40: 0 | F40: 802 | G40: 794 | H40: 0 | I40: =IF(D40=0,"-",E40/D40) -> - | J40: =IF(F40=0,"-",G40/F40) -> 0.99002494
A41: 22 | B41: GOALS TRAINING AND ASSESSMENT INSTITUTE INC. | C41: 5 | D41: 741 | E41: 681 | F41: 0 | G41: 0 | H41: 11 | I41: =IF(D41=0,"-",E41/D41) -> 0.91902834 | J41: =IF(F41=0,"-",G41/F41) -> - | L41: There are two Facebook pages for the same institution. I used the phone number of the Facebook page that had the latest post, which was on November 2025. | M41: No | N41: No | O41: Yes | P41: No | Q41: No | T41: 2 | Z41: 0917 701 8481 | AA41: goalsinstitute2017@gmail.com | AC41: {=SUMPRODUCT(--(M41:Q41="YES"))} -> 1 | AD41: =COUNTIF($AC$7:AC41, ">=3") -> 12
A42: 18 | B42: LEMERY COLLEGES, INC. | C42: 4 | D42: 770 | E42: 673 | F42: 0 | G42: 0 | H42: 7 | I42: =IF(D42=0,"-",E42/D42) -> 0.87402597 | J42: =IF(F42=0,"-",G42/F42) -> - | T42: 2 | AC42: {=SUMPRODUCT(--(M42:Q42="YES"))} -> 0 | AD42: =COUNTIF($AC$7:AC42, ">=3") -> 12
A43: 27 | B43: PR1ME INSTITUTE FOR SKILLS DEVELOPMENT AND ASSESSMENT CENTER, INC. | C43: 5 | D43: 705 | E43: 638 | F43: 833 | G43: 821 | H43: 14 | I43: =IF(D43=0,"-",E43/D43) -> 0.90496454 | J43: =IF(F43=0,"-",G43/F43) -> 0.98559424 | L43: Facebook page was updated last May 26. The phone number provided does not work. | M43: Yes | N43: Yes | O43: Yes | P43: No | Q43: No | T43: 2 | Z43: 0951 957 4236 | AA43: pr1metrainingcenter.inc@gmail.com | AC43: {=SUMPRODUCT(--(M43:Q43="YES"))} -> 3 | AD43: =COUNTIF($AC$7:AC43, ">=3") -> 13
A44: 39 | B44: COLLEGE OF SAN BENILDO-RIZAL FOUNDATION, INC. | C44: 10 | D44: 498 | E44: 623 | F44: 0 | G44: 0 | H44: 14 | I44: =IF(D44=0,"-",E44/D44) -> 1.251004 | J44: =IF(F44=0,"-",G44/F44) -> - | L44: You would have to wait a while where there are enough students to hold a class so that it actually makes financial sense to hold classes. To apply, it has to be walk-in. There is no online registration. | M44: Yes | N44: Yes | O44: Yes | P44: Yes | Q44: Yes | R44: https://www.sanbenildo.edu.ph/tesda | S44: 2nd Priority | T44: 2 | U44: None (Waiting for full batch) | V44: N/A | W44: N/A | X44: Onsite (Walk-in application) | Z44: 0930 127 1906 | AA44: trainingcenter@sanbenildo.edu.ph | AC44: {=SUMPRODUCT(--(M44:Q44="YES"))} -> 5 | AD44: =COUNTIF($AC$7:AC44, ">=3") -> 14
A45: 35 | B45: TESDA-LLDA PROVINCIAL TRAINING CENTER | C45: 15 | D45: 531 | E45: 587 | F45: 2220 | G45: 2145 | H45: 13 | I45: =IF(D45=0,"-",E45/D45) -> 1.1054614 | J45: =IF(F45=0,"-",G45/F45) -> 0.96621622 | L45: The landline number in the TESDA webpage was actually a landline for some person's house. I did not want to call any of the other phone numbers given. Also, the latest post from TESDA was from April 23, 2021. | M45: No | N45: No | O45: Yes | P45: No | Q45: No | T45: 2 | AC45: {=SUMPRODUCT(--(M45:Q45="YES"))} -> 1 | AD45: =COUNTIF($AC$7:AC45, ">=3") -> 14
A46: 30 | B46: LORD YAHWEH BUSINESS COLLEGES AND MARITIME ACADEMY INCORPORATED | C46: 4 | D46: 628 | E46: 584 | F46: 0 | G46: 0 | H46: 11 | I46: =IF(D46=0,"-",E46/D46) -> 0.92993631 | J46: =IF(F46=0,"-",G46/F46) -> - | L46: The Facebook page was last updated on June 26. The program is offered strictly under a scholarship basis, with no option for paid enrollment. Interested applicants are advised to visit the Facebook page and follow the instructions to be added to the group chat for further details. Please note that the phone number listed on the Facebook page is not functional. Only the contact number provided within the posts should be used for inquiries. | M46: Yes | N46: Yes | O46: Yes | P46: Yes | Q46: No | S46: 2nd Priority | T46: 2 | U46: None (Pending TESDA funding) | V46: Free (Scholarship only) | W46: Yes (No paid option) | X46: Online (FB page and then go to group chat instructions) | Z46: (049) 545 0165 | AA46: lordyahwehmaritime@gmail.com | AC46: {=SUMPRODUCT(--(M46:Q46="YES"))} -> 4 | AD46: =COUNTIF($AC$7:AC46, ">=3") -> 15
A47: 388 | B47: BWEST COLLEGE (BOATER'S WHEEL EDUCATIONAL SYSTEM AND TECHNOLOGY) INC. | C47: 7 | D47: 0 | E47: 0 | F47: 1706 | G47: 1569 | H47: 0 | I47: =IF(D47=0,"-",E47/D47) -> - | J47: =IF(F47=0,"-",G47/F47) -> 0.91969519
A48: 477 | B48: ETHOMAX GOOD SERVANT MULTI-PURPOSE COOPERATIVE (EGOS - MPC) | C48: 7 | D48: 0 | E48: 0 | F48: 414 | G48: 403 | H48: 0 | I48: =IF(D48=0,"-",E48/D48) -> - | J48: =IF(F48=0,"-",G48/F48) -> 0.97342995
A49: 38 | B49: EQUINOX TRAINING CENTER INC. | C49: 5 | D49: 505 | E49: 560 | F49: 155 | G49: 156 | H49: 7 | I49: =IF(D49=0,"-",E49/D49) -> 1.1089109 | J49: =IF(F49=0,"-",G49/F49) -> 1.0064516 | T49: 2 | AC49: {=SUMPRODUCT(--(M49:Q49="YES"))} -> 0 | AD49: =COUNTIF($AC$7:AC49, ">=3") -> 15
A50: 20 | B50: LAGUNA COLLEGE OF ARTS AND TECHNOLOGY INC. | C50: 8 | D50: 757 | E50: 551 | F50: 945 | G50: 923 | H50: 11 | I50: =IF(D50=0,"-",E50/D50) -> 0.72787318 | J50: =IF(F50=0,"-",G50/F50) -> 0.97671958 | L50: Facebook page was updated last July 6. There is scholarships for Food and Beverages NC I and II (but they prioritize those who had already regitered beforehand). For regular training, it is Php 16 000 for house and training pero wala po na may gusto ngayon and need 15 people. For the register, just register to google forms | M50: Yes | N50: No | O50: Yes | P50: Yes | Q50: No | S50: Yes | T50: 2 | U50: None (Waiting for full batch) | V50: Free (Scholarship), Php 16,000 (Regular; with housing) | X50: Online (Google Form) | Z50: 0910 752 1723 | AA50: N/A | AC50: {=SUMPRODUCT(--(M50:Q50="YES"))} -> 3 | AD50: =COUNTIF($AC$7:AC50, ">=3") -> 16
A51: 14 | B51: Jacobo Z. Gonzales Memorial School of Arts and Trades | C51: 19 | D51: 880 | E51: 533 | F51: 0 | G51: 0 | H51: 26 | I51: =IF(D51=0,"-",E51/D51) -> 0.60568182 | J51: =IF(F51=0,"-",G51/F51) -> - | L51: They have a website, but it's not easily shown that they have a website: https://www.jzgmsat.edu.ph/ Website is updated last July 3. The mobile number and landline I dialed was unattended, but I will add both in the fields. For the Housekeeping NC II, the kailangan is 25. Palista muna sa admission and then tanong sa requirements. Kailangan muna enroll. This is the second time I called they answered. The Housekeeping NC II is waitlisted. Special training si Housekeeping with Php 3,000 (assessment fee is Php 1,108). For the scholarhsip, it is still pending. For application, it needs to be onsite. | M51: Yes | N51: Yes | O51: Yes | P51: Yes | Q51: Yes | R51: https://www.jzgmsat.edu.ph/ | S51: Yes | T51: 2 | U51: None (Waiting for full batch) | V51: Php 3,000 (assessment fee is Php 1,108). | W51: Yes | X51: Onsite (Walk-in application) | Z51: (049) - 511 - 6130 | AA51: zgmsat@tesda.gov.ph | AC51: {=SUMPRODUCT(--(M51:Q51="YES"))} -> 5 | AD51: =COUNTIF($AC$7:AC51, ">=3") -> 17
A52: 33 | B52: R AND R SKILLS TRAINING CENTER INC. | C52: 3 | D52: 569 | E52: 515 | F52: 595 | G52: 589 | H52: 6 | I52: =IF(D52=0,"-",E52/D52) -> 0.90509666 | J52: =IF(F52=0,"-",G52/F52) -> 0.98991597 | T52: 2 | AC52: {=SUMPRODUCT(--(M52:Q52="YES"))} -> 0 | AD52: =COUNTIF($AC$7:AC52, ">=3") -> 17
A53: 42 | B53: ANGELITA V. DEL MUNDO FOUNDATION | C53: 6 | D53: 457 | E53: 504 | F53: 0 | G53: 0 | H53: 7 | I53: =IF(D53=0,"-",E53/D53) -> 1.1028446 | J53: =IF(F53=0,"-",G53/F53) -> - | T53: 2 | AC53: {=SUMPRODUCT(--(M53:Q53="YES"))} -> 0 | AD53: =COUNTIF($AC$7:AC53, ">=3") -> 17
A54: 46 | B54: MENDOZA TRAINING AND ASSESSMENT CENTER INC. | C54: 3 | D54: 424 | E54: 449 | F54: 319 | G54: 318 | H54: 9 | I54: =IF(D54=0,"-",E54/D54) -> 1.0589623 | J54: =IF(F54=0,"-",G54/F54) -> 0.9968652 | L54: The Facebook page does not easily give the contact details. I had to find it through the TESDA Webpage. Facebook was updated last July 2. | M54: Yes | N54: Yes | O54: Yes | P54: No | Q54: No | T54: 2 | AC54: {=SUMPRODUCT(--(M54:Q54="YES"))} -> 3 | AD54: =COUNTIF($AC$7:AC54, ">=3") -> 18
A55: 40 | B55: ITECH TECHNICAL VOCATIONAL INSTITUTE CORP. | C55: 3 | D55: 491 | E55: 429 | F55: 0 | G55: 0 | H55: 8 | I55: =IF(D55=0,"-",E55/D55) -> 0.87372709 | J55: =IF(F55=0,"-",G55/F55) -> - | T55: 2 | AC55: {=SUMPRODUCT(--(M55:Q55="YES"))} -> 0 | AD55: =COUNTIF($AC$7:AC55, ">=3") -> 18
A56: 130 | B56: SAN ANTONIO SKILLS DEVELOPMENT CENTER INC. | C56: 6 | D56: 174 | E56: 210 | F56: 469 | G56: 399 | H56: 1 | I56: =IF(D56=0,"-",E56/D56) -> 1.2068966 | J56: =IF(F56=0,"-",G56/F56) -> 0.85074627
A57: 190 | B57: TRENT INFORMATION FIRST TECHNICAL CAREER INSTITUTE INC. | C57: 6 | D57: 100 | E57: 99 | F57: 587 | G57: 570 | H57: 2 | I57: =IF(D57=0,"-",E57/D57) -> 0.99 | J57: =IF(F57=0,"-",G57/F57) -> 0.97103918
A58: 350 | B58: ST. MICHAEL TVET TRAINING AND ASSESSMENT CENTER INC. | C58: 6 | D58: 23 | E58: 23 | F58: 401 | G58: 367 | H58: 3 | I58: =IF(D58=0,"-",E58/D58) -> 1 | J58: =IF(F58=0,"-",G58/F58) -> 0.91521197
A59: 383 | B59: PHILIPPINE HEAVY EQUIPMENT OPERATOR AND ASSESSMENT TRAINING CENTER INC. | C59: 6 | D59: 5 | E59: 5 | F59: 481 | G59: 448 | H59: 2 | I59: =IF(D59=0,"-",E59/D59) -> 1 | J59: =IF(F59=0,"-",G59/F59) -> 0.93139293
A60: 397 | B60: ANGELITA V. DEL MUNDO FOUNDATION (AVM FOUNDATION) INC. | C60: 6 | D60: 0 | E60: 0 | F60: 512 | G60: 545 | H60: 0 | I60: =IF(D60=0,"-",E60/D60) -> - | J60: =IF(F60=0,"-",G60/F60) -> 1.0644531
A61: 399 | B61: ASIAN INSTITUTE OF TECHNOLOGY AND EDUCATION, INC. | C61: 6 | D61: 0 | E61: 0 | F61: 494 | G61: 478 | H61: 0 | I61: =IF(D61=0,"-",E61/D61) -> - | J61: =IF(F61=0,"-",G61/F61) -> 0.96761134
A62: 418 | B62: PHILTECH INSTITUTE OF ARTS AND TECHNOLOGY INC. | C62: 6 | D62: 0 | E62: 0 | F62: 387 | G62: 340 | H62: 0 | I62: =IF(D62=0,"-",E62/D62) -> - | J62: =IF(F62=0,"-",G62/F62) -> 0.87855297
A63: 453 | B63: ISHRM SCHOOL SYSTEM, INC. - BACOOR | C63: 6 | D63: 0 | E63: 0 | F63: 1213 | G63: 1207 | H63: 0 | I63: =IF(D63=0,"-",E63/D63) -> - | J63: =IF(F63=0,"-",G63/F63) -> 0.99505359
A64: 457 | B64: RIZAL PROVINCIAL TECHNICAL EDUCATION AND SKILLS DEVELOPMENT CENTER - BINANGONAN | C64: 6 | D64: 0 | E64: 0 | F64: 1302 | G64: 1311 | H64: 0 | I64: =IF(D64=0,"-",E64/D64) -> - | J64: =IF(F64=0,"-",G64/F64) -> 1.0069124
A65: 465 | B65: ROYAL BRITISH COLLEGE INC. | C65: 6 | D65: 0 | E65: 0 | F65: 274 | G65: 270 | H65: 0 | I65: =IF(D65=0,"-",E65/D65) -> - | J65: =IF(F65=0,"-",G65/F65) -> 0.98540146
A66: 467 | B66: ROGATIONIST COLLEGE (ST. ANTHONY'S BOYS VILLAGE), INC. | C66: 6 | D66: 0 | E66: 0 | F66: 521 | G66: 502 | H66: 0 | I66: =IF(D66=0,"-",E66/D66) -> - | J66: =IF(F66=0,"-",G66/F66) -> 0.96353167
A67: 478 | B67: MILLENIAL'S CHOICE TRAINING INSTITUTE AND ASSESSMENT CENTER, INC. | C67: 6 | D67: 0 | E67: 0 | F67: 1910 | G67: 1853 | H67: 0 | I67: =IF(D67=0,"-",E67/D67) -> - | J67: =IF(F67=0,"-",G67/F67) -> 0.97015707
... A71: 540 | B71: ADVENT CAREGIVER SCHOOL, INC. | C71: 6 | D71: 0 | E71: 0 | F71: 2861 | G71: 2822 | H71: 0 | I71: =IF(D71=0,"-",E71/D71) -> - | J71: =IF(F71=0,"-",G71/F71) -> 0.9863684
A72: 54 | B72: THE FORKS TRAINING AND ASSESSMENT SOLUTIONS INC. | C72: 5 | D72: 374 | E72: 403 | F72: 1372 | G72: 1279 | H72: 5 | I72: =IF(D72=0,"-",E72/D72) -> 1.0775401 | J72: =IF(F72=0,"-",G72/F72) -> 0.93221574 | K72: 1 | L72: Facebook page was updated last Feburary 6, 2023. The Google Maps is not even clear because there is another one in Manila, which can confuse because the main institution is in Batangas. | M72: No | N72: No | O72: No | P72: No | Q72: Yes | R72: https://www.theforkstasi.com/ | S72: 2nd Priority | T72: 2 | AC72: {=SUMPRODUCT(--(M72:Q72="YES"))} -> 1 | AD72: =COUNTIF($AC$7:AC72, ">=3") -> 18
A73: 57 | B73: Provincial Training Center - Lipa | C73: 4 | D73: 363 | E73: 399 | F73: 0 | G73: 0 | H73: 5 | I73: =IF(D73=0,"-",E73/D73) -> 1.0991736 | J73: =IF(F73=0,"-",G73/F73) -> - | K73: 1 | T73: 2 | AC73: {=SUMPRODUCT(--(M73:Q73="YES"))} -> 0 | AD73: =COUNTIF($AC$7:AC73, ">=3") -> 18
A74: 37 | B74: KEYSTONE TECHNICAL INSTITUTE OF LOPEZ QUEZON, INC. | C74: 9 | D74: 513 | E74: 376 | F74: 1639 | G74: 1578 | H74: 9 | I74: =IF(D74=0,"-",E74/D74) -> 0.73294347 | J74: =IF(F74=0,"-",G74/F74) -> 0.96278218 | K74: 1 | L74: Baka wala nang scholarship, possible next year na. for the regular classes, walang offer. For the price of development and assessment, is Php 5,825. Meron ding regular class from PUP (partnered with them) with 45 days of training. To apply, you need to be onsite so that you can get the requirements and fill out the participant profile. | M74: Yes | N74: No | O74: Yes | P74: Yes | Q74: No | T74: 2 | U74: None (Pending TESDA funding) | V74: ₱5,825 (Assessment; Food and Beverages NC II) | W74: No (No scholarship currently) | X74: Onsite (Walk-in application) | Z74: 0920 614 4418 | AA74: keystonetechnical.lopez@gmail.com | AC74: {=SUMPRODUCT(--(M74:Q74="YES"))} -> 3 | AD74: =COUNTIF($AC$7:AC74, ">=3") -> 19
A75: 23 | B75: BATANGAS EASTERN COLLEGES, INC. | C75: 9 | D75: 734 | E75: 362 | F75: 530 | G75: 504 | H75: 10 | I75: =IF(D75=0,"-",E75/D75) -> 0.49318801 | J75: =IF(F75=0,"-",G75/F75) -> 0.9509434 | K75: 1 | L75: Facebook page was updated last July 7. The phone number works, but I cannot hear anything from the other end of the line. They also have a website that is updated and very pretty. | M75: Yes | N75: Yes | O75: Yes | P75: No | Q75: Yes | R75: https://bec.edu.ph/ | S75: Yes | T75: 2 | Z75: (043) 575 3616 | AA75: beacon@bec.edu.ph | AC75: {=SUMPRODUCT(--(M75:Q75="YES"))} -> 4 | AD75: =COUNTIF($AC$7:AC75, ">=3") -> 20
A76: 73 | B76: UNITECH EDUCATIONAL INSTITUTE (UEI) INC. | C76: 7 | D76: 307 | E76: 330 | F76: 1546 | G76: 1502 | H76: 6 | I76: =IF(D76=0,"-",E76/D76) -> 1.0749186 | J76: =IF(F76=0,"-",G76/F76) -> 0.97153946 | K76: 1 | L76: Facebook page was updated last June 25. Ang available right now ay baking. No scheduled right now for baking. We can enroll in the school right now so that once it is available, they will call once available. This is TESDA scholarship, they do not accept. Onsite lang. Everything is thru scholarship. | M76: Yes | N76: Yes | O76: Yes | P76: Yes | Q76: No | T76: 2 | Z76: 0907 077 0616 | AA76: unitech.UEI@gmail.com | AC76: {=SUMPRODUCT(--(M76:Q76="YES"))} -> 4 | AD76: =COUNTIF($AC$7:AC76, ">=3") -> 21
A77: 58 | B77: Quezon National Agricultural School | C77: 9 | D77: 359 | E77: 329 | F77: 0 | G77: 0 | H77: 13 | I77: =IF(D77=0,"-",E77/D77) -> 0.91643454 | J77: =IF(F77=0,"-",G77/F77) -> - | K77: 1 | L77: Facebook page was updated last June 8. | M77: Yes | N77: No | O77: Yes | P77: No | Q77: Yes | R77: https://qnas.edu.ph/ | T77: 2 | Z77: registration@qnas.edu.ph | AA77: 0946 617 7983 | AC77: {=SUMPRODUCT(--(M77:Q77="YES"))} -> 3 | AD77: =COUNTIF($AC$7:AC77, ">=3") -> 22
A78: 50 | B78: Advent Caregiver School Inc. | C78: 4 | D78: 390 | E78: 325 | F78: 0 | G78: 0 | H78: 9 | I78: =IF(D78=0,"-",E78/D78) -> 0.83333333 | J78: =IF(F78=0,"-",G78/F78) -> - | K78: 1 | L78: Facebook page was updated last June 13. When I called, they said that they currently do not have the actual person who replies to the questions, but they did answer the phone. I will just have to call apparently in one hour. | M78: Yes | N78: Yes | O78: Yes | P78: Yes | Q78: No | T78: 2 | U78: N/A | V78: N/A | W78: N/A | X78: N/A | Z78: 0917 587 3195 | AA78: adventcaregiverschool@yahoo.com | AC78: {=SUMPRODUCT(--(M78:Q78="YES"))} -> 4 | AD78: =COUNTIF($AC$7:AC78, ">=3") -> 23
A79: 61 | B79: WESTBRIDGE INSTITUTE OF TECHNOLOGY | C79: 5 | D79: 352 | E79: 325 | F79: 0 | G79: 0 | H79: 8 | I79: =IF(D79=0,"-",E79/D79) -> 0.92329545 | J79: =IF(F79=0,"-",G79/F79) -> - | K79: 1 | T79: 2 | AC79: {=SUMPRODUCT(--(M79:Q79="YES"))} -> 0 | AD79: =COUNTIF($AC$7:AC79, ">=3") -> 23
A80: 77 | B80: SCHOLA ANGELICUS, INC. | C80: 7 | D80: 302 | E80: 321 | F80: 170 | G80: 170 | H80: 9 | I80: =IF(D80=0,"-",E80/D80) -> 1.0629139 | J80: =IF(F80=0,"-",G80/F80) -> 1 | K80: 1 | T80: 2 | AC80: {=SUMPRODUCT(--(M80:Q80="YES"))} -> 0 | AD80: =COUNTIF($AC$7:AC80, ">=3") -> 23
A81: 52 | B81: BRIGHTWELL TECHNICAL EDUCATION TRAINING AND ASSESSMENT CENTER, INC. | C81: 6 | D81: 386 | E81: 321 | F81: 397 | G81: 339 | H81: 9 | I81: =IF(D81=0,"-",E81/D81) -> 0.83160622 | J81: =IF(F81=0,"-",G81/F81) -> 0.85390428 | K81: 1 | T81: 2 | AC81: {=SUMPRODUCT(--(M81:Q81="YES"))} -> 0 | AD81: =COUNTIF($AC$7:AC81, ">=3") -> 23
A82: 70 | B82: Technical Skills System of Lucena Inc. | C82: 3 | D82: 323 | E82: 318 | F82: 0 | G82: 0 | H82: 7 | I82: =IF(D82=0,"-",E82/D82) -> 0.98452012 | J82: =IF(F82=0,"-",G82/F82) -> - | K82: 1 | T82: 2 | AC82: {=SUMPRODUCT(--(M82:Q82="YES"))} -> 0 | AD82: =COUNTIF($AC$7:AC82, ">=3") -> 23
A83: 78 | B83: EL ROYALE CREDIT COOPERATIVE | C83: 4 | D83: 302 | E83: 302 | F83: 0 | G83: 0 | H83: 12 | I83: =IF(D83=0,"-",E83/D83) -> 1 | J83: =IF(F83=0,"-",G83/F83) -> - | K83: 1 | L83: The Facebook page is not readily accessible because the first link when the name is searched up is the Cooperative itself, NOT the TESDA training center. When I called the phone number over three days, it was always unavailable. | M83: No | N83: No | O83: Yes | P83: No | Q83: No | T83: 2 | AC83: {=SUMPRODUCT(--(M83:Q83="YES"))} -> 1 | AD83: =COUNTIF($AC$7:AC83, ">=3") -> 23
A84: 62 | B84: SWEET NATURE FARMS | C84: 3 | D84: 351 | E84: 300 | F84: 0 | G84: 0 | H84: 8 | I84: =IF(D84=0,"-",E84/D84) -> 0.85470085 | J84: =IF(F84=0,"-",G84/F84) -> - | K84: 1 | T84: 2 | AC84: {=SUMPRODUCT(--(M84:Q84="YES"))} -> 0 | AD84: =COUNTIF($AC$7:AC84, ">=3") -> 23
A85: 92 | B85: Rizal Provincial Technical Education and Skills Development Center - Binangonan | C85: 6 | D85: 254 | E85: 299 | F85: 0 | G85: 0 | H85: 10 | I85: =IF(D85=0,"-",E85/D85) -> 1.1771654 | J85: =IF(F85=0,"-",G85/F85) -> - | K85: 1 | L85: This was easily confused with the other center in Cainta. I don't think they are even alive since the last post about this specific center was June 24, 2020. | M85: No | N85: No | O85: No | P85: No | Q85: No | T85: 2 | AC85: {=SUMPRODUCT(--(M85:Q85="YES"))} -> 0 | AD85: =COUNTIF($AC$7:AC85, ">=3") -> 23
A86: 109 | B86: Rizal Provincial Technical Education and Skills Development Center - Cainta | C86: 8 | D86: 209 | E86: 293 | F86: 0 | G86: 0 | H86: 8 | I86: =IF(D86=0,"-",E86/D86) -> 1.4019139 | J86: =IF(F86=0,"-",G86/F86) -> - | K86: 1 | L86: They are still alive. The Facebook page is hard to find, but they do have a website, which is still functioning, and the phone number they gave works. They transferred me over to another phone number, and I had to wait for an hour. | M86: Yes | N86: No | O86: No | P86: Yes | Q86: Yes | R86: https://rptesdccainta.com/about | S86: Yes | T86: 2 | U86: N/A | V86: N/A | W86: N/A | X86: N/A | Z86: (02)8656-9937 | AA86: ptccainta@tesda.gov.ph | AC86: {=SUMPRODUCT(--(M86:Q86="YES"))} -> 3 | AD86: =COUNTIF($AC$7:AC86, ">=3") -> 24
A87: 65 | B87: OFFSHORE-ONSHORE INSTITUTE OF TECHNOLOGY, INC. | C87: 4 | D87: 343 | E87: 293 | F87: 794 | G87: 789 | H87: 10 | I87: =IF(D87=0,"-",E87/D87) -> 0.85422741 | J87: =IF(F87=0,"-",G87/F87) -> 0.99370277 | K87: 1 | L87: Facebook page was updated last June 27, 2018. | M87: No | N87: No | O87: Yes | P87: No | Q87: No | T87: 2 | AC87: {=SUMPRODUCT(--(M87:Q87="YES"))} -> 1 | AD87: =COUNTIF($AC$7:AC87, ">=3") -> 24
A88: 276 | B88: ST. GABRIEL COLLEGE OF TECHNOLOGY AND ASSESSMENT CENTER INC. | C88: 5 | D88: 50 | E88: 50 | F88: 639 | G88: 528 | H88: 1 | I88: =IF(D88=0,"-",E88/D88) -> 1 | J88: =IF(F88=0,"-",G88/F88) -> 0.82629108
A89: 311 | B89: CAGANDAHAN SKILLS DEVELOPMENT INC. | C89: 5 | D89: 41 | E89: 24 | F89: 203 | G89: 203 | H89: 1 | I89: =IF(D89=0,"-",E89/D89) -> 0.58536585 | J89: =IF(F89=0,"-",G89/F89) -> 1
A90: 403 | B90: UMA VERDE ECONATURE FARM INC. | C90: 5 | D90: 0 | E90: 0 | F90: 522 | G90: 512 | H90: 0 | I90: =IF(D90=0,"-",E90/D90) -> - | J90: =IF(F90=0,"-",G90/F90) -> 0.98084291
A91: 409 | B91: LFS TRAINING AND ASSESSMENT CENTER, INC | C91: 5 | D91: 0 | E91: 0 | F91: 349 | G91: 371 | H91: 0 | I91: =IF(D91=0,"-",E91/D91) -> - | J91: =IF(F91=0,"-",G91/F91) -> 1.0630372
A92: 410 | B92: LORD YAHWEH BUSINESS COLLEGES & MARITIME ACADEMY INCORPORATED | C92: 5 | D92: 0 | E92: 0 | F92: 745 | G92: 819 | H92: 0 | I92: =IF(D92=0,"-",E92/D92) -> - | J92: =IF(F92=0,"-",G92/F92) -> 1.0993289
A93: 412 | B93: AUTOZONE DRIVING SCHOOL INC. | C93: 5 | D93: 0 | E93: 0 | F93: 759 | G93: 732 | H93: 0 | I93: =IF(D93=0,"-",E93/D93) -> - | J93: =IF(F93=0,"-",G93/F93) -> 0.96442688
A94: 426 | B94: GRABSUM SCHOOL INC. | C94: 5 | D94: 0 | E94: 0 | F94: 313 | G94: 271 | H94: 0 | I94: =IF(D94=0,"-",E94/D94) -> - | J94: =IF(F94=0,"-",G94/F94) -> 0.8658147
A95: 431 | B95: GOALS TRAINING AND ASSESSMENT INSTITUTE INC | C95: 5 | D95: 0 | E95: 0 | F95: 1575 | G95: 1516 | H95: 0 | I95: =IF(D95=0,"-",E95/D95) -> - | J95: =IF(F95=0,"-",G95/F95) -> 0.96253968
A96: 447 | B96: EL ROYALE HOTELIER TRAINING CENTER INC. | C96: 5 | D96: 0 | E96: 0 | F96: 1156 | G96: 1099 | H96: 0 | I96: =IF(D96=0,"-",E96/D96) -> - | J96: =IF(F96=0,"-",G96/F96) -> 0.95069204
A97: 485 | B97: SACRED HEART COLLEGE OF LUCENA CITY, INC. | C97: 5 | D97: 0 | E97: 0 | F97: 312 | G97: 287 | H97: 0 | I97: =IF(D97=0,"-",E97/D97) -> - | J97: =IF(F97=0,"-",G97/F97) -> 0.91987179
A98: 487 | B98: DMPC SKILLED WORKS TRAINING AND ASSESSMENT CENTER INC. | C98: 5 | D98: 0 | E98: 0 | F98: 378 | G98: 353 | H98: 0 | I98: =IF(D98=0,"-",E98/D98) -> - | J98: =IF(F98=0,"-",G98/F98) -> 0.93386243
A99: 492 | B99: CENTER FOR COMPETENCIES ENHANCEMENT AND DEVELOPMENT, INCORPORATED | C99: 5 | D99: 0 | E99: 0 | F99: 1440 | G99: 1352 | H99: 0 | I99: =IF(D99=0,"-",E99/D99) -> - | J99: =IF(F99=0,"-",G99/F99) -> 0.93888889
... A102: 542 | B102: ACEBA SCIENCE & TECH. INSTITUTE INC. | C102: 5 | D102: 0 | E102: 0 | F102: 755 | G102: 699 | H102: 0 | I102: =IF(D102=0,"-",E102/D102) -> - | J102: =IF(F102=0,"-",G102/F102) -> 0.92582781
A103: 64 | B103: CRUZEDAL TRAINING & ASSESSMENT CENTER INC. | C103: 4 | D103: 346 | E103: 292 | F103: 307 | G103: 300 | H103: 5 | I103: =IF(D103=0,"-",E103/D103) -> 0.84393064 | J103: =IF(F103=0,"-",G103/F103) -> 0.9771987 | K103: 1 | T103: 2 | AC103: {=SUMPRODUCT(--(M103:Q103="YES"))} -> 0 | AD103: =COUNTIF($AC$7:AC103, ">=3") -> 24
A104: 34 | B104: The Foundation for Professional Training Inc. - Anihan Technical School | C104: 3 | D104: 541 | E104: 291 | F104: 0 | G104: 0 | H104: 11 | I104: =IF(D104=0,"-",E104/D104) -> 0.53789279 | J104: =IF(F104=0,"-",G104/F104) -> - | K104: 1 | L104: Facebook page was updated last July 6. They have an updated website, which also posted last July 6. | M104: Yes | N104: Yes | O104: Yes | P104: No | Q104: Yes | R104: https://anihan.edu.ph/ | S104: Yes | T104: 2 | Z104: 0939 266 6108 | AA104: info@anihan.edu.ph | AC104: {=SUMPRODUCT(--(M104:Q104="YES"))} -> 4 | AD104: =COUNTIF($AC$7:AC104, ">=3") -> 25
A105: 80 | B105: XAVIER TECHNICAL TRAINING CENTER CORP. | C105: 9 | D105: 290 | E105: 288 | F105: 1386 | G105: 1378 | H105: 5 | I105: =IF(D105=0,"-",E105/D105) -> 0.99310345 | J105: =IF(F105=0,"-",G105/F105) -> 0.99422799 | K105: 1 | L105: Facebook page was updated last June 24. Magsisimula na sya ng July 11 (Saturday). Regular training sya. Kung scholar, nakalagay na kung para sa scholar. The price is Php 17,000 (kasama na ang NC I and NC II at materials. Kasama na rin ang assessment). To register, punta na sa Xavier. Day-off on Thursday an hanggang 4 PM. No online. | M105: Yes | N105: Yes | O105: Yes | P105: Yes | Q105: No | T105: 2 | U105: July 11 (Saturday) | V105: Php 17,000 (Training + Assessment; SMAW NC I & NC II) | W105: No (No scholarship currently) | X105: Onsite (Walk-in application) | Z105: 0962 263 9719 | AA105: xaviertech.sjdm@gmail.com | AC105: {=SUMPRODUCT(--(M105:Q105="YES"))} -> 4 | AD105: =COUNTIF($AC$7:AC105, ">=3") -> 26
A106: 82 | B106: IMPERIUM TRAINING CENTER INC. | C106: 3 | D106: 277 | E106: 286 | F106: 2389 | G106: 2356 | H106: 6 | I106: =IF(D106=0,"-",E106/D106) -> 1.032491 | J106: =IF(F106=0,"-",G106/F106) -> 0.98618669 | K106: 1 | L106: Facebook page was updated last October 15, 2019 | M106: No | N106: No | O106: Yes | P106: No | Q106: No | T106: 2 | AC106: {=SUMPRODUCT(--(M106:Q106="YES"))} -> 1 | AD106: =COUNTIF($AC$7:AC106, ">=3") -> 26
...

Sheet Leads for NCR and 4A
A1: Record Id | B1: Is Converted | C1: Lead Owner.id | D1: Lead Owner | E1: Company | F1: First Name | G1: Last Name | H1: Title | I1: Priority Level | J1: Email | K1: Sureness | L1: Phone | M1: Mobile | N1: Website | O1: Lead Source | P1: Lead Status | Q1: Created By.id | R1: Created By | S1: Modified By.id | T1: Modified By | U1: Created Time | V1: Modified Time | W1: Lead Name | X1: City | Y1: Description | Z1: Salutation | AA1: Secondary Email | AB1: Last Activity Time | AC1: Tag | AD1: Converted Date Time | AE1: Lead Conversion Time | AF1: Unsubscribed Mode | AG1: Unsubscribed Time | AH1: Converted Account.id | AI1: Converted Account | AJ1: Converted Contact.id | AK1: Converted Contact | AL1: Converted Deal.id | AM1: Converted Deal | AN1: Change Log Time | AO1: Locked | AP1: Last Enriched Time | AQ1: Enrich Status | AR1: Partner Type | AS1: Connect with University Entrepreneurship Prgm. | AT1: Get more information about the alliance | AU1: Partner with you as a mentor | AV1: Connect with programs aimed at entrepreneurs /SB | AW1: Other | AX1: Industria o Sector | AY1: ¿Qué esperas obtener de esta masterclass? | AZ1: Retos más importantes para este año | BA1: Que le preguntarías al fundador de Rappi | BB1: ¿En qué punto se encuentra tu emprendimiento? | BC1: Interest Level | BD1: Sector. | BE1: State/Province | BF1: Country. | BG1: Web o redes del emprendimiento | BH1: Prinicipal reto | BI1: Tipo de Aliado | BJ1: Fecha de inicio de operaciones | BK1: Número de Empleados | BL1: Número de clientes que pagan | BM1: Pitch de Startup | BN1: Ventas Anuales | BO1: Tipo de fondeo recibido | BP1: Principales Canales de Ventas | BQ1: Get more information about Emplea+
E2: TESDA Women's Center | F2: Gerrelen | G2: Balbin | H2: Senior TESD Specialist, Training Management Unit Head | I2: 1st Priority | J2: gdbalbin@tesda.gov.ph | K2: Yes (Website) | O2: Cold call | P2: Sourced
E3: PSAA INTERNATIONAL ACADEMY INC. | F3: Riza | G3: Sorima-Matias | H3: Training Director | I3: 1st Priority | J3: psaamanila@hotmail.com | K3: Yes (Website)
E4: MILESTONE TECHNOLOGICAL INSTITUTE, INC. | F4: Fernando | G4: Libao | H4: Center Manager | I4: 1st Priority | J4: milestone.camanava2022@gmail.com / mti.developer.ph@gmail.com | K4: Maybe??? (Came From 2024 EGAC Dataset)
E5: CENTER FOR ASIAN CULINARY STUDIES INC. | F5: Eugenio | G5: Gonzalez | H5: Culinary Arts Director | I5: 1st Priority | J5: cacschef@gmail.com | K5: Yes (Website)
E6: MECHATRONICS TECHNOLOGIES CORP. | F6: Xerxes Gamaliel | G6: Itao | H6: Managing Director | I6: 1st Priority | J6: mechatronicstechnologiescorp@yahoo.com | K6: Yes (Website)
E7: CENTER FOR BARISTA AND TOURISM ACADEMY TRAINING AND ASSESSMENT, INC. | F7: Deejae | G7: Juanta | H7: Founder | I7: 2nd Priority | J7: qc.cenbartvimis@gmail.com / training.cfb@gmail.com | K7: Yes (Website)
E8: ACADEMY ASIA SCHOOL OF TECHNOLOGY AND THE ARTS, INC. | F8: Jamie | G8: Dolera | H8: Managing Director | I8: 1st Priority | J8: academy.asia@gmail.com | K8: Most Likely (Fact-Checked from Pre-2024 Sources)
E9: SEAMAC INTERNATIONAL TRAINING INSTITUTE, INC. | F9: Teresita | G9: Marcos | H9: Center Manager | I9: 2nd Priority | J9: ne.guarina@seamac.ph.education / seamactraining@yahoo.com | K9: Don't Trust (Came From 2024 EGAC Dataset. But contact person works now in Exact Colleges)
E10: ASIA SOURCE ICOLLEGE INC. | F10: Jethro | G10: Orejuela | H10: School Director | I10: 2nd Priority | J10: asiasource.academics@gmail.com / asic2014@asiasourceicollege.edu.ph | K10: Yes (Facebook)
E11: UNO CAREGIVER AND DOMESTIC MNGT TRAINING, INC. | F11: Mary Grace Rosalia | G11: Gulan | H11: Center Manager | I11: 1st Priority | J11: uno_training@yahoo.com / uno.training88@gmail.com | K11: Don't Trust (Came From 2024 EGAC Dataset. But contact person works now in NASTA)
E12: TECHVOC SKILLS INC. | F12: Melody | G12: Cruz | H12: School Head | I12: 1st Priority | J12: techvoc_skills.incorporated@yahoo.com | K12: Yes (Tiktok)
E13: REGIONAL TRAINING CENTER - NCR | F13: Jerry | G13: Taroy | H13: Supervising TESD Specialist, Head – Training, Research, Assessment and Extension Unit (TREAU) | I13: 1st Priority | J13: rtcncr@tesda.gov.ph | K13: Yes (Website)
E14: SMI INSTITUTE INC. | F14: Cristina | G14: Aplasca | H14: Center Manager | I14: 1st Priority | J14: smiacademicenter@gmail.com | K14: Yes (Facebook)
... E41: THE FORKS TRAINING AND ASSESSMENT SOLUTIONS INC. | F41: Carlenne Joy | G41: Benamer | H41: Center Administrator | I41: 2nd Priority | J41: theforksbatangas@yahoo.com | K41: Yes (Website)

Sheet NC Combinations
A1: Top NC Combinations for 1st Priority Institutions
A2: 174 common combinations. Ranked by absolute frequency. NOT computed live. This was just copy and pasted from the Github under 09_LEADS
A3: https://github.com/BSDSBA-JF/wadwani_intern
A5: itemset | B5: Absolute Frequency | C5: Relative Frequency
A6: ('Housekeeping NC II',) | B6: 13 | C6: 0.56521739
A7: ('Food and Beverage Services NC II',) | B7: 12 | C7: 0.52173913
A8: ('Food and Beverage Services NC II', 'Housekeeping NC II') | B8: 10 | C8: 0.43478261
A9: ('Trainers Methodology Level I',) | B9: 9 | C9: 0.39130435
A10: ('Bartending NC II', 'Food and Beverage Services NC II') | B10: 8 | C10: 0.34782609
A11: ('Cookery NC II', 'Food and Beverage Services NC II') | B11: 7 | C11: 0.30434783
A12: ('Hilot (Wellness Massage) NC II',) | B12: 7 | C12: 0.30434783
A13: ('Bartending NC II', 'Food and Beverage Services NC II', 'Housekeeping NC II') | B13: 7 | C13: 0.30434783
A14: ('Bartending NC II', 'Housekeeping NC II') | B14: 7 | C14: 0.30434783
A15: ('Cookery NC II', 'Housekeeping NC II') | B15: 6 | C15: 0.26086957
A16: ('Housekeeping NC II', 'Trainers Methodology Level I') | B16: 6 | C16: 0.26086957
A17: ('Front Office Services NC II', 'Housekeeping NC II') | B17: 5 | C17: 0.2173913
... A25: ('Mechatronics Servicing NC II',) | B25: 5 | C25: 0.2173913
A26: ('Bartending NC II', 'Cookery NC II') | B26: 5 | C26: 0.2173913 | E26: `
A27: ('Cookery NC II', 'Food and Beverage Services NC II', 'Housekeeping NC II') | B27: 5 | C27: 0.2173913
A28: ('Food and Beverage Services NC II', 'Housekeeping NC II', 'Trainers Methodology Level I') | B28: 5 | C28: 0.2173913
A29: ('Food and Beverage Services NC II', 'Trainers Methodology Level I') | B29: 5 | C29: 0.2173913
A30: ('Bartending NC II', 'Cookery NC II', 'Food and Beverage Services NC II') | B30: 5 | C30: 0.2173913
A31: ('Barista NC II', 'Bartending NC II') | B31: 4 | C31: 0.17391304
A32: ('Shielded Metal Arc Welding (SMAW) NC I', 'Shielded Metal Arc Welding (SMAW) NC II') | B32: 4 | C32: 0.17391304
A33: ('Bookkeeping NC III', 'Food and Beverage Services NC II') | B33: 4 | C33: 0.17391304
A34: ('Bookkeeping NC III', 'Trainers Methodology Level I') | B34: 4 | C34: 0.17391304
A35: ('Barista NC II', 'Food and Beverage Services NC II', 'Housekeeping NC II') | B35: 4 | C35: 0.17391304
A36: ('Barista NC II', 'Housekeeping NC II') | B36: 4 | C36: 0.17391304
A37: ('Driving NC II', 'Electronic Products Assembly and Servicing NC II', 'Trainers Methodology Level I') | B37: 4 | C37: 0.17391304
A38: ('Shielded Metal Arc Welding (SMAW) NC I', 'Trainers Methodology Level I') | B38: 4 | C38: 0.17391304
... A179: ('Bookkeeping NC III', 'Food and Beverage Services NC II', 'Front Office Services NC II') | B179: 3 | C179: 0.13043478

Sheet Sectors
A1: Top Sectors for 1st Priority Institutions
A2: 24 First Priority Institutions.
A3: https://github.com/BSDSBA-JF/wadwani_intern
A5: Institution | B5: Qualifications | C5: Sectors | D5: Specialized Sector | E5: Graduates
A6: TESDA Women's Center | B6: {'Housekeeping NC II', 'Bookkeeping NC III', 'Trainers Methodology Level I', 'Shielded Metal Arc Welding (SMAW) NC I', 'Driving NC II', 'Bartending NC II', 'Gas Metal Arc Welding (GMAW) NC II', 'Shielded Metal Arc Welding (SMAW) NC II', 'Electronic Products Assembly and Servicing NC II', 'Barista NC II', 'Bread and Pastry Production NC II', 'Cookery NC II', 'Plumbing NC I', 'Plumbing NC II', 'Dressmaking NC II', 'Electrical Installation and Maintenance NC II', 'Food and Beverage Services NC II', 'Automotive Servicing NC I'} | C6: ['TOURISM SECTOR', 'HEALTH, SOCIAL, AND OTHER COMMUNITY DEVELOPMENT SERVICES SECTOR', 'TVET SECTOR', 'METALS AND ENGINEERING SECTOR', 'AUTOMOTIVE AND LAND TRANSPORT SECTOR', 'TOURISM SECTOR', 'METALS AND ENGINEERING SECTOR', 'METALS AND ENGINEERING SECTOR', 'ELECTRICAL & ELECTRONICS SECTOR', 'TOURISM SECTOR', 'TOURISM SECTOR', 'TOURISM SECTOR', 'CONSTRUCTION SECTOR', 'CONSTRUCTION SECTOR', 'GARMENTS SECTOR', 'ELECTRICAL & ELECTRONICS SECTOR', 'TOURISM SECTOR', 'AUTOMOTIVE AND LAND TRANSPORT SECTOR'] | D6: TOURISM SECTOR | E6: {=IFERROR( _xlfn.XLOOKUP(TRUE, EXACT(Table4[[#This Row],[Institution]], 'Top Centers - NCR'!B:B), 'Top Centers - NCR'!E:E ), _xlfn.XLOOKUP(TRUE, EXACT(Table4[[#This Row],[Institution]], 'Top Centers - 4A'!B:B), 'Top Centers - 4A'!E:E ) )} -> 2491
A7: TECHVOC SKILLS INC. | B7: {'Contact Center Services NC II', 'Plumbing NC II', 'Hilot (Wellness Massage) NC II', 'Tile Setting NC II'} | C7: ['INFORMATION AND COMMUNICATION TECHNOLOGY (ICT) SECTOR', 'CONSTRUCTION SECTOR', 'HEALTH, SOCIAL, AND OTHER COMMUNITY DEVELOPMENT SERVICES SECTOR', 'CONSTRUCTION SECTOR'] | D7: CONSTRUCTION SECTOR | E7: {=IFERROR( _xlfn.XLOOKUP(TRUE, EXACT(Table4[[#This Row],[Institution]], 'Top Centers - NCR'!B:B), 'Top Centers - NCR'!E:E ), _xlfn.XLOOKUP(TRUE, EXACT(Table4[[#This Row],[Institution]], 'Top Centers - 4A'!B:B), 'Top Centers - 4A'!E:E ) )} -> 1917
A8: UNO CAREGIVER AND DOMESTIC MNGT TRAINING, INC. | B8: {'Housekeeping NC II', 'Trainers Methodology Level I', 'Domestic Work NC II', 'Events Management Services NC III', 'Bartending NC II', 'Barista NC II', 'Bread and Pastry Production NC II', 'Health Care Services NC II', 'Housekeeping NC III', 'Caregiving NC II', 'Caregiving (Elderly) NC II', 'Food and Beverage Services NC II', 'Food and Beverage Services NC III'} | C8: ['TOURISM SECTOR', 'TVET SECTOR', 'HEALTH, SOCIAL, AND OTHER COMMUNITY DEVELOPMENT SERVICES SECTOR', 'TOURISM SECTOR', 'TOURISM SECTOR', 'TOURISM SECTOR', 'TOURISM SECTOR', 'HEALTH, SOCIAL, AND OTHER COMMUNITY DEVELOPMENT SERVICES SECTOR', 'TOURISM SECTOR', 'HEALTH, SOCIAL, AND OTHER COMMUNITY DEVELOPMENT SERVICES SECTOR', 'HEALTH, SOCIAL, AND OTHER COMMUNITY DEVELOPMENT SERVICES SECTOR', 'TOURISM SECTOR', 'TOURISM SECTOR'] | D8: TOURISM SECTOR | E8: {=IFERROR( _xlfn.XLOOKUP(TRUE, EXACT(Table4[[#This Row],[Institution]], 'Top Centers - NCR'!B:B), 'Top Centers - NCR'!E:E ), _xlfn.XLOOKUP(TRUE, EXACT(Table4[[#This Row],[Institution]], 'Top Centers - 4A'!B:B), 'Top Centers - 4A'!E:E ) )} -> 1703
A9: REGIONAL TRAINING CENTER - NCR | B9: {'Mechatronics Servicing NC II', 'Visual Graphic Design NC III', 'Trainers Methodology Level I', 'PV Systems Installation NC II', 'Shielded Metal Arc Welding (SMAW) NC I', 'Shielded Metal Arc Welding (SMAW) NC II', 'RAC Servicing (DomRAC) NC II', "Ship's Catering Services NC I", 'Commercial Air-conditioning Installation and Servicing NC III', 'Trainers Methodology Level II', 'Shielded Metal Arc Welding (SMAW) NC III', 'Mechatronics Servicing NC III'} | C9: ['ELECTRICAL & ELECTRONICS SECTOR', 'INFORMATION AND COMMUNICATION TECHNOLOGY (ICT) SECTOR', 'TVET SECTOR', 'CONSTRUCTION SECTOR', 'METALS AND ENGINEERING SECTOR', 'METALS AND ENGINEERING SECTOR', 'HEATING, VENTILATION, AIR CONDITIONING AND REFRIGERATION', 'MARITIME SECTOR', 'HEATING, VENTILATION, AIR CONDITIONING AND REFRIGERATION', 'TVET SECTOR', 'METALS AND ENGINEERING SECTOR', 'ELECTRICAL & ELECTRONICS SECTOR'] | D9: METALS AND ENGINEERING SECTOR | E9: {=IFERROR( _xlfn.XLOOKUP(TRUE, EXACT(Table4[[#This Row],[Institution]], 'Top Centers - NCR'!B:B), 'Top Centers - NCR'!E:E ), _xlfn.XLOOKUP(TRUE, EXACT(Table4[[#This Row],[Institution]], 'Top Centers - 4A'!B:B), 'Top Centers - 4A'!E:E ) )} -> 1438
A10: Colegio de Santo Cristo De Burgos Corporation | B10: {'Housekeeping NC II', 'Trainers Methodology Level I', 'Driving NC II', 'Bread and Pastry Production NC II', 'Food and Beverage Services NC II'} | C10: ['TOURISM SECTOR', 'TVET SECTOR', 'AUTOMOTIVE AND LAND TRANSPORT SECTOR', 'TOURISM SECTOR', 'TOURISM SECTOR'] | D10: TOURISM SECTOR | E10: {=IFERROR( _xlfn.XLOOKUP(TRUE, EXACT(Table4[[#This Row],[Institution]], 'Top Centers - NCR'!B:B), 'Top Centers - NCR'!E:E ), _xlfn.XLOOKUP(TRUE, EXACT(Table4[[#This Row],[Institution]], 'Top Centers - 4A'!B:B), 'Top Centers - 4A'!E:E ) )} -> 1187
A11: PSAA INTERNATIONAL ACADEMY INC. | B11: {'Housekeeping NC II', 'Trainers Methodology Level I', 'Bookkeeping NC III', 'Domestic Work NC II', 'Events Management Services NC III', 'Bartending NC II', 'Cookery NC II', 'Bread and Pastry Production NC II', 'Barista NC II', 'Health Care Services NC II', 'Front Office Services NC II', 'Caregiving NC II', 'Tourism Promotion Services NC II', 'Caregiving (Elderly) NC II', 'Travel Services NC II', 'Food and Beverage Services NC II'} | C11: ['TOURISM SECTOR', 'TVET SECTOR', 'HEALTH, SOCIAL, AND OTHER COMMUNITY DEVELOPMENT SERVICES SECTOR', 'HEALTH, SOCIAL, AND OTHER COMMUNITY DEVELOPMENT SERVICES SECTOR', 'TOURISM SECTOR', 'TOURISM SECTOR', 'TOURISM SECTOR', 'TOURISM SECTOR', 'TOURISM SECTOR', 'HEALTH, SOCIAL, AND OTHER COMMUNITY DEVELOPMENT SERVICES SECTOR', 'TOURISM SECTOR', 'HEALTH, SOCIAL, AND OTHER COMMUNITY DEVELOPMENT SERVICES SECTOR', 'TOURISM SECTOR', 'HEALTH, SOCIAL, AND OTHER COMMUNITY DEVELOPMENT SERVICES SECTOR', 'TOURISM SECTOR', 'TOURISM SECTOR'] | D11: TOURISM SECTOR | E11: {=IFERROR( _xlfn.XLOOKUP(TRUE, EXACT(Table4[[#This Row],[Institution]], 'Top Centers - NCR'!B:B), 'Top Centers - NCR'!E:E ), _xlfn.XLOOKUP(TRUE, EXACT(Table4[[#This Row],[Institution]], 'Top Centers - 4A'!B:B), 'Top Centers - 4A'!E:E ) )} -> 1169
A12: MILESTONE TECHNOLOGICAL INSTITUTE, INC. | B12: {'Mechatronics Servicing NC II', 'Events Management Services NC III', 'Programming (Java) NC III', 'Bread and Pastry Production NC II', 'Hilot (Wellness Massage) NC II'} | C12: ['ELECTRICAL & ELECTRONICS SECTOR', 'TOURISM SECTOR', 'INFORMATION AND COMMUNICATION TECHNOLOGY (ICT) SECTOR', 'TOURISM SECTOR', 'HEALTH, SOCIAL, AND OTHER COMMUNITY DEVELOPMENT SERVICES SECTOR'] | D12: TOURISM SECTOR | E12: {=IFERROR( _xlfn.XLOOKUP(TRUE, EXACT(Table4[[#This Row],[Institution]], 'Top Centers - NCR'!B:B), 'Top Centers - NCR'!E:E ), _xlfn.XLOOKUP(TRUE, EXACT(Table4[[#This Row],[Institution]], 'Top Centers - 4A'!B:B), 'Top Centers - 4A'!E:E ) )} -> 970
A13: MECHATRONICS TECHNOLOGIES CORP. | B13: {'Mechatronics Servicing NC II', 'Electrical Installation and Maintenance NC IV', 'PV Systems Installation NC II', 'Instrumentation and Control Servicing NC II', 'RAC Servicing (DomRAC) NC II', 'Electrical Installation and Maintenance NC III', 'Mechatronics Servicing NC III', 'Mechatronics Servicing NC IV', 'Electrical Installation and Maintenance NC II'} | C13: ['ELECTRICAL & ELECTRONICS SECTOR', 'ELECTRICAL & ELECTRONICS SECTOR', 'CONSTRUCTION SECTOR', 'ELECTRICAL & ELECTRONICS SECTOR', 'HEATING, VENTILATION, AIR CONDITIONING AND REFRIGERATION', 'ELECTRICAL & ELECTRONICS SECTOR', 'ELECTRICAL & ELECTRONICS SECTOR', 'ELECTRICAL & ELECTRONICS SECTOR', 'ELECTRICAL & ELECTRONICS SECTOR'] | D13: ELECTRICAL & ELECTRONICS SECTOR | E13: {=IFERROR( _xlfn.XLOOKUP(TRUE, EXACT(Table4[[#This Row],[Institution]], 'Top Centers - NCR'!B:B), 'Top Centers - NCR'!E:E ), _xlfn.XLOOKUP(TRUE, EXACT(Table4[[#This Row],[Institution]], 'Top Centers - 4A'!B:B), 'Top Centers - 4A'!E:E ) )} -> 957
A14: Regional Training Center - CALABARZON | B14: {'Mechatronics Servicing NC II', 'Bookkeeping NC III', 'PV Systems Installation NC II', 'Shielded Metal Arc Welding (SMAW) NC I', 'Trainers Methodology Level I', 'Driving NC II', 'Pipefitting (Metallic) NC II', 'Gas Metal Arc Welding (GMAW) NC I', 'Electronic Products Assembly and Servicing NC II', 'Bread and Pastry Production NC II', 'Electrical Installation and Maintenance NC III', 'Gas Tungsten Arc Welding (GTAW) NC II', 'Plumbing NC I', 'Shielded Metal Arc Welding (SMAW) NC III', 'Construction Painting NC II', 'Electrical Installation and Maintenance NC II', 'Organic Agriculture Production NC II', 'Automotive Servicing NC I'} | C14: ['ELECTRICAL & ELECTRONICS SECTOR', 'HEALTH, SOCIAL, AND OTHER COMMUNITY DEVELOPMENT SERVICES SECTOR', 'CONSTRUCTION SECTOR', 'METALS AND ENGINEERING SECTOR', 'TVET SECTOR', 'AUTOMOTIVE AND LAND TRANSPORT SECTOR', 'CONSTRUCTION SECTOR', 'METALS AND ENGINEERING SECTOR', 'ELECTRICAL & ELECTRONICS SECTOR', 'TOURISM SECTOR', 'ELECTRICAL & ELECTRONICS SECTOR', 'METALS AND ENGINEERING SECTOR', 'CONSTRUCTION SECTOR', 'METALS AND ENGINEERING SECTOR', 'CONSTRUCTION SECTOR', 'ELECTRICAL & ELECTRONICS SECTOR', 'AGRICULTURE, FORESTRY AND FISHERY SECTOR', 'AUTOMOTIVE AND LAND TRANSPORT SECTOR'] | D14: CONSTRUCTION SECTOR | E14: {=IFERROR( _xlfn.XLOOKUP(TRUE, EXACT(Table4[[#This Row],[Institution]], 'Top Centers - NCR'!B:B), 'Top Centers - NCR'!E:E ), _xlfn.XLOOKUP(TRUE, EXACT(Table4[[#This Row],[Institution]], 'Top Centers - 4A'!B:B), 'Top Centers - 4A'!E:E ) )} -> 871
A15: SOCIO INTER SKILLS TRAINING ACADEMY (SISTA) INC. | B15: {'Housekeeping NC II', 'Domestic Work NC II', 'Hilot (Wellness Massage) NC II', 'Caregiving (Elderly) NC II'} | C15: ['TOURISM SECTOR', 'HEALTH, SOCIAL, AND OTHER COMMUNITY DEVELOPMENT SERVICES SECTOR', 'HEALTH, SOCIAL, AND OTHER COMMUNITY DEVELOPMENT SERVICES SECTOR', 'HEALTH, SOCIAL, AND OTHER COMMUNITY DEVELOPMENT SERVICES SECTOR'] | D15: HEALTH, SOCIAL, AND OTHER COMMUNITY DEVELOPMENT SERVICES SECTOR | E15: {=IFERROR( _xlfn.XLOOKUP(TRUE, EXACT(Table4[[#This Row],[Institution]], 'Top Centers - NCR'!B:B), 'Top Centers - NCR'!E:E ), _xlfn.XLOOKUP(TRUE, EXACT(Table4[[#This Row],[Institution]], 'Top Centers - 4A'!B:B), 'Top Centers - 4A'!E:E ) )} -> 841
A16: SOUTHERN LUZON TECHNOLOGICAL COLLEGE FOUNDATION, INC. | B16: {'Visual Graphic Design NC III', 'Trainers Methodology Level I', 'Programming (Java) NC III', 'Computer Systems Servicing NC II', 'Hilot (Wellness Massage) NC II', 'Web Development NC III', 'Contact Center Services NC II', 'Massage Therapy NC II'} | C16: ['INFORMATION AND COMMUNICATION TECHNOLOGY (ICT) SECTOR', 'TVET SECTOR', 'INFORMATION AND COMMUNICATION TECHNOLOGY (ICT) SECTOR', 'ELECTRICAL & ELECTRONICS SECTOR', 'HEALTH, SOCIAL, AND OTHER COMMUNITY DEVELOPMENT SERVICES SECTOR', 'INFORMATION AND COMMUNICATION TECHNOLOGY (ICT) SECTOR', 'INFORMATION AND COMMUNICATION TECHNOLOGY (ICT) SECTOR', 'HEALTH, SOCIAL, AND OTHER COMMUNITY DEVELOPMENT SERVICES SECTOR'] | D16: INFORMATION AND COMMUNICATION TECHNOLOGY (ICT) SECTOR | E16: {=IFERROR( _xlfn.XLOOKUP(TRUE, EXACT(Table4[[#This Row],[Institution]], 'Top Centers - NCR'!B:B), 'Top Centers - NCR'!E:E ), _xlfn.XLOOKUP(TRUE, EXACT(Table4[[#This Row],[Institution]], 'Top Centers - 4A'!B:B), 'Top Centers - 4A'!E:E ) )} -> 838
A17: RIGHT FOCUS TRAINING CENTER, INC. | B17: {'Housekeeping NC II', 'Domestic Work NC II', 'Shielded Metal Arc Welding (SMAW) NC I', 'Shielded Metal Arc Welding (SMAW) NC II', 'Bread and Pastry Production NC II', 'Caregiving NC II'} | C17: ['TOURISM SECTOR', 'HEALTH, SOCIAL, AND OTHER COMMUNITY DEVELOPMENT SERVICES SECTOR', 'METALS AND ENGINEERING SECTOR', 'METALS AND ENGINEERING SECTOR', 'TOURISM SECTOR', 'HEALTH, SOCIAL, AND OTHER COMMUNITY DEVELOPMENT SERVICES SECTOR'] | D17: METALS AND ENGINEERING SECTOR | E17: {=IFERROR( _xlfn.XLOOKUP(TRUE, EXACT(Table4[[#This Row],[Institution]], 'Top Centers - NCR'!B:B), 'Top Centers - NCR'!E:E ), _xlfn.XLOOKUP(TRUE, EXACT(Table4[[#This Row],[Institution]], 'Top Centers - 4A'!B:B), 'Top Centers - 4A'!E:E ) )} -> 764
... A29: Rizal Provincial Technical Education and Skills Development Center - Cainta | B29: {'Trainers Methodology Level I', 'Tile Setting NC II', 'Driving NC II', 'Electrical Installation and Maintenance NC III', 'Electronic Products Assembly and Servicing NC II', 'Health Care Services NC II', 'Dressmaking NC II', 'Electrical Installation and Maintenance NC II'} | C29: ['TVET SECTOR', 'CONSTRUCTION SECTOR', 'AUTOMOTIVE AND LAND TRANSPORT SECTOR', 'ELECTRICAL & ELECTRONICS SECTOR', 'ELECTRICAL & ELECTRONICS SECTOR', 'HEALTH, SOCIAL, AND OTHER COMMUNITY DEVELOPMENT SERVICES SECTOR', 'GARMENTS SECTOR', 'ELECTRICAL & ELECTRONICS SECTOR'] | D29: ELECTRICAL & ELECTRONICS SECTOR | E29: {=IFERROR( _xlfn.XLOOKUP(TRUE, EXACT(Table4[[#This Row],[Institution]], 'Top Centers - NCR'!B:B), 'Top Centers - NCR'!E:E ), _xlfn.XLOOKUP(TRUE, EXACT(Table4[[#This Row],[Institution]], 'Top Centers - 4A'!B:B), 'Top Centers - 4A'!E:E ) )} -> 293
D32: =COUNTIF(Table4[Specialized Sector], "TOURISM SECTOR") -> 14

Sheet Construction - Overview
A1: Construction Trades: Demand by Qualification
A2: Built-environment programs only. Two businesses shown: Training (Enrolled) vs Assessment (Certified).
A4: Qualification | B4: Centres | C4: Enrolled | D4: Graduates | E4: Assessed | F4: Certified
A5: Shielded Metal Arc Welding (SMAW) NC I | B5: 138 | C5: 8097 | D5: 8402 | E5: 9459 | F5: 9302
A6: Shielded Metal Arc Welding (SMAW) NC II | B6: 138 | C6: 7313 | D6: 7453 | E6: 14948 | F6: 14734
A7: Electrical Installation and Maintenance NC II | B7: 106 | C7: 4851 | D7: 5010 | E7: 17409 | F7: 16865
A8: Heavy Equipment Operation (Forklift) NC II | B8: 31 | C8: 2142 | D8: 2007 | E8: 9271 | F8: 8833
A9: Tile Setting NC II | B9: 13 | C9: 1564 | D9: 1453 | E9: 1031 | F9: 1025
A10: Heavy Equipment Operation (Hydraulic Excavator) NC II | B10: 20 | C10: 1494 | D10: 1347 | E10: 2457 | F10: 2360
A11: Carpentry NC II | B11: 21 | C11: 1271 | D11: 1242 | E11: 1624 | F11: 1619
A12: Shielded Metal Arc Welding (SMAW) NC III | B12: 14 | C12: 670 | D12: 753 | E12: 560 | F12: 554
A13: Scaffolding Works (Supported Type Scaffold) NC II | B13: 27 | C13: 596 | D13: 557 | E13: 5920 | F13: 5729
A14: Electrical Installation and Maintenance NC III | B14: 17 | C14: 494 | D14: 504 | E14: 703 | F14: 683
A15: Masonry NC II | B15: 14 | C15: 365 | D15: 402 | E15: 815 | F15: 812
A16: Gas Metal Arc Welding (GMAW) NC II | B16: 16 | C16: 358 | D16: 302 | E16: 897 | F16: 883
... A47: System Formworks Installation NC II | B47: 1 | C47: 0 | D47: 0 | E47: 370 | F47: 370
A48: TOTAL (construction) | B48: =SUM(B5:B47) -> 678 | C48: =SUM(C5:C47) -> 30586 | D48: =SUM(D5:D47) -> 30680 | E48: =SUM(E5:E47) -> 74451 | F48: =SUM(F5:F47) -> 72490
A50: Construction enrolment by region
A51: Region | B51: Centres | C51: Enrolled | D51: Certified
A52: 4A | B52: 163 | C52: 18427 | D52: 34838
A53: NCR | B53: 110 | C53: 12159 | D53: 37652

Sheet Construction - Top Centres
A1: Top Construction-Trade Centres
A2: Ranked by construction Enrolled. Cert col reveals assessment-led players (high Cert, low Enrolled).
A4: Rank | B4: Institution | C4: Region | D4: Quals | E4: Enrolled | F4: Graduates | G4: Assessed | H4: Certified
A5: 1 | B5: PHILIPPINE INDUSTRIAL EQUIPMENT TECHNICAL INSTITUTE, INC. | C5: 4A | D5: 2 | E5: 1135 | F5: 1110 | G5: 0 | H5: 0
A6: 2 | B6: ADAO LEARNING INSTITUTE INC. | C6: 4A | D6: 2 | E6: 909 | F6: 853 | G6: 766 | H6: 753
A7: 3 | B7: LUCENA TECHNOLOGICAL INSTITUTE INCORPORATED | C7: 4A | D7: 3 | E7: 848 | F7: 1102 | G7: 805 | H7: 788
A8: 4 | B8: SP CASTRO CONSTRUCTION SERVICES | C8: 4A | D8: 4 | E8: 825 | F8: 773 | G8: 0 | H8: 0
A9: 5 | B9: TECHVOC SKILLS INC. | C9: NCR | D9: 2 | E9: 804 | F9: 617 | G9: 540 | H9: 535
A10: 6 | B10: QTEK TRAINING AND ASSESSMENT CENTER INC. | C10: NCR | D10: 4 | E10: 723 | F10: 644 | G10: 492 | H10: 487
A11: 7 | B11: PHILIPPINE SCHOOL FOR TECHNOLOGY DEVELOPMENT AND INNOVATION INC. | C11: NCR | D11: 4 | E11: 683 | F11: 636 | G11: 530 | H11: 529
A12: 8 | B12: SYNERGY ASSESSMENT & TRAINING CENTER | C12: 4A | D12: 3 | E12: 637 | F12: 681 | G12: 0 | H12: 0
A13: 9 | B13: TESDA Women's Center | C13: NCR | D13: 6 | E13: 619 | F13: 622 | G13: 0 | H13: 0
A14: 10 | B14: AUTOZONE DRIVING SCHOOLINC. | C14: 4A | D14: 3 | E14: 618 | F14: 548 | G14: 0 | H14: 0
A15: 11 | B15: KAMELO MANPOWER SKILLS DEVELOPMENT CENTER INC. | C15: 4A | D15: 4 | E15: 595 | F15: 737 | G15: 0 | H15: 0
A16: 12 | B16: Skillful Training and Assessment Center Inc. | C16: 4A | D16: 3 | E16: 594 | F16: 715 | G16: 0 | H16: 0
... A44: 40 | B44: MEPF TECHNOLOGICAL INSTITUTE (MTI) INC. | C44: NCR | D44: 3 | E44: 244 | F44: 217 | G44: 450 | H44: 442

Sheet Ms. Coloma's List
A1: Name Given by Ms. Maria Coloma | B1: Can be Found? | C1: Name in the Dataset | D1: Is in NCR or 4A? | E1: Enrolled | F1: Graduated | G1: Assessed | H1: Certified | I1: Trainers
A2: UNC Naga (Hospitality Management, Tourism, Information Technology) | B2: N | D2: N
A3: -NCF Naga (Information Technology, Computer Programming, Business Administration) | B3: Y | C3: NAGA COLLEGE FOUNDATION, INC. | D3: N | E3: 0 | F3: 57 | G3: 0 | H3: 0 | I3: 0
A4: CSPC Camarines Sur (Automotive Servicing, Electrical Installation and Maintenance, Welding) | B4: N | D4: N
A5: Letran Calamba (Hospitality Management, Culinary Arts, Business Administration) | B5: N | D5: Y
A6: NU Laguna (Information Technology, Tourism, Hospitality Management) | B6: N | C6: National University in Manila is in the database, but not Laguna | D6: Y
A7: EAC Dasmariñas (Healthcare Services, Hospitality Management, Business Administration) | B7: Y | C7: Emilio Aguinaldo Educational Corporation Doing Business Under The Name And Style Of Aguinaldo International School And Emilio Aguinaldo College (formerly: Emilio Aguinaldo College) | D7: Y | E7: 123 | F7: 80 | G7: 0 | H7: 0 | I7: 4
A8: Mapúa Malayan Colleges Laguna (Engineering Technology, Information Technology, Industrial Technology) | B8: Y | C8: MALAYAN COLLEGES LAGUNA, INC. LED BY A MAPUA SCHOOL OF ENGINEERING | D8: Y | E8: 12 | F8: 0 | G8: 0 | H8: 0 | I8: 1
A9: Trimex Colleges (Automotive Servicing, Electrical Installation, Computer Systems Servicing) | B9: Y | C9: Trimex Colleges, Inc. / TRIMEX COLLEGES INC. | D9: Y | E9: 273 | F9: 195 | G9: 128 | H9: 126 | I9: 8
A10: PHINMA Union College (Hospitality Management, Tourism, Business Administration) | B10: N | D10: Y
A11: PHINMA Rizal College (Information Technology, Business Administration, Education) | B11: N | D11: Y
A12: Dualtech Training Center (Mechatronics, Industrial Automation, Electrical Technology) | B12: N | D12: Y
A13: LPU Batangas (Hospitality Management, Culinary Arts, Tourism) | B13: Y | C13: LYCEUM OF THE PHILIPPINES UNIVERSITY - BATANGAS, INC. | D13: Y | E13: 0 | F13: 0 | G13: 2650 | H13: 2626 | I13: 0
A14: San Pablo Colleges (Healthcare Services, Information Technology, Business Administration) | B14: N | D14: Y
A15: St. Benilde Calamba (Hospitality Management, Culinary Arts, Tourism) | B15: Y | C15: ST. BENILDE COLLEGE OF SCIENCE AND TECHNOLOGY AND ASSESSMENT CENTER (SILANG CAVITE), INC. | D15: Y | E15: 135 | F15: 109 | G15: 0 | H15: 0 | I15: 4
A16: Pamantasan ng Cabuyao (Information Technology, Engineering Technology, Business Administration) | B16: Y | C16: CABUYAO INTEGRATED NATIONAL HIGH SCHOOL | D16: Y | E16: 142 | F16: 112 | G16: 744 | H16: 682 | I16: 6
A17: City College of Calamba (Computer Systems Servicing, Electrical Installation, Business Administration) | B17: N | D17: Y
A18: Romblon State University (Agricultural Technology, Fisheries Technology, Information Technology) | B18: N | D18: N
A19: Regional Training Center Calabarzon (Automotive Servicing, Welding, Electrical Installation) | B19: Y | C19: Regional Training Center - CALABARZON | D19: Y | E19: 715 | F19: 871 | G19: 0 | H19: 0 | I19: 22
A20: Southern Luzon Technological College Foundation (Industrial Technology, Information Technology, Automotive Servicing) | B20: Y | C20: This one is the weirdest because it had four names and also three centers. They are in Pilar, Sorsogon; Pio Duran, Albay; and Pasig City, NCR. | D20: N | E20: =SUM(E21:E24) -> 3522 | F20: =SUM(F21:F24) -> 4673 | G20: =SUM(G21:G24) -> 6537 | H20: =SUM(H21:H24) -> 5937 | I20: =SUM(I21:I24) -> 62
B21: Sorsogon | C21: SOUTHERN LUZON TECHNOLOGICAL COLLEGE FOUNDATION PILAR INC. | E21: 0 | F21: 0 | G21: 150 | H21: 150 | I21: 0
B22: Sorsogon | C22: Southern Luzon Technological College Foundation Pilar, Inc. | E22: 96 | F22: 95 | G22: 0 | H22: 0 | I22: 4
B23: Albay | C23: SOUTHERN LUZON TECHNOLOGICAL COLLEGE FOUNDATION PIODURAN INCORPORATED | E23: 300 | F23: 300 | G23: 0 | H23: 0 | I23: 4
B24: NCR | C24: SOUTHERN LUZON TECHNOLOGICAL COLLEGE FOUNDATION, INC. | E24: 3126 | F24: 4278 | G24: 6387 | H24: 5787 | I24: 54

Sheet Clean Data
A1: Institution Name | B1: City | C1: Province | D1: Region | E1: Reg | F1: Qualification | G1: IsConstruction | H1: Is_Development | I1: Is_Assessment | J1: Trainer Count | K1: Enrolled | L1: Graduates | M1: Number of Accredited Ass Qual | N1: Assessed | O1: Certified
A2: PHILIPPINE CALL CENTER INSTITUTE INC. | B2: Makati City | C2: PASMAK | D2: National Capital Region (NCR) | E2: NCR | F2: Computer Systems Servicing NC II | G2: =FALSE() -> FALSE | H2: 1 | I2: 0 | J2: 17 | K2: 2569 | L2: 2773 | M2: 0 | N2: 0 | O2: 0
A3: EAST AND WEST CENTER OF EXCELLENCE IN TRAINING CORPORATION | B3: Alaminos | C3: Laguna | D3: Region IVA - CALABARZON | E3: 4A | F3: Contact Center Services NC II | G3: =FALSE() -> FALSE | H3: 1 | I3: 0 | J3: 8 | K3: 1792 | L3: 1615 | M3: 0 | N3: 0 | O3: 0
A4: HYPER YOUNG INSTITUTE OF TECHNOLOGY INC. | B4: Pasig City | C4: PAMAMARISAN | D4: National Capital Region (NCR) | E4: NCR | F4: Computer Systems Servicing NC II | G4: =FALSE() -> FALSE | H4: 1 | I4: 1 | J4: 6 | K4: 1256 | L4: 1238 | M4: 1 | N4: 969 | O4: 908
A5: CARENET HEALTHCARE INSTITUTE INC. | B5: Makati City | C5: PASMAK | D5: National Capital Region (NCR) | E5: NCR | F5: Barista NC II | G5: =FALSE() -> FALSE | H5: 1 | I5: 1 | J5: 8 | K5: 1115 | L5: 1180 | M5: 1 | N5: 567 | O5: 556
A6: THE BIG FIVE TRAINING AND ASSESSMENT CENTER INC. | B6: San Pablo City | C6: Laguna | D6: Region IVA - CALABARZON | E6: 4A | F6: Bread and Pastry Production NC II | G6: =FALSE() -> FALSE | H6: 1 | I6: 1 | J6: 4 | K6: 1276 | L6: 1025 | M6: 1 | N6: 821 | O6: 821
A7: SOUTHERN INSTITUTE OF MARITIME STUDIES-MANILA INC. | B7: Ermita, City of Manila | C7: City of Manila | D7: National Capital Region (NCR) | E7: NCR | F7: Ship's Catering Services NC I | G7: =FALSE() -> FALSE | H7: 1 | I7: 0 | J7: 5 | K7: 1019 | L7: 1010 | M7: 0 | N7: 0 | O7: 0
A8: TECHVOC SKILLS INC. | B8: Sampaloc, City of Manila | C8: City of Manila | D8: National Capital Region (NCR) | E8: NCR | F8: Contact Center Services NC II | G8: =FALSE() -> FALSE | H8: 1 | I8: 0 | J8: 4 | K8: 858 | L8: 941 | M8: 0 | N8: 0 | O8: 0
A9: MINDTECH TRAINING & DEVELOPMENT INSTITUTE, INC. | B9: Pasig City | C9: PAMAMARISAN | D9: National Capital Region (NCR) | E9: NCR | F9: Computer Systems Servicing NC II | G9: =FALSE() -> FALSE | H9: 1 | I9: 0 | J9: 2 | K9: 764 | L9: 930 | M9: 0 | N9: 0 | O9: 0
A10: NATIONAL INSTITUTE FOR TECHNICAL AND VOCATIONAL CAREERS, INC. | B10: Quezon City | C10: Quezon City | D10: National Capital Region (NCR) | E10: NCR | F10: Barista NC II | G10: =FALSE() -> FALSE | H10: 1 | I10: 0 | J10: 5 | K10: 770 | L10: 860 | M10: 0 | N10: 0 | O10: 0
A11: RMC EAGLES TRAINING AND ASSESSMENT CENTER INC. | B11: Caloocan City | C11: CAMANAVA | D11: National Capital Region (NCR) | E11: NCR | F11: Driving NC II | G11: =FALSE() -> FALSE | H11: 1 | I11: 1 | J11: 3 | K11: 768 | L11: 811 | M11: 1 | N11: 673 | O11: 672
A12: CARENET HEALTHCARE INSTITUTE INC. | B12: Makati City | C12: PASMAK | D12: National Capital Region (NCR) | E12: NCR | F12: Hilot (Wellness Massage) NC II | G12: =FALSE() -> FALSE | H12: 1 | I12: 1 | J12: 7 | K12: 742 | L12: 765 | M12: 1 | N12: 337 | O12: 337
A13: TRIPLE K'S EAST CAPITOL KITCHEN CORP. DOING BUSINESS UNDER THE NAME AND STYLE OF SPICES AND HERBS TR | B13: Pasig City | C13: PAMAMARISAN | D13: National Capital Region (NCR) | E13: NCR | F13: Bread and Pastry Production NC II | G13: =FALSE() -> FALSE | H13: 1 | I13: 1 | J13: 3 | K13: 691 | L13: 727 | M13: 1 | N13: 496 | O13: 488
... A17: MINDTECH TRAINING & DEVELOPMENT INSTITUTE, INC. | B17: Pasig City | C17: PAMAMARISAN | D17: National Capital Region (NCR) | E17: NCR | F17: Events Management Services NC III | G17: =FALSE() -> FALSE | H17: 1 | I17: 0 | J17: 2 | K17: 644 | L17: 642 | M17: 0 | N17: 0 | O17: 0
A18: TECHVOC SKILLS INC. | B18: Sampaloc, City of Manila | C18: City of Manila | D18: National Capital Region (NCR) | E18: NCR | F18: Tile Setting NC II | G18: =TRUE() -> TRUE | H18: 1 | I18: 0 | J18: 5 | K18: 804 | L18: 617 | M18: 0 | N18: 0 | O18: 0
A19: UNO CAREGIVER AND DOMESTIC MNGT TRAINING, INC. | B19: Makati City | C19: PASMAK | D19: National Capital Region (NCR) | E19: NCR | F19: Domestic Work NC II | G19: =FALSE() -> FALSE | H19: 1 | I19: 1 | J19: 5 | K19: 600 | L19: 615 | M19: 1 | N19: 558 | O19: 558
A20: FAR EAST MARITIME FOUNDATION INC. | B20: Ermita, City of Manila | C20: City of Manila | D20: National Capital Region (NCR) | E20: NCR | F20: Ship's Catering Services NC I | G20: =FALSE() -> FALSE | H20: 1 | I20: 0 | J20: 3 | K20: 616 | L20: 614 | M20: 0 | N20: 0 | O20: 0
A21: CENTER FOR INTERNATIONAL INDUSTRIES COMPETENCE CORP. | B21: Quezon City | C21: Quezon City | D21: National Capital Region (NCR) | E21: NCR | F21: Contact Center Services NC II | G21: =FALSE() -> FALSE | H21: 1 | I21: 0 | J21: 4 | K21: 312 | L21: 599 | M21: 0 | N21: 0 | O21: 0
A22: LUCENA TECHNOLOGICAL INSTITUTE INCORPORATED | B22: Lucena City | C22: Quezon | D22: Region IVA - CALABARZON | E22: 4A | F22: Shielded Metal Arc Welding (SMAW) NC II | G22: =TRUE() -> TRUE | H22: 1 | I22: 1 | J22: 14 | K22: 434 | L22: 591 | M22: 1 | N22: 485 | O22: 470
A23: TELECALL INSTITUTE OF TECHNOLOGY INC. | B23: Cabuyao | C23: Laguna | D23: Region IVA - CALABARZON | E23: 4A | F23: Contact Center Services NC II | G23: =FALSE() -> FALSE | H23: 1 | I23: 0 | J23: 5 | K23: 522 | L23: 582 | M23: 0 | N23: 0 | O23: 0
A24: TRIPLE K'S EAST CAPITOL KITCHEN CORP. DOING BUSINESS UNDER THE NAME AND STYLE OF SPICES AND HERBS TR | B24: Pasig City | C24: PAMAMARISAN | D24: National Capital Region (NCR) | E24: NCR | F24: Cookery NC II | G24: =FALSE() -> FALSE | H24: 1 | I24: 1 | J24: 3 | K24: 458 | L24: 571 | M24: 1 | N24: 612 | O24: 612
A25: ASIA PACIFIC CAREGIVER & HEALTHCARE TRAINING CENTER, INC. | B25: Quezon City | C25: Quezon City | D25: National Capital Region (NCR) | E25: NCR | F25: Caregiving NC II | G25: =FALSE() -> FALSE | H25: 1 | I25: 1 | J25: 3 | K25: 738 | L25: 556 | M25: 1 | N25: 196 | O25: 196
A26: PHILIPPINE INDUSTRIAL EQUIPMENT TECHNICAL INSTITUTE, INC. | B26: City of Biñan | C26: Laguna | D26: Region IVA - CALABARZON | E26: 4A | F26: Heavy Equipment Operation (Hydraulic Excavator) NC II | G26: =TRUE() -> TRUE | H26: 1 | I26: 0 | J26: 3 | K26: 531 | L26: 554 | M26: 0 | N26: 0 | O26: 0
A27: SYLVRE AGRI-FARM & ASSESSMENT CENTER INC. | B27: Siniloan | C27: Laguna | D27: Region IVA - CALABARZON | E27: 4A | F27: Rice Machinery Operations NC II | G27: =FALSE() -> FALSE | H27: 1 | I27: 0 | J27: 6 | K27: 463 | L27: 551 | M27: 0 | N27: 0 | O27: 0
A28: B AND B ACADEMY FOR SKILLS TRAINING AND ASSESSMENT INC. | B28: Pasig City | C28: PAMAMARISAN | D28: National Capital Region (NCR) | E28: NCR | F28: Bread and Pastry Production NC II | G28: =FALSE() -> FALSE | H28: 1 | I28: 1 | J28: 2 | K28: 521 | L28: 538 | M28: 1 | N28: 361 | O28: 360
A29: PHILIPPINE INDUSTRIAL EQUIPMENT TECHNICAL INSTITUTE, INC. | B29: City of Biñan | C29: Laguna | D29: Region IVA - CALABARZON | E29: 4A | F29: Heavy Equipment Operation (Forklift) NC II | G29: =TRUE() -> TRUE | H29: 1 | I29: 0 | J29: 4 | K29: 504 | L29: 531 | M29: 0 | N29: 0 | O29: 0
A30: MUNTIPARLASTAPAT DISTRICT TRAINING AND ASSESSMENT CENTER | B30: Taguig City | C30: MUNTIPARLASTAPAT | D30: National Capital Region (NCR) | E30: NCR | F30: Driving NC II | G30: =FALSE() -> FALSE | H30: 1 | I30: 1 | J30: 2 | K30: 292 | L30: 524 | M30: 1 | N30: 322 | O30: 300
A31: RMC EAGLES TRAINING AND ASSESSMENT CENTER INC. | B31: Caloocan City | C31: CAMANAVA | D31: National Capital Region (NCR) | E31: NCR | F31: Events Management Services NC III | G31: =FALSE() -> FALSE | H31: 1 | I31: 1 | J31: 3 | K31: 609 | L31: 507 | M31: 1 | N31: 113 | O31: 112
A32: SLDM COLLEGES OF QUEZON CITY, INC. | B32: Quezon City | C32: Quezon City | D32: National Capital Region (NCR) | E32: NCR | F32: Bread and Pastry Production NC II | G32: =FALSE() -> FALSE | H32: 1 | I32: 0 | J32: 2 | K32: 453 | L32: 505 | M32: 0 | N32: 0 | O32: 0
A33: B AND B ACADEMY FOR SKILLS TRAINING AND ASSESSMENT INC. | B33: Pasig City | C33: PAMAMARISAN | D33: National Capital Region (NCR) | E33: NCR | F33: Tourism Promotion Services NC II | G33: =FALSE() -> FALSE | H33: 1 | I33: 1 | J33: 1 | K33: 220 | L33: 499 | M33: 1 | N33: 323 | O33: 316
A34: Colegio de Santo Cristo De Burgos Corporation | B34: Sariaya | C34: Quezon | D34: Region IVA - CALABARZON | E34: 4A | F34: Bread and Pastry Production NC II | G34: =FALSE() -> FALSE | H34: 1 | I34: 0 | J34: 5 | K34: 514 | L34: 499 | M34: 0 | N34: 0 | O34: 0
A35: DIVINE MERCY INTERNATIONAL INSTITUTE INC. | B35: Silang | C35: Cavite | D35: Region IVA - CALABARZON | E35: 4A | F35: Barista NC II | G35: =FALSE() -> FALSE | H35: 1 | I35: 0 | J35: 4 | K35: 469 | L35: 497 | M35: 0 | N35: 0 | O35: 0
A36: ADAO LEARNING INSTITUTE INC. | B36: Kalayaan | C36: Laguna | D36: Region IVA - CALABARZON | E36: 4A | F36: Electrical Installation and Maintenance NC II | G36: =TRUE() -> TRUE | H36: 1 | I36: 1 | J36: 5 | K36: 508 | L36: 481 | M36: 1 | N36: 595 | O36: 585
A37: High Vision Training Center, Inc. | B37: Quezon City | C37: Quezon City | D37: National Capital Region (NCR) | E37: NCR | F37: Domestic Work NC II | G37: =FALSE() -> FALSE | H37: 1 | I37: 0 | J37: 4 | K37: 447 | L37: 480 | M37: 0 | N37: 0 | O37: 0
A38: LE PRIME INSTITUTE OF TECHNOLOGY INC. | B38: Lipa City | C38: Batangas | D38: Region IVA - CALABARZON | E38: 4A | F38: Events Management Services NC III | G38: =FALSE() -> FALSE | H38: 1 | I38: 1 | J38: 2 | K38: 401 | L38: 479 | M38: 1 | N38: 797 | O38: 773
A39: ASIANTOUCH INTERNATIONAL TRAINING INSTITUTE, INC. | B39: Marikina City | C39: PAMAMARISAN | D39: National Capital Region (NCR) | E39: NCR | F39: Bread and Pastry Production NC II | G39: =FALSE() -> FALSE | H39: 1 | I39: 1 | J39: 3 | K39: 590 | L39: 478 | M39: 1 | N39: 316 | O39: 316
A40: HORIZONS INSTITUTE OF TECHNOLOGY CORPORATION | B40: Caloocan City | C40: CAMANAVA | D40: National Capital Region (NCR) | E40: NCR | F40: Bread and Pastry Production NC II | G40: =FALSE() -> FALSE | H40: 1 | I40: 1 | J40: 2 | K40: 406 | L40: 462 | M40: 1 | N40: 252 | O40: 252
A41: ASIAN SCHOOL OF ADVANCED TECHNOLOGY INC. | B41: Bacoor City | C41: Cavite | D41: Region IVA - CALABARZON | E41: 4A | F41: Caregiving (Elderly) NC II | G41: =FALSE() -> FALSE | H41: 1 | I41: 0 | J41: 3 | K41: 401 | L41: 462 | M41: 0 | N41: 0 | O41: 0
A42: A1VENTURES TECHNICAL AND VOCATIONAL ACADEMY INC. | B42: Quezon City | C42: Quezon City | D42: National Capital Region (NCR) | E42: NCR | F42: Computer Systems Servicing NC II | G42: =FALSE() -> FALSE | H42: 1 | I42: 0 | J42: 4 | K42: 471 | L42: 461 | M42: 0 | N42: 0 | O42: 0
A43: D' RISING SUN TRAINING CENTER PHILS. INC. | B43: Marikina City | C43: PAMAMARISAN | D43: National Capital Region (NCR) | E43: NCR | F43: Slaughtering Operations (Swine) NC II | G43: =FALSE() -> FALSE | H43: 1 | I43: 0 | J43: 3 | K43: 417 | L43: 458 | M43: 0 | N43: 0 | O43: 0
A44: Computer Site Ins. Inc. | B44: San Pedro | C44: Laguna | D44: Region IVA - CALABARZON | E44: 4A | F44: Contact Center Services NC II | G44: =FALSE() -> FALSE | H44: 1 | I44: 0 | J44: 3 | K44: 557 | L44: 457 | M44: 0 | N44: 0 | O44: 0
A45: A1VENTURES TECHNICAL AND VOCATIONAL ACADEMY INC. | B45: Quezon City | C45: Quezon City | D45: National Capital Region (NCR) | E45: NCR | F45: Events Management Services NC III | G45: =FALSE() -> FALSE | H45: 1 | I45: 0 | J45: 2 | K45: 550 | L45: 452 | M45: 0 | N45: 0 | O45: 0
A46: MAGSAYSAY CENTER FOR HOSPITALITY AND CULINARY ARTS, INC. | B46: Mandaluyong City | C46: PAMAMARISAN | D46: National Capital Region (NCR) | E46: NCR | F46: Cookery NC II | G46: =FALSE() -> FALSE | H46: 1 | I46: 0 | J46: 1 | K46: 329 | L46: 449 | M46: 0 | N46: 0 | O46: 0
A47: Colegio de Santo Cristo De Burgos Corporation | B47: Sariaya | C47: Quezon | D47: Region IVA - CALABARZON | E47: 4A | F47: Driving NC II | G47: =FALSE() -> FALSE | H47: 1 | I47: 0 | J47: 3 | K47: 435 | L47: 448 | M47: 0 | N47: 0 | O47: 0
A48: MECHATRONICS TECHNOLOGIES CORP. | B48: Quezon City | C48: Quezon City | D48: National Capital Region (NCR) | E48: NCR | F48: Mechatronics Servicing NC II | G48: =FALSE() -> FALSE | H48: 1 | I48: 1 | J48: 3 | K48: 525 | L48: 445 | M48: 1 | N48: 461 | O48: 449
... A69: DIVINE MERCY INTERNATIONAL INSTITUTE INC. | B69: Silang | C69: Cavite | D69: Region IVA - CALABARZON | E69: 4A | F69: Bread and Pastry Production NC II | G69: =FALSE() -> FALSE | H69: 1 | I69: 0 | J69: 9 | K69: 459 | L69: 379 | M69: 0 | N69: 0 | O69: 0
A70: ADAO LEARNING INSTITUTE INC. | B70: Kalayaan | C70: Laguna | D70: Region IVA - CALABARZON | E70: 4A | F70: Carpentry NC II | G70: =TRUE() -> TRUE | H70: 1 | I70: 1 | J70: 4 | K70: 401 | L70: 372 | M70: 1 | N70: 171 | O70: 168
A71: RIGHT FOCUS TRAINING CENTER, INC. | B71: Santa Cruz, City of Manila | C71: City of Manila | D71: National Capital Region (NCR) | E71: NCR | F71: Domestic Work NC II | G71: =FALSE() -> FALSE | H71: 1 | I71: 0 | J71: 1 | K71: 392 | L71: 370 | M71: 0 | N71: 0 | O71: 0
A72: TELECALL INSTITUTE OF TECHNOLOGY INC. | B72: Pasig City | C72: PAMAMARISAN | D72: National Capital Region (NCR) | E72: NCR | F72: Computer Systems Servicing NC II | G72: =FALSE() -> FALSE | H72: 1 | I72: 0 | J72: 5 | K72: 427 | L72: 367 | M72: 0 | N72: 0 | O72: 0
A73: GENUINE SERVICE PRESIDENT TRAINING AND ASSESSMENT CENTER INC. | B73: Lucena City | C73: Quezon | D73: Region IVA - CALABARZON | E73: 4A | F73: Bread and Pastry Production NC II | G73: =FALSE() -> FALSE | H73: 1 | I73: 1 | J73: 4 | K73: 365 | L73: 364 | M73: 1 | N73: 313 | O73: 312
A74: OPTIMUM SKILLS SOURCE INSTITUTE CORP. | B74: San Juan City | C74: PAMAMARISAN | D74: National Capital Region (NCR) | E74: NCR | F74: Contact Center Services NC II | G74: =FALSE() -> FALSE | H74: 1 | I74: 0 | J74: 2 | K74: 365 | L74: 362 | M74: 0 | N74: 0 | O74: 0
A75: SOCIO INTER SKILLS TRAINING ACADEMY (SISTA) INC. | B75: Makati City | C75: PASMAK | D75: National Capital Region (NCR) | E75: NCR | F75: Hilot (Wellness Massage) NC II | G75: =FALSE() -> FALSE | H75: 1 | I75: 1 | J75: 4 | K75: 420 | L75: 360 | M75: 1 | N75: 223 | O75: 223
A76: NATIONAL INSTITUTE FOR TECHNICAL AND VOCATIONAL CAREERS, INC. | B76: Quezon City | C76: Quezon City | D76: National Capital Region (NCR) | E76: NCR | F76: Contact Center Services NC II | G76: =FALSE() -> FALSE | H76: 1 | I76: 0 | J76: 4 | K76: 387 | L76: 360 | M76: 0 | N76: 0 | O76: 0
A77: TECHVOC SKILLS INC. | B77: Sampaloc, City of Manila | C77: City of Manila | D77: National Capital Region (NCR) | E77: NCR | F77: Hilot (Wellness Massage) NC II | G77: =FALSE() -> FALSE | H77: 1 | I77: 0 | J77: 3 | K77: 366 | L77: 359 | M77: 0 | N77: 0 | O77: 0
A78: THE MOLINO INSTITUTE OF SCIENCE AND TECHNOLOGY INC. | B78: Candelaria | C78: Quezon | D78: Region IVA - CALABARZON | E78: 4A | F78: Bread and Pastry Production NC II | G78: =FALSE() -> FALSE | H78: 1 | I78: 1 | J78: 5 | K78: 465 | L78: 358 | M78: 1 | N78: 270 | O78: 263
A79: ST. MARTIN SCHOOL OF ADVANCED TECHNOLOGY AND CAREGIVER INC. | B79: City of Dasmariñas | C79: Cavite | D79: Region IVA - CALABARZON | E79: 4A | F79: Caregiving NC II | G79: =FALSE() -> FALSE | H79: 1 | I79: 0 | J79: 5 | K79: 328 | L79: 357 | M79: 0 | N79: 0 | O79: 0
A80: HIGH PERFORMANCE INTERNATIONAL TRAINING CENTER AND TRADE TEST, INC. | B80: Paco, City of Manila | C80: City of Manila | D80: National Capital Region (NCR) | E80: NCR | F80: Domestic Work NC II | G80: =FALSE() -> FALSE | H80: 1 | I80: 0 | J80: 1 | K80: 354 | L80: 354 | M80: 0 | N80: 0 | O80: 0
A81: SYNERGY ASSESSMENT & TRAINING CENTER | B81: Malvar | C81: Batangas | D81: Region IVA - CALABARZON | E81: 4A | F81: Events Management Services NC III | G81: =FALSE() -> FALSE | H81: 1 | I81: 0 | J81: 2 | K81: 334 | L81: 353 | M81: 0 | N81: 0 | O81: 0
A82: POWER LINK CENTER FOR ADVANCED TECHNICAL SKILLS DEVELOPMENT INC. | B82: Malate, City of Manila | C82: City of Manila | D82: National Capital Region (NCR) | E82: NCR | F82: Cookery NC II | G82: =FALSE() -> FALSE | H82: 1 | I82: 0 | J82: 5 | K82: 455 | L82: 352 | M82: 0 | N82: 0 | O82: 0
... A97: TESDA Women's Center | B97: Taguig City | C97: MUNTIPARLASTAPAT | D97: National Capital Region (NCR) | E97: NCR | F97: Bookkeeping NC III | G97: =FALSE() -> FALSE | H97: 1 | I97: 0 | J97: 2 | K97: 310 | L97: 333 | M97: 0 | N97: 0 | O97: 0
A98: Laborlink Technical Institute Corporation | B98: Quezon City | C98: Quezon City | D98: National Capital Region (NCR) | E98: NCR | F98: Shielded Metal Arc Welding (SMAW) NC II | G98: =TRUE() -> TRUE | H98: 1 | I98: 0 | J98: 2 | K98: 224 | L98: 330 | M98: 0 | N98: 0 | O98: 0
A99: HUMAN RESOURCE DEVELOPMENT CENTER (HRDC) | B99: Taguig City | C99: MUNTIPARLASTAPAT | D99: National Capital Region (NCR) | E99: NCR | F99: Electrical Installation and Maintenance NC III | G99: =TRUE() -> TRUE | H99: 1 | I99: 0 | J99: 2 | K99: 329 | L99: 328 | M99: 0 | N99: 0 | O99: 0
A100: HEZEKIAH VOCATIONAL & TECHNOLOGICAL TRAINING INSTITUTE, (HVTTI) INC. | B100: Imus | C100: Cavite | D100: Region IVA - CALABARZON | E100: 4A | F100: Contact Center Services NC II | G100: =FALSE() -> FALSE | H100: 1 | I100: 0 | J100: 4 | K100: 384 | L100: 327 | M100: 0 | N100: 0 | O100: 0
A101: GLOBETEK SCIENCE FOUNDATION INC. | B101: Makati City | C101: PASMAK | D101: National Capital Region (NCR) | E101: NCR | F101: Bread and Pastry Production NC II | G101: =FALSE() -> FALSE | H101: 1 | I101: 1 | J101: 4 | K101: 348 | L101: 326 | M101: 1 | N101: 171 | O101: 168
A102: SYNERGY ASSESSMENT & TRAINING CENTER | B102: Malvar | C102: Batangas | D102: Region IVA - CALABARZON | E102: 4A | F102: Shielded Metal Arc Welding (SMAW) NC I | G102: =TRUE() -> TRUE | H102: 1 | I102: 0 | J102: 5 | K102: 264 | L102: 323 | M102: 0 | N102: 0 | O102: 0
A103: PHILIPPINE SCHOOL FOR TECHNOLOGY DEVELOPMENT AND INNOVATION INC. | B103: Valenzuela City | C103: CAMANAVA | D103: National Capital Region (NCR) | E103: NCR | F103: Electrical Installation and Maintenance NC II | G103: =TRUE() -> TRUE | H103: 1 | I103: 1 | J103: 1 | K103: 357 | L103: 322 | M103: 1 | N103: 73 | O103: 73
A104: LUCENA TECHNOLOGICAL INSTITUTE INCORPORATED | B104: Lucena City | C104: Quezon | D104: Region IVA - CALABARZON | E104: 4A | F104: Shielded Metal Arc Welding (SMAW) NC I | G104: =TRUE() -> TRUE | H104: 1 | I104: 1 | J104: 7 | K104: 221 | L104: 318 | M104: 1 | N104: 219 | O104: 219
A105: AUTOZONE DRIVING SCHOOLINC. | B105: San Pedro | C105: Laguna | D105: Region IVA - CALABARZON | E105: 4A | F105: Driving NC II | G105: =FALSE() -> FALSE | H105: 1 | I105: 0 | J105: 3 | K105: 317 | L105: 317 | M105: 0 | N105: 0 | O105: 0
A106: KAMELO MANPOWER SKILLS DEVELOPMENT CENTER INC. | B106: Batangas City | C106: Batangas | D106: Region IVA - CALABARZON | E106: 4A | F106: Shielded Metal Arc Welding (SMAW) NC II | G106: =TRUE() -> TRUE | H106: 1 | I106: 0 | J106: 4 | K106: 207 | L106: 317 | M106: 0 | N106: 0 | O106: 0
A107: SACRED HEART TECHNICAL & VOCATIONAL ASSESSMENT CENTER INC. | B107: Quezon City | C107: Quezon City | D107: National Capital Region (NCR) | E107: NCR | F107: Bread and Pastry Production NC II | G107: =FALSE() -> FALSE | H107: 1 | I107: 1 | J107: 3 | K107: 144 | L107: 316 | M107: 1 | N107: 265 | O107: 265
A108: PHILIPPINE SCHOOL FOR TECHNOLOGY DEVELOPMENT AND INNOVATION INC. | B108: Valenzuela City | C108: CAMANAVA | D108: National Capital Region (NCR) | E108: NCR | F108: Shielded Metal Arc Welding (SMAW) NC II | G108: =TRUE() -> TRUE | H108: 1 | I108: 1 | J108: 1 | K108: 326 | L108: 314 | M108: 1 | N108: 149 | O108: 149
A109: Skillful Training and Assessment Center Inc. | B109: Lemery | C109: Batangas | D109: Region IVA - CALABARZON | E109: 4A | F109: Shielded Metal Arc Welding (SMAW) NC I | G109: =TRUE() -> TRUE | H109: 1 | I109: 0 | J109: 2 | K109: 243 | L109: 314 | M109: 0 | N109: 0 | O109: 0
A110: RUBIKS MANPOWER TRAINING CENTER INC. | B110: Lipa City | C110: Batangas | D110: Region IVA - CALABARZON | E110: 4A | F110: Bread and Pastry Production NC II | G110: =FALSE() -> FALSE | H110: 1 | I110: 1 | J110: 4 | K110: 291 | L110: 313 | M110: 1 | N110: 424 | O110: 428
A111: QTEK TRAINING AND ASSESSMENT CENTER INC. | B111: Mandaluyong City | C111: PAMAMARISAN | D111: National Capital Region (NCR) | E111: NCR | F111: Carpentry NC II | G111: =TRUE() -> TRUE | H111: 1 | I111: 0 | J111: 3 | K111: 373 | L111: 312 | M111: 0 | N111: 0 | O111: 0
A112: THE BIG FIVE TRAINING AND ASSESSMENT CENTER INC. | B112: San Pablo City | C112: Laguna | D112: Region IVA - CALABARZON | E112: 4A | F112: Computer Systems Servicing NC II | G112: =FALSE() -> FALSE | H112: 1 | I112: 1 | J112: 6 | K112: 485 | L112: 311 | M112: 1 | N112: 365 | O112: 547
A113: COLEGIO DE SAN EXPEDITO, IN.C | B113: Sariaya | C113: Quezon | D113: Region IVA - CALABARZON | E113: 4A | F113: Bread and Pastry Production NC II | G113: =FALSE() -> FALSE | H113: 1 | I113: 0 | J113: 3 | K113: 304 | L113: 309 | M113: 0 | N113: 0 | O113: 0
A114: INTERNATIONAL TRAINING FOR ENHANCEMENT & ASSESSMENT CENTER, INC. | B114: Parañaque City | C114: MUNTIPARLASTAPAT | D114: National Capital Region (NCR) | E114: NCR | F114: Shielded Metal Arc Welding (SMAW) NC I | G114: =TRUE() -> TRUE | H114: 1 | I114: 0 | J114: 2 | K114: 163 | L114: 308 | M114: 0 | N114: 0 | O114: 0
A115: GATEWAYS INSTITUTE OF SCIENCE & TECHNOLOGY, INC. (Mandaluyong) | B115: Mandaluyong City | C115: PAMAMARISAN | D115: National Capital Region (NCR) | E115: NCR | F115: Bread and Pastry Production NC II | G115: =FALSE() -> FALSE | H115: 1 | I115: 0 | J115: 2 | K115: 315 | L115: 307 | M115: 0 | N115: 0 | O115: 0
A116: MARANATHA TECHNOLOGICAL INSTITUTE AND TRAINING CENTER CORPORATION | B116: Valenzuela City | C116: CAMANAVA | D116: National Capital Region (NCR) | E116: NCR | F116: Events Management Services NC III | G116: =FALSE() -> FALSE | H116: 1 | I116: 0 | J116: 4 | K116: 310 | L116: 307 | M116: 0 | N116: 0 | O116: 0
A117: ST. CATHERINE INSTITUTE OF TECHNOLOGY, INC. | B117: Malabon City | C117: CAMANAVA | D117: National Capital Region (NCR) | E117: NCR | F117: Bread and Pastry Production NC II | G117: =FALSE() -> FALSE | H117: 1 | I117: 0 | J117: 1 | K117: 179 | L117: 306 | M117: 0 | N117: 0 | O117: 0
A118: Computer Site Ins. Inc. | B118: San Pedro | C118: Laguna | D118: Region IVA - CALABARZON | E118: 4A | F118: Technical Drafting NC II | G118: =FALSE() -> FALSE | H118: 1 | I118: 0 | J118: 5 | K118: 365 | L118: 306 | M118: 0 | N118: 0 | O118: 0
A119: JOYSIS TECH VOC INC. | B119: Malabon City | C119: CAMANAVA | D119: National Capital Region (NCR) | E119: NCR | F119: Programming (Java) NC III | G119: =FALSE() -> FALSE | H119: 1 | I119: 0 | J119: 3 | K119: 279 | L119: 304 | M119: 0 | N119: 0 | O119: 0
A120: THE BIG FIVE TRAINING AND ASSESSMENT CENTER INC. | B120: San Pablo City | C120: Laguna | D120: Region IVA - CALABARZON | E120: 4A | F120: Electronic Products Assembly and Servicing NC II | G120: =FALSE() -> FALSE | H120: 1 | I120: 1 | J120: 2 | K120: 352 | L120: 303 | M120: 1 | N120: 307 | O120: 310
A121: CAPT. WILIJADO P. ABUID FOUNDATION, INC. | B121: Pasay City | C121: PASMAK | D121: National Capital Region (NCR) | E121: NCR | F121: Ship's Catering Services NC I | G121: =FALSE() -> FALSE | H121: 1 | I121: 1 | J121: 4 | K121: 1131 | L121: 300 | M121: 1 | N121: 2304 | O121: 2301
A122: COLLEGE OF SAINT AMATIEL INC. | B122: Malabon City | C122: CAMANAVA | D122: National Capital Region (NCR) | E122: NCR | F122: Bread and Pastry Production NC II | G122: =FALSE() -> FALSE | H122: 1 | I122: 1 | J122: 2 | K122: 256 | L122: 299 | M122: 1 | N122: 122 | O122: 122
A123: ST. THOMAS AQUINAS INSTITUTE OF CALOOCAN INC. | B123: Caloocan City | C123: CAMANAVA | D123: National Capital Region (NCR) | E123: NCR | F123: Bread and Pastry Production NC II | G123: =FALSE() -> FALSE | H123: 1 | I123: 0 | J123: 4 | K123: 383 | L123: 298 | M123: 0 | N123: 0 | O123: 0
A124: TESDA MANILA TRAINING AND ASSESSMENT CENTER (TMTAC) | B124: Paco, City of Manila | C124: City of Manila | D124: National Capital Region (NCR) | E124: NCR | F124: Trainers Methodology Level I | G124: =FALSE() -> FALSE | H124: 1 | I124: 0 | J124: 2 | K124: 304 | L124: 297 | M124: 0 | N124: 0 | O124: 0
A125: ASIAN ENTREPRENEURS TECHNOLOGICAL INSTITUTE, INC. | B125: Pasig City | C125: PAMAMARISAN | D125: National Capital Region (NCR) | E125: NCR | F125: Computer Systems Servicing NC II | G125: =FALSE() -> FALSE | H125: 1 | I125: 0 | J125: 2 | K125: 197 | L125: 296 | M125: 0 | N125: 0 | O125: 0
A126: Top Choice Training Institute and Assessment Center | B126: Parañaque City | C126: MUNTIPARLASTAPAT | D126: National Capital Region (NCR) | E126: NCR | F126: Driving (Passenger Bus/Straight Truck) NC III | G126: =FALSE() -> FALSE | H126: 1 | I126: 0 | J126: 3 | K126: 235 | L126: 295 | M126: 0 | N126: 0 | O126: 0
A127: Skillful Training and Assessment Center Inc. | B127: Lemery | C127: Batangas | D127: Region IVA - CALABARZON | E127: 4A | F127: Shielded Metal Arc Welding (SMAW) NC II | G127: =TRUE() -> TRUE | H127: 1 | I127: 0 | J127: 3 | K127: 267 | L127: 295 | M127: 0 | N127: 0 | O127: 0
A128: ST. THOMAS AQUINAS INSTITUTE OF CALOOCAN INC. | B128: Caloocan City | C128: CAMANAVA | D128: National Capital Region (NCR) | E128: NCR | F128: Events Management Services NC III | G128: =FALSE() -> FALSE | H128: 1 | I128: 0 | J128: 1 | K128: 379 | L128: 294 | M128: 0 | N128: 0 | O128: 0
A129: ARAYA SKILLS DEVELOPMENT INSTITUTE, CORP. | B129: San Juan City | C129: PAMAMARISAN | D129: National Capital Region (NCR) | E129: NCR | F129: Trainers Methodology Level I | G129: =FALSE() -> FALSE | H129: 1 | I129: 0 | J129: 2 | K129: 405 | L129: 294 | M129: 0 | N129: 0 | O129: 0
A130: PSAA INTERNATIONAL ACADEMY INC. | B130: Pandacan, City of Manila | C130: City of Manila | D130: National Capital Region (NCR) | E130: NCR | F130: Cookery NC II | G130: =FALSE() -> FALSE | H130: 1 | I130: 1 | J130: 5 | K130: 380 | L130: 293 | M130: 1 | N130: 404 | O130: 404
A131: TRIDENT-ASSESSMENT AND TECHNICAL TRAINING CENTER INC. | B131: Caloocan City | C131: CAMANAVA | D131: National Capital Region (NCR) | E131: NCR | F131: Events Management Services NC III | G131: =FALSE() -> FALSE | H131: 1 | I131: 1 | J131: 2 | K131: 312 | L131: 293 | M131: 1 | N131: 111 | O131: 111
A132: MANILA CULINARY & HOSPITALITY ACADEMY, INC. | B132: San Juan City | C132: PAMAMARISAN | D132: National Capital Region (NCR) | E132: NCR | F132: Cookery NC II | G132: =FALSE() -> FALSE | H132: 1 | I132: 0 | J132: 3 | K132: 252 | L132: 289 | M132: 0 | N132: 0 | O132: 0
A133: TESDA-NAVOTAAS TRAINING INSTITUTE | B133: Navotas City | C133: CAMANAVA | D133: National Capital Region (NCR) | E133: NCR | F133: RAC Servicing (DomRAC) NC II | G133: =FALSE() -> FALSE | H133: 1 | I133: 1 | J133: 3 | K133: 103 | L133: 288 | M133: 1 | N133: 202 | O133: 197
A134: REGIONAL TRAINING CENTER - NCR | B134: Taguig City | C134: MUNTIPARLASTAPAT | D134: National Capital Region (NCR) | E134: NCR | F134: PV Systems Installation NC II | G134: =FALSE() -> FALSE | H134: 1 | I134: 1 | J134: 2 | K134: 199 | L134: 288 | M134: 1 | N134: 124 | O134: 105
A135: MILESTONE TECHNOLOGICAL INSTITUTE, INC. | B135: Valenzuela City | C135: CAMANAVA | D135: National Capital Region (NCR) | E135: NCR | F135: Events Management Services NC III | G135: =FALSE() -> FALSE | H135: 1 | I135: 0 | J135: 3 | K135: 353 | L135: 287 | M135: 0 | N135: 0 | O135: 0
A136: SOUTHERN LUZON TECHNOLOGICAL COLLEGE FOUNDATION, INC. | B136: Pasig City | C136: PAMAMARISAN | D136: National Capital Region (NCR) | E136: NCR | F136: Programming (Java) NC III | G136: =FALSE() -> FALSE | H136: 1 | I136: 0 | J136: 2 | K136: 133 | L136: 287 | M136: 0 | N136: 0 | O136: 0
A137: STO. NIÑO DE NOVALICHES SCHOOL INC. | B137: Quezon City | C137: Quezon City | D137: National Capital Region (NCR) | E137: NCR | F137: Automotive Servicing NC I | G137: =FALSE() -> FALSE | H137: 1 | I137: 1 | J137: 2 | K137: 250 | L137: 286 | M137: 1 | N137: 109 | O137: 109
...
